Workbook
Name \a: #N/A
Name \d: #REF!
Name \I: #REF!
Name \jy: #REF!
Name \P: #REF!
Name \r: #REF!
Name \x: #N/A
Name \xjy: #REF!
Name \z: #N/A
Name _1_24_method_test: #REF!
Name _1C_: #REF!
Name _801192.SI: "'=OFFSET(动态图标!$+Sheet1!$C$16,1,,COUNT(动态图标!$C:$C))"""
Name _a: #N/A
Name _aaa1: #N/A
Name _C: #REF!
Name _d: #N/A
Name _jgc10: OFFSET(#REF!,0,1*(#REF!-1),COUNTA(#REF!),1)
Name _JX4: #REF!
Name _pb300: OFFSET(#REF!,0,0,COUNTA(#REF!),1)
Name _pe300: OFFSET(#REF!,0,0,COUNTA(#REF!),1)
Name _r: #N/A
Name _sum2: #REF!
Name _TEM1: #REF!
Name _TEM2: #REF!
Name _x: #N/A
Name _Z: #REF!
Name A: #REF!
Name aa: #REF!
Name AAA: #REF!
Name abc: #REF!
Name Add__Cash: #REF!
Name Add__Listed_Investments: #REF!
Name Add__Other_Investments: #REF!
Name All_Institutions: #REF!
Name ALLM: #REF!
Name ALPHABETA: #REF!
Name Asset_Beta: #REF!
Name Asset_classes: #REF!
Name Asset_Concentrations: #REF!
Name Average_premium_rates: #REF!
Name A股加权市净率: #REF!
Name A股加权市盈率: #REF!
Name A股与H股加权溢价: #REF!
Name B: #N/A
Name Balance_sheet: #REF!
Name Balance_sheet_history: #REF!
Name Bank_industry: #REF!
Name bb: #REF!
Name bd_title: #REF!
Name BETA: #REF!
Name brokerCodes: #REF!
Name brokerCodesList: #REF!
Name brokerCodesListMaster: #REF!
Name brokerNames: #REF!
Name brokerNamesList: #REF!
Name brokerNamesListMaster: #REF!
Name Bubble: "Bubble"
Name calendarize: #REF!
Name calendarized: #REF!
Name calendarNames: #REF!

Sheet 联系方式及申明
A1: 数据库联系人：王先爽、文雪阳

Sheet 横向对比
A1: 注：一季报、三季报无连续的逾期、关注、重组、三阶段数据，假设以上规模与前一报告期保持一致
A2: 输入报告期 | B2: 46022 | C2: 上市银行 | D2: 国有行 | E2: 股份行 | F2: 城商行 | G2: 农商行 | H2: AH股 | I2: 纯H股 | J2: 国有1 | K2: 国有2 | L2: 国有3 | M2: 国有4 | N2: 国有5 | O2: 国有6 | P2: 股份1 | Q2: 股份2 | R2: 股份3 | S2: 股份4 | T2: 股份5 | U2: 股份6 | V2: 股份7 | W2: 股份8 | X2: 股份9 | Y2: 城商1 | Z2: 城商2 | AA2: 城商3 | AB2: 城商4 | AC2: 城商5 | AD2: 城商6 | AE2: 城商7 | AF2: 城商8 | AG2: 城商9 | AH2: 城商10 | AI2: 城商11 | AJ2: 城商12 | AK2: 城商13 | AL2: 城商14 | AM2: 城商15 | AN2: 城商16 | AO2: 城商17 | AP2: 农商1 | AQ2: 农商2 | AR2: 农商3 | AS2: 农商4 | AT2: 农商5 | AU2: 农商6 | AV2: 农商7 | AW2: 农商8 | AX2: 农商9 | AY2: 农商10 | AZ2: 纯H股1 | BA2: 纯H股2 | BB2: 纯H股3 | BC2: 纯H股4 | BD2: 纯H股5 | BE2: 纯H股6 | BF2: 纯H股7 | BG2: 纯H股8 | BH2: 纯H股9 | BI2: 纯H股10 | BJ2: 纯H股11 | BK2: 纯H股12 | BL2: 纯H股13
A3: 上市银行仅包括A股上市的42家银行 | B3: 单位：亿元 | J3: 1国有 | K3: 1国有 | L3: 1国有 | M3: 1国有 | N3: 1国有 | O3: 1国有 | P3: 2股份 | Q3: 2股份 | R3: 2股份 | S3: 2股份 | T3: 2股份 | U3: 2股份 | V3: 2股份 | W3: 2股份 | X3: 2股份 | Y3: 3城商 | Z3: 3城商 | AA3: 3城商 | AB3: 3城商 | AC3: 3城商 | AD3: 3城商 | AE3: 3城商 | AF3: 3城商 | AG3: 3城商 | AH3: 3城商 | AI3: 3城商 | AJ3: 3城商 | AK3: 3城商 | AL3: 3城商 | AM3: 3城商 | AN3: 3城商 | AO3: 3城商 | AP3: 4农商 | AQ3: 4农商 | AR3: 4农商 | AS3: 4农商 | AT3: 4农商 | AU3: 4农商 | AV3: 4农商 | AW3: 4农商 | AX3: 4农商 | AY3: 4农商
B4: =B2 -> 46022 | C4: 上市银行 | D4: 国有行 | E4: 股份行 | F4: 城商行 | G4: 农商行 | H4: =H2 -> AH股 | I4: =I2 -> 纯H股 | J4: 工商 | K4: 建设 | L4: 农业 | M4: 中国 | N4: 邮储 | O4: 交通 | P4: 招商 | Q4: 兴业 | R4: 浦发 | S4: 中信 | T4: 民生 | U4: 光大 | V4: 平安 | W4: 华夏 | X4: 浙商 | Y4: 北京 | Z4: 江苏 | AA4: 上海 | AB4: 宁波 | AC4: 南京 | AD4: 杭州 | AE4: 成都 | AF4: 长沙 | AG4: 重庆 | AH4: 贵阳 | AI4: 郑州 | AJ4: 苏州 | AK4: 青岛 | AL4: 齐鲁 | AM4: 兰州 | AN4: 西安 | AO4: 厦门 | AP4: 渝农 | AQ4: 沪农 | AR4: 青农 | AS4: 常熟 | AT4: 紫金 | AU4: 无锡 | AV4: 张家港 | AW4: 苏农 | AX4: 瑞丰 | AY4: 江阴 | AZ4: 中原 | BA4: 广州农商 | BB4: 天津 | BC4: 江西 | BD4: 泸州 | BE4: 甘肃 | BF4: 晋商 | BG4: 徽商 | BH4: 哈尔滨 | BI4: 贵州 | BJ4: 渤海 | BK4: 威海 | BL4: 东莞农商 | BO4: ="净利润TTM增速VS期初超额拨备利润倍数-"&TEXT(B2,"YYYY/MM") -> 净利润TTM增速VS期初超额拨备利润倍数-2025/12
A5: ① | B5: 贷款总额 | C5: =IFERROR(INDEX(【输出】数据汇总!$A:$AZ,MATCH(横向对比!C$4&横向对比!$B5,【输出】数据汇总!$A:$A,0),MATCH(横向对比!$B$4,【输出】数据汇总!$1:$1,0))/100,"") -> 1862821.1 | D5: =IFERROR(INDEX(【输出】数据汇总!$A:$AZ,MATCH(横向对比!D$4&横向对比!$B5,【输出】数据汇总!$A:$A,0),MATCH(横向对比!$B$4,【输出】数据汇总!$1:$1,0))/100,"") -> 1275931.8 | E5: =IFERROR(INDEX(【输出】数据汇总!$A:$AZ,MATCH(横向对比!E$4&横向对比!$B5,【输出】数据汇总!$A:$A,0),MATCH(横向对比!$B$4,【输出】数据汇总!$1:$1,0))/100,"") -> 410549.64 | F5: =IFERROR(INDEX(【输出】数据汇总!$A:$AZ,MATCH(横向对比!F$4&横向对比!$B5,【输出】数据汇总!$A:$A,0),MATCH(横向对比!$B$4,【输出】数据汇总!$1:$1,0))/100,"") -> 147599.65 | G5: =IFERROR(INDEX(【输出】数据汇总!$A:$AZ,MATCH(横向对比!G$4&横向对比!$B5,【输出】数据汇总!$A:$A,0),MATCH(横向对比!$B$4,【输出】数据汇总!$1:$1,0))/100,"") -> 28740.002 | H5: =IFERROR(INDEX(【输出】数据汇总!$A:$AZ,MATCH(横向对比!H$4&横向对比!$B5,【输出】数据汇总!$A:$A,0),MATCH(横向对比!$B$4,【输出】数据汇总!$1:$1,0))/100,"") | I5: =IFERROR(INDEX(【输出】数据汇总!$A:$AZ,MATCH(横向对比!I$4&横向对比!$B5,【输出】数据汇总!$A:$A,0),MATCH(横向对比!$B$4,【输出】数据汇总!$1:$1,0))/100,"") -> 63802.973 | J5: =IFERROR(INDEX(【输出】数据汇总!$A:$AZ,MATCH(横向对比!J$4&横向对比!$B5,【输出】数据汇总!$A:$A,0),MATCH(横向对比!$B$4,【输出】数据汇总!$1:$1,0))/100,"") -> 305061.14 | ... BL5: =IFERROR(INDEX(【输出】数据汇总!$A:$AZ,MATCH(横向对比!BL$4&横向对比!$B5,【输出】数据汇总!$A:$A,0),MATCH(横向对比!$B$4,【输出】数据汇总!$1:$1,0))/100,"") -> 4090.3122
A6: ② | B6: 逾期贷款余额 | C6: =IFERROR(INDEX(【输出】数据汇总!$A:$AZ,MATCH(横向对比!C$4&横向对比!$B6,【输出】数据汇总!$A:$A,0),MATCH(横向对比!$B$4,【输出】数据汇总!$1:$1,0))/100,"") -> 24524.321 | D6: =IFERROR(INDEX(【输出】数据汇总!$A:$AZ,MATCH(横向对比!D$4&横向对比!$B6,【输出】数据汇总!$A:$A,0),MATCH(横向对比!$B$4,【输出】数据汇总!$1:$1,0))/100,"") -> 17244.89 | E6: =IFERROR(INDEX(【输出】数据汇总!$A:$AZ,MATCH(横向对比!E$4&横向对比!$B6,【输出】数据汇总!$A:$A,0),MATCH(横向对比!$B$4,【输出】数据汇总!$1:$1,0))/100,"") -> 6818.95 | F6: =IFERROR(INDEX(【输出】数据汇总!$A:$AZ,MATCH(横向对比!F$4&横向对比!$B6,【输出】数据汇总!$A:$A,0),MATCH(横向对比!$B$4,【输出】数据汇总!$1:$1,0))/100,"") -> 296.20313 | G6: =IFERROR(INDEX(【输出】数据汇总!$A:$AZ,MATCH(横向对比!G$4&横向对比!$B6,【输出】数据汇总!$A:$A,0),MATCH(横向对比!$B$4,【输出】数据汇总!$1:$1,0))/100,"") -> 164.27824 | H6: =IFERROR(INDEX(【输出】数据汇总!$A:$AZ,MATCH(横向对比!H$4&横向对比!$B6,【输出】数据汇总!$A:$A,0),MATCH(横向对比!$B$4,【输出】数据汇总!$1:$1,0))/100,"") | I6: =IFERROR(INDEX(【输出】数据汇总!$A:$AZ,MATCH(横向对比!I$4&横向对比!$B6,【输出】数据汇总!$A:$A,0),MATCH(横向对比!$B$4,【输出】数据汇总!$1:$1,0))/100,"") -> 2052.1078 | J6: =IFERROR(INDEX(【输出】数据汇总!$A:$AZ,MATCH(横向对比!J$4&横向对比!$B6,【输出】数据汇总!$A:$A,0),MATCH(横向对比!$B$4,【输出】数据汇总!$1:$1,0))/100,"") -> 4627.35 | ... BL6: =IFERROR(INDEX(【输出】数据汇总!$A:$AZ,MATCH(横向对比!BL$4&横向对比!$B6,【输出】数据汇总!$A:$A,0),MATCH(横向对比!$B$4,【输出】数据汇总!$1:$1,0))/100,"") -> 94.75837
A7: ③ | B7: 重组贷款余额 | C7: =IFERROR(INDEX(【输出】数据汇总!$A:$AZ,MATCH(横向对比!C$4&横向对比!$B7,【输出】数据汇总!$A:$A,0),MATCH(横向对比!$B$4,【输出】数据汇总!$1:$1,0))/100,"") -> 9099.3913 | D7: =IFERROR(INDEX(【输出】数据汇总!$A:$AZ,MATCH(横向对比!D$4&横向对比!$B7,【输出】数据汇总!$A:$A,0),MATCH(横向对比!$B$4,【输出】数据汇总!$1:$1,0))/100,"") -> 6406.08 | E7: =IFERROR(INDEX(【输出】数据汇总!$A:$AZ,MATCH(横向对比!E$4&横向对比!$B7,【输出】数据汇总!$A:$A,0),MATCH(横向对比!$B$4,【输出】数据汇总!$1:$1,0))/100,"") -> 2636.12 | F7: =IFERROR(INDEX(【输出】数据汇总!$A:$AZ,MATCH(横向对比!F$4&横向对比!$B7,【输出】数据汇总!$A:$A,0),MATCH(横向对比!$B$4,【输出】数据汇总!$1:$1,0))/100,"") -> 10.88911 | G7: =IFERROR(INDEX(【输出】数据汇总!$A:$AZ,MATCH(横向对比!G$4&横向对比!$B7,【输出】数据汇总!$A:$A,0),MATCH(横向对比!$B$4,【输出】数据汇总!$1:$1,0))/100,"") -> 46.302178 | H7: =IFERROR(INDEX(【输出】数据汇总!$A:$AZ,MATCH(横向对比!H$4&横向对比!$B7,【输出】数据汇总!$A:$A,0),MATCH(横向对比!$B$4,【输出】数据汇总!$1:$1,0))/100,"") | I7: =IFERROR(INDEX(【输出】数据汇总!$A:$AZ,MATCH(横向对比!I$4&横向对比!$B7,【输出】数据汇总!$A:$A,0),MATCH(横向对比!$B$4,【输出】数据汇总!$1:$1,0))/100,"") -> 695.65569 | J7: =IFERROR(INDEX(【输出】数据汇总!$A:$AZ,MATCH(横向对比!J$4&横向对比!$B7,【输出】数据汇总!$A:$A,0),MATCH(横向对比!$B$4,【输出】数据汇总!$1:$1,0))/100,"") -> 1560.27 | ... BL7: =IFERROR(INDEX(【输出】数据汇总!$A:$AZ,MATCH(横向对比!BL$4&横向对比!$B7,【输出】数据汇总!$A:$A,0),MATCH(横向对比!$B$4,【输出】数据汇总!$1:$1,0))/100,"") -> 8.85676
A8: ④ | B8: 不良贷款余额 | C8: =IFERROR(INDEX(【输出】数据汇总!$A:$AZ,MATCH(横向对比!C$4&横向对比!$B8,【输出】数据汇总!$A:$A,0),MATCH(横向对比!$B$4,【输出】数据汇总!$1:$1,0))/100,"") -> 21227.878 | D8: =IFERROR(INDEX(【输出】数据汇总!$A:$AZ,MATCH(横向对比!D$4&横向对比!$B8,【输出】数据汇总!$A:$A,0),MATCH(横向对比!$B$4,【输出】数据汇总!$1:$1,0))/100,"") -> 16029.94 | E8: =IFERROR(INDEX(【输出】数据汇总!$A:$AZ,MATCH(横向对比!E$4&横向对比!$B8,【输出】数据汇总!$A:$A,0),MATCH(横向对比!$B$4,【输出】数据汇总!$1:$1,0))/100,"") -> 4901.85 | F8: =IFERROR(INDEX(【输出】数据汇总!$A:$AZ,MATCH(横向对比!F$4&横向对比!$B8,【输出】数据汇总!$A:$A,0),MATCH(横向对比!$B$4,【输出】数据汇总!$1:$1,0))/100,"") -> 169.04226 | G8: =IFERROR(INDEX(【输出】数据汇总!$A:$AZ,MATCH(横向对比!G$4&横向对比!$B8,【输出】数据汇总!$A:$A,0),MATCH(横向对比!$B$4,【输出】数据汇总!$1:$1,0))/100,"") -> 127.04607 | H8: =IFERROR(INDEX(【输出】数据汇总!$A:$AZ,MATCH(横向对比!H$4&横向对比!$B8,【输出】数据汇总!$A:$A,0),MATCH(横向对比!$B$4,【输出】数据汇总!$1:$1,0))/100,"") | I8: =IFERROR(INDEX(【输出】数据汇总!$A:$AZ,MATCH(横向对比!I$4&横向对比!$B8,【输出】数据汇总!$A:$A,0),MATCH(横向对比!$B$4,【输出】数据汇总!$1:$1,0))/100,"") -> 1085.1866 | J8: =IFERROR(INDEX(【输出】数据汇总!$A:$AZ,MATCH(横向对比!J$4&横向对比!$B8,【输出】数据汇总!$A:$A,0),MATCH(横向对比!$B$4,【输出】数据汇总!$1:$1,0))/100,"") -> 3990.13 | ... BL8: =IFERROR(INDEX(【输出】数据汇总!$A:$AZ,MATCH(横向对比!BL$4&横向对比!$B8,【输出】数据汇总!$A:$A,0),MATCH(横向对比!$B$4,【输出】数据汇总!$1:$1,0))/100,"") -> 73.216589
A9: ⑤ | B9: 关注类贷款余额 | C9: =IFERROR(INDEX(【输出】数据汇总!$A:$AZ,MATCH(横向对比!C$4&横向对比!$B9,【输出】数据汇总!$A:$A,0),MATCH(横向对比!$B$4,【输出】数据汇总!$1:$1,0))/100,"") -> 29337.196 | D9: =IFERROR(INDEX(【输出】数据汇总!$A:$AZ,MATCH(横向对比!D$4&横向对比!$B9,【输出】数据汇总!$A:$A,0),MATCH(横向对比!$B$4,【输出】数据汇总!$1:$1,0))/100,"") -> 21089.63 | E9: =IFERROR(INDEX(【输出】数据汇总!$A:$AZ,MATCH(横向对比!E$4&横向对比!$B9,【输出】数据汇总!$A:$A,0),MATCH(横向对比!$B$4,【输出】数据汇总!$1:$1,0))/100,"") -> 7867.03 | F9: =IFERROR(INDEX(【输出】数据汇总!$A:$AZ,MATCH(横向对比!F$4&横向对比!$B9,【输出】数据汇总!$A:$A,0),MATCH(横向对比!$B$4,【输出】数据汇总!$1:$1,0))/100,"") -> 207.84482 | G9: =IFERROR(INDEX(【输出】数据汇总!$A:$AZ,MATCH(横向对比!G$4&横向对比!$B9,【输出】数据汇总!$A:$A,0),MATCH(横向对比!$B$4,【输出】数据汇总!$1:$1,0))/100,"") -> 172.69087 | H9: =IFERROR(INDEX(【输出】数据汇总!$A:$AZ,MATCH(横向对比!H$4&横向对比!$B9,【输出】数据汇总!$A:$A,0),MATCH(横向对比!$B$4,【输出】数据汇总!$1:$1,0))/100,"") | I9: =IFERROR(INDEX(【输出】数据汇总!$A:$AZ,MATCH(横向对比!I$4&横向对比!$B9,【输出】数据汇总!$A:$A,0),MATCH(横向对比!$B$4,【输出】数据汇总!$1:$1,0))/100,"") -> 1860.9933 | J9: =IFERROR(INDEX(【输出】数据汇总!$A:$AZ,MATCH(横向对比!J$4&横向对比!$B9,【输出】数据汇总!$A:$A,0),MATCH(横向对比!$B$4,【输出】数据汇总!$1:$1,0))/100,"") -> 5946.56 | ... BL9: =IFERROR(INDEX(【输出】数据汇总!$A:$AZ,MATCH(横向对比!BL$4&横向对比!$B9,【输出】数据汇总!$A:$A,0),MATCH(横向对比!$B$4,【输出】数据汇总!$1:$1,0))/100,"") -> 87.20042
A10: ⑥=MAX(②+③，④+⑤) | B10: 广义风险贷款 | C10: =MAX(C6+C7,C8+C9) -> 50565.074 | D10: =MAX(D6+D7,D8+D9) -> 37119.57 | E10: =MAX(E6+E7,E8+E9) -> 12768.88 | F10: =MAX(F6+F7,F8+F9) -> 376.88708 | G10: =MAX(G6+G7,G8+G9) -> 299.73694 | H10: =MAX(H6+H7,H8+H9) -> #VALUE! | I10: =MAX(I6+I7,I8+I9) -> 2946.1799 | J10: =IFERROR(INDEX(【输出】数据汇总!$A:$AZ,MATCH(横向对比!J$4&横向对比!$B10,【输出】数据汇总!$A:$A,0),MATCH(横向对比!$B$4,【输出】数据汇总!$1:$1,0))/100,"") -> 9942.8609 | K10: =IFERROR(INDEX(【输出】数据汇总!$A:$AZ,MATCH(横向对比!K$4&横向对比!$B10,【输出】数据汇总!$A:$A,0),MATCH(横向对比!$B$4,【输出】数据汇总!$1:$1,0))/100,"") -> 8545.5503 | L10: =IFERROR(INDEX(【输出】数据汇总!$A:$AZ,MATCH(横向对比!L$4&横向对比!$B10,【输出】数据汇总!$A:$A,0),MATCH(横向对比!$B$4,【输出】数据汇总!$1:$1,0))/100,"") -> 7222.2739 | M10: =IFERROR(INDEX(【输出】数据汇总!$A:$AZ,MATCH(横向对比!M$4&横向对比!$B10,【输出】数据汇总!$A:$A,0),MATCH(横向对比!$B$4,【输出】数据汇总!$1:$1,0))/100,"") -> 6313.8242 | N10: =IFERROR(INDEX(【输出】数据汇总!$A:$AZ,MATCH(横向对比!N$4&横向对比!$B10,【输出】数据汇总!$A:$A,0),MATCH(横向对比!$B$4,【输出】数据汇总!$1:$1,0))/100,"") -> 2433.07 | O10: =IFERROR(INDEX(【输出】数据汇总!$A:$AZ,MATCH(横向对比!O$4&横向对比!$B10,【输出】数据汇总!$A:$A,0),MATCH(横向对比!$B$4,【输出】数据汇总!$1:$1,0))/100,"") -> 2676.2471 | P10: =IFERROR(INDEX(【输出】数据汇总!$A:$AZ,MATCH(横向对比!P$4&横向对比!$B10,【输出】数据汇总!$A:$A,0),MATCH(横向对比!$B$4,【输出】数据汇总!$1:$1,0))/100,"") -> 1720.8575 | Q10: =IFERROR(INDEX(【输出】数据汇总!$A:$AZ,MATCH(横向对比!Q$4&横向对比!$B10,【输出】数据汇总!$A:$A,0),MATCH(横向对比!$B$4,【输出】数据汇总!$1:$1,0))/100,"") -> 1646.4053 | ... BL10: =IFERROR(INDEX(【输出】数据汇总!$A:$AZ,MATCH(横向对比!BL$4&横向对比!$B10,【输出】数据汇总!$A:$A,0),MATCH(横向对比!$B$4,【输出】数据汇总!$1:$1,0))/100,"") -> 160.41701
A11: ⑦ | B11: 非信贷资产第三阶段额 | C11: =IFERROR(INDEX(【输出】数据汇总!$A:$AZ,MATCH(横向对比!C$4&横向对比!$B11,【输出】数据汇总!$A:$A,0),MATCH(横向对比!$B$4,【输出】数据汇总!$1:$1,0))/100,"") -> 4130.8113 | D11: =IFERROR(INDEX(【输出】数据汇总!$A:$AZ,MATCH(横向对比!D$4&横向对比!$B11,【输出】数据汇总!$A:$A,0),MATCH(横向对比!$B$4,【输出】数据汇总!$1:$1,0))/100,"") -> 512.63 | E11: =IFERROR(INDEX(【输出】数据汇总!$A:$AZ,MATCH(横向对比!E$4&横向对比!$B11,【输出】数据汇总!$A:$A,0),MATCH(横向对比!$B$4,【输出】数据汇总!$1:$1,0))/100,"") -> 2695.32 | F11: =IFERROR(INDEX(【输出】数据汇总!$A:$AZ,MATCH(横向对比!F$4&横向对比!$B11,【输出】数据汇总!$A:$A,0),MATCH(横向对比!$B$4,【输出】数据汇总!$1:$1,0))/100,"") -> 898.88537 | G11: =IFERROR(INDEX(【输出】数据汇总!$A:$AZ,MATCH(横向对比!G$4&横向对比!$B11,【输出】数据汇总!$A:$A,0),MATCH(横向对比!$B$4,【输出】数据汇总!$1:$1,0))/100,"") -> 23.97595 | H11: =IFERROR(INDEX(【输出】数据汇总!$A:$AZ,MATCH(横向对比!H$4&横向对比!$B11,【输出】数据汇总!$A:$A,0),MATCH(横向对比!$B$4,【输出】数据汇总!$1:$1,0))/100,"") | I11: =IFERROR(INDEX(【输出】数据汇总!$A:$AZ,MATCH(横向对比!I$4&横向对比!$B11,【输出】数据汇总!$A:$A,0),MATCH(横向对比!$B$4,【输出】数据汇总!$1:$1,0))/100,"") -> 1038.2064 | J11: =IFERROR(INDEX(【输出】数据汇总!$A:$AZ,MATCH(横向对比!J$4&横向对比!$B11,【输出】数据汇总!$A:$A,0),MATCH(横向对比!$B$4,【输出】数据汇总!$1:$1,0))/100,"") -> 35.42 | ... BL11: =IFERROR(INDEX(【输出】数据汇总!$A:$AZ,MATCH(横向对比!BL$4&横向对比!$B11,【输出】数据汇总!$A:$A,0),MATCH(横向对比!$B$4,【输出】数据汇总!$1:$1,0))/100,"") -> 0.74179
A12: ⑧ | B12: 贷款拨备额 | C12: =IFERROR(INDEX(【输出】数据汇总!$A:$AZ,MATCH(横向对比!C$4&横向对比!$B12,【输出】数据汇总!$A:$A,0),MATCH(横向对比!$B$4,【输出】数据汇总!$1:$1,0))/100,"") -> 51227.472 | D12: =IFERROR(INDEX(【输出】数据汇总!$A:$AZ,MATCH(横向对比!D$4&横向对比!$B12,【输出】数据汇总!$A:$A,0),MATCH(横向对比!$B$4,【输出】数据汇总!$1:$1,0))/100,"") -> 39815.4 | E12: =IFERROR(INDEX(【输出】数据汇总!$A:$AZ,MATCH(横向对比!E$4&横向对比!$B12,【输出】数据汇总!$A:$A,0),MATCH(横向对比!$B$4,【输出】数据汇总!$1:$1,0))/100,"") -> 10559.18 | F12: =IFERROR(INDEX(【输出】数据汇总!$A:$AZ,MATCH(横向对比!F$4&横向对比!$B12,【输出】数据汇总!$A:$A,0),MATCH(横向对比!$B$4,【输出】数据汇总!$1:$1,0))/100,"") -> 391.06529 | G12: =IFERROR(INDEX(【输出】数据汇总!$A:$AZ,MATCH(横向对比!G$4&横向对比!$B12,【输出】数据汇总!$A:$A,0),MATCH(横向对比!$B$4,【输出】数据汇总!$1:$1,0))/100,"") -> 461.82664 | H12: =IFERROR(INDEX(【输出】数据汇总!$A:$AZ,MATCH(横向对比!H$4&横向对比!$B12,【输出】数据汇总!$A:$A,0),MATCH(横向对比!$B$4,【输出】数据汇总!$1:$1,0))/100,"") | I12: =IFERROR(INDEX(【输出】数据汇总!$A:$AZ,MATCH(横向对比!I$4&横向对比!$B12,【输出】数据汇总!$A:$A,0),MATCH(横向对比!$B$4,【输出】数据汇总!$1:$1,0))/100,"") -> 2142.1342 | J12: =IFERROR(INDEX(【输出】数据汇总!$A:$AZ,MATCH(横向对比!J$4&横向对比!$B12,【输出】数据汇总!$A:$A,0),MATCH(横向对比!$B$4,【输出】数据汇总!$1:$1,0))/100,"") -> 8522.74 | ... BL12: =IFERROR(INDEX(【输出】数据汇总!$A:$AZ,MATCH(横向对比!BL$4&横向对比!$B12,【输出】数据汇总!$A:$A,0),MATCH(横向对比!$B$4,【输出】数据汇总!$1:$1,0))/100,"") -> 151.09982
A13: ⑨=⑧-⑥*100% | B13: 超额贷款拨备额 | C13: =IFERROR(C12-C10*100%,"") -> 662.39791 | D13: =IFERROR(D12-D10*100%,"") -> 2695.83 | E13: =IFERROR(E12-E10*100%,"") -> -2209.7 | F13: =IFERROR(F12-F10*100%,"") -> 14.17821 | G13: =IFERROR(G12-G10*100%,"") -> 162.0897 | H13: =IFERROR(H12-H10*100%,"") | I13: =IFERROR(I12-I10*100%,"") -> -804.04571 | J13: =IFERROR(J12-J10*100%,"") -> -1420.1209 | ... BL13: =IFERROR(BL12-BL10*100%,"") -> -9.3171893
A14: ⑦ | B14: 非信贷资产第三阶段额 | C14: =IFERROR(INDEX(【输出】数据汇总!$A:$AZ,MATCH(横向对比!C$4&横向对比!$B14,【输出】数据汇总!$A:$A,0),MATCH(横向对比!$B$4,【输出】数据汇总!$1:$1,0))/100,"") -> 4130.8113 | D14: =IFERROR(INDEX(【输出】数据汇总!$A:$AZ,MATCH(横向对比!D$4&横向对比!$B14,【输出】数据汇总!$A:$A,0),MATCH(横向对比!$B$4,【输出】数据汇总!$1:$1,0))/100,"") -> 512.63 | E14: =IFERROR(INDEX(【输出】数据汇总!$A:$AZ,MATCH(横向对比!E$4&横向对比!$B14,【输出】数据汇总!$A:$A,0),MATCH(横向对比!$B$4,【输出】数据汇总!$1:$1,0))/100,"") -> 2695.32 | F14: =IFERROR(INDEX(【输出】数据汇总!$A:$AZ,MATCH(横向对比!F$4&横向对比!$B14,【输出】数据汇总!$A:$A,0),MATCH(横向对比!$B$4,【输出】数据汇总!$1:$1,0))/100,"") -> 898.88537 | G14: =IFERROR(INDEX(【输出】数据汇总!$A:$AZ,MATCH(横向对比!G$4&横向对比!$B14,【输出】数据汇总!$A:$A,0),MATCH(横向对比!$B$4,【输出】数据汇总!$1:$1,0))/100,"") -> 23.97595 | H14: =IFERROR(INDEX(【输出】数据汇总!$A:$AZ,MATCH(横向对比!H$4&横向对比!$B14,【输出】数据汇总!$A:$A,0),MATCH(横向对比!$B$4,【输出】数据汇总!$1:$1,0))/100,"") | I14: =IFERROR(INDEX(【输出】数据汇总!$A:$AZ,MATCH(横向对比!I$4&横向对比!$B14,【输出】数据汇总!$A:$A,0),MATCH(横向对比!$B$4,【输出】数据汇总!$1:$1,0))/100,"") -> 1038.2064 | J14: =IFERROR(INDEX(【输出】数据汇总!$A:$AZ,MATCH(横向对比!J$4&横向对比!$B14,【输出】数据汇总!$A:$A,0),MATCH(横向对比!$B$4,【输出】数据汇总!$1:$1,0))/100,"") -> 35.42 | ... BL14: =IFERROR(INDEX(【输出】数据汇总!$A:$AZ,MATCH(横向对比!BL$4&横向对比!$B14,【输出】数据汇总!$A:$A,0),MATCH(横向对比!$B$4,【输出】数据汇总!$1:$1,0))/100,"") -> 0.74179
A15: ⑩ | B15: 非信贷拨备额 | C15: =IFERROR(INDEX(【输出】数据汇总!$A:$AZ,MATCH(横向对比!C$4&横向对比!$B15,【输出】数据汇总!$A:$A,0),MATCH(横向对比!$B$4,【输出】数据汇总!$1:$1,0))/100,"") -> 3084.47 | D15: =IFERROR(INDEX(【输出】数据汇总!$A:$AZ,MATCH(横向对比!D$4&横向对比!$B15,【输出】数据汇总!$A:$A,0),MATCH(横向对比!$B$4,【输出】数据汇总!$1:$1,0))/100,"") -> 54.89 | E15: =IFERROR(INDEX(【输出】数据汇总!$A:$AZ,MATCH(横向对比!E$4&横向对比!$B15,【输出】数据汇总!$A:$A,0),MATCH(横向对比!$B$4,【输出】数据汇总!$1:$1,0))/100,"") -> 3029.58 | F15: =IFERROR(INDEX(【输出】数据汇总!$A:$AZ,MATCH(横向对比!F$4&横向对比!$B15,【输出】数据汇总!$A:$A,0),MATCH(横向对比!$B$4,【输出】数据汇总!$1:$1,0))/100,"") | G15: =IFERROR(INDEX(【输出】数据汇总!$A:$AZ,MATCH(横向对比!G$4&横向对比!$B15,【输出】数据汇总!$A:$A,0),MATCH(横向对比!$B$4,【输出】数据汇总!$1:$1,0))/100,"") | H15: =IFERROR(INDEX(【输出】数据汇总!$A:$AZ,MATCH(横向对比!H$4&横向对比!$B15,【输出】数据汇总!$A:$A,0),MATCH(横向对比!$B$4,【输出】数据汇总!$1:$1,0))/100,"") | I15: =IFERROR(INDEX(【输出】数据汇总!$A:$AZ,MATCH(横向对比!I$4&横向对比!$B15,【输出】数据汇总!$A:$A,0),MATCH(横向对比!$B$4,【输出】数据汇总!$1:$1,0))/100,"") -> 988.42977 | J15: =IFERROR(INDEX(【输出】数据汇总!$A:$AZ,MATCH(横向对比!J$4&横向对比!$B15,【输出】数据汇总!$A:$A,0),MATCH(横向对比!$B$4,【输出】数据汇总!$1:$1,0))/100,"") -> 979.66 | ... BL15: =IFERROR(INDEX(【输出】数据汇总!$A:$AZ,MATCH(横向对比!BL$4&横向对比!$B15,【输出】数据汇总!$A:$A,0),MATCH(横向对比!$B$4,【输出】数据汇总!$1:$1,0))/100,"") -> 5.84178
A16: ⑪=⑩-⑦*100% | B16: 超额非信贷拨备 | C16: =IFERROR(IF(C14="",C15-0,C15-C14*100%),"") -> -1046.3413 | D16: =IFERROR(IF(D14="",D15-0,D15-D14*100%),"") -> -457.74 | E16: =IFERROR(IF(E14="",E15-0,E15-E14*100%),"") -> 334.26 | F16: =IFERROR(IF(F14="",F15-0,F15-F14*100%),"") | G16: =IFERROR(IF(G14="",G15-0,G15-G14*100%),"") | H16: =IFERROR(IF(H14="",H15-0,H15-H14*100%),"") | I16: =IFERROR(IF(I14="",I15-0,I15-I14*100%),"") -> -49.7766 | J16: =IFERROR(IF(J14="",J15-0,J15-J14*100%),"") -> 944.24 | ... BL16: =IFERROR(IF(BL14="",BL15-0,BL15-BL14*100%),"") -> 5.09999
A17: ⑪+⑨ | B17: 超额拨备额 | C17: =IFERROR(C13+C16,"") -> -383.9434 | D17: =IFERROR(D13+D16,"") -> 2238.09 | E17: =IFERROR(E13+E16,"") -> -1875.44 | F17: =IFERROR(F13+F16,"") | G17: =IFERROR(G13+G16,"") | H17: =IFERROR(H13+H16,"") | I17: =IFERROR(I13+I16,"") -> -853.82231 | J17: =IFERROR(J13+J16,"") -> -475.88093 | ... BL17: =IFERROR(BL13+BL16,"") -> -4.2171993
B18: 归母净利润(TTM) | C18: =IFERROR(INDEX(【输出】数据汇总!$A:$AZ,MATCH(横向对比!C$4&横向对比!$B18,【输出】数据汇总!$A:$A,0),MATCH(横向对比!$B$4,【输出】数据汇总!$1:$1,0))/100,"") -> 20608.668 | D18: =IFERROR(INDEX(【输出】数据汇总!$A:$AZ,MATCH(横向对比!D$4&横向对比!$B18,【输出】数据汇总!$A:$A,0),MATCH(横向对比!$B$4,【输出】数据汇总!$1:$1,0))/100,"") -> 14245.56 | E18: =IFERROR(INDEX(【输出】数据汇总!$A:$AZ,MATCH(横向对比!E$4&横向对比!$B18,【输出】数据汇总!$A:$A,0),MATCH(横向对比!$B$4,【输出】数据汇总!$1:$1,0))/100,"") -> 5004.38 | F18: =IFERROR(INDEX(【输出】数据汇总!$A:$AZ,MATCH(横向对比!F$4&横向对比!$B18,【输出】数据汇总!$A:$A,0),MATCH(横向对比!$B$4,【输出】数据汇总!$1:$1,0))/100,"") -> 1154.4745 | G18: =IFERROR(INDEX(【输出】数据汇总!$A:$AZ,MATCH(横向对比!G$4&横向对比!$B18,【输出】数据汇总!$A:$A,0),MATCH(横向对比!$B$4,【输出】数据汇总!$1:$1,0))/100,"") -> 204.25364 | H18: =IFERROR(INDEX(【输出】数据汇总!$A:$AZ,MATCH(横向对比!H$4&横向对比!$B18,【输出】数据汇总!$A:$A,0),MATCH(横向对比!$B$4,【输出】数据汇总!$1:$1,0))/100,"") | I18: =IFERROR(INDEX(【输出】数据汇总!$A:$AZ,MATCH(横向对比!I$4&横向对比!$B18,【输出】数据汇总!$A:$A,0),MATCH(横向对比!$B$4,【输出】数据汇总!$1:$1,0))/100,"") -> 476.31644 | J18: =IFERROR(INDEX(【输出】数据汇总!$A:$AZ,MATCH(横向对比!J$4&横向对比!$B18,【输出】数据汇总!$A:$A,0),MATCH(横向对比!$B$4,【输出】数据汇总!$1:$1,0))/100,"") -> 3685.62 | ... BL18: =IFERROR(INDEX(【输出】数据汇总!$A:$AZ,MATCH(横向对比!BL$4&横向对比!$B18,【输出】数据汇总!$A:$A,0),MATCH(横向对比!$B$4,【输出】数据汇总!$1:$1,0))/100,"") -> 38.53908
B19: 归母净资产 | C19: =IFERROR(INDEX(【输出】数据汇总!$A:$AZ,MATCH(横向对比!C$4&横向对比!$B19,【输出】数据汇总!$A:$A,0),MATCH(横向对比!$B$4,【输出】数据汇总!$1:$1,0))/100,"") -> 242495.04 | D19: =IFERROR(INDEX(【输出】数据汇总!$A:$AZ,MATCH(横向对比!D$4&横向对比!$B19,【输出】数据汇总!$A:$A,0),MATCH(横向对比!$B$4,【输出】数据汇总!$1:$1,0))/100,"") -> 166382.74 | E19: =IFERROR(INDEX(【输出】数据汇总!$A:$AZ,MATCH(横向对比!E$4&横向对比!$B19,【输出】数据汇总!$A:$A,0),MATCH(横向对比!$B$4,【输出】数据汇总!$1:$1,0))/100,"") -> 62645.53 | F19: =IFERROR(INDEX(【输出】数据汇总!$A:$AZ,MATCH(横向对比!F$4&横向对比!$B19,【输出】数据汇总!$A:$A,0),MATCH(横向对比!$B$4,【输出】数据汇总!$1:$1,0))/100,"") -> 11274.123 | G19: =IFERROR(INDEX(【输出】数据汇总!$A:$AZ,MATCH(横向对比!G$4&横向对比!$B19,【输出】数据汇总!$A:$A,0),MATCH(横向对比!$B$4,【输出】数据汇总!$1:$1,0))/100,"") -> 2192.6507 | H19: =IFERROR(INDEX(【输出】数据汇总!$A:$AZ,MATCH(横向对比!H$4&横向对比!$B19,【输出】数据汇总!$A:$A,0),MATCH(横向对比!$B$4,【输出】数据汇总!$1:$1,0))/100,"") | I19: =IFERROR(INDEX(【输出】数据汇总!$A:$AZ,MATCH(横向对比!I$4&横向对比!$B19,【输出】数据汇总!$A:$A,0),MATCH(横向对比!$B$4,【输出】数据汇总!$1:$1,0))/100,"") -> 8837.0222 | J19: =IFERROR(INDEX(【输出】数据汇总!$A:$AZ,MATCH(横向对比!J$4&横向对比!$B19,【输出】数据汇总!$A:$A,0),MATCH(横向对比!$B$4,【输出】数据汇总!$1:$1,0))/100,"") -> 42442.59 | ... BL19: =IFERROR(INDEX(【输出】数据汇总!$A:$AZ,MATCH(横向对比!BL$4&横向对比!$B19,【输出】数据汇总!$A:$A,0),MATCH(横向对比!$B$4,【输出】数据汇总!$1:$1,0))/100,"") -> 602.94841
B20: 逾期率 | C20: =IFERROR(INDEX(【输出】数据汇总!$A:$AZ,MATCH(横向对比!C$4&横向对比!$B20,【输出】数据汇总!$A:$A,0),MATCH(横向对比!$B$4,【输出】数据汇总!$1:$1,0)),"") -> 0.01586935 | D20: =IFERROR(INDEX(【输出】数据汇总!$A:$AZ,MATCH(横向对比!D$4&横向对比!$B20,【输出】数据汇总!$A:$A,0),MATCH(横向对比!$B$4,【输出】数据汇总!$1:$1,0)),"") -> 0.013524708 | E20: =IFERROR(INDEX(【输出】数据汇总!$A:$AZ,MATCH(横向对比!E$4&横向对比!$B20,【输出】数据汇总!$A:$A,0),MATCH(横向对比!$B$4,【输出】数据汇总!$1:$1,0)),"") -> 0.017091767 | F20: =IFERROR(INDEX(【输出】数据汇总!$A:$AZ,MATCH(横向对比!F$4&横向对比!$B20,【输出】数据汇总!$A:$A,0),MATCH(横向对比!$B$4,【输出】数据汇总!$1:$1,0)),"") -> 0.017350052 | G20: =IFERROR(INDEX(【输出】数据汇总!$A:$AZ,MATCH(横向对比!G$4&横向对比!$B20,【输出】数据汇总!$A:$A,0),MATCH(横向对比!$B$4,【输出】数据汇总!$1:$1,0)),"") -> 0.015510873 | H20: =IFERROR(INDEX(【输出】数据汇总!$A:$AZ,MATCH(横向对比!H$4&横向对比!$B20,【输出】数据汇总!$A:$A,0),MATCH(横向对比!$B$4,【输出】数据汇总!$1:$1,0)),"") | I20: =IFERROR(INDEX(【输出】数据汇总!$A:$AZ,MATCH(横向对比!I$4&横向对比!$B20,【输出】数据汇总!$A:$A,0),MATCH(横向对比!$B$4,【输出】数据汇总!$1:$1,0)),"") -> 0.032596739 | J20: =IFERROR(INDEX(【输出】数据汇总!$A:$AZ,MATCH(横向对比!J$4&横向对比!$B20,【输出】数据汇总!$A:$A,0),MATCH(横向对比!$B$4,【输出】数据汇总!$1:$1,0)),"") -> 0.015168599 | ... BL20: =IFERROR(INDEX(【输出】数据汇总!$A:$AZ,MATCH(横向对比!BL$4&横向对比!$B20,【输出】数据汇总!$A:$A,0),MATCH(横向对比!$B$4,【输出】数据汇总!$1:$1,0)),"") -> 0.023166537
B21: 重组率 | C21: =IFERROR(INDEX(【输出】数据汇总!$A:$AZ,MATCH(横向对比!C$4&横向对比!$B21,【输出】数据汇总!$A:$A,0),MATCH(横向对比!$B$4,【输出】数据汇总!$1:$1,0)),"") -> 0.003969853 | D21: =IFERROR(INDEX(【输出】数据汇总!$A:$AZ,MATCH(横向对比!D$4&横向对比!$B21,【输出】数据汇总!$A:$A,0),MATCH(横向对比!$B$4,【输出】数据汇总!$1:$1,0)),"") -> 0.0051598449 | E21: =IFERROR(INDEX(【输出】数据汇总!$A:$AZ,MATCH(横向对比!E$4&横向对比!$B21,【输出】数据汇总!$A:$A,0),MATCH(横向对比!$B$4,【输出】数据汇总!$1:$1,0)),"") -> 0.0067544424 | F21: =IFERROR(INDEX(【输出】数据汇总!$A:$AZ,MATCH(横向对比!F$4&横向对比!$B21,【输出】数据汇总!$A:$A,0),MATCH(横向对比!$B$4,【输出】数据汇总!$1:$1,0)),"") -> 0.0010841402 | G21: =IFERROR(INDEX(【输出】数据汇总!$A:$AZ,MATCH(横向对比!G$4&横向对比!$B21,【输出】数据汇总!$A:$A,0),MATCH(横向对比!$B$4,【输出】数据汇总!$1:$1,0)),"") -> 0.0028809844 | H21: =IFERROR(INDEX(【输出】数据汇总!$A:$AZ,MATCH(横向对比!H$4&横向对比!$B21,【输出】数据汇总!$A:$A,0),MATCH(横向对比!$B$4,【输出】数据汇总!$1:$1,0)),"") | I21: =IFERROR(INDEX(【输出】数据汇总!$A:$AZ,MATCH(横向对比!I$4&横向对比!$B21,【输出】数据汇总!$A:$A,0),MATCH(横向对比!$B$4,【输出】数据汇总!$1:$1,0)),"") -> 0.010163036 | J21: =IFERROR(INDEX(【输出】数据汇总!$A:$AZ,MATCH(横向对比!J$4&横向对比!$B21,【输出】数据汇总!$A:$A,0),MATCH(横向对比!$B$4,【输出】数据汇总!$1:$1,0)),"") -> 0.0051146141 | ... BL21: =IFERROR(INDEX(【输出】数据汇总!$A:$AZ,MATCH(横向对比!BL$4&横向对比!$B21,【输出】数据汇总!$A:$A,0),MATCH(横向对比!$B$4,【输出】数据汇总!$1:$1,0)),"") -> 0.0021653017
B22: 不良贷款率 | C22: =IFERROR(INDEX(【输出】数据汇总!$A:$AZ,MATCH(横向对比!C$4&横向对比!$B22,【输出】数据汇总!$A:$A,0),MATCH(横向对比!$B$4,【输出】数据汇总!$1:$1,0)),"") -> 0.011705556 | D22: =IFERROR(INDEX(【输出】数据汇总!$A:$AZ,MATCH(横向对比!D$4&横向对比!$B22,【输出】数据汇总!$A:$A,0),MATCH(横向对比!$B$4,【输出】数据汇总!$1:$1,0)),"") -> 0.01225 | E22: =IFERROR(INDEX(【输出】数据汇总!$A:$AZ,MATCH(横向对比!E$4&横向对比!$B22,【输出】数据汇总!$A:$A,0),MATCH(横向对比!$B$4,【输出】数据汇总!$1:$1,0)),"") -> 0.012388889 | F22: =IFERROR(INDEX(【输出】数据汇总!$A:$AZ,MATCH(横向对比!F$4&横向对比!$B22,【输出】数据汇总!$A:$A,0),MATCH(横向对比!$B$4,【输出】数据汇总!$1:$1,0)),"") -> 0.012733333 | G22: =IFERROR(INDEX(【输出】数据汇总!$A:$AZ,MATCH(横向对比!G$4&横向对比!$B22,【输出】数据汇总!$A:$A,0),MATCH(横向对比!$B$4,【输出】数据汇总!$1:$1,0)),"") -> 0.00945 | H22: =IFERROR(INDEX(【输出】数据汇总!$A:$AZ,MATCH(横向对比!H$4&横向对比!$B22,【输出】数据汇总!$A:$A,0),MATCH(横向对比!$B$4,【输出】数据汇总!$1:$1,0)),"") | I22: =IFERROR(INDEX(【输出】数据汇总!$A:$AZ,MATCH(横向对比!I$4&横向对比!$B22,【输出】数据汇总!$A:$A,0),MATCH(横向对比!$B$4,【输出】数据汇总!$1:$1,0)),"") -> 0.017592308 | J22: =IFERROR(INDEX(【输出】数据汇总!$A:$AZ,MATCH(横向对比!J$4&横向对比!$B22,【输出】数据汇总!$A:$A,0),MATCH(横向对比!$B$4,【输出】数据汇总!$1:$1,0)),"") -> 0.0131 | ... BL22: =IFERROR(INDEX(【输出】数据汇总!$A:$AZ,MATCH(横向对比!BL$4&横向对比!$B22,【输出】数据汇总!$A:$A,0),MATCH(横向对比!$B$4,【输出】数据汇总!$1:$1,0)),"") -> 0.0179
B23: 关注贷款率 | C23: =IFERROR(INDEX(【输出】数据汇总!$A:$AZ,MATCH(横向对比!C$4&横向对比!$B23,【输出】数据汇总!$A:$A,0),MATCH(横向对比!$B$4,【输出】数据汇总!$1:$1,0)),"") -> 0.016283089 | D23: =IFERROR(INDEX(【输出】数据汇总!$A:$AZ,MATCH(横向对比!D$4&横向对比!$B23,【输出】数据汇总!$A:$A,0),MATCH(横向对比!$B$4,【输出】数据汇总!$1:$1,0)),"") -> 0.016333851 | E23: =IFERROR(INDEX(【输出】数据汇总!$A:$AZ,MATCH(横向对比!E$4&横向对比!$B23,【输出】数据汇总!$A:$A,0),MATCH(横向对比!$B$4,【输出】数据汇总!$1:$1,0)),"") -> 0.020224906 | F23: =IFERROR(INDEX(【输出】数据汇总!$A:$AZ,MATCH(横向对比!F$4&横向对比!$B23,【输出】数据汇总!$A:$A,0),MATCH(横向对比!$B$4,【输出】数据汇总!$1:$1,0)),"") -> 0.01506918 | G23: =IFERROR(INDEX(【输出】数据汇总!$A:$AZ,MATCH(横向对比!G$4&横向对比!$B23,【输出】数据汇总!$A:$A,0),MATCH(横向对比!$B$4,【输出】数据汇总!$1:$1,0)),"") -> 0.013504419 | H23: =IFERROR(INDEX(【输出】数据汇总!$A:$AZ,MATCH(横向对比!H$4&横向对比!$B23,【输出】数据汇总!$A:$A,0),MATCH(横向对比!$B$4,【输出】数据汇总!$1:$1,0)),"") | I23: =IFERROR(INDEX(【输出】数据汇总!$A:$AZ,MATCH(横向对比!I$4&横向对比!$B23,【输出】数据汇总!$A:$A,0),MATCH(横向对比!$B$4,【输出】数据汇总!$1:$1,0)),"") -> 0.031361884 | J23: =IFERROR(INDEX(【输出】数据汇总!$A:$AZ,MATCH(横向对比!J$4&横向对比!$B23,【输出】数据汇总!$A:$A,0),MATCH(横向对比!$B$4,【输出】数据汇总!$1:$1,0)),"") -> 0.01949301 | ... BL23: =IFERROR(INDEX(【输出】数据汇总!$A:$AZ,MATCH(横向对比!BL$4&横向对比!$B23,【输出】数据汇总!$A:$A,0),MATCH(横向对比!$B$4,【输出】数据汇总!$1:$1,0)),"") -> 0.021318769
B24: 逾期+重组率 | C24: =IFERROR(C20+C21,"") -> 0.019839203 | D24: =IFERROR(D20+D21,"") -> 0.018684553 | E24: =IFERROR(E20+E21,"") -> 0.023846209 | F24: =IFERROR(F20+F21,"") -> 0.018434193 | G24: =IFERROR(G20+G21,"") -> 0.018391857 | H24: =IFERROR(H20+H21,"") | I24: =IFERROR(I20+I21,"") -> 0.042759775 | J24: =IFERROR(J20+J21,"") -> 0.020283213 | ... BL24: =IFERROR(BL20+BL21,"") -> 0.025331839
B25: 不良+关注率 | C25: =IFERROR(C22+C23,"") -> 0.027988645 | D25: =IFERROR(D22+D23,"") -> 0.028583851 | E25: =IFERROR(E22+E23,"") -> 0.032613795 | F25: =IFERROR(F22+F23,"") -> 0.027802514 | G25: =IFERROR(G22+G23,"") -> 0.022954419 | H25: =IFERROR(H22+H23,"") | I25: =IFERROR(I22+I23,"") -> 0.048954192 | J25: =IFERROR(J22+J23,"") -> 0.03259301 | ... BL25: =IFERROR(BL22+BL23,"") -> 0.039218769
A26: ⑥/① | B26: 广义风险贷款比率 | C26: =IFERROR(INDEX(【输出】数据汇总!$A:$AZ,MATCH(横向对比!C$4&横向对比!$B26,【输出】数据汇总!$A:$A,0),MATCH(横向对比!$B$4,【输出】数据汇总!$1:$1,0)),"") -> 0.027994659 | D26: =IFERROR(INDEX(【输出】数据汇总!$A:$AZ,MATCH(横向对比!D$4&横向对比!$B26,【输出】数据汇总!$A:$A,0),MATCH(横向对比!$B$4,【输出】数据汇总!$1:$1,0)),"") -> 0.028583851 | E26: =IFERROR(INDEX(【输出】数据汇总!$A:$AZ,MATCH(横向对比!E$4&横向对比!$B26,【输出】数据汇总!$A:$A,0),MATCH(横向对比!$B$4,【输出】数据汇总!$1:$1,0)),"") -> 0.032637853 | F26: =IFERROR(INDEX(【输出】数据汇总!$A:$AZ,MATCH(横向对比!F$4&横向对比!$B26,【输出】数据汇总!$A:$A,0),MATCH(横向对比!$B$4,【输出】数据汇总!$1:$1,0)),"") -> 0.027802514 | G26: =IFERROR(INDEX(【输出】数据汇总!$A:$AZ,MATCH(横向对比!G$4&横向对比!$B26,【输出】数据汇总!$A:$A,0),MATCH(横向对比!$B$4,【输出】数据汇总!$1:$1,0)),"") -> 0.022954419 | H26: =IFERROR(INDEX(【输出】数据汇总!$A:$AZ,MATCH(横向对比!H$4&横向对比!$B26,【输出】数据汇总!$A:$A,0),MATCH(横向对比!$B$4,【输出】数据汇总!$1:$1,0)),"") | I26: =IFERROR(INDEX(【输出】数据汇总!$A:$AZ,MATCH(横向对比!I$4&横向对比!$B26,【输出】数据汇总!$A:$A,0),MATCH(横向对比!$B$4,【输出】数据汇总!$1:$1,0)),"") -> 0.059157771 | J26: =IFERROR(INDEX(【输出】数据汇总!$A:$AZ,MATCH(横向对比!J$4&横向对比!$B26,【输出】数据汇总!$A:$A,0),MATCH(横向对比!$B$4,【输出】数据汇总!$1:$1,0)),"") -> 0.03259301 | ... BL26: =IFERROR(INDEX(【输出】数据汇总!$A:$AZ,MATCH(横向对比!BL$4&横向对比!$B26,【输出】数据汇总!$A:$A,0),MATCH(横向对比!$B$4,【输出】数据汇总!$1:$1,0)),"") -> 0.039218769
B27: 广义不良资产率 | C27: =IFERROR(INDEX(【输出】数据汇总!$A:$AZ,MATCH(横向对比!C$4&横向对比!$B27,【输出】数据汇总!$A:$A,0),MATCH(横向对比!$B$4,【输出】数据汇总!$1:$1,0)),"") -> 0.020501883 | D27: =IFERROR(INDEX(【输出】数据汇总!$A:$AZ,MATCH(横向对比!D$4&横向对比!$B27,【输出】数据汇总!$A:$A,0),MATCH(横向对比!$B$4,【输出】数据汇总!$1:$1,0)),"") -> 0.018134305 | E27: =IFERROR(INDEX(【输出】数据汇总!$A:$AZ,MATCH(横向对比!E$4&横向对比!$B27,【输出】数据汇总!$A:$A,0),MATCH(横向对比!$B$4,【输出】数据汇总!$1:$1,0)),"") -> 0.024301325 | F27: =IFERROR(INDEX(【输出】数据汇总!$A:$AZ,MATCH(横向对比!F$4&横向对比!$B27,【输出】数据汇总!$A:$A,0),MATCH(横向对比!$B$4,【输出】数据汇总!$1:$1,0)),"") -> 0.024956978 | G27: =IFERROR(INDEX(【输出】数据汇总!$A:$AZ,MATCH(横向对比!G$4&横向对比!$B27,【输出】数据汇总!$A:$A,0),MATCH(横向对比!$B$4,【输出】数据汇总!$1:$1,0)),"") -> 0.014614924 | H27: =IFERROR(INDEX(【输出】数据汇总!$A:$AZ,MATCH(横向对比!H$4&横向对比!$B27,【输出】数据汇总!$A:$A,0),MATCH(横向对比!$B$4,【输出】数据汇总!$1:$1,0)),"") | I27: =IFERROR(INDEX(【输出】数据汇总!$A:$AZ,MATCH(横向对比!I$4&横向对比!$B27,【输出】数据汇总!$A:$A,0),MATCH(横向对比!$B$4,【输出】数据汇总!$1:$1,0)),"") -> 0.040573345 | J27: =IFERROR(INDEX(【输出】数据汇总!$A:$AZ,MATCH(横向对比!J$4&横向对比!$B27,【输出】数据汇总!$A:$A,0),MATCH(横向对比!$B$4,【输出】数据汇总!$1:$1,0)),"") -> 0.020277644 | ... BL27: =IFERROR(INDEX(【输出】数据汇总!$A:$AZ,MATCH(横向对比!BL$4&横向对比!$B27,【输出】数据汇总!$A:$A,0),MATCH(横向对比!$B$4,【输出】数据汇总!$1:$1,0)),"") -> 0.021182164
B28: 拨备覆盖率 | C28: =IFERROR(INDEX(【输出】数据汇总!$A:$AZ,MATCH(横向对比!C$4&横向对比!$B28,【输出】数据汇总!$A:$A,0),MATCH(横向对比!$B$4,【输出】数据汇总!$1:$1,0)),"") -> 2.5897146 | D28: =IFERROR(INDEX(【输出】数据汇总!$A:$AZ,MATCH(横向对比!D$4&横向对比!$B28,【输出】数据汇总!$A:$A,0),MATCH(横向对比!$B$4,【输出】数据汇总!$1:$1,0)),"") -> 2.2933167 | E28: =IFERROR(INDEX(【输出】数据汇总!$A:$AZ,MATCH(横向对比!E$4&横向对比!$B28,【输出】数据汇总!$A:$A,0),MATCH(横向对比!$B$4,【输出】数据汇总!$1:$1,0)),"") -> 2.0593667 | F28: =IFERROR(INDEX(【输出】数据汇总!$A:$AZ,MATCH(横向对比!F$4&横向对比!$B28,【输出】数据汇总!$A:$A,0),MATCH(横向对比!$B$4,【输出】数据汇总!$1:$1,0)),"") -> 2.4123 | G28: =IFERROR(INDEX(【输出】数据汇总!$A:$AZ,MATCH(横向对比!G$4&横向对比!$B28,【输出】数据汇总!$A:$A,0),MATCH(横向对比!$B$4,【输出】数据汇总!$1:$1,0)),"") -> 3.593875 | H28: =IFERROR(INDEX(【输出】数据汇总!$A:$AZ,MATCH(横向对比!H$4&横向对比!$B28,【输出】数据汇总!$A:$A,0),MATCH(横向对比!$B$4,【输出】数据汇总!$1:$1,0)),"") | I28: =IFERROR(INDEX(【输出】数据汇总!$A:$AZ,MATCH(横向对比!I$4&横向对比!$B28,【输出】数据汇总!$A:$A,0),MATCH(横向对比!$B$4,【输出】数据汇总!$1:$1,0)),"") -> 2.1033154 | J28: =IFERROR(INDEX(【输出】数据汇总!$A:$AZ,MATCH(横向对比!J$4&横向对比!$B28,【输出】数据汇总!$A:$A,0),MATCH(横向对比!$B$4,【输出】数据汇总!$1:$1,0)),"") -> 2.136 | ... BL28: =IFERROR(INDEX(【输出】数据汇总!$A:$AZ,MATCH(横向对比!BL$4&横向对比!$B28,【输出】数据汇总!$A:$A,0),MATCH(横向对比!$B$4,【输出】数据汇总!$1:$1,0)),"") -> 2.0768
B29: 超额拨备/归母净利润(TTM) | C29: =C17/C18 -> -0.01863019 | D29: =D17/D18 -> 0.1571079 | E29: =E17/E18 -> -0.37475971 | F29: =F17/F18 -> #VALUE! | G29: =G17/G18 -> #VALUE! | H29: =H17/H18 -> #VALUE! | I29: =I17/I18 -> -1.7925527 | J29: =IFERROR(INDEX(【输出】数据汇总!$A:$AZ,MATCH(横向对比!J$4&横向对比!$B29,【输出】数据汇总!$A:$A,0),MATCH(横向对比!$B$4,【输出】数据汇总!$1:$1,0)),"") -> -0.12911829 | K29: =IFERROR(INDEX(【输出】数据汇总!$A:$AZ,MATCH(横向对比!K$4&横向对比!$B29,【输出】数据汇总!$A:$A,0),MATCH(横向对比!$B$4,【输出】数据汇总!$1:$1,0)),"") -> 0.052445121 | L29: =IFERROR(INDEX(【输出】数据汇总!$A:$AZ,MATCH(横向对比!L$4&横向对比!$B29,【输出】数据汇总!$A:$A,0),MATCH(横向对比!$B$4,【输出】数据汇总!$1:$1,0)),"") -> 1.0776063 | M29: =IFERROR(INDEX(【输出】数据汇总!$A:$AZ,MATCH(横向对比!M$4&横向对比!$B29,【输出】数据汇总!$A:$A,0),MATCH(横向对比!$B$4,【输出】数据汇总!$1:$1,0)),"") -> -0.096310287 | N29: =IFERROR(INDEX(【输出】数据汇总!$A:$AZ,MATCH(横向对比!N$4&横向对比!$B29,【输出】数据汇总!$A:$A,0),MATCH(横向对比!$B$4,【输出】数据汇总!$1:$1,0)),"") -> -0.27094872 | O29: =IFERROR(INDEX(【输出】数据汇总!$A:$AZ,MATCH(横向对比!O$4&横向对比!$B29,【输出】数据汇总!$A:$A,0),MATCH(横向对比!$B$4,【输出】数据汇总!$1:$1,0)),"") -> -0.14999382 | P29: =IFERROR(INDEX(【输出】数据汇总!$A:$AZ,MATCH(横向对比!P$4&横向对比!$B29,【输出】数据汇总!$A:$A,0),MATCH(横向对比!$B$4,【输出】数据汇总!$1:$1,0)),"") -> 0.81879369 | Q29: =IFERROR(INDEX(【输出】数据汇总!$A:$AZ,MATCH(横向对比!Q$4&横向对比!$B29,【输出】数据汇总!$A:$A,0),MATCH(横向对比!$B$4,【输出】数据汇总!$1:$1,0)),"") -> -0.12770954 | ... BL29: =IFERROR(INDEX(【输出】数据汇总!$A:$AZ,MATCH(横向对比!BL$4&横向对比!$B29,【输出】数据汇总!$A:$A,0),MATCH(横向对比!$B$4,【输出】数据汇总!$1:$1,0)),"") -> -0.10942657
B30: 超额拨备/归母净资产 | C30: =C17/C19 -> -0.0015833041 | D30: =D17/D19 -> 0.013451455 | E30: =E17/E19 -> -0.029937332 | F30: =F17/F19 -> #VALUE! | G30: =G17/G19 -> #VALUE! | H30: =H17/H19 -> #VALUE! | I30: =I17/I19 -> -0.096618781 | J30: =IFERROR(INDEX(【输出】数据汇总!$A:$AZ,MATCH(横向对比!J$4&横向对比!$B30,【输出】数据汇总!$A:$A,0),MATCH(横向对比!$B$4,【输出】数据汇总!$1:$1,0)),"") -> -0.011212344 | K30: =IFERROR(INDEX(【输出】数据汇总!$A:$AZ,MATCH(横向对比!K$4&横向对比!$B30,【输出】数据汇总!$A:$A,0),MATCH(横向对比!$B$4,【输出】数据汇总!$1:$1,0)),"") -> 0.0048517533 | L30: =IFERROR(INDEX(【输出】数据汇总!$A:$AZ,MATCH(横向对比!L$4&横向对比!$B30,【输出】数据汇总!$A:$A,0),MATCH(横向对比!$B$4,【输出】数据汇总!$1:$1,0)),"") -> 0.096882909 | M30: =IFERROR(INDEX(【输出】数据汇总!$A:$AZ,MATCH(横向对比!M$4&横向对比!$B30,【输出】数据汇总!$A:$A,0),MATCH(横向对比!$B$4,【输出】数据汇总!$1:$1,0)),"") -> -0.0076387357 | N30: =IFERROR(INDEX(【输出】数据汇总!$A:$AZ,MATCH(横向对比!N$4&横向对比!$B30,【输出】数据汇总!$A:$A,0),MATCH(横向对比!$B$4,【输出】数据汇总!$1:$1,0)),"") -> -0.02041295 | O30: =IFERROR(INDEX(【输出】数据汇总!$A:$AZ,MATCH(横向对比!O$4&横向对比!$B30,【输出】数据汇总!$A:$A,0),MATCH(横向对比!$B$4,【输出】数据汇总!$1:$1,0)),"") -> -0.011300305 | P30: =IFERROR(INDEX(【输出】数据汇总!$A:$AZ,MATCH(横向对比!P$4&横向对比!$B30,【输出】数据汇总!$A:$A,0),MATCH(横向对比!$B$4,【输出】数据汇总!$1:$1,0)),"") -> 0.096605916 | Q30: =IFERROR(INDEX(【输出】数据汇总!$A:$AZ,MATCH(横向对比!Q$4&横向对比!$B30,【输出】数据汇总!$A:$A,0),MATCH(横向对比!$B$4,【输出】数据汇总!$1:$1,0)),"") -> -0.010971892 | ... BL30: =IFERROR(INDEX(【输出】数据汇总!$A:$AZ,MATCH(横向对比!BL$4&横向对比!$B30,【输出】数据汇总!$A:$A,0),MATCH(横向对比!$B$4,【输出】数据汇总!$1:$1,0)),"") -> -0.0069942954
B31: 归母净利润增速(TTM) | C31: =IFERROR(INDEX(【输出】数据汇总!$A:$AZ,MATCH(横向对比!C$4&横向对比!$B31,【输出】数据汇总!$A:$A,0),MATCH(横向对比!$B$4,【输出】数据汇总!$1:$1,0)),"") -> -0.0013858927 | D31: =IFERROR(INDEX(【输出】数据汇总!$A:$AZ,MATCH(横向对比!D$4&横向对比!$B31,【输出】数据汇总!$A:$A,0),MATCH(横向对比!$B$4,【输出】数据汇总!$1:$1,0)),"") -> 0.017214133 | E31: =IFERROR(INDEX(【输出】数据汇总!$A:$AZ,MATCH(横向对比!E$4&横向对比!$B31,【输出】数据汇总!$A:$A,0),MATCH(横向对比!$B$4,【输出】数据汇总!$1:$1,0)),"") -> -0.019985919 | F31: =IFERROR(INDEX(【输出】数据汇总!$A:$AZ,MATCH(横向对比!F$4&横向对比!$B31,【输出】数据汇总!$A:$A,0),MATCH(横向对比!$B$4,【输出】数据汇总!$1:$1,0)),"") | G31: =IFERROR(INDEX(【输出】数据汇总!$A:$AZ,MATCH(横向对比!G$4&横向对比!$B31,【输出】数据汇总!$A:$A,0),MATCH(横向对比!$B$4,【输出】数据汇总!$1:$1,0)),"") | H31: =IFERROR(INDEX(【输出】数据汇总!$A:$AZ,MATCH(横向对比!H$4&横向对比!$B31,【输出】数据汇总!$A:$A,0),MATCH(横向对比!$B$4,【输出】数据汇总!$1:$1,0)),"") | I31: =IFERROR(INDEX(【输出】数据汇总!$A:$AZ,MATCH(横向对比!I$4&横向对比!$B31,【输出】数据汇总!$A:$A,0),MATCH(横向对比!$B$4,【输出】数据汇总!$1:$1,0)),"") -> 0.042303814 | J31: =IFERROR(INDEX(【输出】数据汇总!$A:$AZ,MATCH(横向对比!J$4&横向对比!$B31,【输出】数据汇总!$A:$A,0),MATCH(横向对比!$B$4,【输出】数据汇总!$1:$1,0)),"") -> 0.0073770783 | ... BL31: =IFERROR(INDEX(【输出】数据汇总!$A:$AZ,MATCH(横向对比!BL$4&横向对比!$B31,【输出】数据汇总!$A:$A,0),MATCH(横向对比!$B$4,【输出】数据汇总!$1:$1,0)),"") -> -0.16665953
B34: 45838 | C34: 上市银行 | D34: 国有行 | E34: 股份行 | F34: 城商行 | G34: 农商行 | H34: AH股 | I34: 纯H股 | J34: 国有1 | K34: 国有2 | L34: 国有3 | M34: 国有4 | N34: 国有5 | O34: 国有6 | P34: 股份1 | Q34: 股份2 | R34: 股份3 | S34: 股份4 | T34: 股份5 | U34: 股份6 | V34: 股份7 | W34: 股份8 | X34: 股份9 | Y34: 城商1 | Z34: 城商2 | AA34: 城商3 | AB34: 城商4 | AC34: 城商5 | AD34: 城商6 | AE34: 城商7 | AF34: 城商8 | AG34: 城商9 | AH34: 城商10 | AI34: 城商11 | AJ34: 城商12 | AK34: 城商13 | AL34: 城商14 | AM34: 城商15 | AN34: 城商16 | AO34: 城商17 | AP34: 农商1 | AQ34: 农商2 | AR34: 农商3 | AS34: 农商4 | AT34: 农商5 | AU34: 农商6 | AV34: 农商7 | AW34: 农商8 | AX34: 农商9 | AY34: 农商10 | AZ34: =AZ2 -> 纯H股1 | BA34: =BA2 -> 纯H股2 | BB34: =BB2 -> 纯H股3 | BC34: =BC2 -> 纯H股4 | BD34: =BD2 -> 纯H股5 | BE34: =BE2 -> 纯H股6 | BF34: =BF2 -> 纯H股7 | BG34: =BG2 -> 纯H股8 | ... BL34: =BL2 -> 纯H股13
B35: 单位：亿元 | J35: 1国有 | K35: 1国有 | L35: 1国有 | M35: 1国有 | N35: 1国有 | O35: 1国有 | P35: 2股份 | Q35: 2股份 | R35: 2股份 | S35: 2股份 | T35: 2股份 | U35: 2股份 | V35: 2股份 | W35: 2股份 | X35: 2股份 | Y35: 3城商 | Z35: 3城商 | AA35: 3城商 | AB35: 3城商 | AC35: 3城商 | AD35: 3城商 | AE35: 3城商 | AF35: 3城商 | AG35: 3城商 | AH35: 3城商 | AI35: 3城商 | AJ35: 3城商 | AK35: 3城商 | AL35: 3城商 | AM35: 3城商 | AN35: 3城商 | AO35: 3城商 | AP35: 4农商 | AQ35: 4农商 | AR35: 4农商 | AS35: 4农商 | AT35: 4农商 | AU35: 4农商 | AV35: 4农商 | AW35: 4农商 | AX35: 4农商 | AY35: 4农商
B36: =B34 -> 45838 | C36: 上市银行 | D36: 国有行 | E36: 股份行 | F36: 城商行 | G36: 农商行 | H36: =H34 -> AH股 | I36: =I34 -> 纯H股 | J36: 工商 | K36: 建设 | L36: 农业 | M36: 中国 | N36: 邮储 | O36: 交通 | P36: 招商 | Q36: 兴业 | R36: 浦发 | S36: 中信 | T36: 民生 | U36: 光大 | V36: 平安 | W36: 华夏 | X36: 浙商 | Y36: 北京 | Z36: 江苏 | AA36: 上海 | AB36: 宁波 | AC36: 南京 | AD36: 杭州 | AE36: 成都 | AF36: 长沙 | AG36: 重庆 | AH36: 贵阳 | AI36: 郑州 | AJ36: 苏州 | AK36: 青岛 | AL36: 齐鲁 | AM36: 兰州 | AN36: 西安 | AO36: 厦门 | AP36: 渝农 | AQ36: 沪农 | AR36: 青农 | AS36: 常熟 | AT36: 紫金 | AU36: 无锡 | AV36: 张家港 | AW36: 苏农 | AX36: 瑞丰 | AY36: 江阴 | AZ36: 中原 | BA36: 广州农商 | BB36: 天津 | BC36: 江西 | BD36: 泸州 | BE36: 甘肃 | BF36: 晋商 | BG36: 徽商 | BH36: 哈尔滨 | BI36: 贵州 | BJ36: 渤海 | BK36: 威海 | BL36: 东莞农商
A37: ① | B37: 贷款总额 | C37: =IFERROR(INDEX(【输出】数据汇总!$A:$AZ,MATCH(横向对比!C$4&横向对比!$B37,【输出】数据汇总!$A:$A,0),MATCH(横向对比!$B$36,【输出】数据汇总!$1:$1,0))/100,"") -> 1844280.6 | D37: =IFERROR(INDEX(【输出】数据汇总!$A:$AZ,MATCH(横向对比!D$4&横向对比!$B37,【输出】数据汇总!$A:$A,0),MATCH(横向对比!$B$36,【输出】数据汇总!$1:$1,0))/100,"") -> 1258479.1 | E37: =IFERROR(INDEX(【输出】数据汇总!$A:$AZ,MATCH(横向对比!E$4&横向对比!$B37,【输出】数据汇总!$A:$A,0),MATCH(横向对比!$B$36,【输出】数据汇总!$1:$1,0))/100,"") -> 407161.05 | F37: =IFERROR(INDEX(【输出】数据汇总!$A:$AZ,MATCH(横向对比!F$4&横向对比!$B37,【输出】数据汇总!$A:$A,0),MATCH(横向对比!$B$36,【输出】数据汇总!$1:$1,0))/100,"") -> 148935.56 | G37: =IFERROR(INDEX(【输出】数据汇总!$A:$AZ,MATCH(横向对比!G$4&横向对比!$B37,【输出】数据汇总!$A:$A,0),MATCH(横向对比!$B$36,【输出】数据汇总!$1:$1,0))/100,"") -> 29704.89 | H37: =IFERROR(INDEX(【输出】数据汇总!$A:$AZ,MATCH(横向对比!H$4&横向对比!$B37,【输出】数据汇总!$A:$A,0),MATCH(横向对比!$B$36,【输出】数据汇总!$1:$1,0))/100,"") | I37: =IFERROR(INDEX(【输出】数据汇总!$A:$AZ,MATCH(横向对比!I$4&横向对比!$B37,【输出】数据汇总!$A:$A,0),MATCH(横向对比!$B$36,【输出】数据汇总!$1:$1,0))/100,"") -> 62830.955 | J37: =IFERROR(INDEX(【输出】数据汇总!$A:$AZ,MATCH(横向对比!J$4&横向对比!$B37,【输出】数据汇总!$A:$A,0),MATCH(横向对比!$B$36,【输出】数据汇总!$1:$1,0))/100,"") -> 301856.59 | ... AA37: =IFERROR(INDEX(【输出】数据汇总!$A:$AZ,MATCH(横向对比!AA$4&横向对比!$B37,【输出】数据汇总!$A:$A,0),MATCH(横向对比!$B$36,【输出】数据汇总!$1:$1,0))/100,"") -> 14369.837 | AB37: =IFERROR(INDEX(【输出】数据汇总!$A:$AZ,MATCH(横向对比!AB$36&横向对比!$B37,【输出】数据汇总!$A:$A,0),MATCH(横向对比!$B$36,【输出】数据汇总!$1:$1,0))/100,"") -> 16732.13 | AC37: =IFERROR(INDEX(【输出】数据汇总!$A:$AZ,MATCH(横向对比!AC$4&横向对比!$B37,【输出】数据汇总!$A:$A,0),MATCH(横向对比!$B$36,【输出】数据汇总!$1:$1,0))/100,"") -> 13871.734 | AD37: =IFERROR(INDEX(【输出】数据汇总!$A:$AZ,MATCH(横向对比!AD$4&横向对比!$B37,【输出】数据汇总!$A:$A,0),MATCH(横向对比!$B$36,【输出】数据汇总!$1:$1,0))/100,"") -> 10094.182 | AE37: =IFERROR(INDEX(【输出】数据汇总!$A:$AZ,MATCH(横向对比!AE$4&横向对比!$B37,【输出】数据汇总!$A:$A,0),MATCH(横向对比!$B$36,【输出】数据汇总!$1:$1,0))/100,"") -> 8334.1516 | AF37: =IFERROR(INDEX(【输出】数据汇总!$A:$AZ,MATCH(横向对比!AF$4&横向对比!$B37,【输出】数据汇总!$A:$A,0),MATCH(横向对比!$B$36,【输出】数据汇总!$1:$1,0))/100,"") -> 6026.9159 | AG37: =IFERROR(INDEX(【输出】数据汇总!$A:$AZ,MATCH(横向对比!AG$4&横向对比!$B37,【输出】数据汇总!$A:$A,0),MATCH(横向对比!$B$36,【输出】数据汇总!$1:$1,0))/100,"") -> 4986.4508 | AH37: =IFERROR(INDEX(【输出】数据汇总!$A:$AZ,MATCH(横向对比!AH$4&横向对比!$B37,【输出】数据汇总!$A:$A,0),MATCH(横向对比!$B$36,【输出】数据汇总!$1:$1,0))/100,"") -> 3434.6104 | AI37: =IFERROR(INDEX(【输出】数据汇总!$A:$AZ,MATCH(横向对比!AI$4&横向对比!$B37,【输出】数据汇总!$A:$A,0),MATCH(横向对比!$B$36,【输出】数据汇总!$1:$1,0))/100,"") -> 4060.9446 | AJ37: =IFERROR(INDEX(【输出】数据汇总!$A:$AZ,MATCH(横向对比!AJ$4&横向对比!$B37,【输出】数据汇总!$A:$A,0),MATCH(横向对比!$B$36,【输出】数据汇总!$1:$1,0))/100,"") -> 3634.9715 | ... BA37: =IFERROR(INDEX(【输出】数据汇总!$A:$AZ,MATCH(横向对比!BA$4&横向对比!$B37,【输出】数据汇总!$A:$A,0),MATCH(横向对比!$B$36,【输出】数据汇总!$1:$1,0))/100,"") -> 7173.4444 | BB37: =IFERROR(INDEX(【输出】数据汇总!$A:$AZ,MATCH(横向对比!BB$36&横向对比!$B37,【输出】数据汇总!$A:$A,0),MATCH(横向对比!$B$36,【输出】数据汇总!$1:$1,0))/100,"") -> 4849.6898 | BC37: =IFERROR(INDEX(【输出】数据汇总!$A:$AZ,MATCH(横向对比!BC$4&横向对比!$B37,【输出】数据汇总!$A:$A,0),MATCH(横向对比!$B$36,【输出】数据汇总!$1:$1,0))/100,"") -> 3649.0307 | BD37: =IFERROR(INDEX(【输出】数据汇总!$A:$AZ,MATCH(横向对比!BD$4&横向对比!$B37,【输出】数据汇总!$A:$A,0),MATCH(横向对比!$B$36,【输出】数据汇总!$1:$1,0))/100,"") -> 1168.2949 | BE37: =IFERROR(INDEX(【输出】数据汇总!$A:$AZ,MATCH(横向对比!BE$4&横向对比!$B37,【输出】数据汇总!$A:$A,0),MATCH(横向对比!$B$36,【输出】数据汇总!$1:$1,0))/100,"") -> 2348.2905 | BF37: =IFERROR(INDEX(【输出】数据汇总!$A:$AZ,MATCH(横向对比!BF$4&横向对比!$B37,【输出】数据汇总!$A:$A,0),MATCH(横向对比!$B$36,【输出】数据汇总!$1:$1,0))/100,"") -> 2086.3832 | BG37: =IFERROR(INDEX(【输出】数据汇总!$A:$AZ,MATCH(横向对比!BG$4&横向对比!$B37,【输出】数据汇总!$A:$A,0),MATCH(横向对比!$B$36,【输出】数据汇总!$1:$1,0))/100,"") -> 11005.329 | BH37: =IFERROR(INDEX(【输出】数据汇总!$A:$AZ,MATCH(横向对比!BH$4&横向对比!$B37,【输出】数据汇总!$A:$A,0),MATCH(横向对比!$B$36,【输出】数据汇总!$1:$1,0))/100,"") -> 3975.6626 | BI37: =IFERROR(INDEX(【输出】数据汇总!$A:$AZ,MATCH(横向对比!BI$4&横向对比!$B37,【输出】数据汇总!$A:$A,0),MATCH(横向对比!$B$36,【输出】数据汇总!$1:$1,0))/100,"") -> 3643.4705 | BJ37: =IFERROR(INDEX(【输出】数据汇总!$A:$AZ,MATCH(横向对比!BJ$4&横向对比!$B37,【输出】数据汇总!$A:$A,0),MATCH(横向对比!$B$36,【输出】数据汇总!$1:$1,0))/100,"") -> 9544.2198 | ... BL37: =IFERROR(INDEX(【输出】数据汇总!$A:$AZ,MATCH(横向对比!BL$4&横向对比!$B37,【输出】数据汇总!$A:$A,0),MATCH(横向对比!$B$36,【输出】数据汇总!$1:$1,0))/100,"") -> 3944.1518
A38: ② | B38: 逾期贷款余额 | C38: =IFERROR(INDEX(【输出】数据汇总!$A:$AZ,MATCH(横向对比!C$4&横向对比!$B38,【输出】数据汇总!$A:$A,0),MATCH(横向对比!$B$36,【输出】数据汇总!$1:$1,0))/100,"") -> 26533.771 | D38: =IFERROR(INDEX(【输出】数据汇总!$A:$AZ,MATCH(横向对比!D$4&横向对比!$B38,【输出】数据汇总!$A:$A,0),MATCH(横向对比!$B$36,【输出】数据汇总!$1:$1,0))/100,"") -> 16945.3 | E38: =IFERROR(INDEX(【输出】数据汇总!$A:$AZ,MATCH(横向对比!E$4&横向对比!$B38,【输出】数据汇总!$A:$A,0),MATCH(横向对比!$B$36,【输出】数据汇总!$1:$1,0))/100,"") -> 6959.76 | F38: =IFERROR(INDEX(【输出】数据汇总!$A:$AZ,MATCH(横向对比!F$4&横向对比!$B38,【输出】数据汇总!$A:$A,0),MATCH(横向对比!$B$36,【输出】数据汇总!$1:$1,0))/100,"") -> 2169.1632 | G38: =IFERROR(INDEX(【输出】数据汇总!$A:$AZ,MATCH(横向对比!G$4&横向对比!$B38,【输出】数据汇总!$A:$A,0),MATCH(横向对比!$B$36,【输出】数据汇总!$1:$1,0))/100,"") -> 459.54783 | H38: =IFERROR(INDEX(【输出】数据汇总!$A:$AZ,MATCH(横向对比!H$4&横向对比!$B38,【输出】数据汇总!$A:$A,0),MATCH(横向对比!$B$36,【输出】数据汇总!$1:$1,0))/100,"") | I38: =IFERROR(INDEX(【输出】数据汇总!$A:$AZ,MATCH(横向对比!I$4&横向对比!$B38,【输出】数据汇总!$A:$A,0),MATCH(横向对比!$B$36,【输出】数据汇总!$1:$1,0))/100,"") -> 2356.8758 | J38: =IFERROR(INDEX(【输出】数据汇总!$A:$AZ,MATCH(横向对比!J$4&横向对比!$B38,【输出】数据汇总!$A:$A,0),MATCH(横向对比!$B$36,【输出】数据汇总!$1:$1,0))/100,"") -> 4590 | ... AA38: =IFERROR(INDEX(【输出】数据汇总!$A:$AZ,MATCH(横向对比!AA$4&横向对比!$B38,【输出】数据汇总!$A:$A,0),MATCH(横向对比!$B$36,【输出】数据汇总!$1:$1,0))/100,"") -> 229.32856 | AB38: =IFERROR(INDEX(【输出】数据汇总!$A:$AZ,MATCH(横向对比!AB$36&横向对比!$B38,【输出】数据汇总!$A:$A,0),MATCH(横向对比!$B$36,【输出】数据汇总!$1:$1,0))/100,"") -> 148.22 | AC38: =IFERROR(INDEX(【输出】数据汇总!$A:$AZ,MATCH(横向对比!AC$4&横向对比!$B38,【输出】数据汇总!$A:$A,0),MATCH(横向对比!$B$36,【输出】数据汇总!$1:$1,0))/100,"") -> 176.06707 | AD38: =IFERROR(INDEX(【输出】数据汇总!$A:$AZ,MATCH(横向对比!AD$4&横向对比!$B38,【输出】数据汇总!$A:$A,0),MATCH(横向对比!$B$36,【输出】数据汇总!$1:$1,0))/100,"") -> 61.22921 | AE38: =IFERROR(INDEX(【输出】数据汇总!$A:$AZ,MATCH(横向对比!AE$4&横向对比!$B38,【输出】数据汇总!$A:$A,0),MATCH(横向对比!$B$36,【输出】数据汇总!$1:$1,0))/100,"") -> 64.01745 | AF38: =IFERROR(INDEX(【输出】数据汇总!$A:$AZ,MATCH(横向对比!AF$4&横向对比!$B38,【输出】数据汇总!$A:$A,0),MATCH(横向对比!$B$36,【输出】数据汇总!$1:$1,0))/100,"") -> 134.04604 | AG38: =IFERROR(INDEX(【输出】数据汇总!$A:$AZ,MATCH(横向对比!AG$4&横向对比!$B38,【输出】数据汇总!$A:$A,0),MATCH(横向对比!$B$36,【输出】数据汇总!$1:$1,0))/100,"") -> 78.57164 | AH38: =IFERROR(INDEX(【输出】数据汇总!$A:$AZ,MATCH(横向对比!AH$4&横向对比!$B38,【输出】数据汇总!$A:$A,0),MATCH(横向对比!$B$36,【输出】数据汇总!$1:$1,0))/100,"") -> 97.28655 | AI38: =IFERROR(INDEX(【输出】数据汇总!$A:$AZ,MATCH(横向对比!AI$4&横向对比!$B38,【输出】数据汇总!$A:$A,0),MATCH(横向对比!$B$36,【输出】数据汇总!$1:$1,0))/100,"") -> 210.88098 | AJ38: =IFERROR(INDEX(【输出】数据汇总!$A:$AZ,MATCH(横向对比!AJ$4&横向对比!$B38,【输出】数据汇总!$A:$A,0),MATCH(横向对比!$B$36,【输出】数据汇总!$1:$1,0))/100,"") -> 35.90612 | ... BA38: =IFERROR(INDEX(【输出】数据汇总!$A:$AZ,MATCH(横向对比!BA$4&横向对比!$B38,【输出】数据汇总!$A:$A,0),MATCH(横向对比!$B$36,【输出】数据汇总!$1:$1,0))/100,"") -> 510.93051 | BB38: =IFERROR(INDEX(【输出】数据汇总!$A:$AZ,MATCH(横向对比!BB$36&横向对比!$B38,【输出】数据汇总!$A:$A,0),MATCH(横向对比!$B$36,【输出】数据汇总!$1:$1,0))/100,"") -> 128.33317 | BC38: =IFERROR(INDEX(【输出】数据汇总!$A:$AZ,MATCH(横向对比!BC$4&横向对比!$B38,【输出】数据汇总!$A:$A,0),MATCH(横向对比!$B$36,【输出】数据汇总!$1:$1,0))/100,"") -> 131.70501 | BD38: =IFERROR(INDEX(【输出】数据汇总!$A:$AZ,MATCH(横向对比!BD$4&横向对比!$B38,【输出】数据汇总!$A:$A,0),MATCH(横向对比!$B$36,【输出】数据汇总!$1:$1,0))/100,"") -> 17.88028 | BE38: =IFERROR(INDEX(【输出】数据汇总!$A:$AZ,MATCH(横向对比!BE$4&横向对比!$B38,【输出】数据汇总!$A:$A,0),MATCH(横向对比!$B$36,【输出】数据汇总!$1:$1,0))/100,"") -> 61.335 | BF38: =IFERROR(INDEX(【输出】数据汇总!$A:$AZ,MATCH(横向对比!BF$4&横向对比!$B38,【输出】数据汇总!$A:$A,0),MATCH(横向对比!$B$36,【输出】数据汇总!$1:$1,0))/100,"") -> 42.40352 | BG38: =IFERROR(INDEX(【输出】数据汇总!$A:$AZ,MATCH(横向对比!BG$4&横向对比!$B38,【输出】数据汇总!$A:$A,0),MATCH(横向对比!$B$36,【输出】数据汇总!$1:$1,0))/100,"") -> 133.46406 | BH38: =IFERROR(INDEX(【输出】数据汇总!$A:$AZ,MATCH(横向对比!BH$4&横向对比!$B38,【输出】数据汇总!$A:$A,0),MATCH(横向对比!$B$36,【输出】数据汇总!$1:$1,0))/100,"") -> 516.41793 | BI38: =IFERROR(INDEX(【输出】数据汇总!$A:$AZ,MATCH(横向对比!BI$4&横向对比!$B38,【输出】数据汇总!$A:$A,0),MATCH(横向对比!$B$36,【输出】数据汇总!$1:$1,0))/100,"") -> 101.22117 | BJ38: =IFERROR(INDEX(【输出】数据汇总!$A:$AZ,MATCH(横向对比!BJ$4&横向对比!$B38,【输出】数据汇总!$A:$A,0),MATCH(横向对比!$B$36,【输出】数据汇总!$1:$1,0))/100,"") -> 291.61037 | ... BL38: =IFERROR(INDEX(【输出】数据汇总!$A:$AZ,MATCH(横向对比!BL$4&横向对比!$B38,【输出】数据汇总!$A:$A,0),MATCH(横向对比!$B$36,【输出】数据汇总!$1:$1,0))/100,"") -> 94.75837
A39: ③ | B39: 重组贷款余额 | C39: =IFERROR(INDEX(【输出】数据汇总!$A:$AZ,MATCH(横向对比!C$4&横向对比!$B39,【输出】数据汇总!$A:$A,0),MATCH(横向对比!$B$36,【输出】数据汇总!$1:$1,0))/100,"") -> 9233.5316 | D39: =IFERROR(INDEX(【输出】数据汇总!$A:$AZ,MATCH(横向对比!D$4&横向对比!$B39,【输出】数据汇总!$A:$A,0),MATCH(横向对比!$B$36,【输出】数据汇总!$1:$1,0))/100,"") -> 5968.76 | E39: =IFERROR(INDEX(【输出】数据汇总!$A:$AZ,MATCH(横向对比!E$4&横向对比!$B39,【输出】数据汇总!$A:$A,0),MATCH(横向对比!$B$36,【输出】数据汇总!$1:$1,0))/100,"") -> 2417.65 | F39: =IFERROR(INDEX(【输出】数据汇总!$A:$AZ,MATCH(横向对比!F$4&横向对比!$B39,【输出】数据汇总!$A:$A,0),MATCH(横向对比!$B$36,【输出】数据汇总!$1:$1,0))/100,"") -> 654.5717 | G39: =IFERROR(INDEX(【输出】数据汇总!$A:$AZ,MATCH(横向对比!G$4&横向对比!$B39,【输出】数据汇总!$A:$A,0),MATCH(横向对比!$B$36,【输出】数据汇总!$1:$1,0))/100,"") -> 192.54987 | H39: =IFERROR(INDEX(【输出】数据汇总!$A:$AZ,MATCH(横向对比!H$4&横向对比!$B39,【输出】数据汇总!$A:$A,0),MATCH(横向对比!$B$36,【输出】数据汇总!$1:$1,0))/100,"") | I39: =IFERROR(INDEX(【输出】数据汇总!$A:$AZ,MATCH(横向对比!I$4&横向对比!$B39,【输出】数据汇总!$A:$A,0),MATCH(横向对比!$B$36,【输出】数据汇总!$1:$1,0))/100,"") -> 712.55198 | J39: =IFERROR(INDEX(【输出】数据汇总!$A:$AZ,MATCH(横向对比!J$4&横向对比!$B39,【输出】数据汇总!$A:$A,0),MATCH(横向对比!$B$36,【输出】数据汇总!$1:$1,0))/100,"") -> 1409.62 | ... AA39: =IFERROR(INDEX(【输出】数据汇总!$A:$AZ,MATCH(横向对比!AA$4&横向对比!$B39,【输出】数据汇总!$A:$A,0),MATCH(横向对比!$B$36,【输出】数据汇总!$1:$1,0))/100,"") -> 48.43716 | AB39: =IFERROR(INDEX(【输出】数据汇总!$A:$AZ,MATCH(横向对比!AB$36&横向对比!$B39,【输出】数据汇总!$A:$A,0),MATCH(横向对比!$B$36,【输出】数据汇总!$1:$1,0))/100,"") -> 39.44 | AC39: =IFERROR(INDEX(【输出】数据汇总!$A:$AZ,MATCH(横向对比!AC$4&横向对比!$B39,【输出】数据汇总!$A:$A,0),MATCH(横向对比!$B$36,【输出】数据汇总!$1:$1,0))/100,"") -> 82.38927 | AD39: =IFERROR(INDEX(【输出】数据汇总!$A:$AZ,MATCH(横向对比!AD$4&横向对比!$B39,【输出】数据汇总!$A:$A,0),MATCH(横向对比!$B$36,【输出】数据汇总!$1:$1,0))/100,"") -> 25.63984 | AE39: =IFERROR(INDEX(【输出】数据汇总!$A:$AZ,MATCH(横向对比!AE$4&横向对比!$B39,【输出】数据汇总!$A:$A,0),MATCH(横向对比!$B$36,【输出】数据汇总!$1:$1,0))/100,"") -> 19.44866 | AF39: =IFERROR(INDEX(【输出】数据汇总!$A:$AZ,MATCH(横向对比!AF$4&横向对比!$B39,【输出】数据汇总!$A:$A,0),MATCH(横向对比!$B$36,【输出】数据汇总!$1:$1,0))/100,"") -> 36.49396 | AG39: =IFERROR(INDEX(【输出】数据汇总!$A:$AZ,MATCH(横向对比!AG$4&横向对比!$B39,【输出】数据汇总!$A:$A,0),MATCH(横向对比!$B$36,【输出】数据汇总!$1:$1,0))/100,"") -> 10.04388 | AH39: =IFERROR(INDEX(【输出】数据汇总!$A:$AZ,MATCH(横向对比!AH$4&横向对比!$B39,【输出】数据汇总!$A:$A,0),MATCH(横向对比!$B$36,【输出】数据汇总!$1:$1,0))/100,"") -> 45.40678 | AI39: =IFERROR(INDEX(【输出】数据汇总!$A:$AZ,MATCH(横向对比!AI$4&横向对比!$B39,【输出】数据汇总!$A:$A,0),MATCH(横向对比!$B$36,【输出】数据汇总!$1:$1,0))/100,"") | AJ39: =IFERROR(INDEX(【输出】数据汇总!$A:$AZ,MATCH(横向对比!AJ$4&横向对比!$B39,【输出】数据汇总!$A:$A,0),MATCH(横向对比!$B$36,【输出】数据汇总!$1:$1,0))/100,"") -> 17.01193 | ... BA39: =IFERROR(INDEX(【输出】数据汇总!$A:$AZ,MATCH(横向对比!BA$4&横向对比!$B39,【输出】数据汇总!$A:$A,0),MATCH(横向对比!$B$36,【输出】数据汇总!$1:$1,0))/100,"") -> 336.81 | BB39: =IFERROR(INDEX(【输出】数据汇总!$A:$AZ,MATCH(横向对比!BB$36&横向对比!$B39,【输出】数据汇总!$A:$A,0),MATCH(横向对比!$B$36,【输出】数据汇总!$1:$1,0))/100,"") -> 0 | BC39: =IFERROR(INDEX(【输出】数据汇总!$A:$AZ,MATCH(横向对比!BC$4&横向对比!$B39,【输出】数据汇总!$A:$A,0),MATCH(横向对比!$B$36,【输出】数据汇总!$1:$1,0))/100,"") -> 0 | BD39: =IFERROR(INDEX(【输出】数据汇总!$A:$AZ,MATCH(横向对比!BD$4&横向对比!$B39,【输出】数据汇总!$A:$A,0),MATCH(横向对比!$B$36,【输出】数据汇总!$1:$1,0))/100,"") -> 3.41036 | BE39: =IFERROR(INDEX(【输出】数据汇总!$A:$AZ,MATCH(横向对比!BE$4&横向对比!$B39,【输出】数据汇总!$A:$A,0),MATCH(横向对比!$B$36,【输出】数据汇总!$1:$1,0))/100,"") -> 0 | BF39: =IFERROR(INDEX(【输出】数据汇总!$A:$AZ,MATCH(横向对比!BF$4&横向对比!$B39,【输出】数据汇总!$A:$A,0),MATCH(横向对比!$B$36,【输出】数据汇总!$1:$1,0))/100,"") -> 0 | BG39: =IFERROR(INDEX(【输出】数据汇总!$A:$AZ,MATCH(横向对比!BG$4&横向对比!$B39,【输出】数据汇总!$A:$A,0),MATCH(横向对比!$B$36,【输出】数据汇总!$1:$1,0))/100,"") -> 34.37 | BH39: =IFERROR(INDEX(【输出】数据汇总!$A:$AZ,MATCH(横向对比!BH$4&横向对比!$B39,【输出】数据汇总!$A:$A,0),MATCH(横向对比!$B$36,【输出】数据汇总!$1:$1,0))/100,"") -> 277.98 | BI39: =IFERROR(INDEX(【输出】数据汇总!$A:$AZ,MATCH(横向对比!BI$4&横向对比!$B39,【输出】数据汇总!$A:$A,0),MATCH(横向对比!$B$36,【输出】数据汇总!$1:$1,0))/100,"") -> 33.9851 | BJ39: =IFERROR(INDEX(【输出】数据汇总!$A:$AZ,MATCH(横向对比!BJ$4&横向对比!$B39,【输出】数据汇总!$A:$A,0),MATCH(横向对比!$B$36,【输出】数据汇总!$1:$1,0))/100,"") -> 17.139756 | ... BL39: =IFERROR(INDEX(【输出】数据汇总!$A:$AZ,MATCH(横向对比!BL$4&横向对比!$B39,【输出】数据汇总!$A:$A,0),MATCH(横向对比!$B$36,【输出】数据汇总!$1:$1,0))/100,"") -> 8.85676
A40: ④ | B40: 不良贷款余额 | C40: =IFERROR(INDEX(【输出】数据汇总!$A:$AZ,MATCH(横向对比!C$4&横向对比!$B40,【输出】数据汇总!$A:$A,0),MATCH(横向对比!$B$36,【输出】数据汇总!$1:$1,0))/100,"") -> 22664.333 | D40: =IFERROR(INDEX(【输出】数据汇总!$A:$AZ,MATCH(横向对比!D$4&横向对比!$B40,【输出】数据汇总!$A:$A,0),MATCH(横向对比!$B$36,【输出】数据汇总!$1:$1,0))/100,"") -> 15927.35 | E40: =IFERROR(INDEX(【输出】数据汇总!$A:$AZ,MATCH(横向对比!E$4&横向对比!$B40,【输出】数据汇总!$A:$A,0),MATCH(横向对比!$B$36,【输出】数据汇总!$1:$1,0))/100,"") -> 4877.2 | F40: =IFERROR(INDEX(【输出】数据汇总!$A:$AZ,MATCH(横向对比!F$4&横向对比!$B40,【输出】数据汇总!$A:$A,0),MATCH(横向对比!$B$36,【输出】数据汇总!$1:$1,0))/100,"") -> 1541.0244 | G40: =IFERROR(INDEX(【输出】数据汇总!$A:$AZ,MATCH(横向对比!G$4&横向对比!$B40,【输出】数据汇总!$A:$A,0),MATCH(横向对比!$B$36,【输出】数据汇总!$1:$1,0))/100,"") -> 318.75834 | H40: =IFERROR(INDEX(【输出】数据汇总!$A:$AZ,MATCH(横向对比!H$4&横向对比!$B40,【输出】数据汇总!$A:$A,0),MATCH(横向对比!$B$36,【输出】数据汇总!$1:$1,0))/100,"") | I40: =IFERROR(INDEX(【输出】数据汇总!$A:$AZ,MATCH(横向对比!I$4&横向对比!$B40,【输出】数据汇总!$A:$A,0),MATCH(横向对比!$B$36,【输出】数据汇总!$1:$1,0))/100,"") -> 1107.817 | J40: =IFERROR(INDEX(【输出】数据汇总!$A:$AZ,MATCH(横向对比!J$4&横向对比!$B40,【输出】数据汇总!$A:$A,0),MATCH(横向对比!$B$36,【输出】数据汇总!$1:$1,0))/100,"") -> 4001.05 | ... AA40: =IFERROR(INDEX(【输出】数据汇总!$A:$AZ,MATCH(横向对比!AA$4&横向对比!$B40,【输出】数据汇总!$A:$A,0),MATCH(横向对比!$B$36,【输出】数据汇总!$1:$1,0))/100,"") -> 169.3945 | AB40: =IFERROR(INDEX(【输出】数据汇总!$A:$AZ,MATCH(横向对比!AB$36&横向对比!$B40,【输出】数据汇总!$A:$A,0),MATCH(横向对比!$B$36,【输出】数据汇总!$1:$1,0))/100,"") -> 126.88 | AC40: =IFERROR(INDEX(【输出】数据汇总!$A:$AZ,MATCH(横向对比!AC$4&横向对比!$B40,【输出】数据汇总!$A:$A,0),MATCH(横向对比!$B$36,【输出】数据汇总!$1:$1,0))/100,"") -> 115.93837 | AD40: =IFERROR(INDEX(【输出】数据汇总!$A:$AZ,MATCH(横向对比!AD$4&横向对比!$B40,【输出】数据汇总!$A:$A,0),MATCH(横向对比!$B$36,【输出】数据汇总!$1:$1,0))/100,"") -> 76.59031 | AE40: =IFERROR(INDEX(【输出】数据汇总!$A:$AZ,MATCH(横向对比!AE$4&横向对比!$B40,【输出】数据汇总!$A:$A,0),MATCH(横向对比!$B$36,【输出】数据汇总!$1:$1,0))/100,"") -> 54.80575 | AF40: =IFERROR(INDEX(【输出】数据汇总!$A:$AZ,MATCH(横向对比!AF$4&横向对比!$B40,【输出】数据汇总!$A:$A,0),MATCH(横向对比!$B$36,【输出】数据汇总!$1:$1,0))/100,"") -> 70.46426 | AG40: =IFERROR(INDEX(【输出】数据汇总!$A:$AZ,MATCH(横向对比!AG$4&横向对比!$B40,【输出】数据汇总!$A:$A,0),MATCH(横向对比!$B$36,【输出】数据汇总!$1:$1,0))/100,"") -> 58.40237 | AH40: =IFERROR(INDEX(【输出】数据汇总!$A:$AZ,MATCH(横向对比!AH$4&横向对比!$B40,【输出】数据汇总!$A:$A,0),MATCH(横向对比!$B$36,【输出】数据汇总!$1:$1,0))/100,"") -> 58.2353 | AI40: =IFERROR(INDEX(【输出】数据汇总!$A:$AZ,MATCH(横向对比!AI$4&横向对比!$B40,【输出】数据汇总!$A:$A,0),MATCH(横向对比!$B$36,【输出】数据汇总!$1:$1,0))/100,"") -> 71.6505 | AJ40: =IFERROR(INDEX(【输出】数据汇总!$A:$AZ,MATCH(横向对比!AJ$4&横向对比!$B40,【输出】数据汇总!$A:$A,0),MATCH(横向对比!$B$36,【输出】数据汇总!$1:$1,0))/100,"") -> 30.11518 | ... BA40: =IFERROR(INDEX(【输出】数据汇总!$A:$AZ,MATCH(横向对比!BA$4&横向对比!$B40,【输出】数据汇总!$A:$A,0),MATCH(横向对比!$B$36,【输出】数据汇总!$1:$1,0))/100,"") -> 142.0342 | BB40: =IFERROR(INDEX(【输出】数据汇总!$A:$AZ,MATCH(横向对比!BB$36&横向对比!$B40,【输出】数据汇总!$A:$A,0),MATCH(横向对比!$B$36,【输出】数据汇总!$1:$1,0))/100,"") -> 81.474788 | BC40: =IFERROR(INDEX(【输出】数据汇总!$A:$AZ,MATCH(横向对比!BC$4&横向对比!$B40,【输出】数据汇总!$A:$A,0),MATCH(横向对比!$B$36,【输出】数据汇总!$1:$1,0))/100,"") -> 86.117125 | BD40: =IFERROR(INDEX(【输出】数据汇总!$A:$AZ,MATCH(横向对比!BD$4&横向对比!$B40,【输出】数据汇总!$A:$A,0),MATCH(横向对比!$B$36,【输出】数据汇总!$1:$1,0))/100,"") -> 13.78588 | BE40: =IFERROR(INDEX(【输出】数据汇总!$A:$AZ,MATCH(横向对比!BE$4&横向对比!$B40,【输出】数据汇总!$A:$A,0),MATCH(横向对比!$B$36,【输出】数据汇总!$1:$1,0))/100,"") -> 43.443374 | BF40: =IFERROR(INDEX(【输出】数据汇总!$A:$AZ,MATCH(横向对比!BF$4&横向对比!$B40,【输出】数据汇总!$A:$A,0),MATCH(横向对比!$B$36,【输出】数据汇总!$1:$1,0))/100,"") -> 36.928983 | BG40: =IFERROR(INDEX(【输出】数据汇总!$A:$AZ,MATCH(横向对比!BG$4&横向对比!$B40,【输出】数据汇总!$A:$A,0),MATCH(横向对比!$B$36,【输出】数据汇总!$1:$1,0))/100,"") -> 107.85223 | BH40: =IFERROR(INDEX(【输出】数据汇总!$A:$AZ,MATCH(横向对比!BH$4&横向对比!$B40,【输出】数据汇总!$A:$A,0),MATCH(横向对比!$B$36,【输出】数据汇总!$1:$1,0))/100,"") -> 112.51125 | BI40: =IFERROR(INDEX(【输出】数据汇总!$A:$AZ,MATCH(横向对比!BI$4&横向对比!$B40,【输出】数据汇总!$A:$A,0),MATCH(横向对比!$B$36,【输出】数据汇总!$1:$1,0))/100,"") -> 61.574652 | BJ40: =IFERROR(INDEX(【输出】数据汇总!$A:$AZ,MATCH(横向对比!BJ$4&横向对比!$B40,【输出】数据汇总!$A:$A,0),MATCH(横向对比!$B$36,【输出】数据汇总!$1:$1,0))/100,"") -> 172.75038 | ... BL40: =IFERROR(INDEX(【输出】数据汇总!$A:$AZ,MATCH(横向对比!BL$4&横向对比!$B40,【输出】数据汇总!$A:$A,0),MATCH(横向对比!$B$36,【输出】数据汇总!$1:$1,0))/100,"") -> 73.755638
A41: ⑤ | B41: 关注类贷款余额 | C41: =IFERROR(INDEX(【输出】数据汇总!$A:$AZ,MATCH(横向对比!C$4&横向对比!$B41,【输出】数据汇总!$A:$A,0),MATCH(横向对比!$B$36,【输出】数据汇总!$1:$1,0))/100,"") -> 30849.717 | D41: =IFERROR(INDEX(【输出】数据汇总!$A:$AZ,MATCH(横向对比!D$4&横向对比!$B41,【输出】数据汇总!$A:$A,0),MATCH(横向对比!$B$36,【输出】数据汇总!$1:$1,0))/100,"") -> 20329.15 | E41: =IFERROR(INDEX(【输出】数据汇总!$A:$AZ,MATCH(横向对比!E$4&横向对比!$B41,【输出】数据汇总!$A:$A,0),MATCH(横向对比!$B$36,【输出】数据汇总!$1:$1,0))/100,"") -> 7799.83 | F41: =IFERROR(INDEX(【输出】数据汇总!$A:$AZ,MATCH(横向对比!F$4&横向对比!$B41,【输出】数据汇总!$A:$A,0),MATCH(横向对比!$B$36,【输出】数据汇总!$1:$1,0))/100,"") -> 2183.87 | G41: =IFERROR(INDEX(【输出】数据汇总!$A:$AZ,MATCH(横向对比!G$4&横向对比!$B41,【输出】数据汇总!$A:$A,0),MATCH(横向对比!$B$36,【输出】数据汇总!$1:$1,0))/100,"") -> 536.86737 | H41: =IFERROR(INDEX(【输出】数据汇总!$A:$AZ,MATCH(横向对比!H$4&横向对比!$B41,【输出】数据汇总!$A:$A,0),MATCH(横向对比!$B$36,【输出】数据汇总!$1:$1,0))/100,"") | I41: =IFERROR(INDEX(【输出】数据汇总!$A:$AZ,MATCH(横向对比!I$4&横向对比!$B41,【输出】数据汇总!$A:$A,0),MATCH(横向对比!$B$36,【输出】数据汇总!$1:$1,0))/100,"") -> 2140.4217 | J41: =IFERROR(INDEX(【输出】数据汇总!$A:$AZ,MATCH(横向对比!J$4&横向对比!$B41,【输出】数据汇总!$A:$A,0),MATCH(横向对比!$B$36,【输出】数据汇总!$1:$1,0))/100,"") -> 5758.83 | ... AA41: =IFERROR(INDEX(【输出】数据汇总!$A:$AZ,MATCH(横向对比!AA$4&横向对比!$B41,【输出】数据汇总!$A:$A,0),MATCH(横向对比!$B$36,【输出】数据汇总!$1:$1,0))/100,"") -> 292.86155 | AB41: =IFERROR(INDEX(【输出】数据汇总!$A:$AZ,MATCH(横向对比!AB$36&横向对比!$B41,【输出】数据汇总!$A:$A,0),MATCH(横向对比!$B$36,【输出】数据汇总!$1:$1,0))/100,"") -> 171.02 | AC41: =IFERROR(INDEX(【输出】数据汇总!$A:$AZ,MATCH(横向对比!AC$4&横向对比!$B41,【输出】数据汇总!$A:$A,0),MATCH(横向对比!$B$36,【输出】数据汇总!$1:$1,0))/100,"") -> 146.57639 | AD41: =IFERROR(INDEX(【输出】数据汇总!$A:$AZ,MATCH(横向对比!AD$4&横向对比!$B41,【输出】数据汇总!$A:$A,0),MATCH(横向对比!$B$36,【输出】数据汇总!$1:$1,0))/100,"") -> 51.72787 | AE41: =IFERROR(INDEX(【输出】数据汇总!$A:$AZ,MATCH(横向对比!AE$4&横向对比!$B41,【输出】数据汇总!$A:$A,0),MATCH(横向对比!$B$36,【输出】数据汇总!$1:$1,0))/100,"") -> 36.68327 | AF41: =IFERROR(INDEX(【输出】数据汇总!$A:$AZ,MATCH(横向对比!AF$4&横向对比!$B41,【输出】数据汇总!$A:$A,0),MATCH(横向对比!$B$36,【输出】数据汇总!$1:$1,0))/100,"") -> 199.70884 | AG41: =IFERROR(INDEX(【输出】数据汇总!$A:$AZ,MATCH(横向对比!AG$4&横向对比!$B41,【输出】数据汇总!$A:$A,0),MATCH(横向对比!$B$36,【输出】数据汇总!$1:$1,0))/100,"") -> 102.1187 | AH41: =IFERROR(INDEX(【输出】数据汇总!$A:$AZ,MATCH(横向对比!AH$4&横向对比!$B41,【输出】数据汇总!$A:$A,0),MATCH(横向对比!$B$36,【输出】数据汇总!$1:$1,0))/100,"") -> 107.23273 | AI41: =IFERROR(INDEX(【输出】数据汇总!$A:$AZ,MATCH(横向对比!AI$4&横向对比!$B41,【输出】数据汇总!$A:$A,0),MATCH(横向对比!$B$36,【输出】数据汇总!$1:$1,0))/100,"") -> 82.28182 | AJ41: =IFERROR(INDEX(【输出】数据汇总!$A:$AZ,MATCH(横向对比!AJ$4&横向对比!$B41,【输出】数据汇总!$A:$A,0),MATCH(横向对比!$B$36,【输出】数据汇总!$1:$1,0))/100,"") -> 27.41534 | ... BA41: =IFERROR(INDEX(【输出】数据汇总!$A:$AZ,MATCH(横向对比!BA$4&横向对比!$B41,【输出】数据汇总!$A:$A,0),MATCH(横向对比!$B$36,【输出】数据汇总!$1:$1,0))/100,"") -> 492.9212 | BB41: =IFERROR(INDEX(【输出】数据汇总!$A:$AZ,MATCH(横向对比!BB$36&横向对比!$B41,【输出】数据汇总!$A:$A,0),MATCH(横向对比!$B$36,【输出】数据汇总!$1:$1,0))/100,"") -> 162.203 | BC41: =IFERROR(INDEX(【输出】数据汇总!$A:$AZ,MATCH(横向对比!BC$4&横向对比!$B41,【输出】数据汇总!$A:$A,0),MATCH(横向对比!$B$36,【输出】数据汇总!$1:$1,0))/100,"") -> 136.4697 | BD41: =IFERROR(INDEX(【输出】数据汇总!$A:$AZ,MATCH(横向对比!BD$4&横向对比!$B41,【输出】数据汇总!$A:$A,0),MATCH(横向对比!$B$36,【输出】数据汇总!$1:$1,0))/100,"") -> 18.45647 | BE41: =IFERROR(INDEX(【输出】数据汇总!$A:$AZ,MATCH(横向对比!BE$4&横向对比!$B41,【输出】数据汇总!$A:$A,0),MATCH(横向对比!$B$36,【输出】数据汇总!$1:$1,0))/100,"") -> 110.189 | BF41: =IFERROR(INDEX(【输出】数据汇总!$A:$AZ,MATCH(横向对比!BF$4&横向对比!$B41,【输出】数据汇总!$A:$A,0),MATCH(横向对比!$B$36,【输出】数据汇总!$1:$1,0))/100,"") -> 94.641 | BG41: =IFERROR(INDEX(【输出】数据汇总!$A:$AZ,MATCH(横向对比!BG$4&横向对比!$B41,【输出】数据汇总!$A:$A,0),MATCH(横向对比!$B$36,【输出】数据汇总!$1:$1,0))/100,"") -> 125.5 | BH41: =IFERROR(INDEX(【输出】数据汇总!$A:$AZ,MATCH(横向对比!BH$4&横向对比!$B41,【输出】数据汇总!$A:$A,0),MATCH(横向对比!$B$36,【输出】数据汇总!$1:$1,0))/100,"") -> 237.997 | BI41: =IFERROR(INDEX(【输出】数据汇总!$A:$AZ,MATCH(横向对比!BI$4&横向对比!$B41,【输出】数据汇总!$A:$A,0),MATCH(横向对比!$B$36,【输出】数据汇总!$1:$1,0))/100,"") -> 108.5416 | BJ41: =IFERROR(INDEX(【输出】数据汇总!$A:$AZ,MATCH(横向对比!BJ$4&横向对比!$B41,【输出】数据汇总!$A:$A,0),MATCH(横向对比!$B$36,【输出】数据汇总!$1:$1,0))/100,"") -> 277.65042 | ... BL41: =IFERROR(INDEX(【输出】数据汇总!$A:$AZ,MATCH(横向对比!BL$4&横向对比!$B41,【输出】数据汇总!$A:$A,0),MATCH(横向对比!$B$36,【输出】数据汇总!$1:$1,0))/100,"") -> 74.99926
A42: ⑥=MAX(②+③，④+⑤) | B42: 广义风险贷款 | C42: =MAX(C38+C39,C40+C41) -> 53514.05 | D42: =MAX(D38+D39,D40+D41) -> 36256.5 | E42: =MAX(E38+E39,E40+E41) -> 12677.03 | F42: =MAX(F38+F39,F40+F41) -> 3724.8943 | G42: =MAX(G38+G39,G40+G41) -> 855.62571 | H42: =MAX(H38+H39,H40+H41) -> #VALUE! | I42: =MAX(I38+I39,I40+I41) -> 3248.2387 | J42: =IFERROR(INDEX(【输出】数据汇总!$A:$AZ,MATCH(横向对比!J$4&横向对比!$B42,【输出】数据汇总!$A:$A,0),MATCH(横向对比!$B$36,【输出】数据汇总!$1:$1,0))/100,"") -> 9773.5226 | K42: =IFERROR(INDEX(【输出】数据汇总!$A:$AZ,MATCH(横向对比!K$4&横向对比!$B42,【输出】数据汇总!$A:$A,0),MATCH(横向对比!$B$36,【输出】数据汇总!$1:$1,0))/100,"") -> 8617.2561 | L42: =IFERROR(INDEX(【输出】数据汇总!$A:$AZ,MATCH(横向对比!L$4&横向对比!$B42,【输出】数据汇总!$A:$A,0),MATCH(横向对比!$B$36,【输出】数据汇总!$1:$1,0))/100,"") -> 7132.3695 | M42: =IFERROR(INDEX(【输出】数据汇总!$A:$AZ,MATCH(横向对比!M$4&横向对比!$B42,【输出】数据汇总!$A:$A,0),MATCH(横向对比!$B$36,【输出】数据汇总!$1:$1,0))/100,"") -> 6157.7619 | N42: =IFERROR(INDEX(【输出】数据汇总!$A:$AZ,MATCH(横向对比!N$4&横向对比!$B42,【输出】数据汇总!$A:$A,0),MATCH(横向对比!$B$36,【输出】数据汇总!$1:$1,0))/100,"") -> 2026.8189 | O42: =IFERROR(INDEX(【输出】数据汇总!$A:$AZ,MATCH(横向对比!O$4&横向对比!$B42,【输出】数据汇总!$A:$A,0),MATCH(横向对比!$B$36,【输出】数据汇总!$1:$1,0))/100,"") -> 2582.7779 | P42: =IFERROR(INDEX(【输出】数据汇总!$A:$AZ,MATCH(横向对比!P$4&横向对比!$B42,【输出】数据汇总!$A:$A,0),MATCH(横向对比!$B$36,【输出】数据汇总!$1:$1,0))/100,"") -> 1676.5153 | Q42: =IFERROR(INDEX(【输出】数据汇总!$A:$AZ,MATCH(横向对比!Q$4&横向对比!$B42,【输出】数据汇总!$A:$A,0),MATCH(横向对比!$B$36,【输出】数据汇总!$1:$1,0))/100,"") -> 1617.4408 | ... AA42: =IFERROR(INDEX(【输出】数据汇总!$A:$AZ,MATCH(横向对比!AA$4&横向对比!$B42,【输出】数据汇总!$A:$A,0),MATCH(横向对比!$B$36,【输出】数据汇总!$1:$1,0))/100,"") -> 462.42563 | AB42: =IFERROR(INDEX(【输出】数据汇总!$A:$AZ,MATCH(横向对比!AB$36&横向对比!$B42,【输出】数据汇总!$A:$A,0),MATCH(横向对比!$B$36,【输出】数据汇总!$1:$1,0))/100,"") -> 298.18419 | AC42: =IFERROR(INDEX(【输出】数据汇总!$A:$AZ,MATCH(横向对比!AC$4&横向对比!$B42,【输出】数据汇总!$A:$A,0),MATCH(横向对比!$B$36,【输出】数据汇总!$1:$1,0))/100,"") -> 263.09896 | AD42: =IFERROR(INDEX(【输出】数据汇总!$A:$AZ,MATCH(横向对比!AD$4&横向对比!$B42,【输出】数据汇总!$A:$A,0),MATCH(横向对比!$B$36,【输出】数据汇总!$1:$1,0))/100,"") -> 128.44365 | AE42: =IFERROR(INDEX(【输出】数据汇总!$A:$AZ,MATCH(横向对比!AE$4&横向对比!$B42,【输出】数据汇总!$A:$A,0),MATCH(横向对比!$B$36,【输出】数据汇总!$1:$1,0))/100,"") -> 91.688671 | AF42: =IFERROR(INDEX(【输出】数据汇总!$A:$AZ,MATCH(横向对比!AF$4&横向对比!$B42,【输出】数据汇总!$A:$A,0),MATCH(横向对比!$B$36,【输出】数据汇总!$1:$1,0))/100,"") -> 270.22376 | AG42: =IFERROR(INDEX(【输出】数据汇总!$A:$AZ,MATCH(横向对比!AG$4&横向对比!$B42,【输出】数据汇总!$A:$A,0),MATCH(横向对比!$B$36,【输出】数据汇总!$1:$1,0))/100,"") -> 160.46017 | AH42: =IFERROR(INDEX(【输出】数据汇总!$A:$AZ,MATCH(横向对比!AH$4&横向对比!$B42,【输出】数据汇总!$A:$A,0),MATCH(横向对比!$B$36,【输出】数据汇总!$1:$1,0))/100,"") -> 165.62111 | AI42: =IFERROR(INDEX(【输出】数据汇总!$A:$AZ,MATCH(横向对比!AI$4&横向对比!$B42,【输出】数据汇总!$A:$A,0),MATCH(横向对比!$B$36,【输出】数据汇总!$1:$1,0))/100,"") -> 153.75445 | AJ42: =IFERROR(INDEX(【输出】数据汇总!$A:$AZ,MATCH(横向对比!AJ$4&横向对比!$B42,【输出】数据汇总!$A:$A,0),MATCH(横向对比!$B$36,【输出】数据汇总!$1:$1,0))/100,"") -> 57.585603 | ... BA42: =IFERROR(INDEX(【输出】数据汇总!$A:$AZ,MATCH(横向对比!BA$4&横向对比!$B42,【输出】数据汇总!$A:$A,0),MATCH(横向对比!$B$36,【输出】数据汇总!$1:$1,0))/100,"") -> 847.74051 | BB42: =IFERROR(INDEX(【输出】数据汇总!$A:$AZ,MATCH(横向对比!BB$36&横向对比!$B42,【输出】数据汇总!$A:$A,0),MATCH(横向对比!$B$36,【输出】数据汇总!$1:$1,0))/100,"") -> 243.67779 | BC42: =IFERROR(INDEX(【输出】数据汇总!$A:$AZ,MATCH(横向对比!BC$4&横向对比!$B42,【输出】数据汇总!$A:$A,0),MATCH(横向对比!$B$36,【输出】数据汇总!$1:$1,0))/100,"") -> 222.58683 | BD42: =IFERROR(INDEX(【输出】数据汇总!$A:$AZ,MATCH(横向对比!BD$4&横向对比!$B42,【输出】数据汇总!$A:$A,0),MATCH(横向对比!$B$36,【输出】数据汇总!$1:$1,0))/100,"") -> 32.24235 | BE42: =IFERROR(INDEX(【输出】数据汇总!$A:$AZ,MATCH(横向对比!BE$4&横向对比!$B42,【输出】数据汇总!$A:$A,0),MATCH(横向对比!$B$36,【输出】数据汇总!$1:$1,0))/100,"") -> 153.63237 | BF42: =IFERROR(INDEX(【输出】数据汇总!$A:$AZ,MATCH(横向对比!BF$4&横向对比!$B42,【输出】数据汇总!$A:$A,0),MATCH(横向对比!$B$36,【输出】数据汇总!$1:$1,0))/100,"") -> 131.56998 | BG42: =IFERROR(INDEX(【输出】数据汇总!$A:$AZ,MATCH(横向对比!BG$4&横向对比!$B42,【输出】数据汇总!$A:$A,0),MATCH(横向对比!$B$36,【输出】数据汇总!$1:$1,0))/100,"") -> 233.35223 | BH42: =IFERROR(INDEX(【输出】数据汇总!$A:$AZ,MATCH(横向对比!BH$4&横向对比!$B42,【输出】数据汇总!$A:$A,0),MATCH(横向对比!$B$36,【输出】数据汇总!$1:$1,0))/100,"") -> 794.39793 | BI42: =IFERROR(INDEX(【输出】数据汇总!$A:$AZ,MATCH(横向对比!BI$4&横向对比!$B42,【输出】数据汇总!$A:$A,0),MATCH(横向对比!$B$36,【输出】数据汇总!$1:$1,0))/100,"") -> 170.11625 | BJ42: =IFERROR(INDEX(【输出】数据汇总!$A:$AZ,MATCH(横向对比!BJ$4&横向对比!$B42,【输出】数据汇总!$A:$A,0),MATCH(横向对比!$B$36,【输出】数据汇总!$1:$1,0))/100,"") -> 450.4008 | ... BL42: =IFERROR(INDEX(【输出】数据汇总!$A:$AZ,MATCH(横向对比!BL$4&横向对比!$B42,【输出】数据汇总!$A:$A,0),MATCH(横向对比!$B$36,【输出】数据汇总!$1:$1,0))/100,"") -> 148.7549
A43: ⑦ | B43: 非信贷资产第三阶段额 | C43: =IFERROR(INDEX(【输出】数据汇总!$A:$AZ,MATCH(横向对比!C$4&横向对比!$B43,【输出】数据汇总!$A:$A,0),MATCH(横向对比!$B$36,【输出】数据汇总!$1:$1,0))/100,"") -> 4523.416 | D43: =IFERROR(INDEX(【输出】数据汇总!$A:$AZ,MATCH(横向对比!D$4&横向对比!$B43,【输出】数据汇总!$A:$A,0),MATCH(横向对比!$B$36,【输出】数据汇总!$1:$1,0))/100,"") -> 447.77 | E43: =IFERROR(INDEX(【输出】数据汇总!$A:$AZ,MATCH(横向对比!E$4&横向对比!$B43,【输出】数据汇总!$A:$A,0),MATCH(横向对比!$B$36,【输出】数据汇总!$1:$1,0))/100,"") -> 3104.56 | F43: =IFERROR(INDEX(【输出】数据汇总!$A:$AZ,MATCH(横向对比!F$4&横向对比!$B43,【输出】数据汇总!$A:$A,0),MATCH(横向对比!$B$36,【输出】数据汇总!$1:$1,0))/100,"") -> 932.61143 | G43: =IFERROR(INDEX(【输出】数据汇总!$A:$AZ,MATCH(横向对比!G$4&横向对比!$B43,【输出】数据汇总!$A:$A,0),MATCH(横向对比!$B$36,【输出】数据汇总!$1:$1,0))/100,"") -> 38.47457 | H43: =IFERROR(INDEX(【输出】数据汇总!$A:$AZ,MATCH(横向对比!H$4&横向对比!$B43,【输出】数据汇总!$A:$A,0),MATCH(横向对比!$B$36,【输出】数据汇总!$1:$1,0))/100,"") | I43: =IFERROR(INDEX(【输出】数据汇总!$A:$AZ,MATCH(横向对比!I$4&横向对比!$B43,【输出】数据汇总!$A:$A,0),MATCH(横向对比!$B$36,【输出】数据汇总!$1:$1,0))/100,"") -> 1245.0356 | J43: =IFERROR(INDEX(【输出】数据汇总!$A:$AZ,MATCH(横向对比!J$4&横向对比!$B43,【输出】数据汇总!$A:$A,0),MATCH(横向对比!$B$36,【输出】数据汇总!$1:$1,0))/100,"") -> 37.16 | ... AA43: =IFERROR(INDEX(【输出】数据汇总!$A:$AZ,MATCH(横向对比!AA$4&横向对比!$B43,【输出】数据汇总!$A:$A,0),MATCH(横向对比!$B$36,【输出】数据汇总!$1:$1,0))/100,"") -> 143.09304 | AB43: =IFERROR(INDEX(【输出】数据汇总!$A:$AZ,MATCH(横向对比!AB$36&横向对比!$B43,【输出】数据汇总!$A:$A,0),MATCH(横向对比!$B$36,【输出】数据汇总!$1:$1,0))/100,"") -> 0.6 | AC43: =IFERROR(INDEX(【输出】数据汇总!$A:$AZ,MATCH(横向对比!AC$4&横向对比!$B43,【输出】数据汇总!$A:$A,0),MATCH(横向对比!$B$36,【输出】数据汇总!$1:$1,0))/100,"") -> 31.55011 | AD43: =IFERROR(INDEX(【输出】数据汇总!$A:$AZ,MATCH(横向对比!AD$4&横向对比!$B43,【输出】数据汇总!$A:$A,0),MATCH(横向对比!$B$36,【输出】数据汇总!$1:$1,0))/100,"") -> 4.55112 | AE43: =IFERROR(INDEX(【输出】数据汇总!$A:$AZ,MATCH(横向对比!AE$4&横向对比!$B43,【输出】数据汇总!$A:$A,0),MATCH(横向对比!$B$36,【输出】数据汇总!$1:$1,0))/100,"") -> 0.02107 | AF43: =IFERROR(INDEX(【输出】数据汇总!$A:$AZ,MATCH(横向对比!AF$4&横向对比!$B43,【输出】数据汇总!$A:$A,0),MATCH(横向对比!$B$36,【输出】数据汇总!$1:$1,0))/100,"") -> 41.28941 | AG43: =IFERROR(INDEX(【输出】数据汇总!$A:$AZ,MATCH(横向对比!AG$4&横向对比!$B43,【输出】数据汇总!$A:$A,0),MATCH(横向对比!$B$36,【输出】数据汇总!$1:$1,0))/100,"") -> 11.77096 | AH43: =IFERROR(INDEX(【输出】数据汇总!$A:$AZ,MATCH(横向对比!AH$4&横向对比!$B43,【输出】数据汇总!$A:$A,0),MATCH(横向对比!$B$36,【输出】数据汇总!$1:$1,0))/100,"") -> 46.62566 | AI43: =IFERROR(INDEX(【输出】数据汇总!$A:$AZ,MATCH(横向对比!AI$4&横向对比!$B43,【输出】数据汇总!$A:$A,0),MATCH(横向对比!$B$36,【输出】数据汇总!$1:$1,0))/100,"") -> 154.57822 | AJ43: =IFERROR(INDEX(【输出】数据汇总!$A:$AZ,MATCH(横向对比!AJ$4&横向对比!$B43,【输出】数据汇总!$A:$A,0),MATCH(横向对比!$B$36,【输出】数据汇总!$1:$1,0))/100,"") -> 0.49354515 | ... BA43: =IFERROR(INDEX(【输出】数据汇总!$A:$AZ,MATCH(横向对比!BA$4&横向对比!$B43,【输出】数据汇总!$A:$A,0),MATCH(横向对比!$B$36,【输出】数据汇总!$1:$1,0))/100,"") -> 70.95857 | BB43: =IFERROR(INDEX(【输出】数据汇总!$A:$AZ,MATCH(横向对比!BB$36&横向对比!$B43,【输出】数据汇总!$A:$A,0),MATCH(横向对比!$B$36,【输出】数据汇总!$1:$1,0))/100,"") -> 20.03574 | BC43: =IFERROR(INDEX(【输出】数据汇总!$A:$AZ,MATCH(横向对比!BC$4&横向对比!$B43,【输出】数据汇总!$A:$A,0),MATCH(横向对比!$B$36,【输出】数据汇总!$1:$1,0))/100,"") -> 63.0288 | BD43: =IFERROR(INDEX(【输出】数据汇总!$A:$AZ,MATCH(横向对比!BD$4&横向对比!$B43,【输出】数据汇总!$A:$A,0),MATCH(横向对比!$B$36,【输出】数据汇总!$1:$1,0))/100,"") -> 9.0815 | BE43: =IFERROR(INDEX(【输出】数据汇总!$A:$AZ,MATCH(横向对比!BE$4&横向对比!$B43,【输出】数据汇总!$A:$A,0),MATCH(横向对比!$B$36,【输出】数据汇总!$1:$1,0))/100,"") -> 86.58581 | BF43: =IFERROR(INDEX(【输出】数据汇总!$A:$AZ,MATCH(横向对比!BF$4&横向对比!$B43,【输出】数据汇总!$A:$A,0),MATCH(横向对比!$B$36,【输出】数据汇总!$1:$1,0))/100,"") -> 23.57814 | BG43: =IFERROR(INDEX(【输出】数据汇总!$A:$AZ,MATCH(横向对比!BG$4&横向对比!$B43,【输出】数据汇总!$A:$A,0),MATCH(横向对比!$B$36,【输出】数据汇总!$1:$1,0))/100,"") -> 73.81836 | BH43: =IFERROR(INDEX(【输出】数据汇总!$A:$AZ,MATCH(横向对比!BH$4&横向对比!$B43,【输出】数据汇总!$A:$A,0),MATCH(横向对比!$B$36,【输出】数据汇总!$1:$1,0))/100,"") -> 204.08768 | BI43: =IFERROR(INDEX(【输出】数据汇总!$A:$AZ,MATCH(横向对比!BI$4&横向对比!$B43,【输出】数据汇总!$A:$A,0),MATCH(横向对比!$B$36,【输出】数据汇总!$1:$1,0))/100,"") -> 17.8938 | BJ43: =IFERROR(INDEX(【输出】数据汇总!$A:$AZ,MATCH(横向对比!BJ$4&横向对比!$B43,【输出】数据汇总!$A:$A,0),MATCH(横向对比!$B$36,【输出】数据汇总!$1:$1,0))/100,"") -> 375.29013 | ... BL43: =IFERROR(INDEX(【输出】数据汇总!$A:$AZ,MATCH(横向对比!BL$4&横向对比!$B43,【输出】数据汇总!$A:$A,0),MATCH(横向对比!$B$36,【输出】数据汇总!$1:$1,0))/100,"") -> 0.64617
A44: ⑧ | B44: 贷款拨备额 | C44: =IFERROR(INDEX(【输出】数据汇总!$A:$AZ,MATCH(横向对比!C$4&横向对比!$B44,【输出】数据汇总!$A:$A,0),MATCH(横向对比!$B$36,【输出】数据汇总!$1:$1,0))/100,"") -> 54065.345 | D44: =IFERROR(INDEX(【输出】数据汇总!$A:$AZ,MATCH(横向对比!D$4&横向对比!$B44,【输出】数据汇总!$A:$A,0),MATCH(横向对比!$B$36,【输出】数据汇总!$1:$1,0))/100,"") -> 37803.5 | E44: =IFERROR(INDEX(【输出】数据汇总!$A:$AZ,MATCH(横向对比!E$4&横向对比!$B44,【输出】数据汇总!$A:$A,0),MATCH(横向对比!$B$36,【输出】数据汇总!$1:$1,0))/100,"") -> 10759.78 | F44: =IFERROR(INDEX(【输出】数据汇总!$A:$AZ,MATCH(横向对比!F$4&横向对比!$B44,【输出】数据汇总!$A:$A,0),MATCH(横向对比!$B$36,【输出】数据汇总!$1:$1,0))/100,"") -> 4429.4636 | G44: =IFERROR(INDEX(【输出】数据汇总!$A:$AZ,MATCH(横向对比!G$4&横向对比!$B44,【输出】数据汇总!$A:$A,0),MATCH(横向对比!$B$36,【输出】数据汇总!$1:$1,0))/100,"") -> 1072.6017 | H44: =IFERROR(INDEX(【输出】数据汇总!$A:$AZ,MATCH(横向对比!H$4&横向对比!$B44,【输出】数据汇总!$A:$A,0),MATCH(横向对比!$B$36,【输出】数据汇总!$1:$1,0))/100,"") | I44: =IFERROR(INDEX(【输出】数据汇总!$A:$AZ,MATCH(横向对比!I$4&横向对比!$B44,【输出】数据汇总!$A:$A,0),MATCH(横向对比!$B$36,【输出】数据汇总!$1:$1,0))/100,"") -> 2161.8333 | J44: =IFERROR(INDEX(【输出】数据汇总!$A:$AZ,MATCH(横向对比!J$4&横向对比!$B44,【输出】数据汇总!$A:$A,0),MATCH(横向对比!$B$36,【输出】数据汇总!$1:$1,0))/100,"") -> 8710.64 | ... AA44: =IFERROR(INDEX(【输出】数据汇总!$A:$AZ,MATCH(横向对比!AA$4&横向对比!$B44,【输出】数据汇总!$A:$A,0),MATCH(横向对比!$B$36,【输出】数据汇总!$1:$1,0))/100,"") -> 412.71247 | AB44: =IFERROR(INDEX(【输出】数据汇总!$A:$AZ,MATCH(横向对比!AB$36&横向对比!$B44,【输出】数据汇总!$A:$A,0),MATCH(横向对比!$B$36,【输出】数据汇总!$1:$1,0))/100,"") -> 474.77 | AC44: =IFERROR(INDEX(【输出】数据汇总!$A:$AZ,MATCH(横向对比!AC$4&横向对比!$B44,【输出】数据汇总!$A:$A,0),MATCH(横向对比!$B$36,【输出】数据汇总!$1:$1,0))/100,"") -> 361.32269 | AD44: =IFERROR(INDEX(【输出】数据汇总!$A:$AZ,MATCH(横向对比!AD$4&横向对比!$B44,【输出】数据汇总!$A:$A,0),MATCH(横向对比!$B$36,【输出】数据汇总!$1:$1,0))/100,"") -> 398.09922 | AE44: =IFERROR(INDEX(【输出】数据汇总!$A:$AZ,MATCH(横向对比!AE$4&横向对比!$B44,【输出】数据汇总!$A:$A,0),MATCH(横向对比!$B$36,【输出】数据汇总!$1:$1,0))/100,"") -> 248.07887 | AF44: =IFERROR(INDEX(【输出】数据汇总!$A:$AZ,MATCH(横向对比!AF$4&横向对比!$B44,【输出】数据汇总!$A:$A,0),MATCH(横向对比!$B$36,【输出】数据汇总!$1:$1,0))/100,"") -> 225.42693 | AG44: =IFERROR(INDEX(【输出】数据汇总!$A:$AZ,MATCH(横向对比!AG$4&横向对比!$B44,【输出】数据汇总!$A:$A,0),MATCH(横向对比!$B$36,【输出】数据汇总!$1:$1,0))/100,"") -> 144.99295 | AH44: =IFERROR(INDEX(【输出】数据汇总!$A:$AZ,MATCH(横向对比!AH$4&横向对比!$B44,【输出】数据汇总!$A:$A,0),MATCH(横向对比!$B$36,【输出】数据汇总!$1:$1,0))/100,"") -> 138.97112 | AI44: =IFERROR(INDEX(【输出】数据汇总!$A:$AZ,MATCH(横向对比!AI$4&横向对比!$B44,【输出】数据汇总!$A:$A,0),MATCH(横向对比!$B$36,【输出】数据汇总!$1:$1,0))/100,"") -> 128.39487 | AJ44: =IFERROR(INDEX(【输出】数据汇总!$A:$AZ,MATCH(横向对比!AJ$4&横向对比!$B44,【输出】数据汇总!$A:$A,0),MATCH(横向对比!$B$36,【输出】数据汇总!$1:$1,0))/100,"") -> 131.8775 | ... BA44: =IFERROR(INDEX(【输出】数据汇总!$A:$AZ,MATCH(横向对比!BA$4&横向对比!$B44,【输出】数据汇总!$A:$A,0),MATCH(横向对比!$B$36,【输出】数据汇总!$1:$1,0))/100,"") -> 241.36539 | BB44: =IFERROR(INDEX(【输出】数据汇总!$A:$AZ,MATCH(横向对比!BB$36&横向对比!$B44,【输出】数据汇总!$A:$A,0),MATCH(横向对比!$B$36,【输出】数据汇总!$1:$1,0))/100,"") -> 139.91198 | BC44: =IFERROR(INDEX(【输出】数据汇总!$A:$AZ,MATCH(横向对比!BC$4&横向对比!$B44,【输出】数据汇总!$A:$A,0),MATCH(横向对比!$B$36,【输出】数据汇总!$1:$1,0))/100,"") -> 133.43681 | BD44: =IFERROR(INDEX(【输出】数据汇总!$A:$AZ,MATCH(横向对比!BD$4&横向对比!$B44,【输出】数据汇总!$A:$A,0),MATCH(横向对比!$B$36,【输出】数据汇总!$1:$1,0))/100,"") -> 56.97189 | BE44: =IFERROR(INDEX(【输出】数据汇总!$A:$AZ,MATCH(横向对比!BE$4&横向对比!$B44,【输出】数据汇总!$A:$A,0),MATCH(横向对比!$B$36,【输出】数据汇总!$1:$1,0))/100,"") -> 59.36929 | BF44: =IFERROR(INDEX(【输出】数据汇总!$A:$AZ,MATCH(横向对比!BF$4&横向对比!$B44,【输出】数据汇总!$A:$A,0),MATCH(横向对比!$B$36,【输出】数据汇总!$1:$1,0))/100,"") -> 79.3207 | BG44: =IFERROR(INDEX(【输出】数据汇总!$A:$AZ,MATCH(横向对比!BG$4&横向对比!$B44,【输出】数据汇总!$A:$A,0),MATCH(横向对比!$B$36,【输出】数据汇总!$1:$1,0))/100,"") -> 313.51147 | BH44: =IFERROR(INDEX(【输出】数据汇总!$A:$AZ,MATCH(横向对比!BH$4&横向对比!$B44,【输出】数据汇总!$A:$A,0),MATCH(横向对比!$B$36,【输出】数据汇总!$1:$1,0))/100,"") -> 236.80016 | BI44: =IFERROR(INDEX(【输出】数据汇总!$A:$AZ,MATCH(横向对比!BI$4&横向对比!$B44,【输出】数据汇总!$A:$A,0),MATCH(横向对比!$B$36,【输出】数据汇总!$1:$1,0))/100,"") -> 204.38975 | BJ44: =IFERROR(INDEX(【输出】数据汇总!$A:$AZ,MATCH(横向对比!BJ$4&横向对比!$B44,【输出】数据汇总!$A:$A,0),MATCH(横向对比!$B$36,【输出】数据汇总!$1:$1,0))/100,"") -> 275.79444 | ... BL44: =IFERROR(INDEX(【输出】数据汇总!$A:$AZ,MATCH(横向对比!BL$4&横向对比!$B44,【输出】数据汇总!$A:$A,0),MATCH(横向对比!$B$36,【输出】数据汇总!$1:$1,0))/100,"") -> 139.23353
A45: ⑨=⑧-⑥*100% | B45: 超额贷款拨备额 | C45: =IFERROR(C44-C42*100%,"") -> 551.29524 | D45: =IFERROR(D44-D42*100%,"") -> 1547 | E45: =IFERROR(E44-E42*100%,"") -> -1917.25 | F45: =IFERROR(F44-F42*100%,"") -> 704.56927 | G45: =IFERROR(G44-G42*100%,"") -> 216.97597 | H45: =IFERROR(H44-H42*100%,"") | I45: =IFERROR(I44-I42*100%,"") -> -1086.4053 | J45: =IFERROR(J44-J42*100%,"") -> -1062.8826 | ... BL45: =IFERROR(BL44-BL42*100%,"") -> -9.5213679
A46: ⑦ | B46: 非信贷资产第三阶段额 | C46: =IFERROR(INDEX(【输出】数据汇总!$A:$AZ,MATCH(横向对比!C$4&横向对比!$B46,【输出】数据汇总!$A:$A,0),MATCH(横向对比!$B$36,【输出】数据汇总!$1:$1,0))/100,"") -> 4523.416 | D46: =IFERROR(INDEX(【输出】数据汇总!$A:$AZ,MATCH(横向对比!D$4&横向对比!$B46,【输出】数据汇总!$A:$A,0),MATCH(横向对比!$B$36,【输出】数据汇总!$1:$1,0))/100,"") -> 447.77 | E46: =IFERROR(INDEX(【输出】数据汇总!$A:$AZ,MATCH(横向对比!E$4&横向对比!$B46,【输出】数据汇总!$A:$A,0),MATCH(横向对比!$B$36,【输出】数据汇总!$1:$1,0))/100,"") -> 3104.56 | F46: =IFERROR(INDEX(【输出】数据汇总!$A:$AZ,MATCH(横向对比!F$4&横向对比!$B46,【输出】数据汇总!$A:$A,0),MATCH(横向对比!$B$36,【输出】数据汇总!$1:$1,0))/100,"") -> 932.61143 | G46: =IFERROR(INDEX(【输出】数据汇总!$A:$AZ,MATCH(横向对比!G$4&横向对比!$B46,【输出】数据汇总!$A:$A,0),MATCH(横向对比!$B$36,【输出】数据汇总!$1:$1,0))/100,"") -> 38.47457 | H46: =IFERROR(INDEX(【输出】数据汇总!$A:$AZ,MATCH(横向对比!H$4&横向对比!$B46,【输出】数据汇总!$A:$A,0),MATCH(横向对比!$B$36,【输出】数据汇总!$1:$1,0))/100,"") | I46: =IFERROR(INDEX(【输出】数据汇总!$A:$AZ,MATCH(横向对比!I$4&横向对比!$B46,【输出】数据汇总!$A:$A,0),MATCH(横向对比!$B$36,【输出】数据汇总!$1:$1,0))/100,"") -> 1245.0356 | J46: =IFERROR(INDEX(【输出】数据汇总!$A:$AZ,MATCH(横向对比!J$4&横向对比!$B46,【输出】数据汇总!$A:$A,0),MATCH(横向对比!$B$36,【输出】数据汇总!$1:$1,0))/100,"") -> 37.16 | ... AA46: =IFERROR(INDEX(【输出】数据汇总!$A:$AZ,MATCH(横向对比!AA$4&横向对比!$B46,【输出】数据汇总!$A:$A,0),MATCH(横向对比!$B$36,【输出】数据汇总!$1:$1,0))/100,"") -> 143.09304 | AB46: =IFERROR(INDEX(【输出】数据汇总!$A:$AZ,MATCH(横向对比!AB$36&横向对比!$B46,【输出】数据汇总!$A:$A,0),MATCH(横向对比!$B$36,【输出】数据汇总!$1:$1,0))/100,"") -> 0.6 | AC46: =IFERROR(INDEX(【输出】数据汇总!$A:$AZ,MATCH(横向对比!AC$4&横向对比!$B46,【输出】数据汇总!$A:$A,0),MATCH(横向对比!$B$36,【输出】数据汇总!$1:$1,0))/100,"") -> 31.55011 | AD46: =IFERROR(INDEX(【输出】数据汇总!$A:$AZ,MATCH(横向对比!AD$4&横向对比!$B46,【输出】数据汇总!$A:$A,0),MATCH(横向对比!$B$36,【输出】数据汇总!$1:$1,0))/100,"") -> 4.55112 | AE46: =IFERROR(INDEX(【输出】数据汇总!$A:$AZ,MATCH(横向对比!AE$4&横向对比!$B46,【输出】数据汇总!$A:$A,0),MATCH(横向对比!$B$36,【输出】数据汇总!$1:$1,0))/100,"") -> 0.02107 | AF46: =IFERROR(INDEX(【输出】数据汇总!$A:$AZ,MATCH(横向对比!AF$4&横向对比!$B46,【输出】数据汇总!$A:$A,0),MATCH(横向对比!$B$36,【输出】数据汇总!$1:$1,0))/100,"") -> 41.28941 | AG46: =IFERROR(INDEX(【输出】数据汇总!$A:$AZ,MATCH(横向对比!AG$4&横向对比!$B46,【输出】数据汇总!$A:$A,0),MATCH(横向对比!$B$36,【输出】数据汇总!$1:$1,0))/100,"") -> 11.77096 | AH46: =IFERROR(INDEX(【输出】数据汇总!$A:$AZ,MATCH(横向对比!AH$4&横向对比!$B46,【输出】数据汇总!$A:$A,0),MATCH(横向对比!$B$36,【输出】数据汇总!$1:$1,0))/100,"") -> 46.62566 | AI46: =IFERROR(INDEX(【输出】数据汇总!$A:$AZ,MATCH(横向对比!AI$4&横向对比!$B46,【输出】数据汇总!$A:$A,0),MATCH(横向对比!$B$36,【输出】数据汇总!$1:$1,0))/100,"") -> 154.57822 | AJ46: =IFERROR(INDEX(【输出】数据汇总!$A:$AZ,MATCH(横向对比!AJ$4&横向对比!$B46,【输出】数据汇总!$A:$A,0),MATCH(横向对比!$B$36,【输出】数据汇总!$1:$1,0))/100,"") -> 0.49354515 | ... BA46: =IFERROR(INDEX(【输出】数据汇总!$A:$AZ,MATCH(横向对比!BA$4&横向对比!$B46,【输出】数据汇总!$A:$A,0),MATCH(横向对比!$B$36,【输出】数据汇总!$1:$1,0))/100,"") -> 70.95857 | BB46: =IFERROR(INDEX(【输出】数据汇总!$A:$AZ,MATCH(横向对比!BB$36&横向对比!$B46,【输出】数据汇总!$A:$A,0),MATCH(横向对比!$B$36,【输出】数据汇总!$1:$1,0))/100,"") -> 20.03574 | BC46: =IFERROR(INDEX(【输出】数据汇总!$A:$AZ,MATCH(横向对比!BC$4&横向对比!$B46,【输出】数据汇总!$A:$A,0),MATCH(横向对比!$B$36,【输出】数据汇总!$1:$1,0))/100,"") -> 63.0288 | BD46: =IFERROR(INDEX(【输出】数据汇总!$A:$AZ,MATCH(横向对比!BD$4&横向对比!$B46,【输出】数据汇总!$A:$A,0),MATCH(横向对比!$B$36,【输出】数据汇总!$1:$1,0))/100,"") -> 9.0815 | BE46: =IFERROR(INDEX(【输出】数据汇总!$A:$AZ,MATCH(横向对比!BE$4&横向对比!$B46,【输出】数据汇总!$A:$A,0),MATCH(横向对比!$B$36,【输出】数据汇总!$1:$1,0))/100,"") -> 86.58581 | BF46: =IFERROR(INDEX(【输出】数据汇总!$A:$AZ,MATCH(横向对比!BF$4&横向对比!$B46,【输出】数据汇总!$A:$A,0),MATCH(横向对比!$B$36,【输出】数据汇总!$1:$1,0))/100,"") -> 23.57814 | BG46: =IFERROR(INDEX(【输出】数据汇总!$A:$AZ,MATCH(横向对比!BG$4&横向对比!$B46,【输出】数据汇总!$A:$A,0),MATCH(横向对比!$B$36,【输出】数据汇总!$1:$1,0))/100,"") -> 73.81836 | BH46: =IFERROR(INDEX(【输出】数据汇总!$A:$AZ,MATCH(横向对比!BH$4&横向对比!$B46,【输出】数据汇总!$A:$A,0),MATCH(横向对比!$B$36,【输出】数据汇总!$1:$1,0))/100,"") -> 204.08768 | BI46: =IFERROR(INDEX(【输出】数据汇总!$A:$AZ,MATCH(横向对比!BI$4&横向对比!$B46,【输出】数据汇总!$A:$A,0),MATCH(横向对比!$B$36,【输出】数据汇总!$1:$1,0))/100,"") -> 17.8938 | BJ46: =IFERROR(INDEX(【输出】数据汇总!$A:$AZ,MATCH(横向对比!BJ$4&横向对比!$B46,【输出】数据汇总!$A:$A,0),MATCH(横向对比!$B$36,【输出】数据汇总!$1:$1,0))/100,"") -> 375.29013 | ... BL46: =IFERROR(INDEX(【输出】数据汇总!$A:$AZ,MATCH(横向对比!BL$4&横向对比!$B46,【输出】数据汇总!$A:$A,0),MATCH(横向对比!$B$36,【输出】数据汇总!$1:$1,0))/100,"") -> 0.64617
A47: ⑩ | B47: 非信贷拨备额 | C47: =IFERROR(INDEX(【输出】数据汇总!$A:$AZ,MATCH(横向对比!C$4&横向对比!$B47,【输出】数据汇总!$A:$A,0),MATCH(横向对比!$B$36,【输出】数据汇总!$1:$1,0))/100,"") -> 6837.7702 | D47: =IFERROR(INDEX(【输出】数据汇总!$A:$AZ,MATCH(横向对比!D$4&横向对比!$B47,【输出】数据汇总!$A:$A,0),MATCH(横向对比!$B$36,【输出】数据汇总!$1:$1,0))/100,"") -> 2518.64 | E47: =IFERROR(INDEX(【输出】数据汇总!$A:$AZ,MATCH(横向对比!E$4&横向对比!$B47,【输出】数据汇总!$A:$A,0),MATCH(横向对比!$B$36,【输出】数据汇总!$1:$1,0))/100,"") -> 2977.38 | F47: =IFERROR(INDEX(【输出】数据汇总!$A:$AZ,MATCH(横向对比!F$4&横向对比!$B47,【输出】数据汇总!$A:$A,0),MATCH(横向对比!$B$36,【输出】数据汇总!$1:$1,0))/100,"") -> 1219.6605 | G47: =IFERROR(INDEX(【输出】数据汇总!$A:$AZ,MATCH(横向对比!G$4&横向对比!$B47,【输出】数据汇总!$A:$A,0),MATCH(横向对比!$B$36,【输出】数据汇总!$1:$1,0))/100,"") -> 122.08971 | H47: =IFERROR(INDEX(【输出】数据汇总!$A:$AZ,MATCH(横向对比!H$4&横向对比!$B47,【输出】数据汇总!$A:$A,0),MATCH(横向对比!$B$36,【输出】数据汇总!$1:$1,0))/100,"") | I47: =IFERROR(INDEX(【输出】数据汇总!$A:$AZ,MATCH(横向对比!I$4&横向对比!$B47,【输出】数据汇总!$A:$A,0),MATCH(横向对比!$B$36,【输出】数据汇总!$1:$1,0))/100,"") -> 778.57624 | J47: =IFERROR(INDEX(【输出】数据汇总!$A:$AZ,MATCH(横向对比!J$4&横向对比!$B47,【输出】数据汇总!$A:$A,0),MATCH(横向对比!$B$36,【输出】数据汇总!$1:$1,0))/100,"") -> 1063.22 | ... AA47: =IFERROR(INDEX(【输出】数据汇总!$A:$AZ,MATCH(横向对比!AA$4&横向对比!$B47,【输出】数据汇总!$A:$A,0),MATCH(横向对比!$B$36,【输出】数据汇总!$1:$1,0))/100,"") -> 177.12212 | AB47: =IFERROR(INDEX(【输出】数据汇总!$A:$AZ,MATCH(横向对比!AB$36&横向对比!$B47,【输出】数据汇总!$A:$A,0),MATCH(横向对比!$B$36,【输出】数据汇总!$1:$1,0))/100,"") -> 25.99 | AC47: =IFERROR(INDEX(【输出】数据汇总!$A:$AZ,MATCH(横向对比!AC$4&横向对比!$B47,【输出】数据汇总!$A:$A,0),MATCH(横向对比!$B$36,【输出】数据汇总!$1:$1,0))/100,"") -> 58.03624 | AD47: =IFERROR(INDEX(【输出】数据汇总!$A:$AZ,MATCH(横向对比!AD$4&横向对比!$B47,【输出】数据汇总!$A:$A,0),MATCH(横向对比!$B$36,【输出】数据汇总!$1:$1,0))/100,"") -> 132.2865 | AE47: =IFERROR(INDEX(【输出】数据汇总!$A:$AZ,MATCH(横向对比!AE$4&横向对比!$B47,【输出】数据汇总!$A:$A,0),MATCH(横向对比!$B$36,【输出】数据汇总!$1:$1,0))/100,"") -> 18.4179 | AF47: =IFERROR(INDEX(【输出】数据汇总!$A:$AZ,MATCH(横向对比!AF$4&横向对比!$B47,【输出】数据汇总!$A:$A,0),MATCH(横向对比!$B$36,【输出】数据汇总!$1:$1,0))/100,"") -> 64.67734 | AG47: =IFERROR(INDEX(【输出】数据汇总!$A:$AZ,MATCH(横向对比!AG$4&横向对比!$B47,【输出】数据汇总!$A:$A,0),MATCH(横向对比!$B$36,【输出】数据汇总!$1:$1,0))/100,"") -> 22.85274 | AH47: =IFERROR(INDEX(【输出】数据汇总!$A:$AZ,MATCH(横向对比!AH$4&横向对比!$B47,【输出】数据汇总!$A:$A,0),MATCH(横向对比!$B$36,【输出】数据汇总!$1:$1,0))/100,"") -> 73.86564 | AI47: =IFERROR(INDEX(【输出】数据汇总!$A:$AZ,MATCH(横向对比!AI$4&横向对比!$B47,【输出】数据汇总!$A:$A,0),MATCH(横向对比!$B$36,【输出】数据汇总!$1:$1,0))/100,"") -> 56.88119 | AJ47: =IFERROR(INDEX(【输出】数据汇总!$A:$AZ,MATCH(横向对比!AJ$4&横向对比!$B47,【输出】数据汇总!$A:$A,0),MATCH(横向对比!$B$36,【输出】数据汇总!$1:$1,0))/100,"") -> 28.937278 | ... BA47: =IFERROR(INDEX(【输出】数据汇总!$A:$AZ,MATCH(横向对比!BA$4&横向对比!$B47,【输出】数据汇总!$A:$A,0),MATCH(横向对比!$B$36,【输出】数据汇总!$1:$1,0))/100,"") -> 50.14005 | BB47: =IFERROR(INDEX(【输出】数据汇总!$A:$AZ,MATCH(横向对比!BB$36&横向对比!$B47,【输出】数据汇总!$A:$A,0),MATCH(横向对比!$B$36,【输出】数据汇总!$1:$1,0))/100,"") -> 44.36649 | BC47: =IFERROR(INDEX(【输出】数据汇总!$A:$AZ,MATCH(横向对比!BC$4&横向对比!$B47,【输出】数据汇总!$A:$A,0),MATCH(横向对比!$B$36,【输出】数据汇总!$1:$1,0))/100,"") -> 42.64601 | BD47: =IFERROR(INDEX(【输出】数据汇总!$A:$AZ,MATCH(横向对比!BD$4&横向对比!$B47,【输出】数据汇总!$A:$A,0),MATCH(横向对比!$B$36,【输出】数据汇总!$1:$1,0))/100,"") -> 8.43797 | BE47: =IFERROR(INDEX(【输出】数据汇总!$A:$AZ,MATCH(横向对比!BE$4&横向对比!$B47,【输出】数据汇总!$A:$A,0),MATCH(横向对比!$B$36,【输出】数据汇总!$1:$1,0))/100,"") -> 40.23154 | BF47: =IFERROR(INDEX(【输出】数据汇总!$A:$AZ,MATCH(横向对比!BF$4&横向对比!$B47,【输出】数据汇总!$A:$A,0),MATCH(横向对比!$B$36,【输出】数据汇总!$1:$1,0))/100,"") -> 19.30951 | BG47: =IFERROR(INDEX(【输出】数据汇总!$A:$AZ,MATCH(横向对比!BG$4&横向对比!$B47,【输出】数据汇总!$A:$A,0),MATCH(横向对比!$B$36,【输出】数据汇总!$1:$1,0))/100,"") -> 103.36609 | BH47: =IFERROR(INDEX(【输出】数据汇总!$A:$AZ,MATCH(横向对比!BH$4&横向对比!$B47,【输出】数据汇总!$A:$A,0),MATCH(横向对比!$B$36,【输出】数据汇总!$1:$1,0))/100,"") -> 85.94197 | BI47: =IFERROR(INDEX(【输出】数据汇总!$A:$AZ,MATCH(横向对比!BI$4&横向对比!$B47,【输出】数据汇总!$A:$A,0),MATCH(横向对比!$B$36,【输出】数据汇总!$1:$1,0))/100,"") -> 25.44884 | BJ47: =IFERROR(INDEX(【输出】数据汇总!$A:$AZ,MATCH(横向对比!BJ$4&横向对比!$B47,【输出】数据汇总!$A:$A,0),MATCH(横向对比!$B$36,【输出】数据汇总!$1:$1,0))/100,"") -> 101.68948 | ... BL47: =IFERROR(INDEX(【输出】数据汇总!$A:$AZ,MATCH(横向对比!BL$4&横向对比!$B47,【输出】数据汇总!$A:$A,0),MATCH(横向对比!$B$36,【输出】数据汇总!$1:$1,0))/100,"") -> 13.50222
A48: ⑪=⑩-⑦*100% | B48: 超额非信贷拨备 | C48: =IFERROR(IF(C46="",C47-0,C47-C46*100%),"") -> 2314.3542 | D48: =IFERROR(IF(D46="",D47-0,D47-D46*100%),"") -> 2070.87 | E48: =IFERROR(IF(E46="",E47-0,E47-E46*100%),"") -> -127.18 | F48: =IFERROR(IF(F46="",F47-0,F47-F46*100%),"") -> 287.04907 | G48: =IFERROR(IF(G46="",G47-0,G47-G46*100%),"") -> 83.615136 | H48: =IFERROR(IF(H46="",H47-0,H47-H46*100%),"") | I48: =IFERROR(IF(I46="",I47-0,I47-I46*100%),"") -> -466.45932 | J48: =IFERROR(IF(J46="",J47-0,J47-J46*100%),"") -> 1026.06 | ... BL48: =IFERROR(IF(BL46="",BL47-0,BL47-BL46*100%),"") -> 12.85605
A49: ⑪+⑨ | B49: 超额拨备额 | C49: =IFERROR(C45+C48,"") -> 2865.6494 | D49: =IFERROR(D45+D48,"") -> 3617.87 | E49: =IFERROR(E45+E48,"") -> -2044.43 | F49: =IFERROR(F45+F48,"") -> 991.61834 | G49: =IFERROR(G45+G48,"") -> 300.59111 | H49: =IFERROR(H45+H48,"") | I49: =IFERROR(I45+I48,"") -> -1552.8647 | J49: =IFERROR(J45+J48,"") -> -36.822647 | ... BL49: =IFERROR(BL45+BL48,"") -> 3.3346821
B50: 归母净利润(TTM) | C50: =IFERROR(INDEX(【输出】数据汇总!$A:$AZ,MATCH(横向对比!C$4&横向对比!$B50,【输出】数据汇总!$A:$A,0),MATCH(横向对比!$B$36,【输出】数据汇总!$1:$1,0))/100,"") -> 21527.568 | D50: =IFERROR(INDEX(【输出】数据汇总!$A:$AZ,MATCH(横向对比!D$4&横向对比!$B50,【输出】数据汇总!$A:$A,0),MATCH(横向对比!$B$36,【输出】数据汇总!$1:$1,0))/100,"") -> 14005.65 | E50: =IFERROR(INDEX(【输出】数据汇总!$A:$AZ,MATCH(横向对比!E$4&横向对比!$B50,【输出】数据汇总!$A:$A,0),MATCH(横向对比!$B$36,【输出】数据汇总!$1:$1,0))/100,"") -> 5015.17 | F50: =IFERROR(INDEX(【输出】数据汇总!$A:$AZ,MATCH(横向对比!F$4&横向对比!$B50,【输出】数据汇总!$A:$A,0),MATCH(横向对比!$B$36,【输出】数据汇总!$1:$1,0))/100,"") -> 2075.0129 | G50: =IFERROR(INDEX(【输出】数据汇总!$A:$AZ,MATCH(横向对比!G$4&横向对比!$B50,【输出】数据汇总!$A:$A,0),MATCH(横向对比!$B$36,【输出】数据汇总!$1:$1,0))/100,"") -> 431.7348 | H50: =IFERROR(INDEX(【输出】数据汇总!$A:$AZ,MATCH(横向对比!H$4&横向对比!$B50,【输出】数据汇总!$A:$A,0),MATCH(横向对比!$B$36,【输出】数据汇总!$1:$1,0))/100,"") | I50: =IFERROR(INDEX(【输出】数据汇总!$A:$AZ,MATCH(横向对比!I$4&横向对比!$B50,【输出】数据汇总!$A:$A,0),MATCH(横向对比!$B$36,【输出】数据汇总!$1:$1,0))/100,"") -> 458.7 | J50: =IFERROR(INDEX(【输出】数据汇总!$A:$AZ,MATCH(横向对比!J$4&横向对比!$B50,【输出】数据汇总!$A:$A,0),MATCH(横向对比!$B$36,【输出】数据汇总!$1:$1,0))/100,"") -> 3634.99 | ... AA50: =IFERROR(INDEX(【输出】数据汇总!$A:$AZ,MATCH(横向对比!AA$4&横向对比!$B50,【输出】数据汇总!$A:$A,0),MATCH(横向对比!$B$36,【输出】数据汇总!$1:$1,0))/100,"") -> 238.21839 | AB50: =IFERROR(INDEX(【输出】数据汇总!$A:$AZ,MATCH(横向对比!AB$36&横向对比!$B50,【输出】数据汇总!$A:$A,0),MATCH(横向对比!$B$36,【输出】数据汇总!$1:$1,0))/100,"") -> 282.5 | AC50: =IFERROR(INDEX(【输出】数据汇总!$A:$AZ,MATCH(横向对比!AC$4&横向对比!$B50,【输出】数据汇总!$A:$A,0),MATCH(横向对比!$B$36,【输出】数据汇总!$1:$1,0))/100,"") -> 212.01797 | AD50: =IFERROR(INDEX(【输出】数据汇总!$A:$AZ,MATCH(横向对比!AD$4&横向对比!$B50,【输出】数据汇总!$A:$A,0),MATCH(横向对比!$B$36,【输出】数据汇总!$1:$1,0))/100,"") -> 186.48371 | AE50: =IFERROR(INDEX(【输出】数据汇总!$A:$AZ,MATCH(横向对比!AE$4&横向对比!$B50,【输出】数据汇总!$A:$A,0),MATCH(横向对比!$B$36,【输出】数据汇总!$1:$1,0))/100,"") -> 133.07943 | AF50: =IFERROR(INDEX(【输出】数据汇总!$A:$AZ,MATCH(横向对比!AF$4&横向对比!$B50,【输出】数据汇总!$A:$A,0),MATCH(横向对比!$B$36,【输出】数据汇总!$1:$1,0))/100,"") -> 80.34713 | AG50: =IFERROR(INDEX(【输出】数据汇总!$A:$AZ,MATCH(横向对比!AG$4&横向对比!$B50,【输出】数据汇总!$A:$A,0),MATCH(横向对比!$B$36,【输出】数据汇总!$1:$1,0))/100,"") -> 52.80513 | AH50: =IFERROR(INDEX(【输出】数据汇总!$A:$AZ,MATCH(横向对比!AH$4&横向对比!$B50,【输出】数据汇总!$A:$A,0),MATCH(横向对比!$B$36,【输出】数据汇总!$1:$1,0))/100,"") -> 49.71748 | AI50: =IFERROR(INDEX(【输出】数据汇总!$A:$AZ,MATCH(横向对比!AI$4&横向对比!$B50,【输出】数据汇总!$A:$A,0),MATCH(横向对比!$B$36,【输出】数据汇总!$1:$1,0))/100,"") -> 19.0926 | AJ50: =IFERROR(INDEX(【输出】数据汇总!$A:$AZ,MATCH(横向对比!AJ$4&横向对比!$B50,【输出】数据汇总!$A:$A,0),MATCH(横向对比!$B$36,【输出】数据汇总!$1:$1,0))/100,"") -> 52.498639 | ... BA50: =IFERROR(INDEX(【输出】数据汇总!$A:$AZ,MATCH(横向对比!BA$4&横向对比!$B50,【输出】数据汇总!$A:$A,0),MATCH(横向对比!$B$36,【输出】数据汇总!$1:$1,0))/100,"") -> 19.79852 | BB50: =IFERROR(INDEX(【输出】数据汇总!$A:$AZ,MATCH(横向对比!BB$36&横向对比!$B50,【输出】数据汇总!$A:$A,0),MATCH(横向对比!$B$36,【输出】数据汇总!$1:$1,0))/100,"") -> 38.23412 | BC50: =IFERROR(INDEX(【输出】数据汇总!$A:$AZ,MATCH(横向对比!BC$4&横向对比!$B50,【输出】数据汇总!$A:$A,0),MATCH(横向对比!$B$36,【输出】数据汇总!$1:$1,0))/100,"") -> 9.91315 | BD50: =IFERROR(INDEX(【输出】数据汇总!$A:$AZ,MATCH(横向对比!BD$4&横向对比!$B50,【输出】数据汇总!$A:$A,0),MATCH(横向对比!$B$36,【输出】数据汇总!$1:$1,0))/100,"") -> 13.69818 | BE50: =IFERROR(INDEX(【输出】数据汇总!$A:$AZ,MATCH(横向对比!BE$4&横向对比!$B50,【输出】数据汇总!$A:$A,0),MATCH(横向对比!$B$36,【输出】数据汇总!$1:$1,0))/100,"") -> 5.86521 | BF50: =IFERROR(INDEX(【输出】数据汇总!$A:$AZ,MATCH(横向对比!BF$4&横向对比!$B50,【输出】数据汇总!$A:$A,0),MATCH(横向对比!$B$36,【输出】数据汇总!$1:$1,0))/100,"") -> 17.77057 | BG50: =IFERROR(INDEX(【输出】数据汇总!$A:$AZ,MATCH(横向对比!BG$4&横向对比!$B50,【输出】数据汇总!$A:$A,0),MATCH(横向对比!$B$36,【输出】数据汇总!$1:$1,0))/100,"") -> 155.37407 | BH50: =IFERROR(INDEX(【输出】数据汇总!$A:$AZ,MATCH(横向对比!BH$4&横向对比!$B50,【输出】数据汇总!$A:$A,0),MATCH(横向对比!$B$36,【输出】数据汇总!$1:$1,0))/100,"") -> 10.71987 | BI50: =IFERROR(INDEX(【输出】数据汇总!$A:$AZ,MATCH(横向对比!BI$4&横向对比!$B50,【输出】数据汇总!$A:$A,0),MATCH(横向对比!$B$36,【输出】数据汇总!$1:$1,0))/100,"") -> 37.85044 | BJ50: =IFERROR(INDEX(【输出】数据汇总!$A:$AZ,MATCH(横向对比!BJ$4&横向对比!$B50,【输出】数据汇总!$A:$A,0),MATCH(横向对比!$B$36,【输出】数据汇总!$1:$1,0))/100,"") -> 53.89141 | ... BL50: =IFERROR(INDEX(【输出】数据汇总!$A:$AZ,MATCH(横向对比!BL$4&横向对比!$B50,【输出】数据汇总!$A:$A,0),MATCH(横向对比!$B$36,【输出】数据汇总!$1:$1,0))/100,"") -> 40.83638
B51: 归母净资产 | C51: =IFERROR(INDEX(【输出】数据汇总!$A:$AZ,MATCH(横向对比!C$4&横向对比!$B51,【输出】数据汇总!$A:$A,0),MATCH(横向对比!$B$36,【输出】数据汇总!$1:$1,0))/100,"") -> 250392.95 | D51: =IFERROR(INDEX(【输出】数据汇总!$A:$AZ,MATCH(横向对比!D$4&横向对比!$B51,【输出】数据汇总!$A:$A,0),MATCH(横向对比!$B$36,【输出】数据汇总!$1:$1,0))/100,"") -> 162413.08 | E51: =IFERROR(INDEX(【输出】数据汇总!$A:$AZ,MATCH(横向对比!E$4&横向对比!$B51,【输出】数据汇总!$A:$A,0),MATCH(横向对比!$B$36,【输出】数据汇总!$1:$1,0))/100,"") -> 61371.81 | F51: =IFERROR(INDEX(【输出】数据汇总!$A:$AZ,MATCH(横向对比!F$4&横向对比!$B51,【输出】数据汇总!$A:$A,0),MATCH(横向对比!$B$36,【输出】数据汇总!$1:$1,0))/100,"") -> 22040.662 | G51: =IFERROR(INDEX(【输出】数据汇总!$A:$AZ,MATCH(横向对比!G$4&横向对比!$B51,【输出】数据汇总!$A:$A,0),MATCH(横向对比!$B$36,【输出】数据汇总!$1:$1,0))/100,"") -> 4567.3953 | H51: =IFERROR(INDEX(【输出】数据汇总!$A:$AZ,MATCH(横向对比!H$4&横向对比!$B51,【输出】数据汇总!$A:$A,0),MATCH(横向对比!$B$36,【输出】数据汇总!$1:$1,0))/100,"") | I51: =IFERROR(INDEX(【输出】数据汇总!$A:$AZ,MATCH(横向对比!I$4&横向对比!$B51,【输出】数据汇总!$A:$A,0),MATCH(横向对比!$B$36,【输出】数据汇总!$1:$1,0))/100,"") -> 8658.4512 | J51: =IFERROR(INDEX(【输出】数据汇总!$A:$AZ,MATCH(横向对比!J$4&横向对比!$B51,【输出】数据汇总!$A:$A,0),MATCH(横向对比!$B$36,【输出】数据汇总!$1:$1,0))/100,"") -> 41146.92 | ... AA51: =IFERROR(INDEX(【输出】数据汇总!$A:$AZ,MATCH(横向对比!AA$4&横向对比!$B51,【输出】数据汇总!$A:$A,0),MATCH(横向对比!$B$36,【输出】数据汇总!$1:$1,0))/100,"") -> 2634.8802 | AB51: =IFERROR(INDEX(【输出】数据汇总!$A:$AZ,MATCH(横向对比!AB$36&横向对比!$B51,【输出】数据汇总!$A:$A,0),MATCH(横向对比!$B$36,【输出】数据汇总!$1:$1,0))/100,"") -> 2447.89 | AC51: =IFERROR(INDEX(【输出】数据汇总!$A:$AZ,MATCH(横向对比!AC$4&横向对比!$B51,【输出】数据汇总!$A:$A,0),MATCH(横向对比!$B$36,【输出】数据汇总!$1:$1,0))/100,"") -> 2066.3063 | AD51: =IFERROR(INDEX(【输出】数据汇总!$A:$AZ,MATCH(横向对比!AD$4&横向对比!$B51,【输出】数据汇总!$A:$A,0),MATCH(横向对比!$B$36,【输出】数据汇总!$1:$1,0))/100,"") -> 1605.359 | AE51: =IFERROR(INDEX(【输出】数据汇总!$A:$AZ,MATCH(横向对比!AE$4&横向对比!$B51,【输出】数据汇总!$A:$A,0),MATCH(横向对比!$B$36,【输出】数据汇总!$1:$1,0))/100,"") -> 885.32405 | AF51: =IFERROR(INDEX(【输出】数据汇总!$A:$AZ,MATCH(横向对比!AF$4&横向对比!$B51,【输出】数据汇总!$A:$A,0),MATCH(横向对比!$B$36,【输出】数据汇总!$1:$1,0))/100,"") -> 799.43422 | AG51: =IFERROR(INDEX(【输出】数据汇总!$A:$AZ,MATCH(横向对比!AG$4&横向对比!$B51,【输出】数据汇总!$A:$A,0),MATCH(横向对比!$B$36,【输出】数据汇总!$1:$1,0))/100,"") -> 627.15881 | AH51: =IFERROR(INDEX(【输出】数据汇总!$A:$AZ,MATCH(横向对比!AH$4&横向对比!$B51,【输出】数据汇总!$A:$A,0),MATCH(横向对比!$B$36,【输出】数据汇总!$1:$1,0))/100,"") -> 673.27459 | AI51: =IFERROR(INDEX(【输出】数据汇总!$A:$AZ,MATCH(横向对比!AI$4&横向对比!$B51,【输出】数据汇总!$A:$A,0),MATCH(横向对比!$B$36,【输出】数据汇总!$1:$1,0))/100,"") -> 554.85934 | AJ51: =IFERROR(INDEX(【输出】数据汇总!$A:$AZ,MATCH(横向对比!AJ$4&横向对比!$B51,【输出】数据汇总!$A:$A,0),MATCH(横向对比!$B$36,【输出】数据汇总!$1:$1,0))/100,"") -> 585.90029 | ... BA51: =IFERROR(INDEX(【输出】数据汇总!$A:$AZ,MATCH(横向对比!BA$4&横向对比!$B51,【输出】数据汇总!$A:$A,0),MATCH(横向对比!$B$36,【输出】数据汇总!$1:$1,0))/100,"") -> 947.36925 | BB51: =IFERROR(INDEX(【输出】数据汇总!$A:$AZ,MATCH(横向对比!BB$36&横向对比!$B51,【输出】数据汇总!$A:$A,0),MATCH(横向对比!$B$36,【输出】数据汇总!$1:$1,0))/100,"") -> 690.43443 | BC51: =IFERROR(INDEX(【输出】数据汇总!$A:$AZ,MATCH(横向对比!BC$4&横向对比!$B51,【输出】数据汇总!$A:$A,0),MATCH(横向对比!$B$36,【输出】数据汇总!$1:$1,0))/100,"") -> 475.94885 | BD51: =IFERROR(INDEX(【输出】数据汇总!$A:$AZ,MATCH(横向对比!BD$4&横向对比!$B51,【输出】数据汇总!$A:$A,0),MATCH(横向对比!$B$36,【输出】数据汇总!$1:$1,0))/100,"") -> 129.93011 | BE51: =IFERROR(INDEX(【输出】数据汇总!$A:$AZ,MATCH(横向对比!BE$4&横向对比!$B51,【输出】数据汇总!$A:$A,0),MATCH(横向对比!$B$36,【输出】数据汇总!$1:$1,0))/100,"") -> 340.75627 | BF51: =IFERROR(INDEX(【输出】数据汇总!$A:$AZ,MATCH(横向对比!BF$4&横向对比!$B51,【输出】数据汇总!$A:$A,0),MATCH(横向对比!$B$36,【输出】数据汇总!$1:$1,0))/100,"") -> 285.71854 | BG51: =IFERROR(INDEX(【输出】数据汇总!$A:$AZ,MATCH(横向对比!BG$4&横向对比!$B51,【输出】数据汇总!$A:$A,0),MATCH(横向对比!$B$36,【输出】数据汇总!$1:$1,0))/100,"") -> 1621.2345 | BH51: =IFERROR(INDEX(【输出】数据汇总!$A:$AZ,MATCH(横向对比!BH$4&横向对比!$B51,【输出】数据汇总!$A:$A,0),MATCH(横向对比!$B$36,【输出】数据汇总!$1:$1,0))/100,"") -> 630.94563 | BI51: =IFERROR(INDEX(【输出】数据汇总!$A:$AZ,MATCH(横向对比!BI$4&横向对比!$B51,【输出】数据汇总!$A:$A,0),MATCH(横向对比!$B$36,【输出】数据汇总!$1:$1,0))/100,"") -> 530.42355 | BJ51: =IFERROR(INDEX(【输出】数据汇总!$A:$AZ,MATCH(横向对比!BJ$4&横向对比!$B51,【输出】数据汇总!$A:$A,0),MATCH(横向对比!$B$36,【输出】数据汇总!$1:$1,0))/100,"") -> 1133.1568 | ... BL51: =IFERROR(INDEX(【输出】数据汇总!$A:$AZ,MATCH(横向对比!BL$4&横向对比!$B51,【输出】数据汇总!$A:$A,0),MATCH(横向对比!$B$36,【输出】数据汇总!$1:$1,0))/100,"") -> 598.27029
B52: 逾期率 | C52: =IFERROR(INDEX(【输出】数据汇总!$A:$AZ,MATCH(横向对比!C$4&横向对比!$B52,【输出】数据汇总!$A:$A,0),MATCH(横向对比!$B$36,【输出】数据汇总!$1:$1,0)),"") -> 0.016192075 | D52: =IFERROR(INDEX(【输出】数据汇总!$A:$AZ,MATCH(横向对比!D$4&横向对比!$B52,【输出】数据汇总!$A:$A,0),MATCH(横向对比!$B$36,【输出】数据汇总!$1:$1,0)),"") -> 0.013372734 | E52: =IFERROR(INDEX(【输出】数据汇总!$A:$AZ,MATCH(横向对比!E$4&横向对比!$B52,【输出】数据汇总!$A:$A,0),MATCH(横向对比!$B$36,【输出】数据汇总!$1:$1,0)),"") -> 0.017662812 | F52: =IFERROR(INDEX(【输出】数据汇总!$A:$AZ,MATCH(横向对比!F$4&横向对比!$B52,【输出】数据汇总!$A:$A,0),MATCH(横向对比!$B$36,【输出】数据汇总!$1:$1,0)),"") -> 0.018221158 | G52: =IFERROR(INDEX(【输出】数据汇总!$A:$AZ,MATCH(横向对比!G$4&横向对比!$B52,【输出】数据汇总!$A:$A,0),MATCH(横向对比!$B$36,【输出】数据汇总!$1:$1,0)),"") -> 0.015511594 | H52: =IFERROR(INDEX(【输出】数据汇总!$A:$AZ,MATCH(横向对比!H$4&横向对比!$B52,【输出】数据汇总!$A:$A,0),MATCH(横向对比!$B$36,【输出】数据汇总!$1:$1,0)),"") | I52: =IFERROR(INDEX(【输出】数据汇总!$A:$AZ,MATCH(横向对比!I$4&横向对比!$B52,【输出】数据汇总!$A:$A,0),MATCH(横向对比!$B$36,【输出】数据汇总!$1:$1,0)),"") -> 0.036709832 | J52: =IFERROR(INDEX(【输出】数据汇总!$A:$AZ,MATCH(横向对比!J$4&横向对比!$B52,【输出】数据汇总!$A:$A,0),MATCH(横向对比!$B$36,【输出】数据汇总!$1:$1,0)),"") -> 0.015205896 | ... AA52: =IFERROR(INDEX(【输出】数据汇总!$A:$AZ,MATCH(横向对比!AA$4&横向对比!$B52,【输出】数据汇总!$A:$A,0),MATCH(横向对比!$B$36,【输出】数据汇总!$1:$1,0)),"") -> 0.015959023 | AB52: =IFERROR(INDEX(【输出】数据汇总!$A:$AZ,MATCH(横向对比!AB$36&横向对比!$B52,【输出】数据汇总!$A:$A,0),MATCH(横向对比!$B$36,【输出】数据汇总!$1:$1,0)),"") -> 0.008858406 | AC52: =IFERROR(INDEX(【输出】数据汇总!$A:$AZ,MATCH(横向对比!AC$4&横向对比!$B52,【输出】数据汇总!$A:$A,0),MATCH(横向对比!$B$36,【输出】数据汇总!$1:$1,0)),"") -> 0.012692506 | AD52: =IFERROR(INDEX(【输出】数据汇总!$A:$AZ,MATCH(横向对比!AD$4&横向对比!$B52,【输出】数据汇总!$A:$A,0),MATCH(横向对比!$B$36,【输出】数据汇总!$1:$1,0)),"") -> 0.0060657921 | AE52: =IFERROR(INDEX(【输出】数据汇总!$A:$AZ,MATCH(横向对比!AE$4&横向对比!$B52,【输出】数据汇总!$A:$A,0),MATCH(横向对比!$B$36,【输出】数据汇总!$1:$1,0)),"") -> 0.0076813397 | AF52: =IFERROR(INDEX(【输出】数据汇总!$A:$AZ,MATCH(横向对比!AF$4&横向对比!$B52,【输出】数据汇总!$A:$A,0),MATCH(横向对比!$B$36,【输出】数据汇总!$1:$1,0)),"") -> 0.022241233 | AG52: =IFERROR(INDEX(【输出】数据汇总!$A:$AZ,MATCH(横向对比!AG$4&横向对比!$B52,【输出】数据汇总!$A:$A,0),MATCH(横向对比!$B$36,【输出】数据汇总!$1:$1,0)),"") -> 0.015757027 | AH52: =IFERROR(INDEX(【输出】数据汇总!$A:$AZ,MATCH(横向对比!AH$4&横向对比!$B52,【输出】数据汇总!$A:$A,0),MATCH(横向对比!$B$36,【输出】数据汇总!$1:$1,0)),"") -> 0.028325353 | AI52: =IFERROR(INDEX(【输出】数据汇总!$A:$AZ,MATCH(横向对比!AI$4&横向对比!$B52,【输出】数据汇总!$A:$A,0),MATCH(横向对比!$B$36,【输出】数据汇总!$1:$1,0)),"") -> 0.051929046 | AJ52: =IFERROR(INDEX(【输出】数据汇总!$A:$AZ,MATCH(横向对比!AJ$4&横向对比!$B52,【输出】数据汇总!$A:$A,0),MATCH(横向对比!$B$36,【输出】数据汇总!$1:$1,0)),"") -> 0.0098779646 | ... BA52: =IFERROR(INDEX(【输出】数据汇总!$A:$AZ,MATCH(横向对比!BA$4&横向对比!$B52,【输出】数据汇总!$A:$A,0),MATCH(横向对比!$B$36,【输出】数据汇总!$1:$1,0)),"") -> 0.07122527 | BB52: =IFERROR(INDEX(【输出】数据汇总!$A:$AZ,MATCH(横向对比!BB$36&横向对比!$B52,【输出】数据汇总!$A:$A,0),MATCH(横向对比!$B$36,【输出】数据汇总!$1:$1,0)),"") -> 0.02646214 | BC52: =IFERROR(INDEX(【输出】数据汇总!$A:$AZ,MATCH(横向对比!BC$4&横向对比!$B52,【输出】数据汇总!$A:$A,0),MATCH(横向对比!$B$36,【输出】数据汇总!$1:$1,0)),"") -> 0.036093149 | BD52: =IFERROR(INDEX(【输出】数据汇总!$A:$AZ,MATCH(横向对比!BD$4&横向对比!$B52,【输出】数据汇总!$A:$A,0),MATCH(横向对比!$B$36,【输出】数据汇总!$1:$1,0)),"") -> 0.015304594 | BE52: =IFERROR(INDEX(【输出】数据汇总!$A:$AZ,MATCH(横向对比!BE$4&横向对比!$B52,【输出】数据汇总!$A:$A,0),MATCH(横向对比!$B$36,【输出】数据汇总!$1:$1,0)),"") -> 0.026119 | BF52: =IFERROR(INDEX(【输出】数据汇总!$A:$AZ,MATCH(横向对比!BF$4&横向对比!$B52,【输出】数据汇总!$A:$A,0),MATCH(横向对比!$B$36,【输出】数据汇总!$1:$1,0)),"") -> 0.020323937 | BG52: =IFERROR(INDEX(【输出】数据汇总!$A:$AZ,MATCH(横向对比!BG$4&横向对比!$B52,【输出】数据汇总!$A:$A,0),MATCH(横向对比!$B$36,【输出】数据汇总!$1:$1,0)),"") -> 0.012127221 | BH52: =IFERROR(INDEX(【输出】数据汇总!$A:$AZ,MATCH(横向对比!BH$4&横向对比!$B52,【输出】数据汇总!$A:$A,0),MATCH(横向对比!$B$36,【输出】数据汇总!$1:$1,0)),"") -> 0.12989481 | BI52: =IFERROR(INDEX(【输出】数据汇总!$A:$AZ,MATCH(横向对比!BI$4&横向对比!$B52,【输出】数据汇总!$A:$A,0),MATCH(横向对比!$B$36,【输出】数据汇总!$1:$1,0)),"") -> 0.027781526 | BJ52: =IFERROR(INDEX(【输出】数据汇总!$A:$AZ,MATCH(横向对比!BJ$4&横向对比!$B52,【输出】数据汇总!$A:$A,0),MATCH(横向对比!$B$36,【输出】数据汇总!$1:$1,0)),"") -> 0.03055361 | ... BL52: =IFERROR(INDEX(【输出】数据汇总!$A:$AZ,MATCH(横向对比!BL$4&横向对比!$B52,【输出】数据汇总!$A:$A,0),MATCH(横向对比!$B$36,【输出】数据汇总!$1:$1,0)),"") -> 0.024025031
B53: 重组率 | C53: =IFERROR(INDEX(【输出】数据汇总!$A:$AZ,MATCH(横向对比!C$4&横向对比!$B53,【输出】数据汇总!$A:$A,0),MATCH(横向对比!$B$36,【输出】数据汇总!$1:$1,0)),"") -> 0.0058875476 | D53: =IFERROR(INDEX(【输出】数据汇总!$A:$AZ,MATCH(横向对比!D$4&横向对比!$B53,【输出】数据汇总!$A:$A,0),MATCH(横向对比!$B$36,【输出】数据汇总!$1:$1,0)),"") -> 0.0048920294 | E53: =IFERROR(INDEX(【输出】数据汇总!$A:$AZ,MATCH(横向对比!E$4&横向对比!$B53,【输出】数据汇总!$A:$A,0),MATCH(横向对比!$B$36,【输出】数据汇总!$1:$1,0)),"") -> 0.006173467 | F53: =IFERROR(INDEX(【输出】数据汇总!$A:$AZ,MATCH(横向对比!F$4&横向对比!$B53,【输出】数据汇总!$A:$A,0),MATCH(横向对比!$B$36,【输出】数据汇总!$1:$1,0)),"") -> 0.0067922076 | G53: =IFERROR(INDEX(【输出】数据汇总!$A:$AZ,MATCH(横向对比!G$4&横向对比!$B53,【输出】数据汇总!$A:$A,0),MATCH(横向对比!$B$36,【输出】数据汇总!$1:$1,0)),"") -> 0.0056924863 | H53: =IFERROR(INDEX(【输出】数据汇总!$A:$AZ,MATCH(横向对比!H$4&横向对比!$B53,【输出】数据汇总!$A:$A,0),MATCH(横向对比!$B$36,【输出】数据汇总!$1:$1,0)),"") | I53: =IFERROR(INDEX(【输出】数据汇总!$A:$AZ,MATCH(横向对比!I$4&横向对比!$B53,【输出】数据汇总!$A:$A,0),MATCH(横向对比!$B$36,【输出】数据汇总!$1:$1,0)),"") -> 0.010483379 | J53: =IFERROR(INDEX(【输出】数据汇总!$A:$AZ,MATCH(横向对比!J$4&横向对比!$B53,【输出】数据汇总!$A:$A,0),MATCH(横向对比!$B$36,【输出】数据汇总!$1:$1,0)),"") -> 0.0046698334 | ... AA53: =IFERROR(INDEX(【输出】数据汇总!$A:$AZ,MATCH(横向对比!AA$4&横向对比!$B53,【输出】数据汇总!$A:$A,0),MATCH(横向对比!$B$36,【输出】数据汇总!$1:$1,0)),"") -> 0.0033707522 | AB53: =IFERROR(INDEX(【输出】数据汇总!$A:$AZ,MATCH(横向对比!AB$36&横向对比!$B53,【输出】数据汇总!$A:$A,0),MATCH(横向对比!$B$36,【输出】数据汇总!$1:$1,0)),"") -> 0.0023571416 | AC53: =IFERROR(INDEX(【输出】数据汇总!$A:$AZ,MATCH(横向对比!AC$4&横向对比!$B53,【输出】数据汇总!$A:$A,0),MATCH(横向对比!$B$36,【输出】数据汇总!$1:$1,0)),"") -> 0.0059393634 | AD53: =IFERROR(INDEX(【输出】数据汇总!$A:$AZ,MATCH(横向对比!AD$4&横向对比!$B53,【输出】数据汇总!$A:$A,0),MATCH(横向对比!$B$36,【输出】数据汇总!$1:$1,0)),"") -> 0.0025400612 | AE53: =IFERROR(INDEX(【输出】数据汇总!$A:$AZ,MATCH(横向对比!AE$4&横向对比!$B53,【输出】数据汇总!$A:$A,0),MATCH(横向对比!$B$36,【输出】数据汇总!$1:$1,0)),"") -> 0.00233361 | AF53: =IFERROR(INDEX(【输出】数据汇总!$A:$AZ,MATCH(横向对比!AF$4&横向对比!$B53,【输出】数据汇总!$A:$A,0),MATCH(横向对比!$B$36,【输出】数据汇总!$1:$1,0)),"") -> 0.0060551633 | AG53: =IFERROR(INDEX(【输出】数据汇总!$A:$AZ,MATCH(横向对比!AG$4&横向对比!$B53,【输出】数据汇总!$A:$A,0),MATCH(横向对比!$B$36,【输出】数据汇总!$1:$1,0)),"") -> 0.0020142342 | AH53: =IFERROR(INDEX(【输出】数据汇总!$A:$AZ,MATCH(横向对比!AH$4&横向对比!$B53,【输出】数据汇总!$A:$A,0),MATCH(横向对比!$B$36,【输出】数据汇总!$1:$1,0)),"") -> 0.013220358 | AI53: =IFERROR(INDEX(【输出】数据汇总!$A:$AZ,MATCH(横向对比!AI$4&横向对比!$B53,【输出】数据汇总!$A:$A,0),MATCH(横向对比!$B$36,【输出】数据汇总!$1:$1,0)),"") | AJ53: =IFERROR(INDEX(【输出】数据汇总!$A:$AZ,MATCH(横向对比!AJ$4&横向对比!$B53,【输出】数据汇总!$A:$A,0),MATCH(横向对比!$B$36,【输出】数据汇总!$1:$1,0)),"") -> 0.0046800725 | ... BA53: =IFERROR(INDEX(【输出】数据汇总!$A:$AZ,MATCH(横向对比!BA$4&横向对比!$B53,【输出】数据汇总!$A:$A,0),MATCH(横向对比!$B$36,【输出】数据汇总!$1:$1,0)),"") -> 0.04695234 | BB53: =IFERROR(INDEX(【输出】数据汇总!$A:$AZ,MATCH(横向对比!BB$36&横向对比!$B53,【输出】数据汇总!$A:$A,0),MATCH(横向对比!$B$36,【输出】数据汇总!$1:$1,0)),"") -> 0 | BC53: =IFERROR(INDEX(【输出】数据汇总!$A:$AZ,MATCH(横向对比!BC$4&横向对比!$B53,【输出】数据汇总!$A:$A,0),MATCH(横向对比!$B$36,【输出】数据汇总!$1:$1,0)),"") -> 0 | BD53: =IFERROR(INDEX(【输出】数据汇总!$A:$AZ,MATCH(横向对比!BD$4&横向对比!$B53,【输出】数据汇总!$A:$A,0),MATCH(横向对比!$B$36,【输出】数据汇总!$1:$1,0)),"") -> 0.0029190916 | BE53: =IFERROR(INDEX(【输出】数据汇总!$A:$AZ,MATCH(横向对比!BE$4&横向对比!$B53,【输出】数据汇总!$A:$A,0),MATCH(横向对比!$B$36,【输出】数据汇总!$1:$1,0)),"") -> 0 | BF53: =IFERROR(INDEX(【输出】数据汇总!$A:$AZ,MATCH(横向对比!BF$4&横向对比!$B53,【输出】数据汇总!$A:$A,0),MATCH(横向对比!$B$36,【输出】数据汇总!$1:$1,0)),"") -> 0 | BG53: =IFERROR(INDEX(【输出】数据汇总!$A:$AZ,MATCH(横向对比!BG$4&横向对比!$B53,【输出】数据汇总!$A:$A,0),MATCH(横向对比!$B$36,【输出】数据汇总!$1:$1,0)),"") -> 0.0031230325 | BH53: =IFERROR(INDEX(【输出】数据汇总!$A:$AZ,MATCH(横向对比!BH$4&横向对比!$B53,【输出】数据汇总!$A:$A,0),MATCH(横向对比!$B$36,【输出】数据汇总!$1:$1,0)),"") -> 0.06992042 | BI53: =IFERROR(INDEX(【输出】数据汇总!$A:$AZ,MATCH(横向对比!BI$4&横向对比!$B53,【输出】数据汇总!$A:$A,0),MATCH(横向对比!$B$36,【输出】数据汇总!$1:$1,0)),"") -> 0.0093276725 | BJ53: =IFERROR(INDEX(【输出】数据汇总!$A:$AZ,MATCH(横向对比!BJ$4&横向对比!$B53,【输出】数据汇总!$A:$A,0),MATCH(横向对比!$B$36,【输出】数据汇总!$1:$1,0)),"") -> 0.0017958258 | ... BL53: =IFERROR(INDEX(【输出】数据汇总!$A:$AZ,MATCH(横向对比!BL$4&横向对比!$B53,【输出】数据汇总!$A:$A,0),MATCH(横向对比!$B$36,【输出】数据汇总!$1:$1,0)),"") -> 0.0022455424
B54: 不良贷款率 | C54: =IFERROR(INDEX(【输出】数据汇总!$A:$AZ,MATCH(横向对比!C$4&横向对比!$B54,【输出】数据汇总!$A:$A,0),MATCH(横向对比!$B$36,【输出】数据汇总!$1:$1,0)),"") -> 0.011635049 | D54: =IFERROR(INDEX(【输出】数据汇总!$A:$AZ,MATCH(横向对比!D$4&横向对比!$B54,【输出】数据汇总!$A:$A,0),MATCH(横向对比!$B$36,【输出】数据汇总!$1:$1,0)),"") -> 0.0123 | E54: =IFERROR(INDEX(【输出】数据汇总!$A:$AZ,MATCH(横向对比!E$4&横向对比!$B54,【输出】数据汇总!$A:$A,0),MATCH(横向对比!$B$36,【输出】数据汇总!$1:$1,0)),"") -> 0.012466667 | F54: =IFERROR(INDEX(【输出】数据汇总!$A:$AZ,MATCH(横向对比!F$4&横向对比!$B54,【输出】数据汇总!$A:$A,0),MATCH(横向对比!$B$36,【输出】数据汇总!$1:$1,0)),"") -> 0.011423529 | G54: =IFERROR(INDEX(【输出】数据汇总!$A:$AZ,MATCH(横向对比!G$4&横向对比!$B54,【输出】数据汇总!$A:$A,0),MATCH(横向对比!$B$36,【输出】数据汇总!$1:$1,0)),"") -> 0.01035 | H54: =IFERROR(INDEX(【输出】数据汇总!$A:$AZ,MATCH(横向对比!H$4&横向对比!$B54,【输出】数据汇总!$A:$A,0),MATCH(横向对比!$B$36,【输出】数据汇总!$1:$1,0)),"") | I54: =IFERROR(INDEX(【输出】数据汇总!$A:$AZ,MATCH(横向对比!I$4&横向对比!$B54,【输出】数据汇总!$A:$A,0),MATCH(横向对比!$B$36,【输出】数据汇总!$1:$1,0)),"") -> 0.018 | J54: =IFERROR(INDEX(【输出】数据汇总!$A:$AZ,MATCH(横向对比!J$4&横向对比!$B54,【输出】数据汇总!$A:$A,0),MATCH(横向对比!$B$36,【输出】数据汇总!$1:$1,0)),"") -> 0.0133 | ... AA54: =IFERROR(INDEX(【输出】数据汇总!$A:$AZ,MATCH(横向对比!AA$4&横向对比!$B54,【输出】数据汇总!$A:$A,0),MATCH(横向对比!$B$36,【输出】数据汇总!$1:$1,0)),"") -> 0.0118 | AB54: =IFERROR(INDEX(【输出】数据汇总!$A:$AZ,MATCH(横向对比!AB$36&横向对比!$B54,【输出】数据汇总!$A:$A,0),MATCH(横向对比!$B$36,【输出】数据汇总!$1:$1,0)),"") -> 0.0076 | AC54: =IFERROR(INDEX(【输出】数据汇总!$A:$AZ,MATCH(横向对比!AC$4&横向对比!$B54,【输出】数据汇总!$A:$A,0),MATCH(横向对比!$B$36,【输出】数据汇总!$1:$1,0)),"") -> 0.0084 | AD54: =IFERROR(INDEX(【输出】数据汇总!$A:$AZ,MATCH(横向对比!AD$4&横向对比!$B54,【输出】数据汇总!$A:$A,0),MATCH(横向对比!$B$36,【输出】数据汇总!$1:$1,0)),"") -> 0.0076 | AE54: =IFERROR(INDEX(【输出】数据汇总!$A:$AZ,MATCH(横向对比!AE$4&横向对比!$B54,【输出】数据汇总!$A:$A,0),MATCH(横向对比!$B$36,【输出】数据汇总!$1:$1,0)),"") -> 0.0066 | AF54: =IFERROR(INDEX(【输出】数据汇总!$A:$AZ,MATCH(横向对比!AF$4&横向对比!$B54,【输出】数据汇总!$A:$A,0),MATCH(横向对比!$B$36,【输出】数据汇总!$1:$1,0)),"") -> 0.0117 | AG54: =IFERROR(INDEX(【输出】数据汇总!$A:$AZ,MATCH(横向对比!AG$4&横向对比!$B54,【输出】数据汇总!$A:$A,0),MATCH(横向对比!$B$36,【输出】数据汇总!$1:$1,0)),"") -> 0.0117 | AH54: =IFERROR(INDEX(【输出】数据汇总!$A:$AZ,MATCH(横向对比!AH$4&横向对比!$B54,【输出】数据汇总!$A:$A,0),MATCH(横向对比!$B$36,【输出】数据汇总!$1:$1,0)),"") -> 0.017 | AI54: =IFERROR(INDEX(【输出】数据汇总!$A:$AZ,MATCH(横向对比!AI$4&横向对比!$B54,【输出】数据汇总!$A:$A,0),MATCH(横向对比!$B$36,【输出】数据汇总!$1:$1,0)),"") -> 0.0176 | AJ54: =IFERROR(INDEX(【输出】数据汇总!$A:$AZ,MATCH(横向对比!AJ$4&横向对比!$B54,【输出】数据汇总!$A:$A,0),MATCH(横向对比!$B$36,【输出】数据汇总!$1:$1,0)),"") -> 0.0083 | ... BA54: =IFERROR(INDEX(【输出】数据汇总!$A:$AZ,MATCH(横向对比!BA$4&横向对比!$B54,【输出】数据汇总!$A:$A,0),MATCH(横向对比!$B$36,【输出】数据汇总!$1:$1,0)),"") -> 0.0198 | BB54: =IFERROR(INDEX(【输出】数据汇总!$A:$AZ,MATCH(横向对比!BB$36&横向对比!$B54,【输出】数据汇总!$A:$A,0),MATCH(横向对比!$B$36,【输出】数据汇总!$1:$1,0)),"") -> 0.0168 | BC54: =IFERROR(INDEX(【输出】数据汇总!$A:$AZ,MATCH(横向对比!BC$4&横向对比!$B54,【输出】数据汇总!$A:$A,0),MATCH(横向对比!$B$36,【输出】数据汇总!$1:$1,0)),"") -> 0.0236 | BD54: =IFERROR(INDEX(【输出】数据汇总!$A:$AZ,MATCH(横向对比!BD$4&横向对比!$B54,【输出】数据汇总!$A:$A,0),MATCH(横向对比!$B$36,【输出】数据汇总!$1:$1,0)),"") -> 0.0118 | BE54: =IFERROR(INDEX(【输出】数据汇总!$A:$AZ,MATCH(横向对比!BE$4&横向对比!$B54,【输出】数据汇总!$A:$A,0),MATCH(横向对比!$B$36,【输出】数据汇总!$1:$1,0)),"") -> 0.0185 | BF54: =IFERROR(INDEX(【输出】数据汇总!$A:$AZ,MATCH(横向对比!BF$4&横向对比!$B54,【输出】数据汇总!$A:$A,0),MATCH(横向对比!$B$36,【输出】数据汇总!$1:$1,0)),"") -> 0.0177 | BG54: =IFERROR(INDEX(【输出】数据汇总!$A:$AZ,MATCH(横向对比!BG$4&横向对比!$B54,【输出】数据汇总!$A:$A,0),MATCH(横向对比!$B$36,【输出】数据汇总!$1:$1,0)),"") -> 0.0098 | BH54: =IFERROR(INDEX(【输出】数据汇总!$A:$AZ,MATCH(横向对比!BH$4&横向对比!$B54,【输出】数据汇总!$A:$A,0),MATCH(横向对比!$B$36,【输出】数据汇总!$1:$1,0)),"") -> 0.0283 | BI54: =IFERROR(INDEX(【输出】数据汇总!$A:$AZ,MATCH(横向对比!BI$4&横向对比!$B54,【输出】数据汇总!$A:$A,0),MATCH(横向对比!$B$36,【输出】数据汇总!$1:$1,0)),"") -> 0.0169 | BJ54: =IFERROR(INDEX(【输出】数据汇总!$A:$AZ,MATCH(横向对比!BJ$4&横向对比!$B54,【输出】数据汇总!$A:$A,0),MATCH(横向对比!$B$36,【输出】数据汇总!$1:$1,0)),"") -> 0.0181 | ... BL54: =IFERROR(INDEX(【输出】数据汇总!$A:$AZ,MATCH(横向对比!BL$4&横向对比!$B54,【输出】数据汇总!$A:$A,0),MATCH(横向对比!$B$36,【输出】数据汇总!$1:$1,0)),"") -> 0.0187
B55: 关注贷款率 | C55: =IFERROR(INDEX(【输出】数据汇总!$A:$AZ,MATCH(横向对比!C$4&横向对比!$B55,【输出】数据汇总!$A:$A,0),MATCH(横向对比!$B$36,【输出】数据汇总!$1:$1,0)),"") -> 0.017704036 | D55: =IFERROR(INDEX(【输出】数据汇总!$A:$AZ,MATCH(横向对比!D$4&横向对比!$B55,【输出】数据汇总!$A:$A,0),MATCH(横向对比!$B$36,【输出】数据汇总!$1:$1,0)),"") -> 0.015572489 | E55: =IFERROR(INDEX(【输出】数据汇总!$A:$AZ,MATCH(横向对比!E$4&横向对比!$B55,【输出】数据汇总!$A:$A,0),MATCH(横向对比!$B$36,【输出】数据汇总!$1:$1,0)),"") -> 0.020223518 | F55: =IFERROR(INDEX(【输出】数据汇总!$A:$AZ,MATCH(横向对比!F$4&横向对比!$B55,【输出】数据汇总!$A:$A,0),MATCH(横向对比!$B$36,【输出】数据汇总!$1:$1,0)),"") -> 0.017817125 | G55: =IFERROR(INDEX(【输出】数据汇总!$A:$AZ,MATCH(横向对比!G$4&横向对比!$B55,【输出】数据汇总!$A:$A,0),MATCH(横向对比!$B$36,【输出】数据汇总!$1:$1,0)),"") -> 0.017203013 | H55: =IFERROR(INDEX(【输出】数据汇总!$A:$AZ,MATCH(横向对比!H$4&横向对比!$B55,【输出】数据汇总!$A:$A,0),MATCH(横向对比!$B$36,【输出】数据汇总!$1:$1,0)),"") | I55: =IFERROR(INDEX(【输出】数据汇总!$A:$AZ,MATCH(横向对比!I$4&横向对比!$B55,【输出】数据汇总!$A:$A,0),MATCH(横向对比!$B$36,【输出】数据汇总!$1:$1,0)),"") -> 0.034911925 | J55: =IFERROR(INDEX(【输出】数据汇总!$A:$AZ,MATCH(横向对比!J$4&横向对比!$B55,【输出】数据汇总!$A:$A,0),MATCH(横向对比!$B$36,【输出】数据汇总!$1:$1,0)),"") -> 0.019078033 | ... AA55: =IFERROR(INDEX(【输出】数据汇总!$A:$AZ,MATCH(横向对比!AA$4&横向对比!$B55,【输出】数据汇总!$A:$A,0),MATCH(横向对比!$B$36,【输出】数据汇总!$1:$1,0)),"") -> 0.020380297 | AB55: =IFERROR(INDEX(【输出】数据汇总!$A:$AZ,MATCH(横向对比!AB$36&横向对比!$B55,【输出】数据汇总!$A:$A,0),MATCH(横向对比!$B$36,【输出】数据汇总!$1:$1,0)),"") -> 0.010221054 | AC55: =IFERROR(INDEX(【输出】数据汇总!$A:$AZ,MATCH(横向对比!AC$4&横向对比!$B55,【输出】数据汇总!$A:$A,0),MATCH(横向对比!$B$36,【输出】数据汇总!$1:$1,0)),"") -> 0.010566551 | AD55: =IFERROR(INDEX(【输出】数据汇总!$A:$AZ,MATCH(横向对比!AD$4&横向对比!$B55,【输出】数据汇总!$A:$A,0),MATCH(横向对比!$B$36,【输出】数据汇总!$1:$1,0)),"") -> 0.0051245232 | AE55: =IFERROR(INDEX(【输出】数据汇总!$A:$AZ,MATCH(横向对比!AE$4&横向对比!$B55,【输出】数据汇总!$A:$A,0),MATCH(横向对比!$B$36,【输出】数据汇总!$1:$1,0)),"") -> 0.0044015602 | AF55: =IFERROR(INDEX(【输出】数据汇总!$A:$AZ,MATCH(横向对比!AF$4&横向对比!$B55,【输出】数据汇总!$A:$A,0),MATCH(横向对比!$B$36,【输出】数据汇总!$1:$1,0)),"") -> 0.033136158 | AG55: =IFERROR(INDEX(【输出】数据汇总!$A:$AZ,MATCH(横向对比!AG$4&横向对比!$B55,【输出】数据汇总!$A:$A,0),MATCH(横向对比!$B$36,【输出】数据汇总!$1:$1,0)),"") -> 0.020479235 | AH55: =IFERROR(INDEX(【输出】数据汇总!$A:$AZ,MATCH(横向对比!AH$4&横向对比!$B55,【输出】数据汇总!$A:$A,0),MATCH(横向对比!$B$36,【输出】数据汇总!$1:$1,0)),"") -> 0.031221221 | AI55: =IFERROR(INDEX(【输出】数据汇总!$A:$AZ,MATCH(横向对比!AI$4&横向对比!$B55,【输出】数据汇总!$A:$A,0),MATCH(横向对比!$B$36,【输出】数据汇总!$1:$1,0)),"") -> 0.020261744 | AJ55: =IFERROR(INDEX(【输出】数据汇总!$A:$AZ,MATCH(横向对比!AJ$4&横向对比!$B55,【输出】数据汇总!$A:$A,0),MATCH(横向对比!$B$36,【输出】数据汇总!$1:$1,0)),"") -> 0.0075421059 | ... BA55: =IFERROR(INDEX(【输出】数据汇总!$A:$AZ,MATCH(横向对比!BA$4&横向对比!$B55,【输出】数据汇总!$A:$A,0),MATCH(横向对比!$B$36,【输出】数据汇总!$1:$1,0)),"") -> 0.068714717 | BB55: =IFERROR(INDEX(【输出】数据汇总!$A:$AZ,MATCH(横向对比!BB$36&横向对比!$B55,【输出】数据汇总!$A:$A,0),MATCH(横向对比!$B$36,【输出】数据汇总!$1:$1,0)),"") -> 0.033446057 | BC55: =IFERROR(INDEX(【输出】数据汇总!$A:$AZ,MATCH(横向对比!BC$4&横向对比!$B55,【输出】数据汇总!$A:$A,0),MATCH(横向对比!$B$36,【输出】数据汇总!$1:$1,0)),"") -> 0.03739889 | BD55: =IFERROR(INDEX(【输出】数据汇总!$A:$AZ,MATCH(横向对比!BD$4&横向对比!$B55,【输出】数据汇总!$A:$A,0),MATCH(横向对比!$B$36,【输出】数据汇总!$1:$1,0)),"") -> 0.015797783 | BE55: =IFERROR(INDEX(【输出】数据汇总!$A:$AZ,MATCH(横向对比!BE$4&横向对比!$B55,【输出】数据汇总!$A:$A,0),MATCH(横向对比!$B$36,【输出】数据汇总!$1:$1,0)),"") -> 0.046923071 | BF55: =IFERROR(INDEX(【输出】数据汇总!$A:$AZ,MATCH(横向对比!BF$4&横向对比!$B55,【输出】数据汇总!$A:$A,0),MATCH(横向对比!$B$36,【输出】数据汇总!$1:$1,0)),"") -> 0.045361274 | BG55: =IFERROR(INDEX(【输出】数据汇总!$A:$AZ,MATCH(横向对比!BG$4&横向对比!$B55,【输出】数据汇总!$A:$A,0),MATCH(横向对比!$B$36,【输出】数据汇总!$1:$1,0)),"") -> 0.011403566 | BH55: =IFERROR(INDEX(【输出】数据汇总!$A:$AZ,MATCH(横向对比!BH$4&横向对比!$B55,【输出】数据汇总!$A:$A,0),MATCH(横向对比!$B$36,【输出】数据汇总!$1:$1,0)),"") -> 0.05986348 | BI55: =IFERROR(INDEX(【输出】数据汇总!$A:$AZ,MATCH(横向对比!BI$4&横向对比!$B55,【输出】数据汇总!$A:$A,0),MATCH(横向对比!$B$36,【输出】数据汇总!$1:$1,0)),"") -> 0.029790717 | BJ55: =IFERROR(INDEX(【输出】数据汇总!$A:$AZ,MATCH(横向对比!BJ$4&横向对比!$B55,【输出】数据汇总!$A:$A,0),MATCH(横向对比!$B$36,【输出】数据汇总!$1:$1,0)),"") -> 0.02909095 | ... BL55: =IFERROR(INDEX(【输出】数据汇总!$A:$AZ,MATCH(横向对比!BL$4&横向对比!$B55,【输出】数据汇总!$A:$A,0),MATCH(横向对比!$B$36,【输出】数据汇总!$1:$1,0)),"") -> 0.019015308
B56: 逾期+重组率 | C56: =IFERROR(C52+C53,"") -> 0.022079622 | D56: =IFERROR(D52+D53,"") -> 0.018264764 | E56: =IFERROR(E52+E53,"") -> 0.023836279 | F56: =IFERROR(F52+F53,"") -> 0.025013366 | G56: =IFERROR(G52+G53,"") -> 0.021204081 | H56: =IFERROR(H52+H53,"") | I56: =IFERROR(I52+I53,"") -> 0.04719321 | J56: =IFERROR(J52+J53,"") -> 0.01987573 | ... BL56: =IFERROR(BL52+BL53,"") -> 0.026270574
B57: 不良+关注率 | C57: =IFERROR(C54+C55,"") -> 0.029339085 | D57: =IFERROR(D54+D55,"") -> 0.027872489 | E57: =IFERROR(E54+E55,"") -> 0.032690185 | F57: =IFERROR(F54+F55,"") -> 0.029240654 | G57: =IFERROR(G54+G55,"") -> 0.027553013 | H57: =IFERROR(H54+H55,"") | I57: =IFERROR(I54+I55,"") -> 0.052911925 | J57: =IFERROR(J54+J55,"") -> 0.032378033 | ... BL57: =IFERROR(BL54+BL55,"") -> 0.037715308
A58: ⑥/① | B58: 广义风险贷款比率 | C58: =IFERROR(INDEX(【输出】数据汇总!$A:$AZ,MATCH(横向对比!C$4&横向对比!$B58,【输出】数据汇总!$A:$A,0),MATCH(横向对比!$B$36,【输出】数据汇总!$1:$1,0)),"") -> 0.029707424 | D58: =IFERROR(INDEX(【输出】数据汇总!$A:$AZ,MATCH(横向对比!D$4&横向对比!$B58,【输出】数据汇总!$A:$A,0),MATCH(横向对比!$B$36,【输出】数据汇总!$1:$1,0)),"") -> 0.027872489 | E58: =IFERROR(INDEX(【输出】数据汇总!$A:$AZ,MATCH(横向对比!E$4&横向对比!$B58,【输出】数据汇总!$A:$A,0),MATCH(横向对比!$B$36,【输出】数据汇总!$1:$1,0)),"") -> 0.032690185 | F58: =IFERROR(INDEX(【输出】数据汇总!$A:$AZ,MATCH(横向对比!F$4&横向对比!$B58,【输出】数据汇总!$A:$A,0),MATCH(横向对比!$B$36,【输出】数据汇总!$1:$1,0)),"") -> 0.030694185 | G58: =IFERROR(INDEX(【输出】数据汇总!$A:$AZ,MATCH(横向对比!G$4&横向对比!$B58,【输出】数据汇总!$A:$A,0),MATCH(横向对比!$B$36,【输出】数据汇总!$1:$1,0)),"") -> 0.027572838 | H58: =IFERROR(INDEX(【输出】数据汇总!$A:$AZ,MATCH(横向对比!H$4&横向对比!$B58,【输出】数据汇总!$A:$A,0),MATCH(横向对比!$B$36,【输出】数据汇总!$1:$1,0)),"") | I58: =IFERROR(INDEX(【输出】数据汇总!$A:$AZ,MATCH(横向对比!I$4&横向对比!$B58,【输出】数据汇总!$A:$A,0),MATCH(横向对比!$B$36,【输出】数据汇总!$1:$1,0)),"") -> 0.063782282 | J58: =IFERROR(INDEX(【输出】数据汇总!$A:$AZ,MATCH(横向对比!J$4&横向对比!$B58,【输出】数据汇总!$A:$A,0),MATCH(横向对比!$B$36,【输出】数据汇总!$1:$1,0)),"") -> 0.032378033 | ... AA58: =IFERROR(INDEX(【输出】数据汇总!$A:$AZ,MATCH(横向对比!AA$4&横向对比!$B58,【输出】数据汇总!$A:$A,0),MATCH(横向对比!$B$36,【输出】数据汇总!$1:$1,0)),"") -> 0.032180297 | AB58: =IFERROR(INDEX(【输出】数据汇总!$A:$AZ,MATCH(横向对比!AB$36&横向对比!$B58,【输出】数据汇总!$A:$A,0),MATCH(横向对比!$B$36,【输出】数据汇总!$1:$1,0)),"") -> 0.017821054 | AC58: =IFERROR(INDEX(【输出】数据汇总!$A:$AZ,MATCH(横向对比!AC$4&横向对比!$B58,【输出】数据汇总!$A:$A,0),MATCH(横向对比!$B$36,【输出】数据汇总!$1:$1,0)),"") -> 0.018966551 | AD58: =IFERROR(INDEX(【输出】数据汇总!$A:$AZ,MATCH(横向对比!AD$4&横向对比!$B58,【输出】数据汇总!$A:$A,0),MATCH(横向对比!$B$36,【输出】数据汇总!$1:$1,0)),"") -> 0.012724523 | AE58: =IFERROR(INDEX(【输出】数据汇总!$A:$AZ,MATCH(横向对比!AE$4&横向对比!$B58,【输出】数据汇总!$A:$A,0),MATCH(横向对比!$B$36,【输出】数据汇总!$1:$1,0)),"") -> 0.01100156 | AF58: =IFERROR(INDEX(【输出】数据汇总!$A:$AZ,MATCH(横向对比!AF$4&横向对比!$B58,【输出】数据汇总!$A:$A,0),MATCH(横向对比!$B$36,【输出】数据汇总!$1:$1,0)),"") -> 0.044836158 | AG58: =IFERROR(INDEX(【输出】数据汇总!$A:$AZ,MATCH(横向对比!AG$4&横向对比!$B58,【输出】数据汇总!$A:$A,0),MATCH(横向对比!$B$36,【输出】数据汇总!$1:$1,0)),"") -> 0.032179235 | AH58: =IFERROR(INDEX(【输出】数据汇总!$A:$AZ,MATCH(横向对比!AH$4&横向对比!$B58,【输出】数据汇总!$A:$A,0),MATCH(横向对比!$B$36,【输出】数据汇总!$1:$1,0)),"") -> 0.048221221 | AI58: =IFERROR(INDEX(【输出】数据汇总!$A:$AZ,MATCH(横向对比!AI$4&横向对比!$B58,【输出】数据汇总!$A:$A,0),MATCH(横向对比!$B$36,【输出】数据汇总!$1:$1,0)),"") -> 0.037861744 | AJ58: =IFERROR(INDEX(【输出】数据汇总!$A:$AZ,MATCH(横向对比!AJ$4&横向对比!$B58,【输出】数据汇总!$A:$A,0),MATCH(横向对比!$B$36,【输出】数据汇总!$1:$1,0)),"") -> 0.015842106 | ... BA58: =IFERROR(INDEX(【输出】数据汇总!$A:$AZ,MATCH(横向对比!BA$4&横向对比!$B58,【输出】数据汇总!$A:$A,0),MATCH(横向对比!$B$36,【输出】数据汇总!$1:$1,0)),"") -> 0.11817761 | BB58: =IFERROR(INDEX(【输出】数据汇总!$A:$AZ,MATCH(横向对比!BB$36&横向对比!$B58,【输出】数据汇总!$A:$A,0),MATCH(横向对比!$B$36,【输出】数据汇总!$1:$1,0)),"") -> 0.050246057 | BC58: =IFERROR(INDEX(【输出】数据汇总!$A:$AZ,MATCH(横向对比!BC$4&横向对比!$B58,【输出】数据汇总!$A:$A,0),MATCH(横向对比!$B$36,【输出】数据汇总!$1:$1,0)),"") -> 0.06099889 | BD58: =IFERROR(INDEX(【输出】数据汇总!$A:$AZ,MATCH(横向对比!BD$4&横向对比!$B58,【输出】数据汇总!$A:$A,0),MATCH(横向对比!$B$36,【输出】数据汇总!$1:$1,0)),"") -> 0.027597783 | BE58: =IFERROR(INDEX(【输出】数据汇总!$A:$AZ,MATCH(横向对比!BE$4&横向对比!$B58,【输出】数据汇总!$A:$A,0),MATCH(横向对比!$B$36,【输出】数据汇总!$1:$1,0)),"") -> 0.065423071 | BF58: =IFERROR(INDEX(【输出】数据汇总!$A:$AZ,MATCH(横向对比!BF$4&横向对比!$B58,【输出】数据汇总!$A:$A,0),MATCH(横向对比!$B$36,【输出】数据汇总!$1:$1,0)),"") -> 0.063061274 | BG58: =IFERROR(INDEX(【输出】数据汇总!$A:$AZ,MATCH(横向对比!BG$4&横向对比!$B58,【输出】数据汇总!$A:$A,0),MATCH(横向对比!$B$36,【输出】数据汇总!$1:$1,0)),"") -> 0.021203566 | BH58: =IFERROR(INDEX(【输出】数据汇总!$A:$AZ,MATCH(横向对比!BH$4&横向对比!$B58,【输出】数据汇总!$A:$A,0),MATCH(横向对比!$B$36,【输出】数据汇总!$1:$1,0)),"") -> 0.19981523 | BI58: =IFERROR(INDEX(【输出】数据汇总!$A:$AZ,MATCH(横向对比!BI$4&横向对比!$B58,【输出】数据汇总!$A:$A,0),MATCH(横向对比!$B$36,【输出】数据汇总!$1:$1,0)),"") -> 0.046690717 | BJ58: =IFERROR(INDEX(【输出】数据汇总!$A:$AZ,MATCH(横向对比!BJ$4&横向对比!$B58,【输出】数据汇总!$A:$A,0),MATCH(横向对比!$B$36,【输出】数据汇总!$1:$1,0)),"") -> 0.04719095 | ... BL58: =IFERROR(INDEX(【输出】数据汇总!$A:$AZ,MATCH(横向对比!BL$4&横向对比!$B58,【输出】数据汇总!$A:$A,0),MATCH(横向对比!$B$36,【输出】数据汇总!$1:$1,0)),"") -> 0.037715308
B59: 广义不良资产率 | C59: =IFERROR(INDEX(【输出】数据汇总!$A:$AZ,MATCH(横向对比!C$4&横向对比!$B59,【输出】数据汇总!$A:$A,0),MATCH(横向对比!$B$36,【输出】数据汇总!$1:$1,0)),"") -> 0.020257166 | D59: =IFERROR(INDEX(【输出】数据汇总!$A:$AZ,MATCH(横向对比!D$4&横向对比!$B59,【输出】数据汇总!$A:$A,0),MATCH(横向对比!$B$36,【输出】数据汇总!$1:$1,0)),"") -> 0.017862262 | E59: =IFERROR(INDEX(【输出】数据汇总!$A:$AZ,MATCH(横向对比!E$4&横向对比!$B59,【输出】数据汇总!$A:$A,0),MATCH(横向对比!$B$36,【输出】数据汇总!$1:$1,0)),"") -> 0.025300404 | F59: =IFERROR(INDEX(【输出】数据汇总!$A:$AZ,MATCH(横向对比!F$4&横向对比!$B59,【输出】数据汇总!$A:$A,0),MATCH(横向对比!$B$36,【输出】数据汇总!$1:$1,0)),"") -> 0.020280496 | G59: =IFERROR(INDEX(【输出】数据汇总!$A:$AZ,MATCH(横向对比!G$4&横向对比!$B59,【输出】数据汇总!$A:$A,0),MATCH(横向对比!$B$36,【输出】数据汇总!$1:$1,0)),"") -> 0.017585503 | H59: =IFERROR(INDEX(【输出】数据汇总!$A:$AZ,MATCH(横向对比!H$4&横向对比!$B59,【输出】数据汇总!$A:$A,0),MATCH(横向对比!$B$36,【输出】数据汇总!$1:$1,0)),"") | I59: =IFERROR(INDEX(【输出】数据汇总!$A:$AZ,MATCH(横向对比!I$4&横向对比!$B59,【输出】数据汇总!$A:$A,0),MATCH(横向对比!$B$36,【输出】数据汇总!$1:$1,0)),"") -> 0.045458381 | J59: =IFERROR(INDEX(【输出】数据汇总!$A:$AZ,MATCH(横向对比!J$4&横向对比!$B59,【输出】数据汇总!$A:$A,0),MATCH(横向对比!$B$36,【输出】数据汇总!$1:$1,0)),"") -> 0.020114497 | ... AA59: =IFERROR(INDEX(【输出】数据汇总!$A:$AZ,MATCH(横向对比!AA$4&横向对比!$B59,【输出】数据汇总!$A:$A,0),MATCH(横向对比!$B$36,【输出】数据汇总!$1:$1,0)),"") -> 0.019481998 | AB59: =IFERROR(INDEX(【输出】数据汇总!$A:$AZ,MATCH(横向对比!AB$36&横向对比!$B59,【输出】数据汇总!$A:$A,0),MATCH(横向对比!$B$36,【输出】数据汇总!$1:$1,0)),"") -> 0.0090762095 | AC59: =IFERROR(INDEX(【输出】数据汇总!$A:$AZ,MATCH(横向对比!AC$4&横向对比!$B59,【输出】数据汇总!$A:$A,0),MATCH(横向对比!$B$36,【输出】数据汇总!$1:$1,0)),"") -> 0.010647849 | AD59: =IFERROR(INDEX(【输出】数据汇总!$A:$AZ,MATCH(横向对比!AD$4&横向对比!$B59,【输出】数据汇总!$A:$A,0),MATCH(横向对比!$B$36,【输出】数据汇总!$1:$1,0)),"") -> 0.0062595105 | AE59: =IFERROR(INDEX(【输出】数据汇总!$A:$AZ,MATCH(横向对比!AE$4&横向对比!$B59,【输出】数据汇总!$A:$A,0),MATCH(横向对比!$B$36,【输出】数据汇总!$1:$1,0)),"") -> 0.0069938886 | AF59: =IFERROR(INDEX(【输出】数据汇总!$A:$AZ,MATCH(横向对比!AF$4&横向对比!$B59,【输出】数据汇总!$A:$A,0),MATCH(横向对比!$B$36,【输出】数据汇总!$1:$1,0)),"") -> 0.025898041 | AG59: =IFERROR(INDEX(【输出】数据汇总!$A:$AZ,MATCH(横向对比!AG$4&横向对比!$B59,【输出】数据汇总!$A:$A,0),MATCH(横向对比!$B$36,【输出】数据汇总!$1:$1,0)),"") -> 0.018203494 | AH59: =IFERROR(INDEX(【输出】数据汇总!$A:$AZ,MATCH(横向对比!AH$4&横向对比!$B59,【输出】数据汇总!$A:$A,0),MATCH(横向对比!$B$36,【输出】数据汇总!$1:$1,0)),"") -> 0.031359667 | AI59: =IFERROR(INDEX(【输出】数据汇总!$A:$AZ,MATCH(横向对比!AI$4&横向对比!$B59,【输出】数据汇总!$A:$A,0),MATCH(横向对比!$B$36,【输出】数据汇总!$1:$1,0)),"") -> 0.047261977 | AJ59: =IFERROR(INDEX(【输出】数据汇总!$A:$AZ,MATCH(横向对比!AJ$4&横向对比!$B59,【输出】数据汇总!$A:$A,0),MATCH(横向对比!$B$36,【输出】数据汇总!$1:$1,0)),"") -> 0.0084034409 | ... BA59: =IFERROR(INDEX(【输出】数据汇总!$A:$AZ,MATCH(横向对比!BA$4&横向对比!$B59,【输出】数据汇总!$A:$A,0),MATCH(横向对比!$B$36,【输出】数据汇总!$1:$1,0)),"") -> 0.068843426 | BB59: =IFERROR(INDEX(【输出】数据汇总!$A:$AZ,MATCH(横向对比!BB$36&横向对比!$B59,【输出】数据汇总!$A:$A,0),MATCH(横向对比!$B$36,【输出】数据汇总!$1:$1,0)),"") -> 0.028460726 | BC59: =IFERROR(INDEX(【输出】数据汇总!$A:$AZ,MATCH(横向对比!BC$4&横向对比!$B59,【输出】数据汇总!$A:$A,0),MATCH(横向对比!$B$36,【输出】数据汇总!$1:$1,0)),"") -> 0.051395245 | BD59: =IFERROR(INDEX(【输出】数据汇总!$A:$AZ,MATCH(横向对比!BD$4&横向对比!$B59,【输出】数据汇总!$A:$A,0),MATCH(横向对比!$B$36,【输出】数据汇总!$1:$1,0)),"") -> 0.02305912 | BE59: =IFERROR(INDEX(【输出】数据汇总!$A:$AZ,MATCH(横向对比!BE$4&横向对比!$B59,【输出】数据汇总!$A:$A,0),MATCH(横向对比!$B$36,【输出】数据汇总!$1:$1,0)),"") -> 0.061192957 | BF59: =IFERROR(INDEX(【输出】数据汇总!$A:$AZ,MATCH(横向对比!BF$4&横向对比!$B59,【输出】数据汇总!$A:$A,0),MATCH(横向对比!$B$36,【输出】数据汇总!$1:$1,0)),"") -> 0.041785005 | BG59: =IFERROR(INDEX(【输出】数据汇总!$A:$AZ,MATCH(横向对比!BG$4&横向对比!$B59,【输出】数据汇总!$A:$A,0),MATCH(横向对比!$B$36,【输出】数据汇总!$1:$1,0)),"") -> 0.014770327 | BH59: =IFERROR(INDEX(【输出】数据汇总!$A:$AZ,MATCH(横向对比!BH$4&横向对比!$B59,【输出】数据汇总!$A:$A,0),MATCH(横向对比!$B$36,【输出】数据汇总!$1:$1,0)),"") -> 0.12167841 | BI59: =IFERROR(INDEX(【输出】数据汇总!$A:$AZ,MATCH(横向对比!BI$4&横向对比!$B59,【输出】数据汇总!$A:$A,0),MATCH(横向对比!$B$36,【输出】数据汇总!$1:$1,0)),"") -> 0.031986244 | BJ59: =IFERROR(INDEX(【输出】数据汇总!$A:$AZ,MATCH(横向对比!BJ$4&横向对比!$B59,【输出】数据汇总!$A:$A,0),MATCH(横向对比!$B$36,【输出】数据汇总!$1:$1,0)),"") -> 0.047719241 | ... BL59: =IFERROR(INDEX(【输出】数据汇总!$A:$AZ,MATCH(横向对比!BL$4&横向对比!$B59,【输出】数据汇总!$A:$A,0),MATCH(横向对比!$B$36,【输出】数据汇总!$1:$1,0)),"") -> 0.020621717
B60: 拨备覆盖率 | C60: =IFERROR(INDEX(【输出】数据汇总!$A:$AZ,MATCH(横向对比!C$4&横向对比!$B60,【输出】数据汇总!$A:$A,0),MATCH(横向对比!$B$36,【输出】数据汇总!$1:$1,0)),"") -> 2.7737965 | D60: =IFERROR(INDEX(【输出】数据汇总!$A:$AZ,MATCH(横向对比!D$4&横向对比!$B60,【输出】数据汇总!$A:$A,0),MATCH(横向对比!$B$36,【输出】数据汇总!$1:$1,0)),"") -> 2.3656833 | E60: =IFERROR(INDEX(【输出】数据汇总!$A:$AZ,MATCH(横向对比!E$4&横向对比!$B60,【输出】数据汇总!$A:$A,0),MATCH(横向对比!$B$36,【输出】数据汇总!$1:$1,0)),"") -> 2.1371444 | F60: =IFERROR(INDEX(【输出】数据汇总!$A:$AZ,MATCH(横向对比!F$4&横向对比!$B60,【输出】数据汇总!$A:$A,0),MATCH(横向对比!$B$36,【输出】数据汇总!$1:$1,0)),"") -> 3.0439882 | G60: =IFERROR(INDEX(【输出】数据汇总!$A:$AZ,MATCH(横向对比!G$4&横向对比!$B60,【输出】数据汇总!$A:$A,0),MATCH(横向对比!$B$36,【输出】数据汇总!$1:$1,0)),"") -> 3.54837 | H60: =IFERROR(INDEX(【输出】数据汇总!$A:$AZ,MATCH(横向对比!H$4&横向对比!$B60,【输出】数据汇总!$A:$A,0),MATCH(横向对比!$B$36,【输出】数据汇总!$1:$1,0)),"") | I60: =IFERROR(INDEX(【输出】数据汇总!$A:$AZ,MATCH(横向对比!I$4&横向对比!$B60,【输出】数据汇总!$A:$A,0),MATCH(横向对比!$B$36,【输出】数据汇总!$1:$1,0)),"") -> 2.1240923 | J60: =IFERROR(INDEX(【输出】数据汇总!$A:$AZ,MATCH(横向对比!J$4&横向对比!$B60,【输出】数据汇总!$A:$A,0),MATCH(横向对比!$B$36,【输出】数据汇总!$1:$1,0)),"") -> 2.1771 | ... AA60: =IFERROR(INDEX(【输出】数据汇总!$A:$AZ,MATCH(横向对比!AA$4&横向对比!$B60,【输出】数据汇总!$A:$A,0),MATCH(横向对比!$B$36,【输出】数据汇总!$1:$1,0)),"") -> 2.4364 | AB60: =IFERROR(INDEX(【输出】数据汇总!$A:$AZ,MATCH(横向对比!AB$36&横向对比!$B60,【输出】数据汇总!$A:$A,0),MATCH(横向对比!$B$36,【输出】数据汇总!$1:$1,0)),"") -> 3.7416 | AC60: =IFERROR(INDEX(【输出】数据汇总!$A:$AZ,MATCH(横向对比!AC$4&横向对比!$B60,【输出】数据汇总!$A:$A,0),MATCH(横向对比!$B$36,【输出】数据汇总!$1:$1,0)),"") -> 3.1165 | AD60: =IFERROR(INDEX(【输出】数据汇总!$A:$AZ,MATCH(横向对比!AD$4&横向对比!$B60,【输出】数据汇总!$A:$A,0),MATCH(横向对比!$B$36,【输出】数据汇总!$1:$1,0)),"") -> 5.2089 | AE60: =IFERROR(INDEX(【输出】数据汇总!$A:$AZ,MATCH(横向对比!AE$4&横向对比!$B60,【输出】数据汇总!$A:$A,0),MATCH(横向对比!$B$36,【输出】数据汇总!$1:$1,0)),"") -> 4.5265 | AF60: =IFERROR(INDEX(【输出】数据汇总!$A:$AZ,MATCH(横向对比!AF$4&横向对比!$B60,【输出】数据汇总!$A:$A,0),MATCH(横向对比!$B$36,【输出】数据汇总!$1:$1,0)),"") -> 3.0971 | AG60: =IFERROR(INDEX(【输出】数据汇总!$A:$AZ,MATCH(横向对比!AG$4&横向对比!$B60,【输出】数据汇总!$A:$A,0),MATCH(横向对比!$B$36,【输出】数据汇总!$1:$1,0)),"") -> 2.4827 | AH60: =IFERROR(INDEX(【输出】数据汇总!$A:$AZ,MATCH(横向对比!AH$4&横向对比!$B60,【输出】数据汇总!$A:$A,0),MATCH(横向对比!$B$36,【输出】数据汇总!$1:$1,0)),"") -> 2.3864 | AI60: =IFERROR(INDEX(【输出】数据汇总!$A:$AZ,MATCH(横向对比!AI$4&横向对比!$B60,【输出】数据汇总!$A:$A,0),MATCH(横向对比!$B$36,【输出】数据汇总!$1:$1,0)),"") -> 1.792 | AJ60: =IFERROR(INDEX(【输出】数据汇总!$A:$AZ,MATCH(横向对比!AJ$4&横向对比!$B60,【输出】数据汇总!$A:$A,0),MATCH(横向对比!$B$36,【输出】数据汇总!$1:$1,0)),"") -> 4.3791 | ... BA60: =IFERROR(INDEX(【输出】数据汇总!$A:$AZ,MATCH(横向对比!BA$4&横向对比!$B60,【输出】数据汇总!$A:$A,0),MATCH(横向对比!$B$36,【输出】数据汇总!$1:$1,0)),"") -> 1.6975 | BB60: =IFERROR(INDEX(【输出】数据汇总!$A:$AZ,MATCH(横向对比!BB$36&横向对比!$B60,【输出】数据汇总!$A:$A,0),MATCH(横向对比!$B$36,【输出】数据汇总!$1:$1,0)),"") -> 1.7129 | BC60: =IFERROR(INDEX(【输出】数据汇总!$A:$AZ,MATCH(横向对比!BC$4&横向对比!$B60,【输出】数据汇总!$A:$A,0),MATCH(横向对比!$B$36,【输出】数据汇总!$1:$1,0)),"") -> 1.5485 | BD60: =IFERROR(INDEX(【输出】数据汇总!$A:$AZ,MATCH(横向对比!BD$4&横向对比!$B60,【输出】数据汇总!$A:$A,0),MATCH(横向对比!$B$36,【输出】数据汇总!$1:$1,0)),"") -> 4.1153 | BE60: =IFERROR(INDEX(【输出】数据汇总!$A:$AZ,MATCH(横向对比!BE$4&横向对比!$B60,【输出】数据汇总!$A:$A,0),MATCH(横向对比!$B$36,【输出】数据汇总!$1:$1,0)),"") -> 1.3679 | BF60: =IFERROR(INDEX(【输出】数据汇总!$A:$AZ,MATCH(横向对比!BF$4&横向对比!$B60,【输出】数据汇总!$A:$A,0),MATCH(横向对比!$B$36,【输出】数据汇总!$1:$1,0)),"") -> 2.15 | BG60: =IFERROR(INDEX(【输出】数据汇总!$A:$AZ,MATCH(横向对比!BG$4&横向对比!$B60,【输出】数据汇总!$A:$A,0),MATCH(横向对比!$B$36,【输出】数据汇总!$1:$1,0)),"") -> 2.8994 | BH60: =IFERROR(INDEX(【输出】数据汇总!$A:$AZ,MATCH(横向对比!BH$4&横向对比!$B60,【输出】数据汇总!$A:$A,0),MATCH(横向对比!$B$36,【输出】数据汇总!$1:$1,0)),"") -> 2.0995 | BI60: =IFERROR(INDEX(【输出】数据汇总!$A:$AZ,MATCH(横向对比!BI$4&横向对比!$B60,【输出】数据汇总!$A:$A,0),MATCH(横向对比!$B$36,【输出】数据汇总!$1:$1,0)),"") -> 3.3187 | BJ60: =IFERROR(INDEX(【输出】数据汇总!$A:$AZ,MATCH(横向对比!BJ$4&横向对比!$B60,【输出】数据汇总!$A:$A,0),MATCH(横向对比!$B$36,【输出】数据汇总!$1:$1,0)),"") -> 1.597 | ... BL60: =IFERROR(INDEX(【输出】数据汇总!$A:$AZ,MATCH(横向对比!BL$4&横向对比!$B60,【输出】数据汇总!$A:$A,0),MATCH(横向对比!$B$36,【输出】数据汇总!$1:$1,0)),"") -> 1.9056
B61: 超额拨备/归母净利润(TTM) | C61: =C49/C50 -> 0.13311534 | D61: =D49/D50 -> 0.25831504 | E61: =E49/E50 -> -0.40764919 | F61: =F49/F50 -> 0.47788539 | G61: =G49/G50 -> 0.69624016 | H61: =H49/H50 -> #VALUE! | I61: =I49/I50 -> -3.38536 | J61: =IFERROR(INDEX(【输出】数据汇总!$A:$AZ,MATCH(横向对比!J$4&横向对比!$B61,【输出】数据汇总!$A:$A,0),MATCH(横向对比!$B$36,【输出】数据汇总!$1:$1,0)),"") -> -0.010130055 | K61: =IFERROR(INDEX(【输出】数据汇总!$A:$AZ,MATCH(横向对比!K$4&横向对比!$B61,【输出】数据汇总!$A:$A,0),MATCH(横向对比!$B$36,【输出】数据汇总!$1:$1,0)),"") -> 0.12463853 | L61: =IFERROR(INDEX(【输出】数据汇总!$A:$AZ,MATCH(横向对比!L$4&横向对比!$B61,【输出】数据汇总!$A:$A,0),MATCH(横向对比!$B$36,【输出】数据汇总!$1:$1,0)),"") -> 1.1755334 | M61: =IFERROR(INDEX(【输出】数据汇总!$A:$AZ,MATCH(横向对比!M$4&横向对比!$B61,【输出】数据汇总!$A:$A,0),MATCH(横向对比!$B$36,【输出】数据汇总!$1:$1,0)),"") -> -0.20620271 | N61: =IFERROR(INDEX(【输出】数据汇总!$A:$AZ,MATCH(横向对比!N$4&横向对比!$B61,【输出】数据汇总!$A:$A,0),MATCH(横向对比!$B$36,【输出】数据汇总!$1:$1,0)),"") -> 0.39552671 | O61: =IFERROR(INDEX(【输出】数据汇总!$A:$AZ,MATCH(横向对比!O$4&横向对比!$B61,【输出】数据汇总!$A:$A,0),MATCH(横向对比!$B$36,【输出】数据汇总!$1:$1,0)),"") -> -0.0091267264 | P61: =IFERROR(INDEX(【输出】数据汇总!$A:$AZ,MATCH(横向对比!P$4&横向对比!$B61,【输出】数据汇总!$A:$A,0),MATCH(横向对比!$B$36,【输出】数据汇总!$1:$1,0)),"") -> 0.90661115 | Q61: =IFERROR(INDEX(【输出】数据汇总!$A:$AZ,MATCH(横向对比!Q$4&横向对比!$B61,【输出】数据汇总!$A:$A,0),MATCH(横向对比!$B$36,【输出】数据汇总!$1:$1,0)),"") -> -0.16514323 | ... AA61: =IFERROR(INDEX(【输出】数据汇总!$A:$AZ,MATCH(横向对比!AA$4&横向对比!$B61,【输出】数据汇总!$A:$A,0),MATCH(横向对比!$B$36,【输出】数据汇总!$1:$1,0)),"") -> -0.065839074 | AB61: =IFERROR(INDEX(【输出】数据汇总!$A:$AZ,MATCH(横向对比!AB$36&横向对比!$B61,【输出】数据汇总!$A:$A,0),MATCH(横向对比!$B$36,【输出】数据汇总!$1:$1,0)),"") -> 0.71495863 | AC61: =IFERROR(INDEX(【输出】数据汇总!$A:$AZ,MATCH(横向对比!AC$4&横向对比!$B61,【输出】数据汇总!$A:$A,0),MATCH(横向对比!$B$36,【输出】数据汇总!$1:$1,0)),"") -> 0.58820421 | AD61: =IFERROR(INDEX(【输出】数据汇总!$A:$AZ,MATCH(横向对比!AD$4&横向对比!$B61,【输出】数据汇总!$A:$A,0),MATCH(横向对比!$B$36,【输出】数据汇总!$1:$1,0)),"") -> 2.1309687 | AE61: =IFERROR(INDEX(【输出】数据汇总!$A:$AZ,MATCH(横向对比!AE$4&横向对比!$B61,【输出】数据汇总!$A:$A,0),MATCH(横向对比!$B$36,【输出】数据汇总!$1:$1,0)),"") -> 1.3134038 | AF61: =IFERROR(INDEX(【输出】数据汇总!$A:$AZ,MATCH(横向对比!AF$4&横向对比!$B61,【输出】数据汇总!$A:$A,0),MATCH(横向对比!$B$36,【输出】数据汇总!$1:$1,0)),"") -> -0.26645502 | AG61: =IFERROR(INDEX(【输出】数据汇总!$A:$AZ,MATCH(横向对比!AG$4&横向对比!$B61,【输出】数据汇总!$A:$A,0),MATCH(横向对比!$B$36,【输出】数据汇总!$1:$1,0)),"") -> -0.083049598 | AH61: =IFERROR(INDEX(【输出】数据汇总!$A:$AZ,MATCH(横向对比!AH$4&横向对比!$B61,【输出】数据汇总!$A:$A,0),MATCH(横向对比!$B$36,【输出】数据汇总!$1:$1,0)),"") -> 0.011866931 | AI61: =IFERROR(INDEX(【输出】数据汇总!$A:$AZ,MATCH(横向对比!AI$4&横向对比!$B61,【输出】数据汇总!$A:$A,0),MATCH(横向对比!$B$36,【输出】数据汇总!$1:$1,0)),"") -> -6.4452513 | AJ61: =IFERROR(INDEX(【输出】数据汇总!$A:$AZ,MATCH(横向对比!AJ$4&横向对比!$B61,【输出】数据汇总!$A:$A,0),MATCH(横向对比!$B$36,【输出】数据汇总!$1:$1,0)),"") -> 1.95692 | ... BA61: =IFERROR(INDEX(【输出】数据汇总!$A:$AZ,MATCH(横向对比!BA$4&横向对比!$B61,【输出】数据汇总!$A:$A,0),MATCH(横向对比!$B$36,【输出】数据汇总!$1:$1,0)),"") -> -31.678814 | BB61: =IFERROR(INDEX(【输出】数据汇总!$A:$AZ,MATCH(横向对比!BB$36&横向对比!$B61,【输出】数据汇总!$A:$A,0),MATCH(横向对比!$B$36,【输出】数据汇总!$1:$1,0)),"") -> -2.0775961 | BC61: =IFERROR(INDEX(【输出】数据汇总!$A:$AZ,MATCH(横向对比!BC$4&横向对比!$B61,【输出】数据汇总!$A:$A,0),MATCH(横向对比!$B$36,【输出】数据汇总!$1:$1,0)),"") -> -11.049243 | BD61: =IFERROR(INDEX(【输出】数据汇总!$A:$AZ,MATCH(横向对比!BD$4&横向对比!$B61,【输出】数据汇总!$A:$A,0),MATCH(横向对比!$B$36,【输出】数据汇总!$1:$1,0)),"") -> 1.7583365 | BE61: =IFERROR(INDEX(【输出】数据汇总!$A:$AZ,MATCH(横向对比!BE$4&横向对比!$B61,【输出】数据汇总!$A:$A,0),MATCH(横向对比!$B$36,【输出】数据汇总!$1:$1,0)),"") -> -23.97482 | BF61: =IFERROR(INDEX(【输出】数据汇总!$A:$AZ,MATCH(横向对比!BF$4&横向对比!$B61,【输出】数据汇总!$A:$A,0),MATCH(横向对比!$B$36,【输出】数据汇总!$1:$1,0)),"") -> -3.180422 | BG61: =IFERROR(INDEX(【输出】数据汇总!$A:$AZ,MATCH(横向对比!BG$4&横向对比!$B61,【输出】数据汇总!$A:$A,0),MATCH(横向对比!$B$36,【输出】数据汇总!$1:$1,0)),"") -> 0.70608291 | BH61: =IFERROR(INDEX(【输出】数据汇总!$A:$AZ,MATCH(横向对比!BH$4&横向对比!$B61,【输出】数据汇总!$A:$A,0),MATCH(横向对比!$B$36,【输出】数据汇总!$1:$1,0)),"") -> -63.036537 | BI61: =IFERROR(INDEX(【输出】数据汇总!$A:$AZ,MATCH(横向对比!BI$4&横向对比!$B61,【输出】数据汇总!$A:$A,0),MATCH(横向对比!$B$36,【输出】数据汇总!$1:$1,0)),"") -> 1.1051004 | BJ61: =IFERROR(INDEX(【输出】数据汇总!$A:$AZ,MATCH(横向对比!BJ$4&横向对比!$B61,【输出】数据汇总!$A:$A,0),MATCH(横向对比!$B$36,【输出】数据汇总!$1:$1,0)),"") -> -8.3168544 | ... BL61: =IFERROR(INDEX(【输出】数据汇总!$A:$AZ,MATCH(横向对比!BL$4&横向对比!$B61,【输出】数据汇总!$A:$A,0),MATCH(横向对比!$B$36,【输出】数据汇总!$1:$1,0)),"") -> 0.081659591
B62: 超额拨备/归母净资产 | C62: =C49/C51 -> 0.011444609 | D62: =D49/D51 -> 0.022275731 | E62: =E49/E51 -> -0.0333122 | F62: =F49/F51 -> 0.044990406 | G62: =G49/G51 -> 0.06581237 | H62: =H49/H51 -> #VALUE! | I62: =I49/I51 -> -0.1793467 | J62: =IFERROR(INDEX(【输出】数据汇总!$A:$AZ,MATCH(横向对比!J$4&横向对比!$B62,【输出】数据汇总!$A:$A,0),MATCH(横向对比!$B$36,【输出】数据汇总!$1:$1,0)),"") -> -0.00089490652 | K62: =IFERROR(INDEX(【输出】数据汇总!$A:$AZ,MATCH(横向对比!K$4&横向对比!$B62,【输出】数据汇总!$A:$A,0),MATCH(横向对比!$B$36,【输出】数据汇总!$1:$1,0)),"") -> 0.011659252 | L62: =IFERROR(INDEX(【输出】数据汇总!$A:$AZ,MATCH(横向对比!L$4&横向对比!$B62,【输出】数据汇总!$A:$A,0),MATCH(横向对比!$B$36,【输出】数据汇总!$1:$1,0)),"") -> 0.10685344 | M62: =IFERROR(INDEX(【输出】数据汇总!$A:$AZ,MATCH(横向对比!M$4&横向对比!$B62,【输出】数据汇总!$A:$A,0),MATCH(横向对比!$B$36,【输出】数据汇总!$1:$1,0)),"") -> -0.016346016 | N62: =IFERROR(INDEX(【输出】数据汇总!$A:$AZ,MATCH(横向对比!N$4&横向对比!$B62,【输出】数据汇总!$A:$A,0),MATCH(横向对比!$B$36,【输出】数据汇总!$1:$1,0)),"") -> 0.030183497 | O62: =IFERROR(INDEX(【输出】数据汇总!$A:$AZ,MATCH(横向对比!O$4&横向对比!$B62,【输出】数据汇总!$A:$A,0),MATCH(横向对比!$B$36,【输出】数据汇总!$1:$1,0)),"") -> -0.00066521987 | P62: =IFERROR(INDEX(【输出】数据汇总!$A:$AZ,MATCH(横向对比!P$4&横向对比!$B62,【输出】数据汇总!$A:$A,0),MATCH(横向对比!$B$36,【输出】数据汇总!$1:$1,0)),"") -> 0.10448264 | Q62: =IFERROR(INDEX(【输出】数据汇总!$A:$AZ,MATCH(横向对比!Q$4&横向对比!$B62,【输出】数据汇总!$A:$A,0),MATCH(横向对比!$B$36,【输出】数据汇总!$1:$1,0)),"") -> -0.014477028 | ... AA62: =IFERROR(INDEX(【输出】数据汇总!$A:$AZ,MATCH(横向对比!AA$4&横向对比!$B62,【输出】数据汇总!$A:$A,0),MATCH(横向对比!$B$36,【输出】数据汇总!$1:$1,0)),"") -> -0.0059524825 | AB62: =IFERROR(INDEX(【输出】数据汇总!$A:$AZ,MATCH(横向对比!AB$36&横向对比!$B62,【输出】数据汇总!$A:$A,0),MATCH(横向对比!$B$36,【输出】数据汇总!$1:$1,0)),"") -> 0.082510167 | AC62: =IFERROR(INDEX(【输出】数据汇总!$A:$AZ,MATCH(横向对比!AC$4&横向对比!$B62,【输出】数据汇总!$A:$A,0),MATCH(横向对比!$B$36,【输出】数据汇总!$1:$1,0)),"") -> 0.060354006 | AD62: =IFERROR(INDEX(【输出】数据汇总!$A:$AZ,MATCH(横向对比!AD$4&横向对比!$B62,【输出】数据汇总!$A:$A,0),MATCH(横向对比!$B$36,【输出】数据汇总!$1:$1,0)),"") -> 0.24754023 | AE62: =IFERROR(INDEX(【输出】数据汇总!$A:$AZ,MATCH(横向对比!AE$4&横向对比!$B62,【输出】数据汇总!$A:$A,0),MATCH(横向对比!$B$36,【输出】数据汇总!$1:$1,0)),"") -> 0.19742718 | AF62: =IFERROR(INDEX(【输出】数据汇总!$A:$AZ,MATCH(横向对比!AF$4&横向对比!$B62,【输出】数据汇总!$A:$A,0),MATCH(横向对比!$B$36,【输出】数据汇总!$1:$1,0)),"") -> -0.02678006 | AG62: =IFERROR(INDEX(【输出】数据汇总!$A:$AZ,MATCH(横向对比!AG$4&横向对比!$B62,【输出】数据汇总!$A:$A,0),MATCH(横向对比!$B$36,【输出】数据汇总!$1:$1,0)),"") -> -0.0069925588 | AH62: =IFERROR(INDEX(【输出】数据汇总!$A:$AZ,MATCH(横向对比!AH$4&横向对比!$B62,【输出】数据汇总!$A:$A,0),MATCH(横向对比!$B$36,【输出】数据汇总!$1:$1,0)),"") -> 0.00087630499 | AI62: =IFERROR(INDEX(【输出】数据汇总!$A:$AZ,MATCH(横向对比!AI$4&横向对比!$B62,【输出】数据汇总!$A:$A,0),MATCH(横向对比!$B$36,【输出】数据汇总!$1:$1,0)),"") -> -0.22177982 | AJ62: =IFERROR(INDEX(【输出】数据汇总!$A:$AZ,MATCH(横向对比!AJ$4&横向对比!$B62,【输出】数据汇总!$A:$A,0),MATCH(横向对比!$B$36,【输出】数据汇总!$1:$1,0)),"") -> 0.17534662 | ... BA62: =IFERROR(INDEX(【输出】数据汇总!$A:$AZ,MATCH(横向对比!BA$4&横向对比!$B62,【输出】数据汇总!$A:$A,0),MATCH(横向对比!$B$36,【输出】数据汇总!$1:$1,0)),"") -> -0.66203715 | BB62: =IFERROR(INDEX(【输出】数据汇总!$A:$AZ,MATCH(横向对比!BB$36&横向对比!$B62,【输出】数据汇总!$A:$A,0),MATCH(横向对比!$B$36,【输出】数据汇总!$1:$1,0)),"") -> -0.11505084 | BC62: =IFERROR(INDEX(【输出】数据汇总!$A:$AZ,MATCH(横向对比!BC$4&横向对比!$B62,【输出】数据汇总!$A:$A,0),MATCH(横向对比!$B$36,【输出】数据汇总!$1:$1,0)),"") -> -0.23013567 | BD62: =IFERROR(INDEX(【输出】数据汇总!$A:$AZ,MATCH(横向对比!BD$4&横向对比!$B62,【输出】数据汇总!$A:$A,0),MATCH(横向对比!$B$36,【输出】数据汇总!$1:$1,0)),"") -> 0.18537666 | BE62: =IFERROR(INDEX(【输出】数据汇总!$A:$AZ,MATCH(横向对比!BE$4&横向对比!$B62,【输出】数据汇总!$A:$A,0),MATCH(横向对比!$B$36,【输出】数据汇总!$1:$1,0)),"") -> -0.41266256 | BF62: =IFERROR(INDEX(【输出】数据汇总!$A:$AZ,MATCH(横向对比!BF$4&横向对比!$B62,【输出】数据汇总!$A:$A,0),MATCH(横向对比!$B$36,【输出】数据汇总!$1:$1,0)),"") -> -0.19780975 | BG62: =IFERROR(INDEX(【输出】数据汇总!$A:$AZ,MATCH(横向对比!BG$4&横向对比!$B62,【输出】数据汇总!$A:$A,0),MATCH(横向对比!$B$36,【输出】数据汇总!$1:$1,0)),"") -> 0.067668789 | BH62: =IFERROR(INDEX(【输出】数据汇总!$A:$AZ,MATCH(横向对比!BH$4&横向对比!$B62,【输出】数据汇总!$A:$A,0),MATCH(横向对比!$B$36,【输出】数据汇总!$1:$1,0)),"") -> -1.0710011 | BI62: =IFERROR(INDEX(【输出】数据汇总!$A:$AZ,MATCH(横向对比!BI$4&横向对比!$B62,【输出】数据汇总!$A:$A,0),MATCH(横向对比!$B$36,【输出】数据汇总!$1:$1,0)),"") -> 0.07885875 | BJ62: =IFERROR(INDEX(【输出】数据汇总!$A:$AZ,MATCH(横向对比!BJ$4&横向对比!$B62,【输出】数据汇总!$A:$A,0),MATCH(横向对比!$B$36,【输出】数据汇总!$1:$1,0)),"") -> -0.3955384 | ... BL62: =IFERROR(INDEX(【输出】数据汇总!$A:$AZ,MATCH(横向对比!BL$4&横向对比!$B62,【输出】数据汇总!$A:$A,0),MATCH(横向对比!$B$36,【输出】数据汇总!$1:$1,0)),"") -> 0.0055738721
B63: 归母净利润增速(TTM) | C63: =IFERROR(INDEX(【输出】数据汇总!$A:$AZ,MATCH(横向对比!C$4&横向对比!$B63,【输出】数据汇总!$A:$A,0),MATCH(横向对比!$B$36,【输出】数据汇总!$1:$1,0)),"") -> 0.044040917 | D63: =IFERROR(INDEX(【输出】数据汇总!$A:$AZ,MATCH(横向对比!D$4&横向对比!$B63,【输出】数据汇总!$A:$A,0),MATCH(横向对比!$B$36,【输出】数据汇总!$1:$1,0)),"") -> 0.023093692 | E63: =IFERROR(INDEX(【输出】数据汇总!$A:$AZ,MATCH(横向对比!E$4&横向对比!$B63,【输出】数据汇总!$A:$A,0),MATCH(横向对比!$B$36,【输出】数据汇总!$1:$1,0)),"") -> 0.007137802 | F63: =IFERROR(INDEX(【输出】数据汇总!$A:$AZ,MATCH(横向对比!F$4&横向对比!$B63,【输出】数据汇总!$A:$A,0),MATCH(横向对比!$B$36,【输出】数据汇总!$1:$1,0)),"") -> 0.092497611 | G63: =IFERROR(INDEX(【输出】数据汇总!$A:$AZ,MATCH(横向对比!G$4&横向对比!$B63,【输出】数据汇总!$A:$A,0),MATCH(横向对比!$B$36,【输出】数据汇总!$1:$1,0)),"") -> 0.053434561 | H63: =IFERROR(INDEX(【输出】数据汇总!$A:$AZ,MATCH(横向对比!H$4&横向对比!$B63,【输出】数据汇总!$A:$A,0),MATCH(横向对比!$B$36,【输出】数据汇总!$1:$1,0)),"") | I63: =IFERROR(INDEX(【输出】数据汇总!$A:$AZ,MATCH(横向对比!I$4&横向对比!$B63,【输出】数据汇总!$A:$A,0),MATCH(横向对比!$B$36,【输出】数据汇总!$1:$1,0)),"") -> 0.10354059 | J63: =IFERROR(INDEX(【输出】数据汇总!$A:$AZ,MATCH(横向对比!J$4&横向对比!$B63,【输出】数据汇总!$A:$A,0),MATCH(横向对比!$B$36,【输出】数据汇总!$1:$1,0)),"") -> 0.0077152109 | ... AA63: =IFERROR(INDEX(【输出】数据汇总!$A:$AZ,MATCH(横向对比!AA$4&横向对比!$B63,【输出】数据汇总!$A:$A,0),MATCH(横向对比!$B$36,【输出】数据汇总!$1:$1,0)),"") -> 0.050412884 | AB63: =IFERROR(INDEX(【输出】数据汇总!$A:$AZ,MATCH(横向对比!AB$36&横向对比!$B63,【输出】数据汇总!$A:$A,0),MATCH(横向对比!$B$36,【输出】数据汇总!$1:$1,0)),"") -> 0.076723711 | AC63: =IFERROR(INDEX(【输出】数据汇总!$A:$AZ,MATCH(横向对比!AC$4&横向对比!$B63,【输出】数据汇总!$A:$A,0),MATCH(横向对比!$B$36,【输出】数据汇总!$1:$1,0)),"") -> 0.092235825 | AD63: =IFERROR(INDEX(【输出】数据汇总!$A:$AZ,MATCH(横向对比!AD$4&横向对比!$B63,【输出】数据汇总!$A:$A,0),MATCH(横向对比!$B$36,【输出】数据汇总!$1:$1,0)),"") -> 0.16163158 | AE63: =IFERROR(INDEX(【输出】数据汇总!$A:$AZ,MATCH(横向对比!AE$4&横向对比!$B63,【输出】数据汇总!$A:$A,0),MATCH(横向对比!$B$36,【输出】数据汇总!$1:$1,0)),"") -> 0.085295206 | AF63: =IFERROR(INDEX(【输出】数据汇总!$A:$AZ,MATCH(横向对比!AF$4&横向对比!$B63,【输出】数据汇总!$A:$A,0),MATCH(横向对比!$B$36,【输出】数据汇总!$1:$1,0)),"") -> 0.054162398 | AG63: =IFERROR(INDEX(【输出】数据汇总!$A:$AZ,MATCH(横向对比!AG$4&横向对比!$B63,【输出】数据汇总!$A:$A,0),MATCH(横向对比!$B$36,【输出】数据汇总!$1:$1,0)),"") -> 0.045729383 | AH63: =IFERROR(INDEX(【输出】数据汇总!$A:$AZ,MATCH(横向对比!AH$4&横向对比!$B63,【输出】数据汇总!$A:$A,0),MATCH(横向对比!$B$36,【输出】数据汇总!$1:$1,0)),"") -> -0.072201048 | AI63: =IFERROR(INDEX(【输出】数据汇总!$A:$AZ,MATCH(横向对比!AI$4&横向对比!$B63,【输出】数据汇总!$A:$A,0),MATCH(横向对比!$B$36,【输出】数据汇总!$1:$1,0)),"") -> 0.36634832 | AJ63: =IFERROR(INDEX(【输出】数据汇总!$A:$AZ,MATCH(横向对比!AJ$4&横向对比!$B63,【输出】数据汇总!$A:$A,0),MATCH(横向对比!$B$36,【输出】数据汇总!$1:$1,0)),"") -> 0.067173913 | ... BA63: =IFERROR(INDEX(【输出】数据汇总!$A:$AZ,MATCH(横向对比!BA$4&横向对比!$B63,【输出】数据汇总!$A:$A,0),MATCH(横向对比!$B$36,【输出】数据汇总!$1:$1,0)),"") -> -0.013196247 | BB63: =IFERROR(INDEX(【输出】数据汇总!$A:$AZ,MATCH(横向对比!BB$36&横向对比!$B63,【输出】数据汇总!$A:$A,0),MATCH(横向对比!$B$36,【输出】数据汇总!$1:$1,0)),"") -> -0.21843981 | BC63: =IFERROR(INDEX(【输出】数据汇总!$A:$AZ,MATCH(横向对比!BC$4&横向对比!$B63,【输出】数据汇总!$A:$A,0),MATCH(横向对比!$B$36,【输出】数据汇总!$1:$1,0)),"") -> 1.1670408 | BD63: =IFERROR(INDEX(【输出】数据汇总!$A:$AZ,MATCH(横向对比!BD$4&横向对比!$B63,【输出】数据汇总!$A:$A,0),MATCH(横向对比!$B$36,【输出】数据汇总!$1:$1,0)),"") -> 0.21513065 | BE63: =IFERROR(INDEX(【输出】数据汇总!$A:$AZ,MATCH(横向对比!BE$4&横向对比!$B63,【输出】数据汇总!$A:$A,0),MATCH(横向对比!$B$36,【输出】数据汇总!$1:$1,0)),"") -> -0.070494118 | BF63: =IFERROR(INDEX(【输出】数据汇总!$A:$AZ,MATCH(横向对比!BF$4&横向对比!$B63,【输出】数据汇总!$A:$A,0),MATCH(横向对比!$B$36,【输出】数据汇总!$1:$1,0)),"") -> -0.11110216 | BG63: =IFERROR(INDEX(【输出】数据汇总!$A:$AZ,MATCH(横向对比!BG$4&横向对比!$B63,【输出】数据汇总!$A:$A,0),MATCH(横向对比!$B$36,【输出】数据汇总!$1:$1,0)),"") -> 0.040400735 | BH63: =IFERROR(INDEX(【输出】数据汇总!$A:$AZ,MATCH(横向对比!BH$4&横向对比!$B63,【输出】数据汇总!$A:$A,0),MATCH(横向对比!$B$36,【输出】数据汇总!$1:$1,0)),"") -> 0.1722918 | BI63: =IFERROR(INDEX(【输出】数据汇总!$A:$AZ,MATCH(横向对比!BI$4&横向对比!$B63,【输出】数据汇总!$A:$A,0),MATCH(横向对比!$B$36,【输出】数据汇总!$1:$1,0)),"") -> 0.060390275 | BJ63: =IFERROR(INDEX(【输出】数据汇总!$A:$AZ,MATCH(横向对比!BJ$4&横向对比!$B63,【输出】数据汇总!$A:$A,0),MATCH(横向对比!$B$36,【输出】数据汇总!$1:$1,0)),"") -> 0.15172667 | ... BL63: =IFERROR(INDEX(【输出】数据汇总!$A:$AZ,MATCH(横向对比!BL$4&横向对比!$B63,【输出】数据汇总!$A:$A,0),MATCH(横向对比!$B$36,【输出】数据汇总!$1:$1,0)),"") -> -0.13997622
B67: =B4 -> 46022
A68: 【减】 | B68: =B36 -> 45838
B69: =TEXT(B67,"yyyy/m/d")&A68&TEXT(B68,"yyyy/m/d") -> 2025/12/31【减】2025/6/30 | C69: =C2 -> 上市银行 | D69: =D2 -> 国有行 | E69: =E2 -> 股份行 | F69: =F2 -> 城商行 | G69: =G2 -> 农商行 | H69: =H2 -> AH股 | I69: =I2 -> 纯H股 | J69: =J2 -> 国有1 | ... BL69: =BL2 -> 纯H股13
B70: 单位：亿元 | J70: =J3 -> 1国有 | K70: =K3 -> 1国有 | L70: =L3 -> 1国有 | M70: =M3 -> 1国有 | N70: =N3 -> 1国有 | O70: =O3 -> 1国有 | P70: =P3 -> 2股份 | Q70: =Q3 -> 2股份 | ... AY70: =AY3 -> 4农商
B71: =B69 -> 2025/12/31【减】2025/6/30 | C71: =C4 -> 上市银行 | D71: =D4 -> 国有行 | E71: =E4 -> 股份行 | F71: =F4 -> 城商行 | G71: =G4 -> 农商行 | H71: =H4 -> AH股 | I71: =I4 -> 纯H股 | J71: =J4 -> 工商 | ... BL71: =BL4 -> 东莞农商
B72: 贷款总额 | C72: =IFERROR(C5-C37,"") -> 18540.472 | D72: =IFERROR(D5-D37,"") -> 17452.68 | E72: =IFERROR(E5-E37,"") -> 3388.59 | F72: =IFERROR(F5-F37,"") -> -1335.9096 | G72: =IFERROR(G5-G37,"") -> -964.88836 | H72: =IFERROR(H5-H37,"") | I72: =IFERROR(I5-I37,"") -> 972.01861 | J72: =IFERROR(J5-J37,"") -> 3204.55 | ... BL72: =IFERROR(BL5-BL37,"") -> 146.16049
B73: 逾期贷款余额 | C73: =IFERROR(C6-C38,"") -> -2009.4497 | D73: =IFERROR(D6-D38,"") -> 299.59 | E73: =IFERROR(E6-E38,"") -> -140.81 | F73: =IFERROR(F6-F38,"") -> -1872.9601 | G73: =IFERROR(G6-G38,"") -> -295.2696 | H73: =IFERROR(H6-H38,"") | I73: =IFERROR(I6-I38,"") -> -304.76801 | J73: =IFERROR(J6-J38,"") -> 37.35 | ... BL73: =IFERROR(BL6-BL38,"") -> 0
B74: 重组贷款余额 | C74: =IFERROR(C7-C39,"") -> -134.14028 | D74: =IFERROR(D7-D39,"") -> 437.32 | E74: =IFERROR(E7-E39,"") -> 218.47 | F74: =IFERROR(F7-F39,"") -> -643.68259 | G74: =IFERROR(G7-G39,"") -> -146.24769 | H74: =IFERROR(H7-H39,"") | I74: =IFERROR(I7-I39,"") -> -16.89629 | J74: =IFERROR(J7-J39,"") -> 150.65 | ... BL74: =IFERROR(BL7-BL39,"") -> 0
B75: 不良贷款余额 | C75: =IFERROR(C8-C40,"") -> -1436.4544 | D75: =IFERROR(D8-D40,"") -> 102.59 | E75: =IFERROR(E8-E40,"") -> 24.65 | F75: =IFERROR(F8-F40,"") -> -1371.9821 | G75: =IFERROR(G8-G40,"") -> -191.71228 | H75: =IFERROR(H8-H40,"") | I75: =IFERROR(I8-I40,"") -> -22.630383 | J75: =IFERROR(J8-J40,"") -> -10.92 | ... BL75: =IFERROR(BL8-BL40,"") -> -0.53904864
B76: 关注类贷款余额 | C76: =IFERROR(C9-C41,"") -> -1512.5216 | D76: =IFERROR(D9-D41,"") -> 760.48 | E76: =IFERROR(E9-E41,"") -> 67.2 | F76: =IFERROR(F9-F41,"") -> -1976.0251 | G76: =IFERROR(G9-G41,"") -> -364.17649 | H76: =IFERROR(H9-H41,"") | I76: =IFERROR(I9-I41,"") -> -279.42837 | J76: =IFERROR(J9-J41,"") -> 187.73 | ... BL76: =IFERROR(BL9-BL41,"") -> 12.20116
B77: 广义风险贷款 | C77: =IFERROR(C10-C42,"") -> -2948.976 | D77: =IFERROR(D10-D42,"") -> 863.07 | E77: =IFERROR(E10-E42,"") -> 91.85 | F77: =IFERROR(F10-F42,"") -> -3348.0072 | G77: =IFERROR(G10-G42,"") -> -555.88877 | H77: =IFERROR(H10-H42,"") | I77: =IFERROR(I10-I42,"") -> -302.05875 | J77: =IFERROR(J10-J42,"") -> 169.33829 | ... BL77: =IFERROR(BL10-BL42,"") -> 11.662111
B78: 非信贷资产第三阶段额 | C78: =IFERROR(C11-C43,"") -> -392.60468 | D78: =IFERROR(D11-D43,"") -> 64.86 | E78: =IFERROR(E11-E43,"") -> -409.24 | F78: =IFERROR(F11-F43,"") -> -33.72606 | G78: =IFERROR(G11-G43,"") -> -14.49862 | H78: =IFERROR(H11-H43,"") | I78: =IFERROR(I11-I43,"") -> -206.82919 | J78: =IFERROR(J11-J43,"") -> -1.74 | ... BL78: =IFERROR(BL11-BL43,"") -> 0.09562
B79: 贷款拨备额 | C79: =IFERROR(C12-C44,"") -> -2837.8733 | D79: =IFERROR(D12-D44,"") -> 2011.9 | E79: =IFERROR(E12-E44,"") -> -200.6 | F79: =IFERROR(F12-F44,"") -> -4038.3983 | G79: =IFERROR(G12-G44,"") -> -610.77504 | H79: =IFERROR(H12-H44,"") | I79: =IFERROR(I12-I44,"") -> -19.69913 | J79: =IFERROR(J12-J44,"") -> -187.9 | ... BL79: =IFERROR(BL12-BL44,"") -> 11.86629
B80: 超额贷款拨备额 | C80: =IFERROR(C13-C45,"") -> 111.10267 | D80: =IFERROR(D13-D45,"") -> 1148.83 | E80: =IFERROR(E13-E45,"") -> -292.45 | F80: =IFERROR(F13-F45,"") -> -690.39106 | G80: =IFERROR(G13-G45,"") -> -54.886268 | H80: =IFERROR(H13-H45,"") | I80: =IFERROR(I13-I45,"") -> 282.35962 | J80: =IFERROR(J13-J45,"") -> -357.23829 | ... BL80: =IFERROR(BL13-BL45,"") -> 0.20417864
B81: 非信贷资产第三阶段额 | C81: =IFERROR(C14-C46,"") -> -392.60468 | D81: =IFERROR(D14-D46,"") -> 64.86 | E81: =IFERROR(E14-E46,"") -> -409.24 | F81: =IFERROR(F14-F46,"") -> -33.72606 | G81: =IFERROR(G14-G46,"") -> -14.49862 | H81: =IFERROR(H14-H46,"") | I81: =IFERROR(I14-I46,"") -> -206.82919 | J81: =IFERROR(J14-J46,"") -> -1.74 | ... BL81: =IFERROR(BL14-BL46,"") -> 0.09562
B82: 非信贷拨备额 | C82: =IFERROR(C15-C47,"") -> -3753.3002 | D82: =IFERROR(D15-D47,"") -> -2463.75 | E82: =IFERROR(E15-E47,"") -> 52.2 | F82: =IFERROR(F15-F47,"") | G82: =IFERROR(G15-G47,"") | H82: =IFERROR(H15-H47,"") | I82: =IFERROR(I15-I47,"") -> 209.85353 | J82: =IFERROR(J15-J47,"") -> -83.56 | ... BL82: =IFERROR(BL15-BL47,"") -> -7.66044
B83: 超额非信贷拨备 | C83: =IFERROR(C16-C48,"") -> -3360.6955 | D83: =IFERROR(D16-D48,"") -> -2528.61 | E83: =IFERROR(E16-E48,"") -> 461.44 | F83: =IFERROR(F16-F48,"") | G83: =IFERROR(G16-G48,"") | H83: =IFERROR(H16-H48,"") | I83: =IFERROR(I16-I48,"") -> 416.68272 | J83: =IFERROR(J16-J48,"") -> -81.82 | ... BL83: =IFERROR(BL16-BL48,"") -> -7.75606
... B98: 归母净利润增速(TTM) | C98: =IFERROR(C31-C63,"") -> -0.045426809 | D98: =IFERROR(D31-D63,"") -> -0.0058795586 | E98: =IFERROR(E31-E63,"") -> -0.027123721 | F98: =IFERROR(F31-F63,"") | G98: =IFERROR(G31-G63,"") | H98: =IFERROR(H31-H63,"") | I98: =IFERROR(I31-I63,"") -> -0.061236776 | J98: =IFERROR(J31-J63,"") -> -0.00033813255 | ... BL98: =IFERROR(BL31-BL63,"") -> -0.026683308

Sheet 纵向时序
A1: 可选标签 | D1: 亿元
A2: 工商 | B2: 中原 | C2: 输入银行简称 | D2: 招商 | E2: =【输出】数据汇总!H1 -> 43646 | F2: =【输出】数据汇总!I1 -> 43738 | G2: =【输出】数据汇总!J1 -> 43830 | H2: =【输出】数据汇总!K1 -> 43921 | I2: =【输出】数据汇总!L1 -> 44012 | J2: =【输出】数据汇总!M1 -> 44104 | K2: =【输出】数据汇总!N1 -> 44196 | L2: =【输出】数据汇总!O1 -> 44286 | ... AE2: =【输出】数据汇总!AH1 -> 46022
A3: 建设 | B3: 广州农商 | C3: ① | D3: 贷款总额 | E3: =IFERROR(INDEX(【输出】数据汇总!$A:$AQ,MATCH(纵向时序!$D$2&纵向时序!$D3,【输出】数据汇总!$A:$A,0),MATCH(纵向时序!E$2,【输出】数据汇总!$1:$1,0))/100,"") -> 43235.3 | F3: =IFERROR(INDEX(【输出】数据汇总!$A:$AQ,MATCH(纵向时序!$D$2&纵向时序!$D3,【输出】数据汇总!$A:$A,0),MATCH(纵向时序!F$2,【输出】数据汇总!$1:$1,0))/100,"") -> 44622.59 | G3: =IFERROR(INDEX(【输出】数据汇总!$A:$AQ,MATCH(纵向时序!$D$2&纵向时序!$D3,【输出】数据汇总!$A:$A,0),MATCH(纵向时序!G$2,【输出】数据汇总!$1:$1,0))/100,"") -> 44906.5 | H3: =IFERROR(INDEX(【输出】数据汇总!$A:$AQ,MATCH(纵向时序!$D$2&纵向时序!$D3,【输出】数据汇总!$A:$A,0),MATCH(纵向时序!H$2,【输出】数据汇总!$1:$1,0))/100,"") -> 47326.58 | I3: =IFERROR(INDEX(【输出】数据汇总!$A:$AQ,MATCH(纵向时序!$D$2&纵向时序!$D3,【输出】数据汇总!$A:$A,0),MATCH(纵向时序!I$2,【输出】数据汇总!$1:$1,0))/100,"") -> 48517.15 | J3: =IFERROR(INDEX(【输出】数据汇总!$A:$AQ,MATCH(纵向时序!$D$2&纵向时序!$D3,【输出】数据汇总!$A:$A,0),MATCH(纵向时序!J$2,【输出】数据汇总!$1:$1,0))/100,"") -> 50062.02 | K3: =IFERROR(INDEX(【输出】数据汇总!$A:$AQ,MATCH(纵向时序!$D$2&纵向时序!$D3,【输出】数据汇总!$A:$A,0),MATCH(纵向时序!K$2,【输出】数据汇总!$1:$1,0))/100,"") -> 50291.28 | L3: =IFERROR(INDEX(【输出】数据汇总!$A:$AQ,MATCH(纵向时序!$D$2&纵向时序!$D3,【输出】数据汇总!$A:$A,0),MATCH(纵向时序!L$2,【输出】数据汇总!$1:$1,0))/100,"") -> 53125.29 | ... AE3: =IFERROR(INDEX(【输出】数据汇总!$A:$AQ,MATCH(纵向时序!$D$2&纵向时序!$D3,【输出】数据汇总!$A:$A,0),MATCH(纵向时序!AE$2,【输出】数据汇总!$1:$1,0))/100,"") -> 72580.58
A4: 农业 | B4: 天津 | C4: ② | D4: 逾期贷款余额 | E4: =IFERROR(INDEX(【输出】数据汇总!$A:$AQ,MATCH(纵向时序!$D$2&纵向时序!$D4,【输出】数据汇总!$A:$A,0),MATCH(纵向时序!E$2,【输出】数据汇总!$1:$1,0))/100,"") -> 672.34 | F4: =IFERROR(INDEX(【输出】数据汇总!$A:$AQ,MATCH(纵向时序!$D$2&纵向时序!$D4,【输出】数据汇总!$A:$A,0),MATCH(纵向时序!F$2,【输出】数据汇总!$1:$1,0))/100,"") -> 672.34 | G4: =IFERROR(INDEX(【输出】数据汇总!$A:$AQ,MATCH(纵向时序!$D$2&纵向时序!$D4,【输出】数据汇总!$A:$A,0),MATCH(纵向时序!G$2,【输出】数据汇总!$1:$1,0))/100,"") -> 633.63 | H4: =IFERROR(INDEX(【输出】数据汇总!$A:$AQ,MATCH(纵向时序!$D$2&纵向时序!$D4,【输出】数据汇总!$A:$A,0),MATCH(纵向时序!H$2,【输出】数据汇总!$1:$1,0))/100,"") -> 633.63 | I4: =IFERROR(INDEX(【输出】数据汇总!$A:$AQ,MATCH(纵向时序!$D$2&纵向时序!$D4,【输出】数据汇总!$A:$A,0),MATCH(纵向时序!I$2,【输出】数据汇总!$1:$1,0))/100,"") -> 656.93 | J4: =IFERROR(INDEX(【输出】数据汇总!$A:$AQ,MATCH(纵向时序!$D$2&纵向时序!$D4,【输出】数据汇总!$A:$A,0),MATCH(纵向时序!J$2,【输出】数据汇总!$1:$1,0))/100,"") -> 656.93 | K4: =IFERROR(INDEX(【输出】数据汇总!$A:$AQ,MATCH(纵向时序!$D$2&纵向时序!$D4,【输出】数据汇总!$A:$A,0),MATCH(纵向时序!K$2,【输出】数据汇总!$1:$1,0))/100,"") -> 565.68 | L4: =IFERROR(INDEX(【输出】数据汇总!$A:$AQ,MATCH(纵向时序!$D$2&纵向时序!$D4,【输出】数据汇总!$A:$A,0),MATCH(纵向时序!L$2,【输出】数据汇总!$1:$1,0))/100,"") -> 565.68 | ... AE4: =IFERROR(INDEX(【输出】数据汇总!$A:$AQ,MATCH(纵向时序!$D$2&纵向时序!$D4,【输出】数据汇总!$A:$A,0),MATCH(纵向时序!AE$2,【输出】数据汇总!$1:$1,0))/100,"") -> 906.46
A5: 中国 | B5: 江西 | C5: ③ | D5: 重组贷款余额 | E5: =IFERROR(INDEX(【输出】数据汇总!$A:$AQ,MATCH(纵向时序!$D$2&纵向时序!$D5,【输出】数据汇总!$A:$A,0),MATCH(纵向时序!E$2,【输出】数据汇总!$1:$1,0))/100,"") -> 247.27 | F5: =IFERROR(INDEX(【输出】数据汇总!$A:$AQ,MATCH(纵向时序!$D$2&纵向时序!$D5,【输出】数据汇总!$A:$A,0),MATCH(纵向时序!F$2,【输出】数据汇总!$1:$1,0))/100,"") -> 247.27 | G5: =IFERROR(INDEX(【输出】数据汇总!$A:$AQ,MATCH(纵向时序!$D$2&纵向时序!$D5,【输出】数据汇总!$A:$A,0),MATCH(纵向时序!G$2,【输出】数据汇总!$1:$1,0))/100,"") -> 250.22 | H5: =IFERROR(INDEX(【输出】数据汇总!$A:$AQ,MATCH(纵向时序!$D$2&纵向时序!$D5,【输出】数据汇总!$A:$A,0),MATCH(纵向时序!H$2,【输出】数据汇总!$1:$1,0))/100,"") -> 250.22 | I5: =IFERROR(INDEX(【输出】数据汇总!$A:$AQ,MATCH(纵向时序!$D$2&纵向时序!$D5,【输出】数据汇总!$A:$A,0),MATCH(纵向时序!I$2,【输出】数据汇总!$1:$1,0))/100,"") -> 239.49 | J5: =IFERROR(INDEX(【输出】数据汇总!$A:$AQ,MATCH(纵向时序!$D$2&纵向时序!$D5,【输出】数据汇总!$A:$A,0),MATCH(纵向时序!J$2,【输出】数据汇总!$1:$1,0))/100,"") -> 239.49 | K5: =IFERROR(INDEX(【输出】数据汇总!$A:$AQ,MATCH(纵向时序!$D$2&纵向时序!$D5,【输出】数据汇总!$A:$A,0),MATCH(纵向时序!K$2,【输出】数据汇总!$1:$1,0))/100,"") -> 248.78 | L5: =IFERROR(INDEX(【输出】数据汇总!$A:$AQ,MATCH(纵向时序!$D$2&纵向时序!$D5,【输出】数据汇总!$A:$A,0),MATCH(纵向时序!L$2,【输出】数据汇总!$1:$1,0))/100,"") -> 248.78 | ... AE5: =IFERROR(INDEX(【输出】数据汇总!$A:$AQ,MATCH(纵向时序!$D$2&纵向时序!$D5,【输出】数据汇总!$A:$A,0),MATCH(纵向时序!AE$2,【输出】数据汇总!$1:$1,0))/100,"") -> 283.07
A6: 邮储 | B6: 泸州 | C6: ④ | D6: 不良贷款余额 | E6: =IFERROR(INDEX(【输出】数据汇总!$A:$AQ,MATCH(纵向时序!$D$2&纵向时序!$D6,【输出】数据汇总!$A:$A,0),MATCH(纵向时序!E$2,【输出】数据汇总!$1:$1,0))/100,"") -> 532.21 | F6: =IFERROR(INDEX(【输出】数据汇总!$A:$AQ,MATCH(纵向时序!$D$2&纵向时序!$D6,【输出】数据汇总!$A:$A,0),MATCH(纵向时序!F$2,【输出】数据汇总!$1:$1,0))/100,"") -> 532.61 | G6: =IFERROR(INDEX(【输出】数据汇总!$A:$AQ,MATCH(纵向时序!$D$2&纵向时序!$D6,【输出】数据汇总!$A:$A,0),MATCH(纵向时序!G$2,【输出】数据汇总!$1:$1,0))/100,"") -> 522.75 | H6: =IFERROR(INDEX(【输出】数据汇总!$A:$AQ,MATCH(纵向时序!$D$2&纵向时序!$D6,【输出】数据汇总!$A:$A,0),MATCH(纵向时序!H$2,【输出】数据汇总!$1:$1,0))/100,"") -> 525.82 | I6: =IFERROR(INDEX(【输出】数据汇总!$A:$AQ,MATCH(纵向时序!$D$2&纵向时序!$D6,【输出】数据汇总!$A:$A,0),MATCH(纵向时序!I$2,【输出】数据汇总!$1:$1,0))/100,"") -> 553.28 | J6: =IFERROR(INDEX(【输出】数据汇总!$A:$AQ,MATCH(纵向时序!$D$2&纵向时序!$D6,【输出】数据汇总!$A:$A,0),MATCH(纵向时序!J$2,【输出】数据汇总!$1:$1,0))/100,"") -> 564.66 | K6: =IFERROR(INDEX(【输出】数据汇总!$A:$AQ,MATCH(纵向时序!$D$2&纵向时序!$D6,【输出】数据汇总!$A:$A,0),MATCH(纵向时序!K$2,【输出】数据汇总!$1:$1,0))/100,"") -> 536.15 | L6: =IFERROR(INDEX(【输出】数据汇总!$A:$AQ,MATCH(纵向时序!$D$2&纵向时序!$D6,【输出】数据汇总!$A:$A,0),MATCH(纵向时序!L$2,【输出】数据汇总!$1:$1,0))/100,"") -> 540.57 | ... AE6: =IFERROR(INDEX(【输出】数据汇总!$A:$AQ,MATCH(纵向时序!$D$2&纵向时序!$D6,【输出】数据汇总!$A:$A,0),MATCH(纵向时序!AE$2,【输出】数据汇总!$1:$1,0))/100,"") -> 682.06
A7: 交通 | B7: 盛京 | C7: ⑤ | D7: 关注类贷款余额 | E7: =IFERROR(INDEX(【输出】数据汇总!$A:$AQ,MATCH(纵向时序!$D$2&纵向时序!$D7,【输出】数据汇总!$A:$A,0),MATCH(纵向时序!E$2,【输出】数据汇总!$1:$1,0))/100,"") -> 563.11 | F7: =IFERROR(INDEX(【输出】数据汇总!$A:$AQ,MATCH(纵向时序!$D$2&纵向时序!$D7,【输出】数据汇总!$A:$A,0),MATCH(纵向时序!F$2,【输出】数据汇总!$1:$1,0))/100,"") -> 563.11 | G7: =IFERROR(INDEX(【输出】数据汇总!$A:$AQ,MATCH(纵向时序!$D$2&纵向时序!$D7,【输出】数据汇总!$A:$A,0),MATCH(纵向时序!G$2,【输出】数据汇总!$1:$1,0))/100,"") -> 525.9 | H7: =IFERROR(INDEX(【输出】数据汇总!$A:$AQ,MATCH(纵向时序!$D$2&纵向时序!$D7,【输出】数据汇总!$A:$A,0),MATCH(纵向时序!H$2,【输出】数据汇总!$1:$1,0))/100,"") -> 563.28 | I7: =IFERROR(INDEX(【输出】数据汇总!$A:$AQ,MATCH(纵向时序!$D$2&纵向时序!$D7,【输出】数据汇总!$A:$A,0),MATCH(纵向时序!I$2,【输出】数据汇总!$1:$1,0))/100,"") -> 480.88 | J7: =IFERROR(INDEX(【输出】数据汇总!$A:$AQ,MATCH(纵向时序!$D$2&纵向时序!$D7,【输出】数据汇总!$A:$A,0),MATCH(纵向时序!J$2,【输出】数据汇总!$1:$1,0))/100,"") -> 394.99 | K7: =IFERROR(INDEX(【输出】数据汇总!$A:$AQ,MATCH(纵向时序!$D$2&纵向时序!$D7,【输出】数据汇总!$A:$A,0),MATCH(纵向时序!K$2,【输出】数据汇总!$1:$1,0))/100,"") -> 407.16 | L7: =IFERROR(INDEX(【输出】数据汇总!$A:$AQ,MATCH(纵向时序!$D$2&纵向时序!$D7,【输出】数据汇总!$A:$A,0),MATCH(纵向时序!L$2,【输出】数据汇总!$1:$1,0))/100,"") -> 362.38 | ... AE7: =IFERROR(INDEX(【输出】数据汇总!$A:$AQ,MATCH(纵向时序!$D$2&纵向时序!$D7,【输出】数据汇总!$A:$A,0),MATCH(纵向时序!AE$2,【输出】数据汇总!$1:$1,0))/100,"") -> 1038.6
A8: 招商 | B8: 甘肃 | C8: ⑦ | D8: 非信贷资产第三阶段额 | E8: =IFERROR(INDEX(【输出】数据汇总!$A:$AQ,MATCH(纵向时序!$D$2&纵向时序!$D8,【输出】数据汇总!$A:$A,0),MATCH(纵向时序!E$2,【输出】数据汇总!$1:$1,0))/100,"") -> 80.14 | F8: =IFERROR(INDEX(【输出】数据汇总!$A:$AQ,MATCH(纵向时序!$D$2&纵向时序!$D8,【输出】数据汇总!$A:$A,0),MATCH(纵向时序!F$2,【输出】数据汇总!$1:$1,0))/100,"") -> 80.14 | G8: =IFERROR(INDEX(【输出】数据汇总!$A:$AQ,MATCH(纵向时序!$D$2&纵向时序!$D8,【输出】数据汇总!$A:$A,0),MATCH(纵向时序!G$2,【输出】数据汇总!$1:$1,0))/100,"") -> 53.18 | H8: =IFERROR(INDEX(【输出】数据汇总!$A:$AQ,MATCH(纵向时序!$D$2&纵向时序!$D8,【输出】数据汇总!$A:$A,0),MATCH(纵向时序!H$2,【输出】数据汇总!$1:$1,0))/100,"") -> 53.18 | I8: =IFERROR(INDEX(【输出】数据汇总!$A:$AQ,MATCH(纵向时序!$D$2&纵向时序!$D8,【输出】数据汇总!$A:$A,0),MATCH(纵向时序!I$2,【输出】数据汇总!$1:$1,0))/100,"") -> 36.16 | J8: =IFERROR(INDEX(【输出】数据汇总!$A:$AQ,MATCH(纵向时序!$D$2&纵向时序!$D8,【输出】数据汇总!$A:$A,0),MATCH(纵向时序!J$2,【输出】数据汇总!$1:$1,0))/100,"") -> 36.16 | K8: =IFERROR(INDEX(【输出】数据汇总!$A:$AQ,MATCH(纵向时序!$D$2&纵向时序!$D8,【输出】数据汇总!$A:$A,0),MATCH(纵向时序!K$2,【输出】数据汇总!$1:$1,0))/100,"") -> 150.23 | L8: =IFERROR(INDEX(【输出】数据汇总!$A:$AQ,MATCH(纵向时序!$D$2&纵向时序!$D8,【输出】数据汇总!$A:$A,0),MATCH(纵向时序!L$2,【输出】数据汇总!$1:$1,0))/100,"") -> 150.23 | ... AE8: =IFERROR(INDEX(【输出】数据汇总!$A:$AQ,MATCH(纵向时序!$D$2&纵向时序!$D8,【输出】数据汇总!$A:$A,0),MATCH(纵向时序!AE$2,【输出】数据汇总!$1:$1,0))/100,"") -> 246.29
A9: 兴业 | B9: 晋商 | C9: ⑥=MAX(②+③，④+⑤) | D9: 广义风险贷款 | E9: =MAX(E4+E5,E6+E7) -> 1095.32 | F9: =MAX(F4+F5,F6+F7) -> 1095.72 | G9: =MAX(G4+G5,G6+G7) -> 1048.65 | H9: =MAX(H4+H5,H6+H7) -> 1089.1 | I9: =MAX(I4+I5,I6+I7) -> 1034.16 | J9: =MAX(J4+J5,J6+J7) -> 959.65 | K9: =MAX(K4+K5,K6+K7) -> 943.31 | L9: =MAX(L4+L5,L6+L7) -> 902.95 | ... AE9: =MAX(AE4+AE5,AE6+AE7) -> 1720.66
A10: 浦发 | B10: 徽商 | C10: ⑧ | D10: 贷款拨备额 | E10: =IFERROR(INDEX(【输出】数据汇总!$A:$AQ,MATCH(纵向时序!$D$2&纵向时序!$D10,【输出】数据汇总!$A:$A,0),MATCH(纵向时序!E$2,【输出】数据汇总!$1:$1,0))/100,"") -> 2097.57 | F10: =IFERROR(INDEX(【输出】数据汇总!$A:$AQ,MATCH(纵向时序!$D$2&纵向时序!$D10,【输出】数据汇总!$A:$A,0),MATCH(纵向时序!F$2,【输出】数据汇总!$1:$1,0))/100,"") -> 2180.5586 | G10: =IFERROR(INDEX(【输出】数据汇总!$A:$AQ,MATCH(纵向时序!$D$2&纵向时序!$D10,【输出】数据汇总!$A:$A,0),MATCH(纵向时序!G$2,【输出】数据汇总!$1:$1,0))/100,"") -> 2230.97 | H10: =IFERROR(INDEX(【输出】数据汇总!$A:$AQ,MATCH(纵向时序!$D$2&纵向时序!$D10,【输出】数据汇总!$A:$A,0),MATCH(纵向时序!H$2,【输出】数据汇总!$1:$1,0))/100,"") -> 2372.8679 | I10: =IFERROR(INDEX(【输出】数据汇总!$A:$AQ,MATCH(纵向时序!$D$2&纵向时序!$D10,【输出】数据汇总!$A:$A,0),MATCH(纵向时序!I$2,【输出】数据汇总!$1:$1,0))/100,"") -> 2438.91 | J10: =IFERROR(INDEX(【输出】数据汇总!$A:$AQ,MATCH(纵向时序!$D$2&纵向时序!$D10,【输出】数据汇总!$A:$A,0),MATCH(纵向时序!J$2,【输出】数据汇总!$1:$1,0))/100,"") -> 2398.4498 | K10: =IFERROR(INDEX(【输出】数据汇总!$A:$AQ,MATCH(纵向时序!$D$2&纵向时序!$D10,【输出】数据汇总!$A:$A,0),MATCH(纵向时序!K$2,【输出】数据汇总!$1:$1,0))/100,"") -> 2346.64 | L10: =IFERROR(INDEX(【输出】数据汇总!$A:$AQ,MATCH(纵向时序!$D$2&纵向时序!$D10,【输出】数据汇总!$A:$A,0),MATCH(纵向时序!L$2,【输出】数据汇总!$1:$1,0))/100,"") -> 2372.4536 | ... AE10: =IFERROR(INDEX(【输出】数据汇总!$A:$AQ,MATCH(纵向时序!$D$2&纵向时序!$D10,【输出】数据汇总!$A:$A,0),MATCH(纵向时序!AE$2,【输出】数据汇总!$1:$1,0))/100,"") -> 2672.22
A11: 中信 | B11: 哈尔滨 | C11: ⑨=⑧-⑥*100% | D11: 超额贷款拨备额 | E11: =E10-E9*100% -> 1002.25 | F11: =F10-F9*100% -> 1084.8386 | G11: =G10-G9*100% -> 1182.32 | H11: =H10-H9*100% -> 1283.7679 | I11: =I10-I9*100% -> 1404.75 | J11: =J10-J9*100% -> 1438.7998 | K11: =K10-K9*100% -> 1403.33 | L11: =L10-L9*100% -> 1469.5036 | ... AE11: =AE10-AE9*100% -> 951.56
A12: 民生 | B12: 贵州 | C12: ⑦ | D12: 非信贷资产第三阶段额 | E12: =IF(IFERROR(INDEX(【输出】数据汇总!$A:$AQ,MATCH(纵向时序!$D$2&纵向时序!$D12,【输出】数据汇总!$A:$A,0),MATCH(纵向时序!E$2,【输出】数据汇总!$1:$1,0))/100,"")=0,"",IFERROR(INDEX(【输出】数据汇总!$A:$AQ,MATCH(纵向时序!$D$2&纵向时序!$D12,【输出】数据汇总!$A:$A,0),MATCH(纵向时序!E$2,【输出】数据汇总!$1:$1,0))/100,"")) -> 80.14 | F12: =IF(IFERROR(INDEX(【输出】数据汇总!$A:$AQ,MATCH(纵向时序!$D$2&纵向时序!$D12,【输出】数据汇总!$A:$A,0),MATCH(纵向时序!F$2,【输出】数据汇总!$1:$1,0))/100,"")=0,"",IFERROR(INDEX(【输出】数据汇总!$A:$AQ,MATCH(纵向时序!$D$2&纵向时序!$D12,【输出】数据汇总!$A:$A,0),MATCH(纵向时序!F$2,【输出】数据汇总!$1:$1,0))/100,"")) -> 80.14 | G12: =IF(IFERROR(INDEX(【输出】数据汇总!$A:$AQ,MATCH(纵向时序!$D$2&纵向时序!$D12,【输出】数据汇总!$A:$A,0),MATCH(纵向时序!G$2,【输出】数据汇总!$1:$1,0))/100,"")=0,"",IFERROR(INDEX(【输出】数据汇总!$A:$AQ,MATCH(纵向时序!$D$2&纵向时序!$D12,【输出】数据汇总!$A:$A,0),MATCH(纵向时序!G$2,【输出】数据汇总!$1:$1,0))/100,"")) -> 53.18 | H12: =IF(IFERROR(INDEX(【输出】数据汇总!$A:$AQ,MATCH(纵向时序!$D$2&纵向时序!$D12,【输出】数据汇总!$A:$A,0),MATCH(纵向时序!H$2,【输出】数据汇总!$1:$1,0))/100,"")=0,"",IFERROR(INDEX(【输出】数据汇总!$A:$AQ,MATCH(纵向时序!$D$2&纵向时序!$D12,【输出】数据汇总!$A:$A,0),MATCH(纵向时序!H$2,【输出】数据汇总!$1:$1,0))/100,"")) -> 53.18 | I12: =IF(IFERROR(INDEX(【输出】数据汇总!$A:$AQ,MATCH(纵向时序!$D$2&纵向时序!$D12,【输出】数据汇总!$A:$A,0),MATCH(纵向时序!I$2,【输出】数据汇总!$1:$1,0))/100,"")=0,"",IFERROR(INDEX(【输出】数据汇总!$A:$AQ,MATCH(纵向时序!$D$2&纵向时序!$D12,【输出】数据汇总!$A:$A,0),MATCH(纵向时序!I$2,【输出】数据汇总!$1:$1,0))/100,"")) -> 36.16 | J12: =IF(IFERROR(INDEX(【输出】数据汇总!$A:$AQ,MATCH(纵向时序!$D$2&纵向时序!$D12,【输出】数据汇总!$A:$A,0),MATCH(纵向时序!J$2,【输出】数据汇总!$1:$1,0))/100,"")=0,"",IFERROR(INDEX(【输出】数据汇总!$A:$AQ,MATCH(纵向时序!$D$2&纵向时序!$D12,【输出】数据汇总!$A:$A,0),MATCH(纵向时序!J$2,【输出】数据汇总!$1:$1,0))/100,"")) -> 36.16 | K12: =IF(IFERROR(INDEX(【输出】数据汇总!$A:$AQ,MATCH(纵向时序!$D$2&纵向时序!$D12,【输出】数据汇总!$A:$A,0),MATCH(纵向时序!K$2,【输出】数据汇总!$1:$1,0))/100,"")=0,"",IFERROR(INDEX(【输出】数据汇总!$A:$AQ,MATCH(纵向时序!$D$2&纵向时序!$D12,【输出】数据汇总!$A:$A,0),MATCH(纵向时序!K$2,【输出】数据汇总!$1:$1,0))/100,"")) -> 150.23 | L12: =IF(IFERROR(INDEX(【输出】数据汇总!$A:$AQ,MATCH(纵向时序!$D$2&纵向时序!$D12,【输出】数据汇总!$A:$A,0),MATCH(纵向时序!L$2,【输出】数据汇总!$1:$1,0))/100,"")=0,"",IFERROR(INDEX(【输出】数据汇总!$A:$AQ,MATCH(纵向时序!$D$2&纵向时序!$D12,【输出】数据汇总!$A:$A,0),MATCH(纵向时序!L$2,【输出】数据汇总!$1:$1,0))/100,"")) -> 150.23 | ... AE12: =IF(IFERROR(INDEX(【输出】数据汇总!$A:$AQ,MATCH(纵向时序!$D$2&纵向时序!$D12,【输出】数据汇总!$A:$A,0),MATCH(纵向时序!AE$2,【输出】数据汇总!$1:$1,0))/100,"")=0,"",IFERROR(INDEX(【输出】数据汇总!$A:$AQ,MATCH(纵向时序!$D$2&纵向时序!$D12,【输出】数据汇总!$A:$A,0),MATCH(纵向时序!AE$2,【输出】数据汇总!$1:$1,0))/100,"")) -> 246.29
A13: 光大 | B13: 渤海 | C13: ⑩ | D13: 非信贷拨备额 | E13: =IF(IFERROR(INDEX(【输出】数据汇总!$A:$AQ,MATCH(纵向时序!$D$2&纵向时序!$D13,【输出】数据汇总!$A:$A,0),MATCH(纵向时序!E$2,【输出】数据汇总!$1:$1,0))/100,"")=0,"",IFERROR(INDEX(【输出】数据汇总!$A:$AQ,MATCH(纵向时序!$D$2&纵向时序!$D13,【输出】数据汇总!$A:$A,0),MATCH(纵向时序!E$2,【输出】数据汇总!$1:$1,0))/100,"")) -> 235.01 | F13: =IF(IFERROR(INDEX(【输出】数据汇总!$A:$AQ,MATCH(纵向时序!$D$2&纵向时序!$D13,【输出】数据汇总!$A:$A,0),MATCH(纵向时序!F$2,【输出】数据汇总!$1:$1,0))/100,"")=0,"",IFERROR(INDEX(【输出】数据汇总!$A:$AQ,MATCH(纵向时序!$D$2&纵向时序!$D13,【输出】数据汇总!$A:$A,0),MATCH(纵向时序!F$2,【输出】数据汇总!$1:$1,0))/100,"")) -> 235.01 | G13: =IF(IFERROR(INDEX(【输出】数据汇总!$A:$AQ,MATCH(纵向时序!$D$2&纵向时序!$D13,【输出】数据汇总!$A:$A,0),MATCH(纵向时序!G$2,【输出】数据汇总!$1:$1,0))/100,"")=0,"",IFERROR(INDEX(【输出】数据汇总!$A:$AQ,MATCH(纵向时序!$D$2&纵向时序!$D13,【输出】数据汇总!$A:$A,0),MATCH(纵向时序!G$2,【输出】数据汇总!$1:$1,0))/100,"")) -> 267.12 | H13: =IF(IFERROR(INDEX(【输出】数据汇总!$A:$AQ,MATCH(纵向时序!$D$2&纵向时序!$D13,【输出】数据汇总!$A:$A,0),MATCH(纵向时序!H$2,【输出】数据汇总!$1:$1,0))/100,"")=0,"",IFERROR(INDEX(【输出】数据汇总!$A:$AQ,MATCH(纵向时序!$D$2&纵向时序!$D13,【输出】数据汇总!$A:$A,0),MATCH(纵向时序!H$2,【输出】数据汇总!$1:$1,0))/100,"")) -> 267.12 | I13: =IF(IFERROR(INDEX(【输出】数据汇总!$A:$AQ,MATCH(纵向时序!$D$2&纵向时序!$D13,【输出】数据汇总!$A:$A,0),MATCH(纵向时序!I$2,【输出】数据汇总!$1:$1,0))/100,"")=0,"",IFERROR(INDEX(【输出】数据汇总!$A:$AQ,MATCH(纵向时序!$D$2&纵向时序!$D13,【输出】数据汇总!$A:$A,0),MATCH(纵向时序!I$2,【输出】数据汇总!$1:$1,0))/100,"")) -> 310.32 | J13: =IF(IFERROR(INDEX(【输出】数据汇总!$A:$AQ,MATCH(纵向时序!$D$2&纵向时序!$D13,【输出】数据汇总!$A:$A,0),MATCH(纵向时序!J$2,【输出】数据汇总!$1:$1,0))/100,"")=0,"",IFERROR(INDEX(【输出】数据汇总!$A:$AQ,MATCH(纵向时序!$D$2&纵向时序!$D13,【输出】数据汇总!$A:$A,0),MATCH(纵向时序!J$2,【输出】数据汇总!$1:$1,0))/100,"")) -> 310.32 | K13: =IF(IFERROR(INDEX(【输出】数据汇总!$A:$AQ,MATCH(纵向时序!$D$2&纵向时序!$D13,【输出】数据汇总!$A:$A,0),MATCH(纵向时序!K$2,【输出】数据汇总!$1:$1,0))/100,"")=0,"",IFERROR(INDEX(【输出】数据汇总!$A:$AQ,MATCH(纵向时序!$D$2&纵向时序!$D13,【输出】数据汇总!$A:$A,0),MATCH(纵向时序!K$2,【输出】数据汇总!$1:$1,0))/100,"")) -> 426.87 | L13: =IF(IFERROR(INDEX(【输出】数据汇总!$A:$AQ,MATCH(纵向时序!$D$2&纵向时序!$D13,【输出】数据汇总!$A:$A,0),MATCH(纵向时序!L$2,【输出】数据汇总!$1:$1,0))/100,"")=0,"",IFERROR(INDEX(【输出】数据汇总!$A:$AQ,MATCH(纵向时序!$D$2&纵向时序!$D13,【输出】数据汇总!$A:$A,0),MATCH(纵向时序!L$2,【输出】数据汇总!$1:$1,0))/100,"")) -> 426.87 | ... AE13: =IF(IFERROR(INDEX(【输出】数据汇总!$A:$AQ,MATCH(纵向时序!$D$2&纵向时序!$D13,【输出】数据汇总!$A:$A,0),MATCH(纵向时序!AE$2,【输出】数据汇总!$1:$1,0))/100,"")=0,"",IFERROR(INDEX(【输出】数据汇总!$A:$AQ,MATCH(纵向时序!$D$2&纵向时序!$D13,【输出】数据汇总!$A:$A,0),MATCH(纵向时序!AE$2,【输出】数据汇总!$1:$1,0))/100,"")) -> 524.6
A14: 平安 | B14: 威海 | C14: ⑪=⑩-⑦*100% | D14: 超额非信贷拨备 | E14: =IF(E12="",E13-0,E13-E12*100%) -> 154.87 | F14: =IF(F12="",F13-0,F13-F12*100%) -> 154.87 | G14: =IF(G12="",G13-0,G13-G12*100%) -> 213.94 | H14: =IF(H12="",H13-0,H13-H12*100%) -> 213.94 | I14: =IF(I12="",I13-0,I13-I12*100%) -> 274.16 | J14: =IF(J12="",J13-0,J13-J12*100%) -> 274.16 | K14: =IF(K12="",K13-0,K13-K12*100%) -> 276.64 | L14: =IF(L12="",L13-0,L13-L12*100%) -> 276.64 | ... AE14: =IF(AE12="",AE13-0,AE13-AE12*100%) -> 278.31
A15: 华夏 | B15: 东莞农商 | C15: ⑪+⑨ | D15: 超额拨备额 | E15: =E11+E14 -> 1157.12 | F15: =F11+F14 -> 1239.7086 | G15: =G11+G14 -> 1396.26 | H15: =H11+H14 -> 1497.7079 | I15: =I11+I14 -> 1678.91 | J15: =J11+J14 -> 1712.9598 | K15: =K11+K14 -> 1679.97 | L15: =L11+L14 -> 1746.1436 | ... AE15: =AE11+AE14 -> 1229.87
A16: 浙商 | B16: 国有行 | D16: 归母净利润(TTM) | E16: =IF(IFERROR(INDEX(【输出】数据汇总!$A:$AQ,MATCH(纵向时序!$D$2&纵向时序!$D16,【输出】数据汇总!$A:$A,0),MATCH(纵向时序!E$2,【输出】数据汇总!$1:$1,0))/100,"")=0,"",IFERROR(INDEX(【输出】数据汇总!$A:$AQ,MATCH(纵向时序!$D$2&纵向时序!$D16,【输出】数据汇总!$A:$A,0),MATCH(纵向时序!E$2,【输出】数据汇总!$1:$1,0))/100,"")) -> 864.16 | F16: =IF(IFERROR(INDEX(【输出】数据汇总!$A:$AQ,MATCH(纵向时序!$D$2&纵向时序!$D16,【输出】数据汇总!$A:$A,0),MATCH(纵向时序!F$2,【输出】数据汇总!$1:$1,0))/100,"")=0,"",IFERROR(INDEX(【输出】数据汇总!$A:$AQ,MATCH(纵向时序!$D$2&纵向时序!$D16,【输出】数据汇总!$A:$A,0),MATCH(纵向时序!F$2,【输出】数据汇总!$1:$1,0))/100,"")) -> 904.19 | G16: =IF(IFERROR(INDEX(【输出】数据汇总!$A:$AQ,MATCH(纵向时序!$D$2&纵向时序!$D16,【输出】数据汇总!$A:$A,0),MATCH(纵向时序!G$2,【输出】数据汇总!$1:$1,0))/100,"")=0,"",IFERROR(INDEX(【输出】数据汇总!$A:$AQ,MATCH(纵向时序!$D$2&纵向时序!$D16,【输出】数据汇总!$A:$A,0),MATCH(纵向时序!G$2,【输出】数据汇总!$1:$1,0))/100,"")) -> 928.67 | H16: =IF(IFERROR(INDEX(【输出】数据汇总!$A:$AQ,MATCH(纵向时序!$D$2&纵向时序!$D16,【输出】数据汇总!$A:$A,0),MATCH(纵向时序!H$2,【输出】数据汇总!$1:$1,0))/100,"")=0,"",IFERROR(INDEX(【输出】数据汇总!$A:$AQ,MATCH(纵向时序!$D$2&纵向时序!$D16,【输出】数据汇总!$A:$A,0),MATCH(纵向时序!H$2,【输出】数据汇总!$1:$1,0))/100,"")) -> 954.22 | I16: =IF(IFERROR(INDEX(【输出】数据汇总!$A:$AQ,MATCH(纵向时序!$D$2&纵向时序!$D16,【输出】数据汇总!$A:$A,0),MATCH(纵向时序!I$2,【输出】数据汇总!$1:$1,0))/100,"")=0,"",IFERROR(INDEX(【输出】数据汇总!$A:$AQ,MATCH(纵向时序!$D$2&纵向时序!$D16,【输出】数据汇总!$A:$A,0),MATCH(纵向时序!I$2,【输出】数据汇总!$1:$1,0))/100,"")) -> 920.43 | J16: =IF(IFERROR(INDEX(【输出】数据汇总!$A:$AQ,MATCH(纵向时序!$D$2&纵向时序!$D16,【输出】数据汇总!$A:$A,0),MATCH(纵向时序!J$2,【输出】数据汇总!$1:$1,0))/100,"")=0,"",IFERROR(INDEX(【输出】数据汇总!$A:$AQ,MATCH(纵向时序!$D$2&纵向时序!$D16,【输出】数据汇总!$A:$A,0),MATCH(纵向时序!J$2,【输出】数据汇总!$1:$1,0))/100,"")) -> 922.31 | K16: =IF(IFERROR(INDEX(【输出】数据汇总!$A:$AQ,MATCH(纵向时序!$D$2&纵向时序!$D16,【输出】数据汇总!$A:$A,0),MATCH(纵向时序!K$2,【输出】数据汇总!$1:$1,0))/100,"")=0,"",IFERROR(INDEX(【输出】数据汇总!$A:$AQ,MATCH(纵向时序!$D$2&纵向时序!$D16,【输出】数据汇总!$A:$A,0),MATCH(纵向时序!K$2,【输出】数据汇总!$1:$1,0))/100,"")) -> 973.42 | L16: =IF(IFERROR(INDEX(【输出】数据汇总!$A:$AQ,MATCH(纵向时序!$D$2&纵向时序!$D16,【输出】数据汇总!$A:$A,0),MATCH(纵向时序!L$2,【输出】数据汇总!$1:$1,0))/100,"")=0,"",IFERROR(INDEX(【输出】数据汇总!$A:$AQ,MATCH(纵向时序!$D$2&纵向时序!$D16,【输出】数据汇总!$A:$A,0),MATCH(纵向时序!L$2,【输出】数据汇总!$1:$1,0))/100,"")) -> 1015.62 | ... AE16: =IF(IFERROR(INDEX(【输出】数据汇总!$A:$AQ,MATCH(纵向时序!$D$2&纵向时序!$D16,【输出】数据汇总!$A:$A,0),MATCH(纵向时序!AE$2,【输出】数据汇总!$1:$1,0))/100,"")=0,"",IFERROR(INDEX(【输出】数据汇总!$A:$AQ,MATCH(纵向时序!$D$2&纵向时序!$D16,【输出】数据汇总!$A:$A,0),MATCH(纵向时序!AE$2,【输出】数据汇总!$1:$1,0))/100,"")) -> 1501.81
A17: 北京 | B17: 股份行 | D17: 归母净资产 | E17: =IF(IFERROR(INDEX(【输出】数据汇总!$A:$AQ,MATCH(纵向时序!$D$2&纵向时序!$D17,【输出】数据汇总!$A:$A,0),MATCH(纵向时序!E$2,【输出】数据汇总!$1:$1,0))/100,"")=0,"",IFERROR(INDEX(【输出】数据汇总!$A:$AQ,MATCH(纵向时序!$D$2&纵向时序!$D17,【输出】数据汇总!$A:$A,0),MATCH(纵向时序!E$2,【输出】数据汇总!$1:$1,0))/100,"")) -> 5678.86 | F17: =IF(IFERROR(INDEX(【输出】数据汇总!$A:$AQ,MATCH(纵向时序!$D$2&纵向时序!$D17,【输出】数据汇总!$A:$A,0),MATCH(纵向时序!F$2,【输出】数据汇总!$1:$1,0))/100,"")=0,"",IFERROR(INDEX(【输出】数据汇总!$A:$AQ,MATCH(纵向时序!$D$2&纵向时序!$D17,【输出】数据汇总!$A:$A,0),MATCH(纵向时序!F$2,【输出】数据汇总!$1:$1,0))/100,"")) -> 5964.25 | G17: =IF(IFERROR(INDEX(【输出】数据汇总!$A:$AQ,MATCH(纵向时序!$D$2&纵向时序!$D17,【输出】数据汇总!$A:$A,0),MATCH(纵向时序!G$2,【输出】数据汇总!$1:$1,0))/100,"")=0,"",IFERROR(INDEX(【输出】数据汇总!$A:$AQ,MATCH(纵向时序!$D$2&纵向时序!$D17,【输出】数据汇总!$A:$A,0),MATCH(纵向时序!G$2,【输出】数据汇总!$1:$1,0))/100,"")) -> 6113.01 | H17: =IF(IFERROR(INDEX(【输出】数据汇总!$A:$AQ,MATCH(纵向时序!$D$2&纵向时序!$D17,【输出】数据汇总!$A:$A,0),MATCH(纵向时序!H$2,【输出】数据汇总!$1:$1,0))/100,"")=0,"",IFERROR(INDEX(【输出】数据汇总!$A:$AQ,MATCH(纵向时序!$D$2&纵向时序!$D17,【输出】数据汇总!$A:$A,0),MATCH(纵向时序!H$2,【输出】数据汇总!$1:$1,0))/100,"")) -> 6420.31 | I17: =IF(IFERROR(INDEX(【输出】数据汇总!$A:$AQ,MATCH(纵向时序!$D$2&纵向时序!$D17,【输出】数据汇总!$A:$A,0),MATCH(纵向时序!I$2,【输出】数据汇总!$1:$1,0))/100,"")=0,"",IFERROR(INDEX(【输出】数据汇总!$A:$AQ,MATCH(纵向时序!$D$2&纵向时序!$D17,【输出】数据汇总!$A:$A,0),MATCH(纵向时序!I$2,【输出】数据汇总!$1:$1,0))/100,"")) -> 6325.3 | J17: =IF(IFERROR(INDEX(【输出】数据汇总!$A:$AQ,MATCH(纵向时序!$D$2&纵向时序!$D17,【输出】数据汇总!$A:$A,0),MATCH(纵向时序!J$2,【输出】数据汇总!$1:$1,0))/100,"")=0,"",IFERROR(INDEX(【输出】数据汇总!$A:$AQ,MATCH(纵向时序!$D$2&纵向时序!$D17,【输出】数据汇总!$A:$A,0),MATCH(纵向时序!J$2,【输出】数据汇总!$1:$1,0))/100,"")) -> 7033.06 | K17: =IF(IFERROR(INDEX(【输出】数据汇总!$A:$AQ,MATCH(纵向时序!$D$2&纵向时序!$D17,【输出】数据汇总!$A:$A,0),MATCH(纵向时序!K$2,【输出】数据汇总!$1:$1,0))/100,"")=0,"",IFERROR(INDEX(【输出】数据汇总!$A:$AQ,MATCH(纵向时序!$D$2&纵向时序!$D17,【输出】数据汇总!$A:$A,0),MATCH(纵向时序!K$2,【输出】数据汇总!$1:$1,0))/100,"")) -> 7237.5 | L17: =IF(IFERROR(INDEX(【输出】数据汇总!$A:$AQ,MATCH(纵向时序!$D$2&纵向时序!$D17,【输出】数据汇总!$A:$A,0),MATCH(纵向时序!L$2,【输出】数据汇总!$1:$1,0))/100,"")=0,"",IFERROR(INDEX(【输出】数据汇总!$A:$AQ,MATCH(纵向时序!$D$2&纵向时序!$D17,【输出】数据汇总!$A:$A,0),MATCH(纵向时序!L$2,【输出】数据汇总!$1:$1,0))/100,"")) -> 7551.07 | ... AE17: =IF(IFERROR(INDEX(【输出】数据汇总!$A:$AQ,MATCH(纵向时序!$D$2&纵向时序!$D17,【输出】数据汇总!$A:$A,0),MATCH(纵向时序!AE$2,【输出】数据汇总!$1:$1,0))/100,"")=0,"",IFERROR(INDEX(【输出】数据汇总!$A:$AQ,MATCH(纵向时序!$D$2&纵向时序!$D17,【输出】数据汇总!$A:$A,0),MATCH(纵向时序!AE$2,【输出】数据汇总!$1:$1,0))/100,"")) -> 12728.75
A18: 江苏 | B18: 城商行 | D18: 逾期率 | E18: =IFERROR(INDEX(【输出】数据汇总!$A:$AQ,MATCH(纵向时序!$D$2&纵向时序!$D18,【输出】数据汇总!$A:$A,0),MATCH(纵向时序!E$2,【输出】数据汇总!$1:$1,0)),"") -> 0.015550719 | F18: =IFERROR(INDEX(【输出】数据汇总!$A:$AQ,MATCH(纵向时序!$D$2&纵向时序!$D18,【输出】数据汇总!$A:$A,0),MATCH(纵向时序!F$2,【输出】数据汇总!$1:$1,0)),"") -> 0.015067256 | G18: =IFERROR(INDEX(【输出】数据汇总!$A:$AQ,MATCH(纵向时序!$D$2&纵向时序!$D18,【输出】数据汇总!$A:$A,0),MATCH(纵向时序!G$2,【输出】数据汇总!$1:$1,0)),"") -> 0.014109984 | H18: =IFERROR(INDEX(【输出】数据汇总!$A:$AQ,MATCH(纵向时序!$D$2&纵向时序!$D18,【输出】数据汇总!$A:$A,0),MATCH(纵向时序!H$2,【输出】数据汇总!$1:$1,0)),"") -> 0.01338846 | I18: =IFERROR(INDEX(【输出】数据汇总!$A:$AQ,MATCH(纵向时序!$D$2&纵向时序!$D18,【输出】数据汇总!$A:$A,0),MATCH(纵向时序!I$2,【输出】数据汇总!$1:$1,0)),"") -> 0.013540161 | J18: =IFERROR(INDEX(【输出】数据汇总!$A:$AQ,MATCH(纵向时序!$D$2&纵向时序!$D18,【输出】数据汇总!$A:$A,0),MATCH(纵向时序!J$2,【输出】数据汇总!$1:$1,0)),"") -> 0.013122323 | K18: =IFERROR(INDEX(【输出】数据汇总!$A:$AQ,MATCH(纵向时序!$D$2&纵向时序!$D18,【输出】数据汇总!$A:$A,0),MATCH(纵向时序!K$2,【输出】数据汇总!$1:$1,0)),"") -> 0.011248073 | L18: =IFERROR(INDEX(【输出】数据汇总!$A:$AQ,MATCH(纵向时序!$D$2&纵向时序!$D18,【输出】数据汇总!$A:$A,0),MATCH(纵向时序!L$2,【输出】数据汇总!$1:$1,0)),"") -> 0.010648036 | ... AE18: =IFERROR(INDEX(【输出】数据汇总!$A:$AQ,MATCH(纵向时序!$D$2&纵向时序!$D18,【输出】数据汇总!$A:$A,0),MATCH(纵向时序!AE$2,【输出】数据汇总!$1:$1,0)),"") -> 0.012489016
A19: 上海 | B19: 农商行 | D19: 重组率 | E19: =IFERROR(INDEX(【输出】数据汇总!$A:$AQ,MATCH(纵向时序!$D$2&纵向时序!$D19,【输出】数据汇总!$A:$A,0),MATCH(纵向时序!E$2,【输出】数据汇总!$1:$1,0)),"") -> 0.0057191693 | F19: =IFERROR(INDEX(【输出】数据汇总!$A:$AQ,MATCH(纵向时序!$D$2&纵向时序!$D19,【输出】数据汇总!$A:$A,0),MATCH(纵向时序!F$2,【输出】数据汇总!$1:$1,0)),"") -> 0.0055413637 | G19: =IFERROR(INDEX(【输出】数据汇总!$A:$AQ,MATCH(纵向时序!$D$2&纵向时序!$D19,【输出】数据汇总!$A:$A,0),MATCH(纵向时序!G$2,【输出】数据汇总!$1:$1,0)),"") -> 0.0055720219 | H19: =IFERROR(INDEX(【输出】数据汇总!$A:$AQ,MATCH(纵向时序!$D$2&纵向时序!$D19,【输出】数据汇总!$A:$A,0),MATCH(纵向时序!H$2,【输出】数据汇总!$1:$1,0)),"") -> 0.0052870924 | I19: =IFERROR(INDEX(【输出】数据汇总!$A:$AQ,MATCH(纵向时序!$D$2&纵向时序!$D19,【输出】数据汇总!$A:$A,0),MATCH(纵向时序!I$2,【输出】数据汇总!$1:$1,0)),"") -> 0.0049361927 | J19: =IFERROR(INDEX(【输出】数据汇总!$A:$AQ,MATCH(纵向时序!$D$2&纵向时序!$D19,【输出】数据汇总!$A:$A,0),MATCH(纵向时序!J$2,【输出】数据汇总!$1:$1,0)),"") -> 0.0047838661 | K19: =IFERROR(INDEX(【输出】数据汇总!$A:$AQ,MATCH(纵向时序!$D$2&纵向时序!$D19,【输出】数据汇总!$A:$A,0),MATCH(纵向时序!K$2,【输出】数据汇总!$1:$1,0)),"") -> 0.004946782 | L19: =IFERROR(INDEX(【输出】数据汇总!$A:$AQ,MATCH(纵向时序!$D$2&纵向时序!$D19,【输出】数据汇总!$A:$A,0),MATCH(纵向时序!L$2,【输出】数据汇总!$1:$1,0)),"") -> 0.0046828921 | ... AE19: =IFERROR(INDEX(【输出】数据汇总!$A:$AQ,MATCH(纵向时序!$D$2&纵向时序!$D19,【输出】数据汇总!$A:$A,0),MATCH(纵向时序!AE$2,【输出】数据汇总!$1:$1,0)),"") -> 0.0039000791
A20: 宁波 | B20: 上市银行 | D20: 不良贷款率 | E20: =IFERROR(INDEX(【输出】数据汇总!$A:$AQ,MATCH(纵向时序!$D$2&纵向时序!$D20,【输出】数据汇总!$A:$A,0),MATCH(纵向时序!E$2,【输出】数据汇总!$1:$1,0)),"") -> 0.0123 | F20: =IFERROR(INDEX(【输出】数据汇总!$A:$AQ,MATCH(纵向时序!$D$2&纵向时序!$D20,【输出】数据汇总!$A:$A,0),MATCH(纵向时序!F$2,【输出】数据汇总!$1:$1,0)),"") -> 0.0119 | G20: =IFERROR(INDEX(【输出】数据汇总!$A:$AQ,MATCH(纵向时序!$D$2&纵向时序!$D20,【输出】数据汇总!$A:$A,0),MATCH(纵向时序!G$2,【输出】数据汇总!$1:$1,0)),"") -> 0.0116 | H20: =IFERROR(INDEX(【输出】数据汇总!$A:$AQ,MATCH(纵向时序!$D$2&纵向时序!$D20,【输出】数据汇总!$A:$A,0),MATCH(纵向时序!H$2,【输出】数据汇总!$1:$1,0)),"") -> 0.0111 | I20: =IFERROR(INDEX(【输出】数据汇总!$A:$AQ,MATCH(纵向时序!$D$2&纵向时序!$D20,【输出】数据汇总!$A:$A,0),MATCH(纵向时序!I$2,【输出】数据汇总!$1:$1,0)),"") -> 0.0114 | J20: =IFERROR(INDEX(【输出】数据汇总!$A:$AQ,MATCH(纵向时序!$D$2&纵向时序!$D20,【输出】数据汇总!$A:$A,0),MATCH(纵向时序!J$2,【输出】数据汇总!$1:$1,0)),"") -> 0.0113 | K20: =IFERROR(INDEX(【输出】数据汇总!$A:$AQ,MATCH(纵向时序!$D$2&纵向时序!$D20,【输出】数据汇总!$A:$A,0),MATCH(纵向时序!K$2,【输出】数据汇总!$1:$1,0)),"") -> 0.0107 | L20: =IFERROR(INDEX(【输出】数据汇总!$A:$AQ,MATCH(纵向时序!$D$2&纵向时序!$D20,【输出】数据汇总!$A:$A,0),MATCH(纵向时序!L$2,【输出】数据汇总!$1:$1,0)),"") -> 0.0102 | ... AE20: =IFERROR(INDEX(【输出】数据汇总!$A:$AQ,MATCH(纵向时序!$D$2&纵向时序!$D20,【输出】数据汇总!$A:$A,0),MATCH(纵向时序!AE$2,【输出】数据汇总!$1:$1,0)),"") -> 0.0094
A21: 南京 | B21: AH股 | D21: 关注贷款率 | E21: =IFERROR(INDEX(【输出】数据汇总!$A:$AQ,MATCH(纵向时序!$D$2&纵向时序!$D21,【输出】数据汇总!$A:$A,0),MATCH(纵向时序!E$2,【输出】数据汇总!$1:$1,0)),"") -> 0.013024311 | F21: =IFERROR(INDEX(【输出】数据汇总!$A:$AQ,MATCH(纵向时序!$D$2&纵向时序!$D21,【输出】数据汇总!$A:$A,0),MATCH(纵向时序!F$2,【输出】数据汇总!$1:$1,0)),"") -> 0.012619393 | G21: =IFERROR(INDEX(【输出】数据汇总!$A:$AQ,MATCH(纵向时序!$D$2&纵向时序!$D21,【输出】数据汇总!$A:$A,0),MATCH(纵向时序!G$2,【输出】数据汇总!$1:$1,0)),"") -> 0.011711 | H21: =IFERROR(INDEX(【输出】数据汇总!$A:$AQ,MATCH(纵向时序!$D$2&纵向时序!$D21,【输出】数据汇总!$A:$A,0),MATCH(纵向时序!H$2,【输出】数据汇总!$1:$1,0)),"") -> 0.01190198 | I21: =IFERROR(INDEX(【输出】数据汇总!$A:$AQ,MATCH(纵向时序!$D$2&纵向时序!$D21,【输出】数据汇总!$A:$A,0),MATCH(纵向时序!I$2,【输出】数据汇总!$1:$1,0)),"") -> 0.0099115467 | J21: =IFERROR(INDEX(【输出】数据汇总!$A:$AQ,MATCH(纵向时序!$D$2&纵向时序!$D21,【输出】数据汇总!$A:$A,0),MATCH(纵向时序!J$2,【输出】数据汇总!$1:$1,0)),"") -> 0.0078900132 | K21: =IFERROR(INDEX(【输出】数据汇总!$A:$AQ,MATCH(纵向时序!$D$2&纵向时序!$D21,【输出】数据汇总!$A:$A,0),MATCH(纵向时序!K$2,【输出】数据汇总!$1:$1,0)),"") -> 0.0080960357 | L21: =IFERROR(INDEX(【输出】数据汇总!$A:$AQ,MATCH(纵向时序!$D$2&纵向时序!$D21,【输出】数据汇总!$A:$A,0),MATCH(纵向时序!L$2,【输出】数据汇总!$1:$1,0)),"") -> 0.0068212334 | ... AE21: =IFERROR(INDEX(【输出】数据汇总!$A:$AQ,MATCH(纵向时序!$D$2&纵向时序!$D21,【输出】数据汇总!$A:$A,0),MATCH(纵向时序!AE$2,【输出】数据汇总!$1:$1,0)),"") -> 0.014309613
A22: 杭州 | B22: 纯H股 | D22: 逾期+重组率 | E22: =IFERROR(E18+E19,"") -> 0.021269888 | F22: =IFERROR(F18+F19,"") -> 0.02060862 | G22: =IFERROR(G18+G19,"") -> 0.019682006 | H22: =IFERROR(H18+H19,"") -> 0.018675552 | I22: =IFERROR(I18+I19,"") -> 0.018476353 | J22: =IFERROR(J18+J19,"") -> 0.017906189 | K22: =IFERROR(K18+K19,"") -> 0.016194855 | L22: =IFERROR(L18+L19,"") -> 0.015330928 | ... AE22: =IFERROR(AE18+AE19,"") -> 0.016389095
A23: 成都 | D23: 不良+关注率 | E23: =IFERROR(E20+E21,"") -> 0.025324311 | F23: =IFERROR(F20+F21,"") -> 0.024519393 | G23: =IFERROR(G20+G21,"") -> 0.023311 | H23: =IFERROR(H20+H21,"") -> 0.02300198 | I23: =IFERROR(I20+I21,"") -> 0.021311547 | J23: =IFERROR(J20+J21,"") -> 0.019190013 | K23: =IFERROR(K20+K21,"") -> 0.018796036 | L23: =IFERROR(L20+L21,"") -> 0.017021233 | ... AE23: =IFERROR(AE20+AE21,"") -> 0.023709613
A24: 长沙 | C24: ⑥/① | D24: 广义风险贷款比率 | E24: =E9/E3 -> 0.025333929 | F24: =F9/F3 -> 0.024555276 | G24: =G9/G3 -> 0.023351853 | H24: =H9/H3 -> 0.023012438 | I24: =I9/I3 -> 0.021315349 | J24: =J9/J3 -> 0.019169222 | K24: =K9/K3 -> 0.01875693 | L24: =L9/L3 -> 0.016996613 | ... AE24: =AE9/AE3 -> 0.023706892
A25: 重庆 | D25: 广义不良资产率 | E25: =IFERROR(INDEX(【输出】数据汇总!$A:$AQ,MATCH(纵向时序!$D$2&纵向时序!$D25,【输出】数据汇总!$A:$A,0),MATCH(纵向时序!E$2,【输出】数据汇总!$1:$1,0)),"") -> 0.017828365 | F25: =IFERROR(INDEX(【输出】数据汇总!$A:$AQ,MATCH(纵向时序!$D$2&纵向时序!$D25,【输出】数据汇总!$A:$A,0),MATCH(纵向时序!F$2,【输出】数据汇总!$1:$1,0)),"") -> 0.017407632 | G25: =IFERROR(INDEX(【输出】数据汇总!$A:$AQ,MATCH(纵向时序!$D$2&纵向时序!$D25,【输出】数据汇总!$A:$A,0),MATCH(纵向时序!G$2,【输出】数据汇总!$1:$1,0)),"") -> 0.016134657 | H25: =IFERROR(INDEX(【输出】数据汇总!$A:$AQ,MATCH(纵向时序!$D$2&纵向时序!$D25,【输出】数据汇总!$A:$A,0),MATCH(纵向时序!H$2,【输出】数据汇总!$1:$1,0)),"") -> 0.015741967 | I25: =IFERROR(INDEX(【输出】数据汇总!$A:$AQ,MATCH(纵向时序!$D$2&纵向时序!$D25,【输出】数据汇总!$A:$A,0),MATCH(纵向时序!I$2,【输出】数据汇总!$1:$1,0)),"") -> 0.014315053 | J25: =IFERROR(INDEX(【输出】数据汇总!$A:$AQ,MATCH(纵向时序!$D$2&纵向时序!$D25,【输出】数据汇总!$A:$A,0),MATCH(纵向时序!J$2,【输出】数据汇总!$1:$1,0)),"") -> 0.013116862 | K25: =IFERROR(INDEX(【输出】数据汇总!$A:$AQ,MATCH(纵向时序!$D$2&纵向时序!$D25,【输出】数据汇总!$A:$A,0),MATCH(纵向时序!K$2,【输出】数据汇总!$1:$1,0)),"") -> 0.014200915 | L25: =IFERROR(INDEX(【输出】数据汇总!$A:$AQ,MATCH(纵向时序!$D$2&纵向时序!$D25,【输出】数据汇总!$A:$A,0),MATCH(纵向时序!L$2,【输出】数据汇总!$1:$1,0)),"") -> 0.013175576 | ... AE25: =IFERROR(INDEX(【输出】数据汇总!$A:$AQ,MATCH(纵向时序!$D$2&纵向时序!$D25,【输出】数据汇总!$A:$A,0),MATCH(纵向时序!AE$2,【输出】数据汇总!$1:$1,0)),"") -> 0.015915787
A26: 贵阳 | D26: 拨备覆盖率 | E26: =IFERROR(INDEX(【输出】数据汇总!$A:$AQ,MATCH(纵向时序!$D$2&纵向时序!$D26,【输出】数据汇总!$A:$A,0),MATCH(纵向时序!E$2,【输出】数据汇总!$1:$1,0)),"") -> 3.9412 | F26: =IFERROR(INDEX(【输出】数据汇总!$A:$AQ,MATCH(纵向时序!$D$2&纵向时序!$D26,【输出】数据汇总!$A:$A,0),MATCH(纵向时序!F$2,【输出】数据汇总!$1:$1,0)),"") -> 4.0941 | G26: =IFERROR(INDEX(【输出】数据汇总!$A:$AQ,MATCH(纵向时序!$D$2&纵向时序!$D26,【输出】数据汇总!$A:$A,0),MATCH(纵向时序!G$2,【输出】数据汇总!$1:$1,0)),"") -> 4.2678 | H26: =IFERROR(INDEX(【输出】数据汇总!$A:$AQ,MATCH(纵向时序!$D$2&纵向时序!$D26,【输出】数据汇总!$A:$A,0),MATCH(纵向时序!H$2,【输出】数据汇总!$1:$1,0)),"") -> 4.5127 | I26: =IFERROR(INDEX(【输出】数据汇总!$A:$AQ,MATCH(纵向时序!$D$2&纵向时序!$D26,【输出】数据汇总!$A:$A,0),MATCH(纵向时序!I$2,【输出】数据汇总!$1:$1,0)),"") -> 4.4081 | J26: =IFERROR(INDEX(【输出】数据汇总!$A:$AQ,MATCH(纵向时序!$D$2&纵向时序!$D26,【输出】数据汇总!$A:$A,0),MATCH(纵向时序!J$2,【输出】数据汇总!$1:$1,0)),"") -> 4.2476 | K26: =IFERROR(INDEX(【输出】数据汇总!$A:$AQ,MATCH(纵向时序!$D$2&纵向时序!$D26,【输出】数据汇总!$A:$A,0),MATCH(纵向时序!K$2,【输出】数据汇总!$1:$1,0)),"") -> 4.3768 | L26: =IFERROR(INDEX(【输出】数据汇总!$A:$AQ,MATCH(纵向时序!$D$2&纵向时序!$D26,【输出】数据汇总!$A:$A,0),MATCH(纵向时序!L$2,【输出】数据汇总!$1:$1,0)),"") -> 4.3888 | ... AE26: =IFERROR(INDEX(【输出】数据汇总!$A:$AQ,MATCH(纵向时序!$D$2&纵向时序!$D26,【输出】数据汇总!$A:$A,0),MATCH(纵向时序!AE$2,【输出】数据汇总!$1:$1,0)),"") -> 3.9179
A27: 郑州 | D27: 超额拨备/归母净利润(TTM) | E27: =E15/E16 -> 1.3390113 | F27: =F15/F16 -> 1.3710709 | G27: =G15/G16 -> 1.503505 | H27: =H15/H16 -> 1.5695625 | I27: =I15/I16 -> 1.8240496 | J27: =J15/J16 -> 1.8572495 | K27: =K15/K16 -> 1.7258429 | L27: =L15/L16 -> 1.7192883 | ... AE27: =AE15/AE16 -> 0.81892516
A28: 青岛 | D28: 超额拨备/归母净资产 | E28: =E15/E17 -> 0.20375921 | F28: =F15/F17 -> 0.20785658 | G28: =G15/G17 -> 0.22840794 | H28: =H15/H17 -> 0.23327657 | I28: =I15/I17 -> 0.26542773 | J28: =J15/J17 -> 0.24355825 | K28: =K15/K17 -> 0.23212021 | L28: =L15/L17 -> 0.23124453 | ... AE28: =AE15/AE17 -> 0.096621428
A29: 苏州
A30: 齐鲁 | D30: 建设 | E30: =E2 -> 43646 | F30: =F2 -> 43738 | G30: =G2 -> 43830 | H30: =H2 -> 43921 | I30: =I2 -> 44012 | J30: =J2 -> 44104 | K30: =K2 -> 44196 | L30: =L2 -> 44286 | ... AE30: =AE2 -> 46022
A31: 兰州 | C31: ① | D31: 贷款总额 | E31: =IFERROR(INDEX(【输出】数据汇总!$A:$AQ,MATCH(纵向时序!$D$30&纵向时序!$D31,【输出】数据汇总!$A:$A,0),MATCH(纵向时序!E$2,【输出】数据汇总!$1:$1,0))/100,"") -> 145019.35 | F31: =IFERROR(INDEX(【输出】数据汇总!$A:$AQ,MATCH(纵向时序!$D$30&纵向时序!$D31,【输出】数据汇总!$A:$A,0),MATCH(纵向时序!F$2,【输出】数据汇总!$1:$1,0))/100,"") -> 148327.11 | G31: =IFERROR(INDEX(【输出】数据汇总!$A:$AQ,MATCH(纵向时序!$D$30&纵向时序!$D31,【输出】数据汇总!$A:$A,0),MATCH(纵向时序!G$2,【输出】数据汇总!$1:$1,0))/100,"") -> 149879.06 | H31: =IFERROR(INDEX(【输出】数据汇总!$A:$AQ,MATCH(纵向时序!$D$30&纵向时序!$D31,【输出】数据汇总!$A:$A,0),MATCH(纵向时序!H$2,【输出】数据汇总!$1:$1,0))/100,"") -> 159422.19 | I31: =IFERROR(INDEX(【输出】数据汇总!$A:$AQ,MATCH(纵向时序!$D$30&纵向时序!$D31,【输出】数据汇总!$A:$A,0),MATCH(纵向时序!I$2,【输出】数据汇总!$1:$1,0))/100,"") -> 164304.6 | J31: =IFERROR(INDEX(【输出】数据汇总!$A:$AQ,MATCH(纵向时序!$D$30&纵向时序!$D31,【输出】数据汇总!$A:$A,0),MATCH(纵向时序!J$2,【输出】数据汇总!$1:$1,0))/100,"") -> 166609.35 | K31: =IFERROR(INDEX(【输出】数据汇总!$A:$AQ,MATCH(纵向时序!$D$30&纵向时序!$D31,【输出】数据汇总!$A:$A,0),MATCH(纵向时序!K$2,【输出】数据汇总!$1:$1,0))/100,"") -> 167457.68 | L31: =IFERROR(INDEX(【输出】数据汇总!$A:$AQ,MATCH(纵向时序!$D$30&纵向时序!$D31,【输出】数据汇总!$A:$A,0),MATCH(纵向时序!L$2,【输出】数据汇总!$1:$1,0))/100,"") -> 176267.71 | ... AE31: =IFERROR(INDEX(【输出】数据汇总!$A:$AQ,MATCH(纵向时序!$D$30&纵向时序!$D31,【输出】数据汇总!$A:$A,0),MATCH(纵向时序!AE$2,【输出】数据汇总!$1:$1,0))/100,"") -> 277728.27
A32: 西安 | C32: ② | D32: 逾期贷款余额 | E32: =IFERROR(INDEX(【输出】数据汇总!$A:$AQ,MATCH(纵向时序!$D$30&纵向时序!$D32,【输出】数据汇总!$A:$A,0),MATCH(纵向时序!E$2,【输出】数据汇总!$1:$1,0))/100,"") -> 2077.7 | F32: =IFERROR(INDEX(【输出】数据汇总!$A:$AQ,MATCH(纵向时序!$D$30&纵向时序!$D32,【输出】数据汇总!$A:$A,0),MATCH(纵向时序!F$2,【输出】数据汇总!$1:$1,0))/100,"") -> 2077.7 | G32: =IFERROR(INDEX(【输出】数据汇总!$A:$AQ,MATCH(纵向时序!$D$30&纵向时序!$D32,【输出】数据汇总!$A:$A,0),MATCH(纵向时序!G$2,【输出】数据汇总!$1:$1,0))/100,"") -> 1728.83 | H32: =IFERROR(INDEX(【输出】数据汇总!$A:$AQ,MATCH(纵向时序!$D$30&纵向时序!$D32,【输出】数据汇总!$A:$A,0),MATCH(纵向时序!H$2,【输出】数据汇总!$1:$1,0))/100,"") -> 1728.83 | I32: =IFERROR(INDEX(【输出】数据汇总!$A:$AQ,MATCH(纵向时序!$D$30&纵向时序!$D32,【输出】数据汇总!$A:$A,0),MATCH(纵向时序!I$2,【输出】数据汇总!$1:$1,0))/100,"") -> 1865.92 | J32: =IFERROR(INDEX(【输出】数据汇总!$A:$AQ,MATCH(纵向时序!$D$30&纵向时序!$D32,【输出】数据汇总!$A:$A,0),MATCH(纵向时序!J$2,【输出】数据汇总!$1:$1,0))/100,"") -> 1865.92 | K32: =IFERROR(INDEX(【输出】数据汇总!$A:$AQ,MATCH(纵向时序!$D$30&纵向时序!$D32,【输出】数据汇总!$A:$A,0),MATCH(纵向时序!K$2,【输出】数据汇总!$1:$1,0))/100,"") -> 1822.23 | L32: =IFERROR(INDEX(【输出】数据汇总!$A:$AQ,MATCH(纵向时序!$D$30&纵向时序!$D32,【输出】数据汇总!$A:$A,0),MATCH(纵向时序!L$2,【输出】数据汇总!$1:$1,0))/100,"") -> 1822.23 | ... AE32: =IFERROR(INDEX(【输出】数据汇总!$A:$AQ,MATCH(纵向时序!$D$30&纵向时序!$D32,【输出】数据汇总!$A:$A,0),MATCH(纵向时序!AE$2,【输出】数据汇总!$1:$1,0))/100,"") -> 3678.14
A33: 厦门 | C33: ③ | D33: 重组贷款余额 | E33: =IFERROR(INDEX(【输出】数据汇总!$A:$AQ,MATCH(纵向时序!$D$30&纵向时序!$D33,【输出】数据汇总!$A:$A,0),MATCH(纵向时序!E$2,【输出】数据汇总!$1:$1,0))/100,"") -> 48.46 | F33: =IFERROR(INDEX(【输出】数据汇总!$A:$AQ,MATCH(纵向时序!$D$30&纵向时序!$D33,【输出】数据汇总!$A:$A,0),MATCH(纵向时序!F$2,【输出】数据汇总!$1:$1,0))/100,"") -> 48.46 | G33: =IFERROR(INDEX(【输出】数据汇总!$A:$AQ,MATCH(纵向时序!$D$30&纵向时序!$D33,【输出】数据汇总!$A:$A,0),MATCH(纵向时序!G$2,【输出】数据汇总!$1:$1,0))/100,"") -> 60.3 | H33: =IFERROR(INDEX(【输出】数据汇总!$A:$AQ,MATCH(纵向时序!$D$30&纵向时序!$D33,【输出】数据汇总!$A:$A,0),MATCH(纵向时序!H$2,【输出】数据汇总!$1:$1,0))/100,"") -> 60.3 | I33: =IFERROR(INDEX(【输出】数据汇总!$A:$AQ,MATCH(纵向时序!$D$30&纵向时序!$D33,【输出】数据汇总!$A:$A,0),MATCH(纵向时序!I$2,【输出】数据汇总!$1:$1,0))/100,"") -> 71.69 | J33: =IFERROR(INDEX(【输出】数据汇总!$A:$AQ,MATCH(纵向时序!$D$30&纵向时序!$D33,【输出】数据汇总!$A:$A,0),MATCH(纵向时序!J$2,【输出】数据汇总!$1:$1,0))/100,"") -> 71.69 | K33: =IFERROR(INDEX(【输出】数据汇总!$A:$AQ,MATCH(纵向时序!$D$30&纵向时序!$D33,【输出】数据汇总!$A:$A,0),MATCH(纵向时序!K$2,【输出】数据汇总!$1:$1,0))/100,"") -> 100.9 | L33: =IFERROR(INDEX(【输出】数据汇总!$A:$AQ,MATCH(纵向时序!$D$30&纵向时序!$D33,【输出】数据汇总!$A:$A,0),MATCH(纵向时序!L$2,【输出】数据汇总!$1:$1,0))/100,"") -> 100.9 | ... AE33: =IFERROR(INDEX(【输出】数据汇总!$A:$AQ,MATCH(纵向时序!$D$30&纵向时序!$D33,【输出】数据汇总!$A:$A,0),MATCH(纵向时序!AE$2,【输出】数据汇总!$1:$1,0))/100,"") -> 1263.75
A34: 渝农 | C34: ④ | D34: 不良贷款余额 | E34: =IFERROR(INDEX(【输出】数据汇总!$A:$AQ,MATCH(纵向时序!$D$30&纵向时序!$D34,【输出】数据汇总!$A:$A,0),MATCH(纵向时序!E$2,【输出】数据汇总!$1:$1,0))/100,"") -> 2080.69 | F34: =IFERROR(INDEX(【输出】数据汇总!$A:$AQ,MATCH(纵向时序!$D$30&纵向时序!$D34,【输出】数据汇总!$A:$A,0),MATCH(纵向时序!F$2,【输出】数据汇总!$1:$1,0))/100,"") -> 2113.99 | G34: =IFERROR(INDEX(【输出】数据汇总!$A:$AQ,MATCH(纵向时序!$D$30&纵向时序!$D34,【输出】数据汇总!$A:$A,0),MATCH(纵向时序!G$2,【输出】数据汇总!$1:$1,0))/100,"") -> 2124.73 | H34: =IFERROR(INDEX(【输出】数据汇总!$A:$AQ,MATCH(纵向时序!$D$30&纵向时序!$D34,【输出】数据汇总!$A:$A,0),MATCH(纵向时序!H$2,【输出】数据汇总!$1:$1,0))/100,"") -> 2260.1 | I34: =IFERROR(INDEX(【输出】数据汇总!$A:$AQ,MATCH(纵向时序!$D$30&纵向时序!$D34,【输出】数据汇总!$A:$A,0),MATCH(纵向时序!I$2,【输出】数据汇总!$1:$1,0))/100,"") -> 2455.16 | J34: =IFERROR(INDEX(【输出】数据汇总!$A:$AQ,MATCH(纵向时序!$D$30&纵向时序!$D34,【输出】数据汇总!$A:$A,0),MATCH(纵向时序!J$2,【输出】数据汇总!$1:$1,0))/100,"") -> 2555.28 | K34: =IFERROR(INDEX(【输出】数据汇总!$A:$AQ,MATCH(纵向时序!$D$30&纵向时序!$D34,【输出】数据汇总!$A:$A,0),MATCH(纵向时序!K$2,【输出】数据汇总!$1:$1,0))/100,"") -> 2607.29 | L34: =IFERROR(INDEX(【输出】数据汇总!$A:$AQ,MATCH(纵向时序!$D$30&纵向时序!$D34,【输出】数据汇总!$A:$A,0),MATCH(纵向时序!L$2,【输出】数据汇总!$1:$1,0))/100,"") -> 2742.53 | ... AE34: =IFERROR(INDEX(【输出】数据汇总!$A:$AQ,MATCH(纵向时序!$D$30&纵向时序!$D34,【输出】数据汇总!$A:$A,0),MATCH(纵向时序!AE$2,【输出】数据汇总!$1:$1,0))/100,"") -> 3639.82
A35: 沪农 | C35: ⑤ | D35: 关注类贷款余额 | E35: =IFERROR(INDEX(【输出】数据汇总!$A:$AQ,MATCH(纵向时序!$D$30&纵向时序!$D35,【输出】数据汇总!$A:$A,0),MATCH(纵向时序!E$2,【输出】数据汇总!$1:$1,0))/100,"") -> 4060.8 | F35: =IFERROR(INDEX(【输出】数据汇总!$A:$AQ,MATCH(纵向时序!$D$30&纵向时序!$D35,【输出】数据汇总!$A:$A,0),MATCH(纵向时序!F$2,【输出】数据汇总!$1:$1,0))/100,"") -> 4060.8 | G35: =IFERROR(INDEX(【输出】数据汇总!$A:$AQ,MATCH(纵向时序!$D$30&纵向时序!$D35,【输出】数据汇总!$A:$A,0),MATCH(纵向时序!G$2,【输出】数据汇总!$1:$1,0))/100,"") -> 4391.86 | H35: =IFERROR(INDEX(【输出】数据汇总!$A:$AQ,MATCH(纵向时序!$D$30&纵向时序!$D35,【输出】数据汇总!$A:$A,0),MATCH(纵向时序!H$2,【输出】数据汇总!$1:$1,0))/100,"") -> 4391.86 | I35: =IFERROR(INDEX(【输出】数据汇总!$A:$AQ,MATCH(纵向时序!$D$30&纵向时序!$D35,【输出】数据汇总!$A:$A,0),MATCH(纵向时序!I$2,【输出】数据汇总!$1:$1,0))/100,"") -> 4916.09 | J35: =IFERROR(INDEX(【输出】数据汇总!$A:$AQ,MATCH(纵向时序!$D$30&纵向时序!$D35,【输出】数据汇总!$A:$A,0),MATCH(纵向时序!J$2,【输出】数据汇总!$1:$1,0))/100,"") -> 4916.09 | K35: =IFERROR(INDEX(【输出】数据汇总!$A:$AQ,MATCH(纵向时序!$D$30&纵向时序!$D35,【输出】数据汇总!$A:$A,0),MATCH(纵向时序!K$2,【输出】数据汇总!$1:$1,0))/100,"") -> 4946.38 | L35: =IFERROR(INDEX(【输出】数据汇总!$A:$AQ,MATCH(纵向时序!$D$30&纵向时序!$D35,【输出】数据汇总!$A:$A,0),MATCH(纵向时序!L$2,【输出】数据汇总!$1:$1,0))/100,"") -> 4946.38 | ... AE35: =IFERROR(INDEX(【输出】数据汇总!$A:$AQ,MATCH(纵向时序!$D$30&纵向时序!$D35,【输出】数据汇总!$A:$A,0),MATCH(纵向时序!AE$2,【输出】数据汇总!$1:$1,0))/100,"") -> 4907.31
A36: 青农 | C36: ⑦ | D36: 非信贷资产第三阶段额 | E36: =IFERROR(INDEX(【输出】数据汇总!$A:$AQ,MATCH(纵向时序!$D$30&纵向时序!$D36,【输出】数据汇总!$A:$A,0),MATCH(纵向时序!E$2,【输出】数据汇总!$1:$1,0))/100,"") -> 0 | F36: =IFERROR(INDEX(【输出】数据汇总!$A:$AQ,MATCH(纵向时序!$D$30&纵向时序!$D36,【输出】数据汇总!$A:$A,0),MATCH(纵向时序!F$2,【输出】数据汇总!$1:$1,0))/100,"") -> 0 | G36: =IFERROR(INDEX(【输出】数据汇总!$A:$AQ,MATCH(纵向时序!$D$30&纵向时序!$D36,【输出】数据汇总!$A:$A,0),MATCH(纵向时序!G$2,【输出】数据汇总!$1:$1,0))/100,"") -> 0 | H36: =IFERROR(INDEX(【输出】数据汇总!$A:$AQ,MATCH(纵向时序!$D$30&纵向时序!$D36,【输出】数据汇总!$A:$A,0),MATCH(纵向时序!H$2,【输出】数据汇总!$1:$1,0))/100,"") -> 0 | I36: =IFERROR(INDEX(【输出】数据汇总!$A:$AQ,MATCH(纵向时序!$D$30&纵向时序!$D36,【输出】数据汇总!$A:$A,0),MATCH(纵向时序!I$2,【输出】数据汇总!$1:$1,0))/100,"") -> 0 | J36: =IFERROR(INDEX(【输出】数据汇总!$A:$AQ,MATCH(纵向时序!$D$30&纵向时序!$D36,【输出】数据汇总!$A:$A,0),MATCH(纵向时序!J$2,【输出】数据汇总!$1:$1,0))/100,"") -> 0 | K36: =IFERROR(INDEX(【输出】数据汇总!$A:$AQ,MATCH(纵向时序!$D$30&纵向时序!$D36,【输出】数据汇总!$A:$A,0),MATCH(纵向时序!K$2,【输出】数据汇总!$1:$1,0))/100,"") -> 0 | L36: =IFERROR(INDEX(【输出】数据汇总!$A:$AQ,MATCH(纵向时序!$D$30&纵向时序!$D36,【输出】数据汇总!$A:$A,0),MATCH(纵向时序!L$2,【输出】数据汇总!$1:$1,0))/100,"") -> 0 | ... AC36: =IFERROR(INDEX(【输出】数据汇总!$A:$AQ,MATCH(纵向时序!$D$30&纵向时序!$D36,【输出】数据汇总!$A:$A,0),MATCH(纵向时序!AC$2,【输出】数据汇总!$1:$1,0))/100,"") -> 110.86 | AD36: =IFERROR(INDEX(【输出】数据汇总!$A:$AQ,MATCH(纵向时序!$D$30&纵向时序!$D36,【输出】数据汇总!$A:$A,0),MATCH(纵向时序!AD$30,【输出】数据汇总!$1:$1,0))/100,"") -> 110.86 | AE36: =IFERROR(INDEX(【输出】数据汇总!$A:$AQ,MATCH(纵向时序!$D$30&纵向时序!$D36,【输出】数据汇总!$A:$A,0),MATCH(纵向时序!AE$2,【输出】数据汇总!$1:$1,0))/100,"") -> 99.69
A37: 常熟 | C37: ⑥=MAX(②+③，④+⑤) | D37: 广义风险贷款 | E37: =MAX(E32+E33,E34+E35) -> 6141.49 | F37: =MAX(F32+F33,F34+F35) -> 6174.79 | G37: =MAX(G32+G33,G34+G35) -> 6516.59 | H37: =MAX(H32+H33,H34+H35) -> 6651.96 | I37: =MAX(I32+I33,I34+I35) -> 7371.25 | J37: =MAX(J32+J33,J34+J35) -> 7471.37 | K37: =MAX(K32+K33,K34+K35) -> 7553.67 | L37: =MAX(L32+L33,L34+L35) -> 7688.91 | ... AE37: =MAX(AE32+AE33,AE34+AE35) -> 8547.13
A38: 紫金 | C38: ⑧ | D38: 贷款拨备额 | E38: =IFERROR(INDEX(【输出】数据汇总!$A:$AQ,MATCH(纵向时序!$D$30&纵向时序!$D38,【输出】数据汇总!$A:$A,0),MATCH(纵向时序!E$2,【输出】数据汇总!$1:$1,0))/100,"") -> 4525.43 | F38: =IFERROR(INDEX(【输出】数据汇总!$A:$AQ,MATCH(纵向时序!$D$30&纵向时序!$D38,【输出】数据汇总!$A:$A,0),MATCH(纵向时序!F$2,【输出】数据汇总!$1:$1,0))/100,"") -> 4614.4174 | G38: =IFERROR(INDEX(【输出】数据汇总!$A:$AQ,MATCH(纵向时序!$D$30&纵向时序!$D38,【输出】数据汇总!$A:$A,0),MATCH(纵向时序!G$2,【输出】数据汇总!$1:$1,0))/100,"") -> 4821.58 | H38: =IFERROR(INDEX(【输出】数据汇总!$A:$AQ,MATCH(纵向时序!$D$30&纵向时序!$D38,【输出】数据汇总!$A:$A,0),MATCH(纵向时序!H$2,【输出】数据汇总!$1:$1,0))/100,"") -> 5204.3323 | I38: =IFERROR(INDEX(【输出】数据汇总!$A:$AQ,MATCH(纵向时序!$D$30&纵向时序!$D38,【输出】数据汇总!$A:$A,0),MATCH(纵向时序!I$2,【输出】数据汇总!$1:$1,0))/100,"") -> 5463.61 | J38: =IFERROR(INDEX(【输出】数据汇总!$A:$AQ,MATCH(纵向时序!$D$30&纵向时序!$D38,【输出】数据汇总!$A:$A,0),MATCH(纵向时序!J$2,【输出】数据汇总!$1:$1,0))/100,"") -> 5557.9895 | K38: =IFERROR(INDEX(【输出】数据汇总!$A:$AQ,MATCH(纵向时序!$D$30&纵向时序!$D38,【输出】数据汇总!$A:$A,0),MATCH(纵向时序!K$2,【输出】数据汇总!$1:$1,0))/100,"") -> 5560.63 | L38: =IFERROR(INDEX(【输出】数据汇总!$A:$AQ,MATCH(纵向时序!$D$30&纵向时序!$D38,【输出】数据汇总!$A:$A,0),MATCH(纵向时序!L$2,【输出】数据汇总!$1:$1,0))/100,"") -> 5894.794 | ... AC38: =IFERROR(INDEX(【输出】数据汇总!$A:$AQ,MATCH(纵向时序!$D$30&纵向时序!$D38,【输出】数据汇总!$A:$A,0),MATCH(纵向时序!AC$2,【输出】数据汇总!$1:$1,0))/100,"") -> 8721.65 | AD38: =IFERROR(INDEX(【输出】数据汇总!$A:$AQ,MATCH(纵向时序!$D$30&纵向时序!$D38,【输出】数据汇总!$A:$A,0),MATCH(纵向时序!AD$30,【输出】数据汇总!$1:$1,0))/100,"") -> 8590.4664 | AE38: =IFERROR(INDEX(【输出】数据汇总!$A:$AQ,MATCH(纵向时序!$D$30&纵向时序!$D38,【输出】数据汇总!$A:$A,0),MATCH(纵向时序!AE$2,【输出】数据汇总!$1:$1,0))/100,"") -> 8486.12
A39: 无锡 | C39: ⑨=⑧-⑥*100% | D39: 超额贷款拨备额 | E39: =E38-E37*100% -> -1616.06 | F39: =F38-F37*100% -> -1560.3726 | G39: =G38-G37*100% -> -1695.01 | H39: =H38-H37*100% -> -1447.6277 | I39: =I38-I37*100% -> -1907.64 | J39: =J38-J37*100% -> -1913.3805 | K39: =K38-K37*100% -> -1993.04 | L39: =L38-L37*100% -> -1794.116 | ... AE39: =AE38-AE37*100% -> -61.01
A40: 张家港 | C40: ⑦ | D40: 非信贷资产第三阶段额 | E40: =IF(IFERROR(INDEX(【输出】数据汇总!$A:$AQ,MATCH(纵向时序!$D$30&纵向时序!$D40,【输出】数据汇总!$A:$A,0),MATCH(纵向时序!E$2,【输出】数据汇总!$1:$1,0))/100,"")=0,"",IFERROR(INDEX(【输出】数据汇总!$A:$AQ,MATCH(纵向时序!$D$30&纵向时序!$D40,【输出】数据汇总!$A:$A,0),MATCH(纵向时序!E$2,【输出】数据汇总!$1:$1,0))/100,"")) | F40: =IF(IFERROR(INDEX(【输出】数据汇总!$A:$AQ,MATCH(纵向时序!$D$30&纵向时序!$D40,【输出】数据汇总!$A:$A,0),MATCH(纵向时序!F$2,【输出】数据汇总!$1:$1,0))/100,"")=0,"",IFERROR(INDEX(【输出】数据汇总!$A:$AQ,MATCH(纵向时序!$D$30&纵向时序!$D40,【输出】数据汇总!$A:$A,0),MATCH(纵向时序!F$2,【输出】数据汇总!$1:$1,0))/100,"")) | G40: =IF(IFERROR(INDEX(【输出】数据汇总!$A:$AQ,MATCH(纵向时序!$D$30&纵向时序!$D40,【输出】数据汇总!$A:$A,0),MATCH(纵向时序!G$2,【输出】数据汇总!$1:$1,0))/100,"")=0,"",IFERROR(INDEX(【输出】数据汇总!$A:$AQ,MATCH(纵向时序!$D$30&纵向时序!$D40,【输出】数据汇总!$A:$A,0),MATCH(纵向时序!G$2,【输出】数据汇总!$1:$1,0))/100,"")) | H40: =IF(IFERROR(INDEX(【输出】数据汇总!$A:$AQ,MATCH(纵向时序!$D$30&纵向时序!$D40,【输出】数据汇总!$A:$A,0),MATCH(纵向时序!H$2,【输出】数据汇总!$1:$1,0))/100,"")=0,"",IFERROR(INDEX(【输出】数据汇总!$A:$AQ,MATCH(纵向时序!$D$30&纵向时序!$D40,【输出】数据汇总!$A:$A,0),MATCH(纵向时序!H$2,【输出】数据汇总!$1:$1,0))/100,"")) | I40: =IF(IFERROR(INDEX(【输出】数据汇总!$A:$AQ,MATCH(纵向时序!$D$30&纵向时序!$D40,【输出】数据汇总!$A:$A,0),MATCH(纵向时序!I$2,【输出】数据汇总!$1:$1,0))/100,"")=0,"",IFERROR(INDEX(【输出】数据汇总!$A:$AQ,MATCH(纵向时序!$D$30&纵向时序!$D40,【输出】数据汇总!$A:$A,0),MATCH(纵向时序!I$2,【输出】数据汇总!$1:$1,0))/100,"")) | J40: =IF(IFERROR(INDEX(【输出】数据汇总!$A:$AQ,MATCH(纵向时序!$D$30&纵向时序!$D40,【输出】数据汇总!$A:$A,0),MATCH(纵向时序!J$2,【输出】数据汇总!$1:$1,0))/100,"")=0,"",IFERROR(INDEX(【输出】数据汇总!$A:$AQ,MATCH(纵向时序!$D$30&纵向时序!$D40,【输出】数据汇总!$A:$A,0),MATCH(纵向时序!J$2,【输出】数据汇总!$1:$1,0))/100,"")) | K40: =IF(IFERROR(INDEX(【输出】数据汇总!$A:$AQ,MATCH(纵向时序!$D$30&纵向时序!$D40,【输出】数据汇总!$A:$A,0),MATCH(纵向时序!K$2,【输出】数据汇总!$1:$1,0))/100,"")=0,"",IFERROR(INDEX(【输出】数据汇总!$A:$AQ,MATCH(纵向时序!$D$30&纵向时序!$D40,【输出】数据汇总!$A:$A,0),MATCH(纵向时序!K$2,【输出】数据汇总!$1:$1,0))/100,"")) | L40: =IF(IFERROR(INDEX(【输出】数据汇总!$A:$AQ,MATCH(纵向时序!$D$30&纵向时序!$D40,【输出】数据汇总!$A:$A,0),MATCH(纵向时序!L$2,【输出】数据汇总!$1:$1,0))/100,"")=0,"",IFERROR(INDEX(【输出】数据汇总!$A:$AQ,MATCH(纵向时序!$D$30&纵向时序!$D40,【输出】数据汇总!$A:$A,0),MATCH(纵向时序!L$2,【输出】数据汇总!$1:$1,0))/100,"")) | ... AC40: =IF(IFERROR(INDEX(【输出】数据汇总!$A:$AQ,MATCH(纵向时序!$D$30&纵向时序!$D40,【输出】数据汇总!$A:$A,0),MATCH(纵向时序!AC$2,【输出】数据汇总!$1:$1,0))/100,"")=0,"",IFERROR(INDEX(【输出】数据汇总!$A:$AQ,MATCH(纵向时序!$D$30&纵向时序!$D40,【输出】数据汇总!$A:$A,0),MATCH(纵向时序!AC$2,【输出】数据汇总!$1:$1,0))/100,"")) -> 110.86 | AD40: =IF(IFERROR(INDEX(【输出】数据汇总!$A:$AQ,MATCH(纵向时序!$D$30&纵向时序!$D40,【输出】数据汇总!$A:$A,0),MATCH(纵向时序!AD$30,【输出】数据汇总!$1:$1,0))/100,"")=0,"",IFERROR(INDEX(【输出】数据汇总!$A:$AQ,MATCH(纵向时序!$D$30&纵向时序!$D40,【输出】数据汇总!$A:$A,0),MATCH(纵向时序!AD$30,【输出】数据汇总!$1:$1,0))/100,"")) -> 110.86 | AE40: =IF(IFERROR(INDEX(【输出】数据汇总!$A:$AQ,MATCH(纵向时序!$D$30&纵向时序!$D40,【输出】数据汇总!$A:$A,0),MATCH(纵向时序!AE$2,【输出】数据汇总!$1:$1,0))/100,"")=0,"",IFERROR(INDEX(【输出】数据汇总!$A:$AQ,MATCH(纵向时序!$D$30&纵向时序!$D40,【输出】数据汇总!$A:$A,0),MATCH(纵向时序!AE$2,【输出】数据汇总!$1:$1,0))/100,"")) -> 99.69
A41: 苏农 | C41: ⑩ | D41: 非信贷拨备额 | E41: =IF(IFERROR(INDEX(【输出】数据汇总!$A:$AQ,MATCH(纵向时序!$D$30&纵向时序!$D41,【输出】数据汇总!$A:$A,0),MATCH(纵向时序!E$2,【输出】数据汇总!$1:$1,0))/100,"")=0,"",IFERROR(INDEX(【输出】数据汇总!$A:$AQ,MATCH(纵向时序!$D$30&纵向时序!$D41,【输出】数据汇总!$A:$A,0),MATCH(纵向时序!E$2,【输出】数据汇总!$1:$1,0))/100,"")) -> 455.51 | F41: =IF(IFERROR(INDEX(【输出】数据汇总!$A:$AQ,MATCH(纵向时序!$D$30&纵向时序!$D41,【输出】数据汇总!$A:$A,0),MATCH(纵向时序!F$2,【输出】数据汇总!$1:$1,0))/100,"")=0,"",IFERROR(INDEX(【输出】数据汇总!$A:$AQ,MATCH(纵向时序!$D$30&纵向时序!$D41,【输出】数据汇总!$A:$A,0),MATCH(纵向时序!F$2,【输出】数据汇总!$1:$1,0))/100,"")) -> 455.51 | G41: =IF(IFERROR(INDEX(【输出】数据汇总!$A:$AQ,MATCH(纵向时序!$D$30&纵向时序!$D41,【输出】数据汇总!$A:$A,0),MATCH(纵向时序!G$2,【输出】数据汇总!$1:$1,0))/100,"")=0,"",IFERROR(INDEX(【输出】数据汇总!$A:$AQ,MATCH(纵向时序!$D$30&纵向时序!$D41,【输出】数据汇总!$A:$A,0),MATCH(纵向时序!G$2,【输出】数据汇总!$1:$1,0))/100,"")) -> 540.82 | H41: =IF(IFERROR(INDEX(【输出】数据汇总!$A:$AQ,MATCH(纵向时序!$D$30&纵向时序!$D41,【输出】数据汇总!$A:$A,0),MATCH(纵向时序!H$2,【输出】数据汇总!$1:$1,0))/100,"")=0,"",IFERROR(INDEX(【输出】数据汇总!$A:$AQ,MATCH(纵向时序!$D$30&纵向时序!$D41,【输出】数据汇总!$A:$A,0),MATCH(纵向时序!H$2,【输出】数据汇总!$1:$1,0))/100,"")) -> 540.82 | I41: =IF(IFERROR(INDEX(【输出】数据汇总!$A:$AQ,MATCH(纵向时序!$D$30&纵向时序!$D41,【输出】数据汇总!$A:$A,0),MATCH(纵向时序!I$2,【输出】数据汇总!$1:$1,0))/100,"")=0,"",IFERROR(INDEX(【输出】数据汇总!$A:$AQ,MATCH(纵向时序!$D$30&纵向时序!$D41,【输出】数据汇总!$A:$A,0),MATCH(纵向时序!I$2,【输出】数据汇总!$1:$1,0))/100,"")) -> 588.51 | J41: =IF(IFERROR(INDEX(【输出】数据汇总!$A:$AQ,MATCH(纵向时序!$D$30&纵向时序!$D41,【输出】数据汇总!$A:$A,0),MATCH(纵向时序!J$2,【输出】数据汇总!$1:$1,0))/100,"")=0,"",IFERROR(INDEX(【输出】数据汇总!$A:$AQ,MATCH(纵向时序!$D$30&纵向时序!$D41,【输出】数据汇总!$A:$A,0),MATCH(纵向时序!J$2,【输出】数据汇总!$1:$1,0))/100,"")) -> 588.51 | K41: =IF(IFERROR(INDEX(【输出】数据汇总!$A:$AQ,MATCH(纵向时序!$D$30&纵向时序!$D41,【输出】数据汇总!$A:$A,0),MATCH(纵向时序!K$2,【输出】数据汇总!$1:$1,0))/100,"")=0,"",IFERROR(INDEX(【输出】数据汇总!$A:$AQ,MATCH(纵向时序!$D$30&纵向时序!$D41,【输出】数据汇总!$A:$A,0),MATCH(纵向时序!K$2,【输出】数据汇总!$1:$1,0))/100,"")) -> 593.03 | L41: =IF(IFERROR(INDEX(【输出】数据汇总!$A:$AQ,MATCH(纵向时序!$D$30&纵向时序!$D41,【输出】数据汇总!$A:$A,0),MATCH(纵向时序!L$2,【输出】数据汇总!$1:$1,0))/100,"")=0,"",IFERROR(INDEX(【输出】数据汇总!$A:$AQ,MATCH(纵向时序!$D$30&纵向时序!$D41,【输出】数据汇总!$A:$A,0),MATCH(纵向时序!L$2,【输出】数据汇总!$1:$1,0))/100,"")) -> 593.03 | ... AC41: =IF(IFERROR(INDEX(【输出】数据汇总!$A:$AQ,MATCH(纵向时序!$D$30&纵向时序!$D41,【输出】数据汇总!$A:$A,0),MATCH(纵向时序!AC$2,【输出】数据汇总!$1:$1,0))/100,"")=0,"",IFERROR(INDEX(【输出】数据汇总!$A:$AQ,MATCH(纵向时序!$D$30&纵向时序!$D41,【输出】数据汇总!$A:$A,0),MATCH(纵向时序!AC$2,【输出】数据汇总!$1:$1,0))/100,"")) -> 421.92 | AD41: =IF(IFERROR(INDEX(【输出】数据汇总!$A:$AQ,MATCH(纵向时序!$D$30&纵向时序!$D41,【输出】数据汇总!$A:$A,0),MATCH(纵向时序!AD$30,【输出】数据汇总!$1:$1,0))/100,"")=0,"",IFERROR(INDEX(【输出】数据汇总!$A:$AQ,MATCH(纵向时序!$D$30&纵向时序!$D41,【输出】数据汇总!$A:$A,0),MATCH(纵向时序!AD$30,【输出】数据汇总!$1:$1,0))/100,"")) -> 421.92 | AE41: =IF(IFERROR(INDEX(【输出】数据汇总!$A:$AQ,MATCH(纵向时序!$D$30&纵向时序!$D41,【输出】数据汇总!$A:$A,0),MATCH(纵向时序!AE$2,【输出】数据汇总!$1:$1,0))/100,"")=0,"",IFERROR(INDEX(【输出】数据汇总!$A:$AQ,MATCH(纵向时序!$D$30&纵向时序!$D41,【输出】数据汇总!$A:$A,0),MATCH(纵向时序!AE$2,【输出】数据汇总!$1:$1,0))/100,"")) -> 336.86
A42: 江阴 | C42: ⑪=⑩-⑦*100% | D42: 超额非信贷拨备 | E42: =IF(E40="",E41-0,E41-E40*100%) -> 455.51 | F42: =IF(F40="",F41-0,F41-F40*100%) -> 455.51 | G42: =IF(G40="",G41-0,G41-G40*100%) -> 540.82 | H42: =IF(H40="",H41-0,H41-H40*100%) -> 540.82 | I42: =IF(I40="",I41-0,I41-I40*100%) -> 588.51 | J42: =IF(J40="",J41-0,J41-J40*100%) -> 588.51 | K42: =IF(K40="",K41-0,K41-K40*100%) -> 593.03 | L42: =IF(L40="",L41-0,L41-L40*100%) -> 593.03 | ... AE42: =IF(AE40="",AE41-0,AE41-AE40*100%) -> 237.17
A43: 瑞丰 | C43: ⑪+⑨ | D43: 超额拨备额 | E43: =E39+E42 -> -1160.55 | F43: =F39+F42 -> -1104.8626 | G43: =G39+G42 -> -1154.19 | H43: =H39+H42 -> -906.80773 | I43: =I39+I42 -> -1319.13 | J43: =J39+J42 -> -1324.8705 | K43: =K39+K42 -> -1400.01 | L43: =L39+L42 -> -1201.086 | ... AE43: =AE39+AE42 -> 176.16
D44: 归母净利润(TTM) | E44: =IF(IFERROR(INDEX(【输出】数据汇总!$A:$AQ,MATCH(纵向时序!$D$30&纵向时序!$D44,【输出】数据汇总!$A:$A,0),MATCH(纵向时序!E$2,【输出】数据汇总!$1:$1,0))/100,"")=0,"",IFERROR(INDEX(【输出】数据汇总!$A:$AQ,MATCH(纵向时序!$D$30&纵向时序!$D44,【输出】数据汇总!$A:$A,0),MATCH(纵向时序!E$2,【输出】数据汇总!$1:$1,0))/100,"")) -> 2618.18 | F44: =IF(IFERROR(INDEX(【输出】数据汇总!$A:$AQ,MATCH(纵向时序!$D$30&纵向时序!$D44,【输出】数据汇总!$A:$A,0),MATCH(纵向时序!F$2,【输出】数据汇总!$1:$1,0))/100,"")=0,"",IFERROR(INDEX(【输出】数据汇总!$A:$AQ,MATCH(纵向时序!$D$30&纵向时序!$D44,【输出】数据汇总!$A:$A,0),MATCH(纵向时序!F$2,【输出】数据汇总!$1:$1,0))/100,"")) -> 2658.91 | G44: =IF(IFERROR(INDEX(【输出】数据汇总!$A:$AQ,MATCH(纵向时序!$D$30&纵向时序!$D44,【输出】数据汇总!$A:$A,0),MATCH(纵向时序!G$2,【输出】数据汇总!$1:$1,0))/100,"")=0,"",IFERROR(INDEX(【输出】数据汇总!$A:$AQ,MATCH(纵向时序!$D$30&纵向时序!$D44,【输出】数据汇总!$A:$A,0),MATCH(纵向时序!G$2,【输出】数据汇总!$1:$1,0))/100,"")) -> 2667.33 | H44: =IF(IFERROR(INDEX(【输出】数据汇总!$A:$AQ,MATCH(纵向时序!$D$30&纵向时序!$D44,【输出】数据汇总!$A:$A,0),MATCH(纵向时序!H$2,【输出】数据汇总!$1:$1,0))/100,"")=0,"",IFERROR(INDEX(【输出】数据汇总!$A:$AQ,MATCH(纵向时序!$D$30&纵向时序!$D44,【输出】数据汇总!$A:$A,0),MATCH(纵向时序!H$2,【输出】数据汇总!$1:$1,0))/100,"")) -> 2706.72 | I44: =IF(IFERROR(INDEX(【输出】数据汇总!$A:$AQ,MATCH(纵向时序!$D$30&纵向时序!$D44,【输出】数据汇总!$A:$A,0),MATCH(纵向时序!I$2,【输出】数据汇总!$1:$1,0))/100,"")=0,"",IFERROR(INDEX(【输出】数据汇总!$A:$AQ,MATCH(纵向时序!$D$30&纵向时序!$D44,【输出】数据汇总!$A:$A,0),MATCH(纵向时序!I$2,【输出】数据汇总!$1:$1,0))/100,"")) -> 2501.69 | J44: =IF(IFERROR(INDEX(【输出】数据汇总!$A:$AQ,MATCH(纵向时序!$D$30&纵向时序!$D44,【输出】数据汇总!$A:$A,0),MATCH(纵向时序!J$2,【输出】数据汇总!$1:$1,0))/100,"")=0,"",IFERROR(INDEX(【输出】数据汇总!$A:$AQ,MATCH(纵向时序!$D$30&纵向时序!$D44,【输出】数据汇总!$A:$A,0),MATCH(纵向时序!J$2,【输出】数据汇总!$1:$1,0))/100,"")) -> 2472.21 | K44: =IF(IFERROR(INDEX(【输出】数据汇总!$A:$AQ,MATCH(纵向时序!$D$30&纵向时序!$D44,【输出】数据汇总!$A:$A,0),MATCH(纵向时序!K$2,【输出】数据汇总!$1:$1,0))/100,"")=0,"",IFERROR(INDEX(【输出】数据汇总!$A:$AQ,MATCH(纵向时序!$D$30&纵向时序!$D44,【输出】数据汇总!$A:$A,0),MATCH(纵向时序!K$2,【输出】数据汇总!$1:$1,0))/100,"")) -> 2710.5 | L44: =IF(IFERROR(INDEX(【输出】数据汇总!$A:$AQ,MATCH(纵向时序!$D$30&纵向时序!$D44,【输出】数据汇总!$A:$A,0),MATCH(纵向时序!L$2,【输出】数据汇总!$1:$1,0))/100,"")=0,"",IFERROR(INDEX(【输出】数据汇总!$A:$AQ,MATCH(纵向时序!$D$30&纵向时序!$D44,【输出】数据汇总!$A:$A,0),MATCH(纵向时序!L$2,【输出】数据汇总!$1:$1,0))/100,"")) -> 2733.1 | ... AC44: =IF(IFERROR(INDEX(【输出】数据汇总!$A:$AQ,MATCH(纵向时序!$D$30&纵向时序!$D44,【输出】数据汇总!$A:$A,0),MATCH(纵向时序!AC$2,【输出】数据汇总!$1:$1,0))/100,"")=0,"",IFERROR(INDEX(【输出】数据汇总!$A:$AQ,MATCH(纵向时序!$D$30&纵向时序!$D44,【输出】数据汇总!$A:$A,0),MATCH(纵向时序!AC$2,【输出】数据汇总!$1:$1,0))/100,"")) -> 3333.27 | AD44: =IF(IFERROR(INDEX(【输出】数据汇总!$A:$AQ,MATCH(纵向时序!$D$30&纵向时序!$D44,【输出】数据汇总!$A:$A,0),MATCH(纵向时序!AD$30,【输出】数据汇总!$1:$1,0))/100,"")=0,"",IFERROR(INDEX(【输出】数据汇总!$A:$AQ,MATCH(纵向时序!$D$30&纵向时序!$D44,【输出】数据汇总!$A:$A,0),MATCH(纵向时序!AD$30,【输出】数据汇总!$1:$1,0))/100,"")) -> 3371.61 | AE44: =IF(IFERROR(INDEX(【输出】数据汇总!$A:$AQ,MATCH(纵向时序!$D$30&纵向时序!$D44,【输出】数据汇总!$A:$A,0),MATCH(纵向时序!AE$2,【输出】数据汇总!$1:$1,0))/100,"")=0,"",IFERROR(INDEX(【输出】数据汇总!$A:$AQ,MATCH(纵向时序!$D$30&纵向时序!$D44,【输出】数据汇总!$A:$A,0),MATCH(纵向时序!AE$2,【输出】数据汇总!$1:$1,0))/100,"")) -> 3389.06
D45: 归母净资产 | E45: =IF(IFERROR(INDEX(【输出】数据汇总!$A:$AQ,MATCH(纵向时序!$D$30&纵向时序!$D45,【输出】数据汇总!$A:$A,0),MATCH(纵向时序!E$2,【输出】数据汇总!$1:$1,0))/100,"")=0,"",IFERROR(INDEX(【输出】数据汇总!$A:$AQ,MATCH(纵向时序!$D$30&纵向时序!$D45,【输出】数据汇总!$A:$A,0),MATCH(纵向时序!E$2,【输出】数据汇总!$1:$1,0))/100,"")) -> 20557.56 | F45: =IF(IFERROR(INDEX(【输出】数据汇总!$A:$AQ,MATCH(纵向时序!$D$30&纵向时序!$D45,【输出】数据汇总!$A:$A,0),MATCH(纵向时序!F$2,【输出】数据汇总!$1:$1,0))/100,"")=0,"",IFERROR(INDEX(【输出】数据汇总!$A:$AQ,MATCH(纵向时序!$D$30&纵向时序!$D45,【输出】数据汇总!$A:$A,0),MATCH(纵向时序!F$2,【输出】数据汇总!$1:$1,0))/100,"")) -> 21360.34 | G45: =IF(IFERROR(INDEX(【输出】数据汇总!$A:$AQ,MATCH(纵向时序!$D$30&纵向时序!$D45,【输出】数据汇总!$A:$A,0),MATCH(纵向时序!G$2,【输出】数据汇总!$1:$1,0))/100,"")=0,"",IFERROR(INDEX(【输出】数据汇总!$A:$AQ,MATCH(纵向时序!$D$30&纵向时序!$D45,【输出】数据汇总!$A:$A,0),MATCH(纵向时序!G$2,【输出】数据汇总!$1:$1,0))/100,"")) -> 22162.57 | H45: =IF(IFERROR(INDEX(【输出】数据汇总!$A:$AQ,MATCH(纵向时序!$D$30&纵向时序!$D45,【输出】数据汇总!$A:$A,0),MATCH(纵向时序!H$2,【输出】数据汇总!$1:$1,0))/100,"")=0,"",IFERROR(INDEX(【输出】数据汇总!$A:$AQ,MATCH(纵向时序!$D$30&纵向时序!$D45,【输出】数据汇总!$A:$A,0),MATCH(纵向时序!H$2,【输出】数据汇总!$1:$1,0))/100,"")) -> 23160.47 | I45: =IF(IFERROR(INDEX(【输出】数据汇总!$A:$AQ,MATCH(纵向时序!$D$30&纵向时序!$D45,【输出】数据汇总!$A:$A,0),MATCH(纵向时序!I$2,【输出】数据汇总!$1:$1,0))/100,"")=0,"",IFERROR(INDEX(【输出】数据汇总!$A:$AQ,MATCH(纵向时序!$D$30&纵向时序!$D45,【输出】数据汇总!$A:$A,0),MATCH(纵向时序!I$2,【输出】数据汇总!$1:$1,0))/100,"")) -> 22810.66 | J45: =IF(IFERROR(INDEX(【输出】数据汇总!$A:$AQ,MATCH(纵向时序!$D$30&纵向时序!$D45,【输出】数据汇总!$A:$A,0),MATCH(纵向时序!J$2,【输出】数据汇总!$1:$1,0))/100,"")=0,"",IFERROR(INDEX(【输出】数据汇总!$A:$AQ,MATCH(纵向时序!$D$30&纵向时序!$D45,【输出】数据汇总!$A:$A,0),MATCH(纵向时序!J$2,【输出】数据汇总!$1:$1,0))/100,"")) -> 23223.19 | K45: =IF(IFERROR(INDEX(【输出】数据汇总!$A:$AQ,MATCH(纵向时序!$D$30&纵向时序!$D45,【输出】数据汇总!$A:$A,0),MATCH(纵向时序!K$2,【输出】数据汇总!$1:$1,0))/100,"")=0,"",IFERROR(INDEX(【输出】数据汇总!$A:$AQ,MATCH(纵向时序!$D$30&纵向时序!$D45,【输出】数据汇总!$A:$A,0),MATCH(纵向时序!K$2,【输出】数据汇总!$1:$1,0))/100,"")) -> 23648.08 | L45: =IF(IFERROR(INDEX(【输出】数据汇总!$A:$AQ,MATCH(纵向时序!$D$30&纵向时序!$D45,【输出】数据汇总!$A:$A,0),MATCH(纵向时序!L$2,【输出】数据汇总!$1:$1,0))/100,"")=0,"",IFERROR(INDEX(【输出】数据汇总!$A:$AQ,MATCH(纵向时序!$D$30&纵向时序!$D45,【输出】数据汇总!$A:$A,0),MATCH(纵向时序!L$2,【输出】数据汇总!$1:$1,0))/100,"")) -> 24447.74 | ... AC45: =IF(IFERROR(INDEX(【输出】数据汇总!$A:$AQ,MATCH(纵向时序!$D$30&纵向时序!$D45,【输出】数据汇总!$A:$A,0),MATCH(纵向时序!AC$2,【输出】数据汇总!$1:$1,0))/100,"")=0,"",IFERROR(INDEX(【输出】数据汇总!$A:$AQ,MATCH(纵向时序!$D$30&纵向时序!$D45,【输出】数据汇总!$A:$A,0),MATCH(纵向时序!AC$2,【输出】数据汇总!$1:$1,0))/100,"")) -> 35632.98 | AD45: =IF(IFERROR(INDEX(【输出】数据汇总!$A:$AQ,MATCH(纵向时序!$D$30&纵向时序!$D45,【输出】数据汇总!$A:$A,0),MATCH(纵向时序!AD$30,【输出】数据汇总!$1:$1,0))/100,"")=0,"",IFERROR(INDEX(【输出】数据汇总!$A:$AQ,MATCH(纵向时序!$D$30&纵向时序!$D45,【输出】数据汇总!$A:$A,0),MATCH(纵向时序!AD$30,【输出】数据汇总!$1:$1,0))/100,"")) -> 36333.87 | AE45: =IF(IFERROR(INDEX(【输出】数据汇总!$A:$AQ,MATCH(纵向时序!$D$30&纵向时序!$D45,【输出】数据汇总!$A:$A,0),MATCH(纵向时序!AE$2,【输出】数据汇总!$1:$1,0))/100,"")=0,"",IFERROR(INDEX(【输出】数据汇总!$A:$AQ,MATCH(纵向时序!$D$30&纵向时序!$D45,【输出】数据汇总!$A:$A,0),MATCH(纵向时序!AE$2,【输出】数据汇总!$1:$1,0))/100,"")) -> 36634.11
D46: 逾期率 | E46: =IFERROR(INDEX(【输出】数据汇总!$A:$AQ,MATCH(纵向时序!$D$30&纵向时序!$D46,【输出】数据汇总!$A:$A,0),MATCH(纵向时序!E$2,【输出】数据汇总!$1:$1,0)),"") -> 0.014327054 | F46: =IFERROR(INDEX(【输出】数据汇总!$A:$AQ,MATCH(纵向时序!$D$30&纵向时序!$D46,【输出】数据汇总!$A:$A,0),MATCH(纵向时序!F$2,【输出】数据汇总!$1:$1,0)),"") -> 0.014007554 | G46: =IFERROR(INDEX(【输出】数据汇总!$A:$AQ,MATCH(纵向时序!$D$30&纵向时序!$D46,【输出】数据汇总!$A:$A,0),MATCH(纵向时序!G$2,【输出】数据汇总!$1:$1,0)),"") -> 0.011534833 | H46: =IFERROR(INDEX(【输出】数据汇总!$A:$AQ,MATCH(纵向时序!$D$30&纵向时序!$D46,【输出】数据汇总!$A:$A,0),MATCH(纵向时序!H$2,【输出】数据汇总!$1:$1,0)),"") -> 0.01084435 | I46: =IFERROR(INDEX(【输出】数据汇总!$A:$AQ,MATCH(纵向时序!$D$30&纵向时序!$D46,【输出】数据汇总!$A:$A,0),MATCH(纵向时序!I$2,【输出】数据汇总!$1:$1,0)),"") -> 0.011356468 | J46: =IFERROR(INDEX(【输出】数据汇总!$A:$AQ,MATCH(纵向时序!$D$30&纵向时序!$D46,【输出】数据汇总!$A:$A,0),MATCH(纵向时序!J$2,【输出】数据汇总!$1:$1,0)),"") -> 0.011199371 | K46: =IFERROR(INDEX(【输出】数据汇总!$A:$AQ,MATCH(纵向时序!$D$30&纵向时序!$D46,【输出】数据汇总!$A:$A,0),MATCH(纵向时序!K$2,【输出】数据汇总!$1:$1,0)),"") -> 0.010881734 | L46: =IFERROR(INDEX(【输出】数据汇总!$A:$AQ,MATCH(纵向时序!$D$30&纵向时序!$D46,【输出】数据汇总!$A:$A,0),MATCH(纵向时序!L$2,【输出】数据汇总!$1:$1,0)),"") -> 0.010337855 | ... AC46: =IFERROR(INDEX(【输出】数据汇总!$A:$AQ,MATCH(纵向时序!$D$30&纵向时序!$D46,【输出】数据汇总!$A:$A,0),MATCH(纵向时序!AC$2,【输出】数据汇总!$1:$1,0)),"") -> 0.013249622 | AD46: =IFERROR(INDEX(【输出】数据汇总!$A:$AQ,MATCH(纵向时序!$D$30&纵向时序!$D46,【输出】数据汇总!$A:$A,0),MATCH(纵向时序!AD$30,【输出】数据汇总!$1:$1,0)),"") -> 0.013137369 | AE46: =IFERROR(INDEX(【输出】数据汇总!$A:$AQ,MATCH(纵向时序!$D$30&纵向时序!$D46,【输出】数据汇总!$A:$A,0),MATCH(纵向时序!AE$2,【输出】数据汇总!$1:$1,0)),"") -> 0.013243664
D47: 重组率 | E47: =IFERROR(INDEX(【输出】数据汇总!$A:$AQ,MATCH(纵向时序!$D$30&纵向时序!$D47,【输出】数据汇总!$A:$A,0),MATCH(纵向时序!E$2,【输出】数据汇总!$1:$1,0)),"") -> 0.0003341623 | F47: =IFERROR(INDEX(【输出】数据汇总!$A:$AQ,MATCH(纵向时序!$D$30&纵向时序!$D47,【输出】数据汇总!$A:$A,0),MATCH(纵向时序!F$2,【输出】数据汇总!$1:$1,0)),"") -> 0.00032671034 | G47: =IFERROR(INDEX(【输出】数据汇总!$A:$AQ,MATCH(纵向时序!$D$30&纵向时序!$D47,【输出】数据汇总!$A:$A,0),MATCH(纵向时序!G$2,【输出】数据汇总!$1:$1,0)),"") -> 0.00040232438 | H47: =IFERROR(INDEX(【输出】数据汇总!$A:$AQ,MATCH(纵向时序!$D$30&纵向时序!$D47,【输出】数据汇总!$A:$A,0),MATCH(纵向时序!H$2,【输出】数据汇总!$1:$1,0)),"") -> 0.00037824095 | I47: =IFERROR(INDEX(【输出】数据汇总!$A:$AQ,MATCH(纵向时序!$D$30&纵向时序!$D47,【输出】数据汇总!$A:$A,0),MATCH(纵向时序!I$2,【输出】数据汇总!$1:$1,0)),"") -> 0.00043632375 | J47: =IFERROR(INDEX(【输出】数据汇总!$A:$AQ,MATCH(纵向时序!$D$30&纵向时序!$D47,【输出】数据汇总!$A:$A,0),MATCH(纵向时序!J$2,【输出】数据汇总!$1:$1,0)),"") -> 0.00043028798 | K47: =IFERROR(INDEX(【输出】数据汇总!$A:$AQ,MATCH(纵向时序!$D$30&纵向时序!$D47,【输出】数据汇总!$A:$A,0),MATCH(纵向时序!K$2,【输出】数据汇总!$1:$1,0)),"") -> 0.0006025403 | L47: =IFERROR(INDEX(【输出】数据汇总!$A:$AQ,MATCH(纵向时序!$D$30&纵向时序!$D47,【输出】数据汇总!$A:$A,0),MATCH(纵向时序!L$2,【输出】数据汇总!$1:$1,0)),"") -> 0.00057242475 | ... AC47: =IFERROR(INDEX(【输出】数据汇总!$A:$AQ,MATCH(纵向时序!$D$30&纵向时序!$D47,【输出】数据汇总!$A:$A,0),MATCH(纵向时序!AC$2,【输出】数据汇总!$1:$1,0)),"") -> 0.0043732054 | AD47: =IFERROR(INDEX(【输出】数据汇总!$A:$AQ,MATCH(纵向时序!$D$30&纵向时序!$D47,【输出】数据汇总!$A:$A,0),MATCH(纵向时序!AD$30,【输出】数据汇总!$1:$1,0)),"") -> 0.0043361549 | AE47: =IFERROR(INDEX(【输出】数据汇总!$A:$AQ,MATCH(纵向时序!$D$30&纵向时序!$D47,【输出】数据汇总!$A:$A,0),MATCH(纵向时序!AE$2,【输出】数据汇总!$1:$1,0)),"") -> 0.004550311
D48: 不良贷款率 | E48: =IFERROR(INDEX(【输出】数据汇总!$A:$AQ,MATCH(纵向时序!$D$30&纵向时序!$D48,【输出】数据汇总!$A:$A,0),MATCH(纵向时序!E$2,【输出】数据汇总!$1:$1,0)),"") -> 0.0143 | F48: =IFERROR(INDEX(【输出】数据汇总!$A:$AQ,MATCH(纵向时序!$D$30&纵向时序!$D48,【输出】数据汇总!$A:$A,0),MATCH(纵向时序!F$2,【输出】数据汇总!$1:$1,0)),"") -> 0.0143 | G48: =IFERROR(INDEX(【输出】数据汇总!$A:$AQ,MATCH(纵向时序!$D$30&纵向时序!$D48,【输出】数据汇总!$A:$A,0),MATCH(纵向时序!G$2,【输出】数据汇总!$1:$1,0)),"") -> 0.0142 | H48: =IFERROR(INDEX(【输出】数据汇总!$A:$AQ,MATCH(纵向时序!$D$30&纵向时序!$D48,【输出】数据汇总!$A:$A,0),MATCH(纵向时序!H$2,【输出】数据汇总!$1:$1,0)),"") -> 0.0142 | I48: =IFERROR(INDEX(【输出】数据汇总!$A:$AQ,MATCH(纵向时序!$D$30&纵向时序!$D48,【输出】数据汇总!$A:$A,0),MATCH(纵向时序!I$2,【输出】数据汇总!$1:$1,0)),"") -> 0.0149 | J48: =IFERROR(INDEX(【输出】数据汇总!$A:$AQ,MATCH(纵向时序!$D$30&纵向时序!$D48,【输出】数据汇总!$A:$A,0),MATCH(纵向时序!J$2,【输出】数据汇总!$1:$1,0)),"") -> 0.0153 | K48: =IFERROR(INDEX(【输出】数据汇总!$A:$AQ,MATCH(纵向时序!$D$30&纵向时序!$D48,【输出】数据汇总!$A:$A,0),MATCH(纵向时序!K$2,【输出】数据汇总!$1:$1,0)),"") -> 0.0156 | L48: =IFERROR(INDEX(【输出】数据汇总!$A:$AQ,MATCH(纵向时序!$D$30&纵向时序!$D48,【输出】数据汇总!$A:$A,0),MATCH(纵向时序!L$2,【输出】数据汇总!$1:$1,0)),"") -> 0.0156 | ... AC48: =IFERROR(INDEX(【输出】数据汇总!$A:$AQ,MATCH(纵向时序!$D$30&纵向时序!$D48,【输出】数据汇总!$A:$A,0),MATCH(纵向时序!AC$2,【输出】数据汇总!$1:$1,0)),"") -> 0.0133 | AD48: =IFERROR(INDEX(【输出】数据汇总!$A:$AQ,MATCH(纵向时序!$D$30&纵向时序!$D48,【输出】数据汇总!$A:$A,0),MATCH(纵向时序!AD$30,【输出】数据汇总!$1:$1,0)),"") -> 0.0132 | AE48: =IFERROR(INDEX(【输出】数据汇总!$A:$AQ,MATCH(纵向时序!$D$30&纵向时序!$D48,【输出】数据汇总!$A:$A,0),MATCH(纵向时序!AE$2,【输出】数据汇总!$1:$1,0)),"") -> 0.0131
D49: 关注贷款率 | E49: =IFERROR(INDEX(【输出】数据汇总!$A:$AQ,MATCH(纵向时序!$D$30&纵向时序!$D49,【输出】数据汇总!$A:$A,0),MATCH(纵向时序!E$2,【输出】数据汇总!$1:$1,0)),"") -> 0.02800178 | F49: =IFERROR(INDEX(【输出】数据汇总!$A:$AQ,MATCH(纵向时序!$D$30&纵向时序!$D49,【输出】数据汇总!$A:$A,0),MATCH(纵向时序!F$2,【输出】数据汇总!$1:$1,0)),"") -> 0.027377328 | G49: =IFERROR(INDEX(【输出】数据汇总!$A:$AQ,MATCH(纵向时序!$D$30&纵向时序!$D49,【输出】数据汇总!$A:$A,0),MATCH(纵向时序!G$2,【输出】数据汇总!$1:$1,0)),"") -> 0.029302692 | H49: =IFERROR(INDEX(【输出】数据汇总!$A:$AQ,MATCH(纵向时序!$D$30&纵向时序!$D49,【输出】数据汇总!$A:$A,0),MATCH(纵向时序!H$2,【输出】数据汇总!$1:$1,0)),"") -> 0.027548612 | I49: =IFERROR(INDEX(【输出】数据汇总!$A:$AQ,MATCH(纵向时序!$D$30&纵向时序!$D49,【输出】数据汇总!$A:$A,0),MATCH(纵向时序!I$2,【输出】数据汇总!$1:$1,0)),"") -> 0.029920587 | J49: =IFERROR(INDEX(【输出】数据汇总!$A:$AQ,MATCH(纵向时序!$D$30&纵向时序!$D49,【输出】数据汇总!$A:$A,0),MATCH(纵向时序!J$2,【输出】数据汇总!$1:$1,0)),"") -> 0.029506687 | K49: =IFERROR(INDEX(【输出】数据汇总!$A:$AQ,MATCH(纵向时序!$D$30&纵向时序!$D49,【输出】数据汇总!$A:$A,0),MATCH(纵向时序!K$2,【输出】数据汇总!$1:$1,0)),"") -> 0.02953809 | L49: =IFERROR(INDEX(【输出】数据汇总!$A:$AQ,MATCH(纵向时序!$D$30&纵向时序!$D49,【输出】数据汇总!$A:$A,0),MATCH(纵向时序!L$2,【输出】数据汇总!$1:$1,0)),"") -> 0.028061748 | ... AC49: =IFERROR(INDEX(【输出】数据汇总!$A:$AQ,MATCH(纵向时序!$D$30&纵向时序!$D49,【输出】数据汇总!$A:$A,0),MATCH(纵向时序!AC$2,【输出】数据汇总!$1:$1,0)),"") -> 0.018098436 | AD49: =IFERROR(INDEX(【输出】数据汇总!$A:$AQ,MATCH(纵向时序!$D$30&纵向时序!$D49,【输出】数据汇总!$A:$A,0),MATCH(纵向时序!AD$30,【输出】数据汇总!$1:$1,0)),"") -> 0.017945103 | AE49: =IFERROR(INDEX(【输出】数据汇总!$A:$AQ,MATCH(纵向时序!$D$30&纵向时序!$D49,【输出】数据汇总!$A:$A,0),MATCH(纵向时序!AE$2,【输出】数据汇总!$1:$1,0)),"") -> 0.017669465
D50: 逾期+重组率 | E50: =IFERROR(E46+E47,"") -> 0.014661216 | F50: =IFERROR(F46+F47,"") -> 0.014334264 | G50: =IFERROR(G46+G47,"") -> 0.011937158 | H50: =IFERROR(H46+H47,"") -> 0.011222591 | I50: =IFERROR(I46+I47,"") -> 0.011792792 | J50: =IFERROR(J46+J47,"") -> 0.011629659 | K50: =IFERROR(K46+K47,"") -> 0.011484275 | L50: =IFERROR(L46+L47,"") -> 0.01091028 | ... AE50: =IFERROR(AE46+AE47,"") -> 0.017793975
D51: 不良+关注率 | E51: =IFERROR(E48+E49,"") -> 0.04230178 | F51: =IFERROR(F48+F49,"") -> 0.041677328 | G51: =IFERROR(G48+G49,"") -> 0.043502692 | H51: =IFERROR(H48+H49,"") -> 0.041748612 | I51: =IFERROR(I48+I49,"") -> 0.044820587 | J51: =IFERROR(J48+J49,"") -> 0.044806687 | K51: =IFERROR(K48+K49,"") -> 0.04513809 | L51: =IFERROR(L48+L49,"") -> 0.043661748 | ... AE51: =IFERROR(AE48+AE49,"") -> 0.030769465
C52: ⑥/① | D52: 广义风险贷款比率 | E52: =E37/E31 -> 0.042349452 | F52: =F37/F31 -> 0.041629544 | G52: =G37/G31 -> 0.043478989 | H52: =H37/H31 -> 0.041725434 | I52: =I37/I31 -> 0.044863321 | J52: =J37/J31 -> 0.044843642 | K52: =K37/K31 -> 0.045107934 | L52: =L37/L31 -> 0.043620638 | ... AE52: =AE37/AE31 -> 0.030775153
D53: 广义不良资产率 | E53: =IFERROR(INDEX(【输出】数据汇总!$A:$AQ,MATCH(纵向时序!$D$30&纵向时序!$D53,【输出】数据汇总!$A:$A,0),MATCH(纵向时序!E$2,【输出】数据汇总!$1:$1,0)),"") -> 0.028118704 | F53: =IFERROR(INDEX(【输出】数据汇总!$A:$AQ,MATCH(纵向时序!$D$30&纵向时序!$D53,【输出】数据汇总!$A:$A,0),MATCH(纵向时序!F$2,【输出】数据汇总!$1:$1,0)),"") -> 0.028133543 | G53: =IFERROR(INDEX(【输出】数据汇总!$A:$AQ,MATCH(纵向时序!$D$30&纵向时序!$D53,【输出】数据汇总!$A:$A,0),MATCH(纵向时序!G$2,【输出】数据汇总!$1:$1,0)),"") -> 0.028710747 | H53: =IFERROR(INDEX(【输出】数据汇总!$A:$AQ,MATCH(纵向时序!$D$30&纵向时序!$D53,【输出】数据汇总!$A:$A,0),MATCH(纵向时序!H$2,【输出】数据汇总!$1:$1,0)),"") -> 0.027366116 | I53: =IFERROR(INDEX(【输出】数据汇总!$A:$AQ,MATCH(纵向时序!$D$30&纵向时序!$D53,【输出】数据汇总!$A:$A,0),MATCH(纵向时序!I$2,【输出】数据汇总!$1:$1,0)),"") -> 0.029497648 | J53: =IFERROR(INDEX(【输出】数据汇总!$A:$AQ,MATCH(纵向时序!$D$30&纵向时序!$D53,【输出】数据汇总!$A:$A,0),MATCH(纵向时序!J$2,【输出】数据汇总!$1:$1,0)),"") -> 0.029516821 | K53: =IFERROR(INDEX(【输出】数据汇总!$A:$AQ,MATCH(纵向时序!$D$30&纵向时序!$D53,【输出】数据汇总!$A:$A,0),MATCH(纵向时序!K$2,【输出】数据汇总!$1:$1,0)),"") -> 0.030090089 | L53: =IFERROR(INDEX(【输出】数据汇总!$A:$AQ,MATCH(纵向时序!$D$30&纵向时序!$D53,【输出】数据汇总!$A:$A,0),MATCH(纵向时序!L$2,【输出】数据汇总!$1:$1,0)),"") -> 0.029298943 | ... AC53: =IFERROR(INDEX(【输出】数据汇总!$A:$AQ,MATCH(纵向时序!$D$30&纵向时序!$D53,【输出】数据汇总!$A:$A,0),MATCH(纵向时序!AC$2,【输出】数据汇总!$1:$1,0)),"") -> 0.021065109 | AD53: =IFERROR(INDEX(【输出】数据汇总!$A:$AQ,MATCH(纵向时序!$D$30&纵向时序!$D53,【输出】数据汇总!$A:$A,0),MATCH(纵向时序!AD$30,【输出】数据汇总!$1:$1,0)),"") -> 0.020573159 | AE53: =IFERROR(INDEX(【输出】数据汇总!$A:$AQ,MATCH(纵向时序!$D$30&纵向时序!$D53,【输出】数据汇总!$A:$A,0),MATCH(纵向时序!AE$2,【输出】数据汇总!$1:$1,0)),"") -> 0.020323837
D54: 拨备覆盖率 | E54: =IFERROR(INDEX(【输出】数据汇总!$A:$AQ,MATCH(纵向时序!$D$30&纵向时序!$D54,【输出】数据汇总!$A:$A,0),MATCH(纵向时序!E$2,【输出】数据汇总!$1:$1,0)),"") -> 2.1803 | F54: =IFERROR(INDEX(【输出】数据汇总!$A:$AQ,MATCH(纵向时序!$D$30&纵向时序!$D54,【输出】数据汇总!$A:$A,0),MATCH(纵向时序!F$2,【输出】数据汇总!$1:$1,0)),"") -> 2.1828 | G54: =IFERROR(INDEX(【输出】数据汇总!$A:$AQ,MATCH(纵向时序!$D$30&纵向时序!$D54,【输出】数据汇总!$A:$A,0),MATCH(纵向时序!G$2,【输出】数据汇总!$1:$1,0)),"") -> 2.2769 | H54: =IFERROR(INDEX(【输出】数据汇总!$A:$AQ,MATCH(纵向时序!$D$30&纵向时序!$D54,【输出】数据汇总!$A:$A,0),MATCH(纵向时序!H$2,【输出】数据汇总!$1:$1,0)),"") -> 2.3027 | I54: =IFERROR(INDEX(【输出】数据汇总!$A:$AQ,MATCH(纵向时序!$D$30&纵向时序!$D54,【输出】数据汇总!$A:$A,0),MATCH(纵向时序!I$2,【输出】数据汇总!$1:$1,0)),"") -> 2.2347 | J54: =IFERROR(INDEX(【输出】数据汇总!$A:$AQ,MATCH(纵向时序!$D$30&纵向时序!$D54,【输出】数据汇总!$A:$A,0),MATCH(纵向时序!J$2,【输出】数据汇总!$1:$1,0)),"") -> 2.1751 | K54: =IFERROR(INDEX(【输出】数据汇总!$A:$AQ,MATCH(纵向时序!$D$30&纵向时序!$D54,【输出】数据汇总!$A:$A,0),MATCH(纵向时序!K$2,【输出】数据汇总!$1:$1,0)),"") -> 2.1359 | L54: =IFERROR(INDEX(【输出】数据汇总!$A:$AQ,MATCH(纵向时序!$D$30&纵向时序!$D54,【输出】数据汇总!$A:$A,0),MATCH(纵向时序!L$2,【输出】数据汇总!$1:$1,0)),"") -> 2.1494 | ... AC54: =IFERROR(INDEX(【输出】数据汇总!$A:$AQ,MATCH(纵向时序!$D$30&纵向时序!$D54,【输出】数据汇总!$A:$A,0),MATCH(纵向时序!AC$2,【输出】数据汇总!$1:$1,0)),"") -> 2.394 | AD54: =IFERROR(INDEX(【输出】数据汇总!$A:$AQ,MATCH(纵向时序!$D$30&纵向时序!$D54,【输出】数据汇总!$A:$A,0),MATCH(纵向时序!AD$30,【输出】数据汇总!$1:$1,0)),"") -> 2.3505 | AE54: =IFERROR(INDEX(【输出】数据汇总!$A:$AQ,MATCH(纵向时序!$D$30&纵向时序!$D54,【输出】数据汇总!$A:$A,0),MATCH(纵向时序!AE$2,【输出】数据汇总!$1:$1,0)),"") -> 2.3315
D55: 超额拨备/归母净利润(TTM) | E55: =IFERROR(INDEX(【输出】数据汇总!$A:$AQ,MATCH(纵向时序!$D$30&纵向时序!$D55,【输出】数据汇总!$A:$A,0),MATCH(纵向时序!E$2,【输出】数据汇总!$1:$1,0)),"") -> -0.44062544 | F55: =IFERROR(INDEX(【输出】数据汇总!$A:$AQ,MATCH(纵向时序!$D$30&纵向时序!$D55,【输出】数据汇总!$A:$A,0),MATCH(纵向时序!F$2,【输出】数据汇总!$1:$1,0)),"") -> -0.4181978 | G55: =IFERROR(INDEX(【输出】数据汇总!$A:$AQ,MATCH(纵向时序!$D$30&纵向时序!$D55,【输出】数据汇总!$A:$A,0),MATCH(纵向时序!G$2,【输出】数据汇总!$1:$1,0)),"") -> -0.43404553 | H55: =IFERROR(INDEX(【输出】数据汇总!$A:$AQ,MATCH(纵向时序!$D$30&纵向时序!$D55,【输出】数据汇总!$A:$A,0),MATCH(纵向时序!H$2,【输出】数据汇总!$1:$1,0)),"") -> -0.33638604 | I55: =IFERROR(INDEX(【输出】数据汇总!$A:$AQ,MATCH(纵向时序!$D$30&纵向时序!$D55,【输出】数据汇总!$A:$A,0),MATCH(纵向时序!I$2,【输出】数据汇总!$1:$1,0)),"") -> -0.52448886 | J55: =IFERROR(INDEX(【输出】数据汇总!$A:$AQ,MATCH(纵向时序!$D$30&纵向时序!$D55,【输出】数据汇总!$A:$A,0),MATCH(纵向时序!J$2,【输出】数据汇总!$1:$1,0)),"") -> -0.53341485 | K55: =IFERROR(INDEX(【输出】数据汇总!$A:$AQ,MATCH(纵向时序!$D$30&纵向时序!$D55,【输出】数据汇总!$A:$A,0),MATCH(纵向时序!K$2,【输出】数据汇总!$1:$1,0)),"") -> -0.51837661 | L55: =IFERROR(INDEX(【输出】数据汇总!$A:$AQ,MATCH(纵向时序!$D$30&纵向时序!$D55,【输出】数据汇总!$A:$A,0),MATCH(纵向时序!L$2,【输出】数据汇总!$1:$1,0)),"") -> -0.44211053 | ... AC55: =IFERROR(INDEX(【输出】数据汇总!$A:$AQ,MATCH(纵向时序!$D$30&纵向时序!$D55,【输出】数据汇总!$A:$A,0),MATCH(纵向时序!AC$2,【输出】数据汇总!$1:$1,0)),"") -> 0.12463853 | AD55: =IFERROR(INDEX(【输出】数据汇总!$A:$AQ,MATCH(纵向时序!$D$30&纵向时序!$D55,【输出】数据汇总!$A:$A,0),MATCH(纵向时序!AD$30,【输出】数据汇总!$1:$1,0)),"") -> 0.083271964 | AE55: =IFERROR(INDEX(【输出】数据汇总!$A:$AQ,MATCH(纵向时序!$D$30&纵向时序!$D55,【输出】数据汇总!$A:$A,0),MATCH(纵向时序!AE$2,【输出】数据汇总!$1:$1,0)),"") -> 0.052445121
D56: 超额拨备/归母净资产 | E56: =IFERROR(INDEX(【输出】数据汇总!$A:$AQ,MATCH(纵向时序!$D$30&纵向时序!$D56,【输出】数据汇总!$A:$A,0),MATCH(纵向时序!E$2,【输出】数据汇总!$1:$1,0)),"") -> -0.056117395 | F56: =IFERROR(INDEX(【输出】数据汇总!$A:$AQ,MATCH(纵向时序!$D$30&纵向时序!$D56,【输出】数据汇总!$A:$A,0),MATCH(纵向时序!F$2,【输出】数据汇总!$1:$1,0)),"") -> -0.05205677 | G56: =IFERROR(INDEX(【输出】数据汇总!$A:$AQ,MATCH(纵向时序!$D$30&纵向时序!$D56,【输出】数据汇总!$A:$A,0),MATCH(纵向时序!G$2,【输出】数据汇总!$1:$1,0)),"") -> -0.052238646 | H56: =IFERROR(INDEX(【输出】数据汇总!$A:$AQ,MATCH(纵向时序!$D$30&纵向时序!$D56,【输出】数据汇总!$A:$A,0),MATCH(纵向时序!H$2,【输出】数据汇总!$1:$1,0)),"") -> -0.039312796 | I56: =IFERROR(INDEX(【输出】数据汇总!$A:$AQ,MATCH(纵向时序!$D$30&纵向时序!$D56,【输出】数据汇总!$A:$A,0),MATCH(纵向时序!I$2,【输出】数据汇总!$1:$1,0)),"") -> -0.057521726 | J56: =IFERROR(INDEX(【输出】数据汇总!$A:$AQ,MATCH(纵向时序!$D$30&纵向时序!$D56,【输出】数据汇总!$A:$A,0),MATCH(纵向时序!J$2,【输出】数据汇总!$1:$1,0)),"") -> -0.05678434 | K56: =IFERROR(INDEX(【输出】数据汇总!$A:$AQ,MATCH(纵向时序!$D$30&纵向时序!$D56,【输出】数据汇总!$A:$A,0),MATCH(纵向时序!K$2,【输出】数据汇总!$1:$1,0)),"") -> -0.059415386 | L56: =IFERROR(INDEX(【输出】数据汇总!$A:$AQ,MATCH(纵向时序!$D$30&纵向时序!$D56,【输出】数据汇总!$A:$A,0),MATCH(纵向时序!L$2,【输出】数据汇总!$1:$1,0)),"") -> -0.049425112 | ... AC56: =IFERROR(INDEX(【输出】数据汇总!$A:$AQ,MATCH(纵向时序!$D$30&纵向时序!$D56,【输出】数据汇总!$A:$A,0),MATCH(纵向时序!AC$2,【输出】数据汇总!$1:$1,0)),"") -> 0.011659252 | AD56: =IFERROR(INDEX(【输出】数据汇总!$A:$AQ,MATCH(纵向时序!$D$30&纵向时序!$D56,【输出】数据汇总!$A:$A,0),MATCH(纵向时序!AD$30,【输出】数据汇总!$1:$1,0)),"") -> 0.0077272414 | AE56: =IFERROR(INDEX(【输出】数据汇总!$A:$AQ,MATCH(纵向时序!$D$30&纵向时序!$D56,【输出】数据汇总!$A:$A,0),MATCH(纵向时序!AE$2,【输出】数据汇总!$1:$1,0)),"") -> 0.0048517533
D58: =D2 -> 招商
C59: 【减】 | D59: =D30 -> 建设
D60: =D58&C59&D59 -> 招商【减】建设 | E60: =E30 -> 43646 | F60: =F30 -> 43738 | G60: =G30 -> 43830 | H60: =H30 -> 43921 | I60: =I30 -> 44012 | J60: =J30 -> 44104 | K60: =K30 -> 44196 | L60: =L30 -> 44286 | ... AE60: =AE30 -> 46022
D61: 贷款总额 | E61: =IFERROR(E3-E31,"") -> -101784.05 | F61: =IFERROR(F3-F31,"") -> -103704.52 | G61: =IFERROR(G3-G31,"") -> -104972.56 | H61: =IFERROR(H3-H31,"") -> -112095.61 | I61: =IFERROR(I3-I31,"") -> -115787.45 | J61: =IFERROR(J3-J31,"") -> -116547.33 | K61: =IFERROR(K3-K31,"") -> -117166.4 | L61: =IFERROR(L3-L31,"") -> -123142.42 | ... AE61: =IFERROR(AE3-AE31,"") -> -205147.69
D62: 逾期贷款余额 | E62: =IFERROR(E4-E32,"") -> -1405.36 | F62: =IFERROR(F4-F32,"") -> -1405.36 | G62: =IFERROR(G4-G32,"") -> -1095.2 | H62: =IFERROR(H4-H32,"") -> -1095.2 | I62: =IFERROR(I4-I32,"") -> -1208.99 | J62: =IFERROR(J4-J32,"") -> -1208.99 | K62: =IFERROR(K4-K32,"") -> -1256.55 | L62: =IFERROR(L4-L32,"") -> -1256.55 | ... AE62: =IFERROR(AE4-AE32,"") -> -2771.68
D63: 重组贷款余额 | E63: =IFERROR(E5-E33,"") -> 198.81 | F63: =IFERROR(F5-F33,"") -> 198.81 | G63: =IFERROR(G5-G33,"") -> 189.92 | H63: =IFERROR(H5-H33,"") -> 189.92 | I63: =IFERROR(I5-I33,"") -> 167.8 | J63: =IFERROR(J5-J33,"") -> 167.8 | K63: =IFERROR(K5-K33,"") -> 147.88 | L63: =IFERROR(L5-L33,"") -> 147.88 | ... AE63: =IFERROR(AE5-AE33,"") -> -980.68
D64: 不良贷款余额 | E64: =IFERROR(E6-E34,"") -> -1548.48 | F64: =IFERROR(F6-F34,"") -> -1581.38 | G64: =IFERROR(G6-G34,"") -> -1601.98 | H64: =IFERROR(H6-H34,"") -> -1734.28 | I64: =IFERROR(I6-I34,"") -> -1901.88 | J64: =IFERROR(J6-J34,"") -> -1990.62 | K64: =IFERROR(K6-K34,"") -> -2071.14 | L64: =IFERROR(L6-L34,"") -> -2201.96 | ... AE64: =IFERROR(AE6-AE34,"") -> -2957.76
D65: 关注类贷款余额 | E65: =IFERROR(E7-E35,"") -> -3497.69 | F65: =IFERROR(F7-F35,"") -> -3497.69 | G65: =IFERROR(G7-G35,"") -> -3865.96 | H65: =IFERROR(H7-H35,"") -> -3828.58 | I65: =IFERROR(I7-I35,"") -> -4435.21 | J65: =IFERROR(J7-J35,"") -> -4521.1 | K65: =IFERROR(K7-K35,"") -> -4539.22 | L65: =IFERROR(L7-L35,"") -> -4584 | ... AE65: =IFERROR(AE7-AE35,"") -> -3868.71
D66: 非信贷资产第三阶段额 | E66: =IFERROR(E8-E36,"") -> 80.14 | F66: =IFERROR(F8-F36,"") -> 80.14 | G66: =IFERROR(G8-G36,"") -> 53.18 | H66: =IFERROR(H8-H36,"") -> 53.18 | I66: =IFERROR(I8-I36,"") -> 36.16 | J66: =IFERROR(J8-J36,"") -> 36.16 | K66: =IFERROR(K8-K36,"") -> 150.23 | L66: =IFERROR(L8-L36,"") -> 150.23 | ... AE66: =IFERROR(AE8-AE36,"") -> 146.6
D67: 广义风险贷款 | E67: =IFERROR(E9-E37,"") -> -5046.17 | F67: =IFERROR(F9-F37,"") -> -5079.07 | G67: =IFERROR(G9-G37,"") -> -5467.94 | H67: =IFERROR(H9-H37,"") -> -5562.86 | I67: =IFERROR(I9-I37,"") -> -6337.09 | J67: =IFERROR(J9-J37,"") -> -6511.72 | K67: =IFERROR(K9-K37,"") -> -6610.36 | L67: =IFERROR(L9-L37,"") -> -6785.96 | ... AE67: =IFERROR(AE9-AE37,"") -> -6826.47
D68: 贷款拨备额 | E68: =IFERROR(E10-E38,"") -> -2427.86 | F68: =IFERROR(F10-F38,"") -> -2433.8588 | G68: =IFERROR(G10-G38,"") -> -2590.61 | H68: =IFERROR(H10-H38,"") -> -2831.4644 | I68: =IFERROR(I10-I38,"") -> -3024.7 | J68: =IFERROR(J10-J38,"") -> -3159.5397 | K68: =IFERROR(K10-K38,"") -> -3213.99 | L68: =IFERROR(L10-L38,"") -> -3522.3404 | ... AE68: =IFERROR(AE10-AE38,"") -> -5813.9
